Workbook

Sheet Dashboard
A1: DASHBOARD EJECUTIVO DE CONTROL DE COMBUSTIBLE | GRUPO TRUJANO
A3: FILTROS DEL DASHBOARD (Celdas en amarillo editables en Excel) | E3: ESTADO DE LA CONCILIACIÓN SEMANAL
B4: Obra Seleccionada: | C4: México-Toluca | E4: =IF(I28=0, "🟢 TODO COINCIDE (0 L)", "🔴 DISCREPANCIA: " & I28 & " L")
B5: Fecha Inicio (Lunes): | C5: 46195
B6: Fecha Fin (Rango): | C6: 46202
B7: Precio Diésel ($/L): | C7: 27
B8: Período Resumen: | C8: Semana Seleccionada
A10: COMPARATIVA: SOLICITADO (PETICIONES) VS ENTREGADO EN OBRA
A11: Día | B11: Fecha | C11: Lts Solicitados | D11: Lts Recibidos Obra | E11: Dif. Litros (Obra-Sol) | F11: Costo Solicitado | G11: Costo Real Obra | H11: Dif. Costo (Real-Sol)
A12: Lunes | B12: =C$5 | C12: =IF(C$4="Todas", SUMIFS(Solicitudes!F:F, Solicitudes!C:C, B12), SUMIFS(Solicitudes!F:F, Solicitudes!B:B, C$4, Solicitudes!C:C, B12)) | D12: =IF(C$4="Jalisco", SUMIFS(Captura_Jalisco!G:G, Captura_Jalisco!A:A, B12, Captura_Jalisco!B:B, "Salida"), IF(C$4="Todas", SUMIFS(Captura_Obra!F:F, Captura_Obra!A:A, B12) + SUMIFS(Captura_Jalisco!G:G, Captura_Jalisco!A:A, B12, Captura_Jalisco!B:B, "Salida"), SUMIFS(Captura_Obra!F:F, Captura_Obra!B:B, C$4, Captura_Obra!A:A, B12))) | E12: =D12-C12 | F12: =C12*C$7 | G12: =D12*C$7 | H12: =G12-F12
A13: Martes | B13: =B12+1 | C13: =IF(C$4="Todas", SUMIFS(Solicitudes!F:F, Solicitudes!C:C, B13), SUMIFS(Solicitudes!F:F, Solicitudes!B:B, C$4, Solicitudes!C:C, B13)) | D13: =IF(C$4="Jalisco", SUMIFS(Captura_Jalisco!G:G, Captura_Jalisco!A:A, B13, Captura_Jalisco!B:B, "Salida"), IF(C$4="Todas", SUMIFS(Captura_Obra!F:F, Captura_Obra!A:A, B13) + SUMIFS(Captura_Jalisco!G:G, Captura_Jalisco!A:A, B13, Captura_Jalisco!B:B, "Salida"), SUMIFS(Captura_Obra!F:F, Captura_Obra!B:B, C$4, Captura_Obra!A:A, B13))) | E13: =D13-C13 | F13: =C13*C$7 | G13: =D13*C$7 | H13: =G13-F13
A14: Miércoles | B14: =B13+1 | C14: =IF(C$4="Todas", SUMIFS(Solicitudes!F:F, Solicitudes!C:C, B14), SUMIFS(Solicitudes!F:F, Solicitudes!B:B, C$4, Solicitudes!C:C, B14)) | D14: =IF(C$4="Jalisco", SUMIFS(Captura_Jalisco!G:G, Captura_Jalisco!A:A, B14, Captura_Jalisco!B:B, "Salida"), IF(C$4="Todas", SUMIFS(Captura_Obra!F:F, Captura_Obra!A:A, B14) + SUMIFS(Captura_Jalisco!G:G, Captura_Jalisco!A:A, B14, Captura_Jalisco!B:B, "Salida"), SUMIFS(Captura_Obra!F:F, Captura_Obra!B:B, C$4, Captura_Obra!A:A, B14))) | E14: =D14-C14 | F14: =C14*C$7 | G14: =D14*C$7 | H14: =G14-F14
A15: Jueves | B15: =B14+1 | C15: =IF(C$4="Todas", SUMIFS(Solicitudes!F:F, Solicitudes!C:C, B15), SUMIFS(Solicitudes!F:F, Solicitudes!B:B, C$4, Solicitudes!C:C, B15)) | D15: =IF(C$4="Jalisco", SUMIFS(Captura_Jalisco!G:G, Captura_Jalisco!A:A, B15, Captura_Jalisco!B:B, "Salida"), IF(C$4="Todas", SUMIFS(Captura_Obra!F:F, Captura_Obra!A:A, B15) + SUMIFS(Captura_Jalisco!G:G, Captura_Jalisco!A:A, B15, Captura_Jalisco!B:B, "Salida"), SUMIFS(Captura_Obra!F:F, Captura_Obra!B:B, C$4, Captura_Obra!A:A, B15))) | E15: =D15-C15 | F15: =C15*C$7 | G15: =D15*C$7 | H15: =G15-F15
A16: Viernes | B16: =B15+1 | C16: =IF(C$4="Todas", SUMIFS(Solicitudes!F:F, Solicitudes!C:C, B16), SUMIFS(Solicitudes!F:F, Solicitudes!B:B, C$4, Solicitudes!C:C, B16)) | D16: =IF(C$4="Jalisco", SUMIFS(Captura_Jalisco!G:G, Captura_Jalisco!A:A, B16, Captura_Jalisco!B:B, "Salida"), IF(C$4="Todas", SUMIFS(Captura_Obra!F:F, Captura_Obra!A:A, B16) + SUMIFS(Captura_Jalisco!G:G, Captura_Jalisco!A:A, B16, Captura_Jalisco!B:B, "Salida"), SUMIFS(Captura_Obra!F:F, Captura_Obra!B:B, C$4, Captura_Obra!A:A, B16))) | E16: =D16-C16 | F16: =C16*C$7 | G16: =D16*C$7 | H16: =G16-F16
A17: Sábado | B17: =B16+1 | C17: =IF(C$4="Todas", SUMIFS(Solicitudes!F:F, Solicitudes!C:C, B17), SUMIFS(Solicitudes!F:F, Solicitudes!B:B, C$4, Solicitudes!C:C, B17)) | D17: =IF(C$4="Jalisco", SUMIFS(Captura_Jalisco!G:G, Captura_Jalisco!A:A, B17, Captura_Jalisco!B:B, "Salida"), IF(C$4="Todas", SUMIFS(Captura_Obra!F:F, Captura_Obra!A:A, B17) + SUMIFS(Captura_Jalisco!G:G, Captura_Jalisco!A:A, B17, Captura_Jalisco!B:B, "Salida"), SUMIFS(Captura_Obra!F:F, Captura_Obra!B:B, C$4, Captura_Obra!A:A, B17))) | E17: =D17-C17 | F17: =C17*C$7 | G17: =D17*C$7 | H17: =G17-F17
A18: TOTAL SEMANAL | C18: =SUM(C12:C17) | D18: =SUM(D12:D17) | E18: =SUM(E12:E17) | F18: =SUM(F12:F17) | G18: =SUM(G12:G17) | H18: =SUM(H12:H17)
A20: CONCILIACIÓN FÍSICA Y DISCREPANCIAS (OBRA VS MARIMBA Y PEGASO)
A21: Día | B21: Fecha | C21: Obra Recibió (M) | D21: Marimba Despachó | E21: Dif. Marimba | F21: Obra Recibió (P) | G21: Pegaso Despachó | H21: Dif. Pegaso | I21: Dif. Total (L) | J21: Observaciones / Justificación
A22: Lunes | B22: =B12 | C22: =IF(C$4="Todas", SUMIFS(Captura_Obra!F:F, Captura_Obra!A:A, B22, Captura_Obra!C:C, "Marimba M-01"), SUMIFS(Captura_Obra!F:F, Captura_Obra!B:B, C$4, Captura_Obra!A:A, B22, Captura_Obra!C:C, "Marimba M-01")) | D22: =IF(C$4="Todas", SUMIFS(Captura_Marimba_M01!G:G, Captura_Marimba_M01!A:A, B22, Captura_Marimba_M01!B:B, "Salida"), SUMIFS(Captura_Marimba_M01!G:G, Captura_Marimba_M01!C:C, C$4, Captura_Marimba_M01!A:A, B22, Captura_Marimba_M01!B:B, "Salida")) | E22: =C22-D22 | F22: =IF(C$4="Todas", SUMIFS(Captura_Obra!F:F, Captura_Obra!A:A, B22, Captura_Obra!C:C, "Pegaso Directo"), SUMIFS(Captura_Obra!F:F, Captura_Obra!B:B, C$4, Captura_Obra!A:A, B22, Captura_Obra!C:C, "Pegaso Directo")) | G22: =IF(C$4="Todas", SUMIFS(Captura_Pegaso!H:H, Captura_Pegaso!A:A, B22, Captura_Pegaso!B:B, "Salida"), SUMIFS(Captura_Pegaso!H:H, Captura_Pegaso!D:D, C$4, Captura_Pegaso!A:A, B22, Captura_Pegaso!B:B, "Salida")) | H22: =F22-G22 | I22: =E22+H22
A23: Martes | B23: =B13 | C23: =IF(C$4="Todas", SUMIFS(Captura_Obra!F:F, Captura_Obra!A:A, B23, Captura_Obra!C:C, "Marimba M-01"), SUMIFS(Captura_Obra!F:F, Captura_Obra!B:B, C$4, Captura_Obra!A:A, B23, Captura_Obra!C:C, "Marimba M-01")) | D23: =IF(C$4="Todas", SUMIFS(Captura_Marimba_M01!G:G, Captura_Marimba_M01!A:A, B23, Captura_Marimba_M01!B:B, "Salida"), SUMIFS(Captura_Marimba_M01!G:G, Captura_Marimba_M01!C:C, C$4, Captura_Marimba_M01!A:A, B23, Captura_Marimba_M01!B:B, "Salida")) | E23: =C23-D23 | F23: =IF(C$4="Todas", SUMIFS(Captura_Obra!F:F, Captura_Obra!A:A, B23, Captura_Obra!C:C, "Pegaso Directo"), SUMIFS(Captura_Obra!F:F, Captura_Obra!B:B, C$4, Captura_Obra!A:A, B23, Captura_Obra!C:C, "Pegaso Directo")) | G23: =IF(C$4="Todas", SUMIFS(Captura_Pegaso!H:H, Captura_Pegaso!A:A, B23, Captura_Pegaso!B:B, "Salida"), SUMIFS(Captura_Pegaso!H:H, Captura_Pegaso!D:D, C$4, Captura_Pegaso!A:A, B23, Captura_Pegaso!B:B, "Salida")) | H23: =F23-G23 | I23: =E23+H23
A24: Miércoles | B24: =B14 | C24: =IF(C$4="Todas", SUMIFS(Captura_Obra!F:F, Captura_Obra!A:A, B24, Captura_Obra!C:C, "Marimba M-01"), SUMIFS(Captura_Obra!F:F, Captura_Obra!B:B, C$4, Captura_Obra!A:A, B24, Captura_Obra!C:C, "Marimba M-01")) | D24: =IF(C$4="Todas", SUMIFS(Captura_Marimba_M01!G:G, Captura_Marimba_M01!A:A, B24, Captura_Marimba_M01!B:B, "Salida"), SUMIFS(Captura_Marimba_M01!G:G, Captura_Marimba_M01!C:C, C$4, Captura_Marimba_M01!A:A, B24, Captura_Marimba_M01!B:B, "Salida")) | E24: =C24-D24 | F24: =IF(C$4="Todas", SUMIFS(Captura_Obra!F:F, Captura_Obra!A:A, B24, Captura_Obra!C:C, "Pegaso Directo"), SUMIFS(Captura_Obra!F:F, Captura_Obra!B:B, C$4, Captura_Obra!A:A, B24, Captura_Obra!C:C, "Pegaso Directo")) | G24: =IF(C$4="Todas", SUMIFS(Captura_Pegaso!H:H, Captura_Pegaso!A:A, B24, Captura_Pegaso!B:B, "Salida"), SUMIFS(Captura_Pegaso!H:H, Captura_Pegaso!D:D, C$4, Captura_Pegaso!A:A, B24, Captura_Pegaso!B:B, "Salida")) | H24: =F24-G24 | I24: =E24+H24
A25: Jueves | B25: =B15 | C25: =IF(C$4="Todas", SUMIFS(Captura_Obra!F:F, Captura_Obra!A:A, B25, Captura_Obra!C:C, "Marimba M-01"), SUMIFS(Captura_Obra!F:F, Captura_Obra!B:B, C$4, Captura_Obra!A:A, B25, Captura_Obra!C:C, "Marimba M-01")) | D25: =IF(C$4="Todas", SUMIFS(Captura_Marimba_M01!G:G, Captura_Marimba_M01!A:A, B25, Captura_Marimba_M01!B:B, "Salida"), SUMIFS(Captura_Marimba_M01!G:G, Captura_Marimba_M01!C:C, C$4, Captura_Marimba_M01!A:A, B25, Captura_Marimba_M01!B:B, "Salida")) | E25: =C25-D25 | F25: =IF(C$4="Todas", SUMIFS(Captura_Obra!F:F, Captura_Obra!A:A, B25, Captura_Obra!C:C, "Pegaso Directo"), SUMIFS(Captura_Obra!F:F, Captura_Obra!B:B, C$4, Captura_Obra!A:A, B25, Captura_Obra!C:C, "Pegaso Directo")) | G25: =IF(C$4="Todas", SUMIFS(Captura_Pegaso!H:H, Captura_Pegaso!A:A, B25, Captura_Pegaso!B:B, "Salida"), SUMIFS(Captura_Pegaso!H:H, Captura_Pegaso!D:D, C$4, Captura_Pegaso!A:A, B25, Captura_Pegaso!B:B, "Salida")) | H25: =F25-G25 | I25: =E25+H25
A26: Viernes | B26: =B16 | C26: =IF(C$4="Todas", SUMIFS(Captura_Obra!F:F, Captura_Obra!A:A, B26, Captura_Obra!C:C, "Marimba M-01"), SUMIFS(Captura_Obra!F:F, Captura_Obra!B:B, C$4, Captura_Obra!A:A, B26, Captura_Obra!C:C, "Marimba M-01")) | D26: =IF(C$4="Todas", SUMIFS(Captura_Marimba_M01!G:G, Captura_Marimba_M01!A:A, B26, Captura_Marimba_M01!B:B, "Salida"), SUMIFS(Captura_Marimba_M01!G:G, Captura_Marimba_M01!C:C, C$4, Captura_Marimba_M01!A:A, B26, Captura_Marimba_M01!B:B, "Salida")) | E26: =C26-D26 | F26: =IF(C$4="Todas", SUMIFS(Captura_Obra!F:F, Captura_Obra!A:A, B26, Captura_Obra!C:C, "Pegaso Directo"), SUMIFS(Captura_Obra!F:F, Captura_Obra!B:B, C$4, Captura_Obra!A:A, B26, Captura_Obra!C:C, "Pegaso Directo")) | G26: =IF(C$4="Todas", SUMIFS(Captura_Pegaso!H:H, Captura_Pegaso!A:A, B26, Captura_Pegaso!B:B, "Salida"), SUMIFS(Captura_Pegaso!H:H, Captura_Pegaso!D:D, C$4, Captura_Pegaso!A:A, B26, Captura_Pegaso!B:B, "Salida")) | H26: =F26-G26 | I26: =E26+H26
A27: Sábado | B27: =B17 | C27: =IF(C$4="Todas", SUMIFS(Captura_Obra!F:F, Captura_Obra!A:A, B27, Captura_Obra!C:C, "Marimba M-01"), SUMIFS(Captura_Obra!F:F, Captura_Obra!B:B, C$4, Captura_Obra!A:A, B27, Captura_Obra!C:C, "Marimba M-01")) | D27: =IF(C$4="Todas", SUMIFS(Captura_Marimba_M01!G:G, Captura_Marimba_M01!A:A, B27, Captura_Marimba_M01!B:B, "Salida"), SUMIFS(Captura_Marimba_M01!G:G, Captura_Marimba_M01!C:C, C$4, Captura_Marimba_M01!A:A, B27, Captura_Marimba_M01!B:B, "Salida")) | E27: =C27-D27 | F27: =IF(C$4="Todas", SUMIFS(Captura_Obra!F:F, Captura_Obra!A:A, B27, Captura_Obra!C:C, "Pegaso Directo"), SUMIFS(Captura_Obra!F:F, Captura_Obra!B:B, C$4, Captura_Obra!A:A, B27, Captura_Obra!C:C, "Pegaso Directo")) | G27: =IF(C$4="Todas", SUMIFS(Captura_Pegaso!H:H, Captura_Pegaso!A:A, B27, Captura_Pegaso!B:B, "Salida"), SUMIFS(Captura_Pegaso!H:H, Captura_Pegaso!D:D, C$4, Captura_Pegaso!A:A, B27, Captura_Pegaso!B:B, "Salida")) | H27: =F27-G27 | I27: =E27+H27
A28: TOTAL CONCILIADO | C28: =SUM(C22:C27) | D28: =SUM(D22:D27) | E28: =SUM(E22:E27) | F28: =SUM(F22:F27) | G28: =SUM(G22:G27) | H28: =SUM(H22:H27) | I28: =SUM(I22:I27)
Q30: ="SOLICITUDES DE DISEL DIARIAS Y SEMANALES POR OBRA (SEMANA " & YEAR(C5) & "-" & TEXT(MONTH(C5),"00") & "-" & TEXT(DAY(C5),"00") & ")"
A31: RESUMEN ACUMULADO POR OBRA / PERÍODO SELECCIONADO | Q31: Obra | R31: Solicitante | S31: Lunes | U31: Martes | W31: Miércoles | Y31: Jueves | AA31: Viernes | AC31: Sábado | AE31: Total Semanal Solicitado | AF31: Total Seamanal Autorizado
A32: Obra | B32: Total Litros Suministrados | C32: Costo Total Acumulado | S32: Solicitado | T32: Autorizado | U32: Solicitado | V32: Autorizado | W32: Solicitado | X32: Autorizado | Y32: Solicitado | Z32: Autorizado | AA32: Solicitado | AB32: Autorizado | AC32: Solicitado | AD32: Autorizado
A33: México-Toluca | B33: =IF(C$8="Acumulado Histórico", SUMIFS(Captura_Obra!F:F, Captura_Obra!B:B, A33), IF(C$8="Rango de Fechas", SUMIFS(Captura_Obra!F:F, Captura_Obra!B:B, A33, Captura_Obra!A:A, ">="&C$5, Captura_Obra!A:A, "<="&(C$6+5)), SUMIFS(Captura_Obra!F:F, Captura_Obra!B:B, A33, Captura_Obra!A:A, ">="&C$5, Captura_Obra!A:A, "<="&(C$5+5)))) | C33: =B33*C$7 | P33: m | Q33: =A33 | R33: =VLOOKUP(Q33,Catalogos!$B$4:$C$18,2,FALSE) | S33: =SUMIFS(Solicitudes!$F:$F, Solicitudes!$B:$B, $Q33, Solicitudes!$C:$C, $B$12) | T33: 550 | U33: =SUMIFS(Solicitudes!$F:$F, Solicitudes!$B:$B, $Q33, Solicitudes!$C:$C, $B$13) | V33: 550 | W33: =SUMIFS(Solicitudes!$F:$F, Solicitudes!$B:$B, $Q33, Solicitudes!$C:$C, $B$14) | X33: 550 | Y33: =SUMIFS(Solicitudes!$F:$F, Solicitudes!$B:$B, $Q33, Solicitudes!$C:$C, $B$15) | Z33: 550 | AA33: =SUMIFS(Solicitudes!$F:$F, Solicitudes!$B:$B, $Q33, Solicitudes!$C:$C, $B$16) | AB33: 550 | AC33: =SUMIFS(Solicitudes!$F:$F, Solicitudes!$B:$B, $Q33, Solicitudes!$C:$C, $B$17) | AD33: 0 | AE33: =SUM(S33,U33,W33,Y33,AA33,AC33,) | AF33: =SUM(T33,V33,X33,Z33,AB33,AD33)
A34: Lerma - Tres Marías | B34: =IF(C$8="Acumulado Histórico", SUMIFS(Captura_Obra!F:F, Captura_Obra!B:B, A34), IF(C$8="Rango de Fechas", SUMIFS(Captura_Obra!F:F, Captura_Obra!B:B, A34, Captura_Obra!A:A, ">="&C$5, Captura_Obra!A:A, "<="&(C$6+5)), SUMIFS(Captura_Obra!F:F, Captura_Obra!B:B, A34, Captura_Obra!A:A, ">="&C$5, Captura_Obra!A:A, "<="&(C$5+5)))) | C34: =B34*C$7 | P34: p | Q34: =A34 | R34: =VLOOKUP(Q34,Catalogos!$B$4:$C$18,2,FALSE) | S34: =SUMIFS(Solicitudes!$F:$F, Solicitudes!$B:$B, $Q34, Solicitudes!$C:$C, $B$12) | T34: 400 | U34: =SUMIFS(Solicitudes!$F:$F, Solicitudes!$B:$B, $Q34, Solicitudes!$C:$C, $B$13) | V34: 400 | W34: =SUMIFS(Solicitudes!$F:$F, Solicitudes!$B:$B, $Q34, Solicitudes!$C:$C, $B$14) | X34: 400 | Y34: =SUMIFS(Solicitudes!$F:$F, Solicitudes!$B:$B, $Q34, Solicitudes!$C:$C, $B$15) | Z34: 400 | AA34: =SUMIFS(Solicitudes!$F:$F, Solicitudes!$B:$B, $Q34, Solicitudes!$C:$C, $B$16) | AB34: 400 | AC34: =SUMIFS(Solicitudes!$F:$F, Solicitudes!$B:$B, $Q34, Solicitudes!$C:$C, $B$17) | AD34: =SUMIFS(Solicitudes!$F:$F, Solicitudes!$B:$B, $Q34, Solicitudes!$C:$C, ($B$17+1)) | AE34: =SUM(S34,U34,W34,Y34,AA34,AC34,) | AF34: =SUM(T34,V34,X34,Z34,AB34,AD34)
A35: Chamapa-Lechería | B35: =IF(C$8="Acumulado Histórico", SUMIFS(Captura_Obra!F:F, Captura_Obra!B:B, A35), IF(C$8="Rango de Fechas", SUMIFS(Captura_Obra!F:F, Captura_Obra!B:B, A35, Captura_Obra!A:A, ">="&C$5, Captura_Obra!A:A, "<="&(C$6+5)), SUMIFS(Captura_Obra!F:F, Captura_Obra!B:B, A35, Captura_Obra!A:A, ">="&C$5, Captura_Obra!A:A, "<="&(C$5+5)))) | C35: =B35*C$7 | P35: p | Q35: =A36 | R35: =VLOOKUP(Q35,Catalogos!$B$4:$C$18,2,FALSE) | S35: =SUMIFS(Solicitudes!$F:$F, Solicitudes!$B:$B, $Q35, Solicitudes!$C:$C, $B$12) | T35: 100 | U35: =SUMIFS(Solicitudes!$F:$F, Solicitudes!$B:$B, $Q35, Solicitudes!$C:$C, $B$13) | V35: 100 | W35: =SUMIFS(Solicitudes!$F:$F, Solicitudes!$B:$B, $Q35, Solicitudes!$C:$C, $B$14) | X35: 100 | Y35: =SUMIFS(Solicitudes!$F:$F, Solicitudes!$B:$B, $Q35, Solicitudes!$C:$C, $B$15) | Z35: 100 | AA35: =SUMIFS(Solicitudes!$F:$F, Solicitudes!$B:$B, $Q35, Solicitudes!$C:$C, $B$16) | AB35: 100 | AC35: =SUMIFS(Solicitudes!$F:$F, Solicitudes!$B:$B, $Q35, Solicitudes!$C:$C, $B$17) | AD35: =SUMIFS(Solicitudes!$F:$F, Solicitudes!$B:$B, $Q35, Solicitudes!$C:$C, ($B$17+1)) | AE35: =SUM(S35,U35,W35,Y35,AA35,AC35,) | AF35: =SUM(T35,V35,X35,Z35,AB35,AD35)
A36: Bacheo Toluca | B36: =IF(C$8="Acumulado Histórico", SUMIFS(Captura_Obra!F:F, Captura_Obra!B:B, A36), IF(C$8="Rango de Fechas", SUMIFS(Captura_Obra!F:F, Captura_Obra!B:B, A36, Captura_Obra!A:A, ">="&C$5, Captura_Obra!A:A, "<="&(C$6+5)), SUMIFS(Captura_Obra!F:F, Captura_Obra!B:B, A36, Captura_Obra!A:A, ">="&C$5, Captura_Obra!A:A, "<="&(C$5+5)))) | C36: =B36*C$7 | P36: p | Q36: =A37 | R36: =VLOOKUP(Q36,Catalogos!$B$4:$C$18,2,FALSE) | S36: =SUMIFS(Solicitudes!$F:$F, Solicitudes!$B:$B, $Q36, Solicitudes!$C:$C, $B$12) | T36: 0 | U36: =SUMIFS(Solicitudes!$F:$F, Solicitudes!$B:$B, $Q36, Solicitudes!$C:$C, $B$13) | V36: 300 | W36: =SUMIFS(Solicitudes!$F:$F, Solicitudes!$B:$B, $Q36, Solicitudes!$C:$C, $B$14) | X36: 1000 | Y36: =SUMIFS(Solicitudes!$F:$F, Solicitudes!$B:$B, $Q36, Solicitudes!$C:$C, $B$15) | Z36: 300 | AA36: =SUMIFS(Solicitudes!$F:$F, Solicitudes!$B:$B, $Q36, Solicitudes!$C:$C, $B$16) | AB36: 0 | AC36: =SUMIFS(Solicitudes!$F:$F, Solicitudes!$B:$B, $Q36, Solicitudes!$C:$C, $B$17) | AD36: =SUMIFS(Solicitudes!$F:$F, Solicitudes!$B:$B, $Q36, Solicitudes!$C:$C, ($B$17+1)) | AE36: =SUM(S36,U36,W36,Y36,AA36,AC36,) | AF36: =SUM(T36,V36,X36,Z36,AB36,AD36)
A37: Planta Asfalto Pegaso | B37: =IF(C$8="Acumulado Histórico", SUMIFS(Captura_Obra!F:F, Captura_Obra!B:B, A37), IF(C$8="Rango de Fechas", SUMIFS(Captura_Obra!F:F, Captura_Obra!B:B, A37, Captura_Obra!A:A, ">="&C$5, Captura_Obra!A:A, "<="&(C$6+5)), SUMIFS(Captura_Obra!F:F, Captura_Obra!B:B, A37, Captura_Obra!A:A, ">="&C$5, Captura_Obra!A:A, "<="&(C$5+5)))) | C37: =B37*C$7 | P37: h | Q37: =A38 | R37: =VLOOKUP(Q37,Catalogos!$B$4:$C$18,2,FALSE) | S37: =SUMIFS(Solicitudes!$F:$F, Solicitudes!$B:$B, $Q37, Solicitudes!$C:$C, $B$12) | T37: 500 | U37: =SUMIFS(Solicitudes!$F:$F, Solicitudes!$B:$B, $Q37, Solicitudes!$C:$C, $B$13) | V37: 500 | W37: =SUMIFS(Solicitudes!$F:$F, Solicitudes!$B:$B, $Q37, Solicitudes!$C:$C, $B$14) | X37: 500 | Y37: =SUMIFS(Solicitudes!$F:$F, Solicitudes!$B:$B, $Q37, Solicitudes!$C:$C, $B$15) | Z37: 500 | AA37: =SUMIFS(Solicitudes!$F:$F, Solicitudes!$B:$B, $Q37, Solicitudes!$C:$C, $B$16) | AB37: 500 | AC37: =SUMIFS(Solicitudes!$F:$F, Solicitudes!$B:$B, $Q37, Solicitudes!$C:$C, $B$17) | AD37: =SUMIFS(Solicitudes!$F:$F, Solicitudes!$B:$B, $Q37, Solicitudes!$C:$C, ($B$17+1)) | AE37: =SUM(S37,U37,W37,Y37,AA37,AC37,) | AF37: =SUM(T37,V37,X37,Z37,AB37,AD37)
A38: Planta Asflato Huixquilucan | B38: =IF(C$8="Acumulado Histórico", SUMIFS(Captura_Obra!F:F, Captura_Obra!B:B, A38), IF(C$8="Rango de Fechas", SUMIFS(Captura_Obra!F:F, Captura_Obra!B:B, A38, Captura_Obra!A:A, ">="&C$5, Captura_Obra!A:A, "<="&(C$6+5)), SUMIFS(Captura_Obra!F:F, Captura_Obra!B:B, A38, Captura_Obra!A:A, ">="&C$5, Captura_Obra!A:A, "<="&(C$5+5)))) | C38: =B38*C$7 | Q38: =A41 | S38: =SUM(S33:S37) | T38: =SUM(T33:T37) | U38: =SUM(U33:U37) | V38: =SUM(V33:V37) | W38: =SUM(W33:W37) | X38: =SUM(X33:X37) | Y38: =SUM(Y33:Y37) | Z38: =SUM(Z33:Z37) | ... AE38: =SUM(AE33:AE37) | AF38: =SUM(T38,V38,X38,Z38,AB38,AD38)
A39: Dragones | B39: =IF(C$8="Acumulado Histórico", SUMIFS(Captura_Obra!F:F, Captura_Obra!B:B, A39), IF(C$8="Rango de Fechas", SUMIFS(Captura_Obra!F:F, Captura_Obra!B:B, A39, Captura_Obra!A:A, ">="&C$5, Captura_Obra!A:A, "<="&(C$6+5)), SUMIFS(Captura_Obra!F:F, Captura_Obra!B:B, A39, Captura_Obra!A:A, ">="&C$5, Captura_Obra!A:A, "<="&(C$5+5)))) | C39: =B39*C$7
A40: Jalisco | B40: =IF(C$8="Acumulado Histórico", SUMIFS(Captura_Jalisco!G:G, Captura_Jalisco!B:B, "Salida"), IF(C$8="Rango de Fechas", SUMIFS(Captura_Jalisco!G:G, Captura_Jalisco!B:B, "Salida", Captura_Jalisco!A:A, ">="&C$5, Captura_Jalisco!A:A, "<="&(C$6+5)), SUMIFS(Captura_Jalisco!G:G, Captura_Jalisco!B:B, "Salida", Captura_Jalisco!A:A, ">="&C$5, Captura_Jalisco!A:A, "<="&(C$5+5)))) | C40: =B40*C$7
A41: TOTAL GENERAL | B41: =SUM(B33:B40) | C41: =SUM(C33:C40)
A43: RESUMEN DE CONSUMO SEMANAL POR OBRA (DETALLE HISTÓRICO POR SEMANA)
B44: Obra (Tabla Semanal): | C44: Jalisco
B45: Precio Diésel ($/L): | C45: 27
A47: Semana (Lunes) | B47: Saldo Inicial (Vales) | C47: Litros Despachados | D47: Costo/L ($) | E47: Costo Combustible ($) | F47: Gasolina | G47: Saldo Final (Vales) | H47: Ajuste semanal | I47: Litros de Disel Acumulado
A48: 46167 | B48: =IF(OR(C$44="Jalisco", C$44="Todas"), Captura_Jalisco!K5, "") | C48: =IF(C$44="Jalisco", SUMIFS(Captura_Jalisco!G:G, Captura_Jalisco!B:B, "Salida", Captura_Jalisco!A:A, ">="&A48, Captura_Jalisco!A:A, "<="&(A48+5)), IF(C$44="Todas", SUMIFS(Captura_Obra!F:F, Captura_Obra!A:A, ">="&A48, Captura_Obra!A:A, "<="&(A48+5)) + SUMIFS(Captura_Jalisco!G:G, Captura_Jalisco!B:B, "Salida", Captura_Jalisco!A:A, ">="&A48, Captura_Jalisco!A:A, "<="&(A48+5)), SUMIFS(Captura_Obra!F:F, Captura_Obra!B:B, C$44, Captura_Obra!A:A, ">="&A48, Captura_Obra!A:A, "<="&(A48+5)))) | D48: =C$45 | E48: =C48*D48 | F48: =IF(OR(C$44="Jalisco", C$44="Todas"), SUMIFS(Captura_Jalisco!$N$5:$N$250, Captura_Jalisco!$A$5:$A$250, ">="&A48, Captura_Jalisco!$A$5:$A$250, "<="&(A48+5)), 0) | G48: =IF(OR(C$44="Jalisco", C$44="Todas"), B48-E48-F48, "") | H48: =IF(OR(C$44="Jalisco", C$44="Todas"), SUMIFS(Captura_Jalisco!$M$5:$M$250, Captura_Jalisco!$A$5:$A$250, ">="&A48, Captura_Jalisco!$A$5:$A$250, "<="&(A48+5)), 0) | I48: =C48
A49: 46174 | B49: =IF(OR(C$44="Jalisco", C$44="Todas"), G48+H48, "") | C49: =IF(C$44="Jalisco", SUMIFS(Captura_Jalisco!G:G, Captura_Jalisco!B:B, "Salida", Captura_Jalisco!A:A, ">="&A49, Captura_Jalisco!A:A, "<="&(A49+5)), IF(C$44="Todas", SUMIFS(Captura_Obra!F:F, Captura_Obra!A:A, ">="&A49, Captura_Obra!A:A, "<="&(A49+5)) + SUMIFS(Captura_Jalisco!G:G, Captura_Jalisco!B:B, "Salida", Captura_Jalisco!A:A, ">="&A49, Captura_Jalisco!A:A, "<="&(A49+5)), SUMIFS(Captura_Obra!F:F, Captura_Obra!B:B, C$44, Captura_Obra!A:A, ">="&A49, Captura_Obra!A:A, "<="&(A49+5)))) | D49: =C$45 | E49: =C49*D49 | F49: =IF(OR(C$44="Jalisco", C$44="Todas"), SUMIFS(Captura_Jalisco!$N$5:$N$250, Captura_Jalisco!$A$5:$A$250, ">="&A49, Captura_Jalisco!$A$5:$A$250, "<="&(A49+5)), 0) | G49: =IF(OR(C$44="Jalisco", C$44="Todas"), B49-E49-F49, "") | H49: =IF(OR(C$44="Jalisco", C$44="Todas"), SUMIFS(Captura_Jalisco!$M$5:$M$250, Captura_Jalisco!$A$5:$A$250, ">="&A49, Captura_Jalisco!$A$5:$A$250, "<="&(A49+5)), 0) | I49: =I48+C49
A50: 46181 | B50: =IF(OR(C$44="Jalisco", C$44="Todas"), G49+H49, "") | C50: =IF(C$44="Jalisco", SUMIFS(Captura_Jalisco!G:G, Captura_Jalisco!B:B, "Salida", Captura_Jalisco!A:A, ">="&A50, Captura_Jalisco!A:A, "<="&(A50+5)), IF(C$44="Todas", SUMIFS(Captura_Obra!F:F, Captura_Obra!A:A, ">="&A50, Captura_Obra!A:A, "<="&(A50+5)) + SUMIFS(Captura_Jalisco!G:G, Captura_Jalisco!B:B, "Salida", Captura_Jalisco!A:A, ">="&A50, Captura_Jalisco!A:A, "<="&(A50+5)), SUMIFS(Captura_Obra!F:F, Captura_Obra!B:B, C$44, Captura_Obra!A:A, ">="&A50, Captura_Obra!A:A, "<="&(A50+5)))) | D50: =C$45 | E50: =C50*D50 | F50: =IF(OR(C$44="Jalisco", C$44="Todas"), SUMIFS(Captura_Jalisco!$N$5:$N$250, Captura_Jalisco!$A$5:$A$250, ">="&A50, Captura_Jalisco!$A$5:$A$250, "<="&(A50+5)), 0) | G50: =IF(OR(C$44="Jalisco", C$44="Todas"), B50-E50-F50, "") | H50: =IF(OR(C$44="Jalisco", C$44="Todas"), SUMIFS(Captura_Jalisco!$M$5:$M$250, Captura_Jalisco!$A$5:$A$250, ">="&A50, Captura_Jalisco!$A$5:$A$250, "<="&(A50+5)), 0) | I50: =I49+C50
A51: 46188 | B51: =IF(OR(C$44="Jalisco", C$44="Todas"), G50+H50, "") | C51: =IF(C$44="Jalisco", SUMIFS(Captura_Jalisco!G:G, Captura_Jalisco!B:B, "Salida", Captura_Jalisco!A:A, ">="&DATE(2026,6,15), Captura_Jalisco!A:A, "<="&DATE(2026,6,18)), IF(C$44="Todas", SUMIFS(Captura_Obra!F:F, Captura_Obra!A:A, ">="&DATE(2026,6,15), Captura_Obra!A:A, "<="&DATE(2026,6,18)) + SUMIFS(Captura_Jalisco!G:G, Captura_Jalisco!B:B, "Salida", Captura_Jalisco!A:A, ">="&DATE(2026,6,15), Captura_Jalisco!A:A, "<="&DATE(2026,6,18)), SUMIFS(Captura_Obra!F:F, Captura_Obra!B:B, C$44, Captura_Obra!A:A, ">="&DATE(2026,6,15), Captura_Obra!A:A, "<="&DATE(2026,6,18)))) | D51: =C$45 | E51: =C51*D51 | F51: =IF(OR(C$44="Jalisco", C$44="Todas"), SUMIFS(Captura_Jalisco!$N$5:$N$250, Captura_Jalisco!$A$5:$A$250, ">="&DATE(2026,6,15), Captura_Jalisco!$A$5:$A$250, "<="&DATE(2026,6,18)), 0) | G51: =IF(OR(C$44="Jalisco", C$44="Todas"), B51-E51-F51, "") | H51: =IF(OR(C$44="Jalisco", C$44="Todas"), SUMIFS(Captura_Jalisco!$M$5:$M$250, Captura_Jalisco!$A$5:$A$250, ">="&DATE(2026,6,15), Captura_Jalisco!$A$5:$A$250, "<="&DATE(2026,6,18)), 0) | I51: =I50+C51
A52: TOTAL ACUMULADO | B52: =IF(OR(C$44="Jalisco", C$44="Todas"), B48, "") | C52: =SUM(C48:C51) | E52: =SUM(E48:E51) | F52: =SUM(F48:F51) | G52: =IF(OR(C$44="Jalisco", C$44="Todas"), G51, "") | H52: =SUM(H48:H51) | I52: =I51
B54: RENDIMIENTO POR OBRA (TODAS LAS OBRAS)
A55: BALANCE DE INVENTARIO DIARIO (KARDEX) POR ALMACÉN
A56: FECHAS | C56: TANQUE PEGASO (LTS) | G56: MARIMBA M-01 (LTS)
A57: Día | B57: Fecha | C57: Inv. Inicial | D57: Entradas (Pipas) | E57: Salidas (Obra) | F57: Inv. Final | G57: Inv. Inicial | H57: Entradas (Gasolinera) | I57: Salidas (Obra) | J57: Inv. Final
A58: Lunes | B58: =$C$5+0 | C58: 6036.51 | D58: 0 | E58: =SUMIFS(Captura_Obra!$F:$F, Captura_Obra!$A:$A, B58, Captura_Obra!$C:$C, "*Pegaso*") | F58: =C58 + D58 - E58 | G58: =SUMIFS(Captura_Marimba_M01!$F:$F, Captura_Marimba_M01!$A:$A, "<"&B58) - SUMIFS(Captura_Obra!$F:$F, Captura_Obra!$A:$A, "<"&B58, Captura_Obra!$C:$C, "*Marimba*") | H58: =SUMIFS(Captura_Marimba_M01!$F:$F, Captura_Marimba_M01!$A:$A, B58) | I58: =SUMIFS(Captura_Obra!$F:$F, Captura_Obra!$A:$A, B58, Captura_Obra!$C:$C, "*Marimba*") | J58: =G58 + H58 - I58
A59: Martes | B59: =$C$5+1 | C59: =F58 | D59: =SUMIFS(Captura_Pegaso!$G:$G, Captura_Pegaso!$A:$A, B59) | E59: =SUMIFS(Captura_Obra!$F:$F, Captura_Obra!$A:$A, B59, Captura_Obra!$C:$C, "*Pegaso*") | F59: =C59 + D59 - E59 | G59: =J58 | H59: =SUMIFS(Captura_Marimba_M01!$F:$F, Captura_Marimba_M01!$A:$A, B59) | I59: =SUMIFS(Captura_Obra!$F:$F, Captura_Obra!$A:$A, B59, Captura_Obra!$C:$C, "*Marimba*") | J59: =G59 + H59 - I59
A60: Miércoles | B60: =$C$5+2 | C60: =F59 | D60: =SUMIFS(Captura_Pegaso!$G:$G, Captura_Pegaso!$A:$A, B60) | E60: =SUMIFS(Captura_Obra!$F:$F, Captura_Obra!$A:$A, B60, Captura_Obra!$C:$C, "*Pegaso*") | F60: =C60 + D60 - E60 | G60: =J59 | H60: =SUMIFS(Captura_Marimba_M01!$F:$F, Captura_Marimba_M01!$A:$A, B60) | I60: =SUMIFS(Captura_Obra!$F:$F, Captura_Obra!$A:$A, B60, Captura_Obra!$C:$C, "*Marimba*") | J60: =G60 + H60 - I60
A61: Jueves | B61: =$C$5+3 | C61: =F60 | D61: =SUMIFS(Captura_Pegaso!$G:$G, Captura_Pegaso!$A:$A, B61) | E61: =SUMIFS(Captura_Obra!$F:$F, Captura_Obra!$A:$A, B61, Captura_Obra!$C:$C, "*Pegaso*") | F61: =C61 + D61 - E61 | G61: =J60 | H61: =SUMIFS(Captura_Marimba_M01!$F:$F, Captura_Marimba_M01!$A:$A, B61) | I61: =SUMIFS(Captura_Obra!$F:$F, Captura_Obra!$A:$A, B61, Captura_Obra!$C:$C, "*Marimba*") | J61: =G61 + H61 - I61
A62: Viernes | B62: =$C$5+4 | C62: =F61 | D62: =SUMIFS(Captura_Pegaso!$G:$G, Captura_Pegaso!$A:$A, B62) | E62: =SUMIFS(Captura_Obra!$F:$F, Captura_Obra!$A:$A, B62, Captura_Obra!$C:$C, "*Pegaso*") | F62: =C62 + D62 - E62 | G62: =J61 | H62: =SUMIFS(Captura_Marimba_M01!$F:$F, Captura_Marimba_M01!$A:$A, B62) | I62: =SUMIFS(Captura_Obra!$F:$F, Captura_Obra!$A:$A, B62, Captura_Obra!$C:$C, "*Marimba*") | J62: =G62 + H62 - I62
A63: Sábado | B63: =$C$5+5 | C63: =F62 | D63: =SUMIFS(Captura_Pegaso!$G:$G, Captura_Pegaso!$A:$A, B63) | E63: =SUMIFS(Captura_Obra!$F:$F, Captura_Obra!$A:$A, B63, Captura_Obra!$C:$C, "*Pegaso*") | F63: =C63 + D63 - E63 | G63: =J62 | H63: =SUMIFS(Captura_Marimba_M01!$F:$F, Captura_Marimba_M01!$A:$A, B63) | I63: =SUMIFS(Captura_Obra!$F:$F, Captura_Obra!$A:$A, B63, Captura_Obra!$C:$C, "*Marimba*") | J63: =G63 + H63 - I63
A64: Domingo | B64: =$C$5+6 | C64: =F63 | D64: =SUMIFS(Captura_Pegaso!$G:$G, Captura_Pegaso!$A:$A, B64) | E64: =SUMIFS(Captura_Obra!$F:$F, Captura_Obra!$A:$A, B64, Captura_Obra!$C:$C, "*Pegaso*") | F64: =C64 + D64 - E64 | G64: =J63 | H64: =SUMIFS(Captura_Marimba_M01!$F:$F, Captura_Marimba_M01!$A:$A, B64) | I64: =SUMIFS(Captura_Obra!$F:$F, Captura_Obra!$A:$A, B64, Captura_Obra!$C:$C, "*Marimba*") | J64: =G64 + H64 - I64
A65: TOTAL SEMANAL | D65: =SUM(D58:D64) | E65: =SUM(E58:E64) | H65: =SUM(H58:H64) | I65: =SUM(I58:I64)

Sheet Conciliacion_Auditoria
A1: AUDITORÍA DE CONCILIACIÓN (CRUCE TRANSACCIONAL)
A3: Origen | B3: Folio Suministro (Pipa) | C3: Folio Recepción (Obra) | D3: Estatus | E3: Fecha | F3: Obra | G3: Máquina / Destino | H3: Lts Entregados | I3: Lts Recibidos | J3: Diferencia Lts | K3: Estatus
A4: =IF(Captura_Pegaso!A5="", "", "Pegaso") | B4: =IF(Captura_Pegaso!A5="", "", Captura_Pegaso!N5) | C4: =IF(Captura_Pegaso!A5="", "", IFERROR(LOOKUP(2, 1/((Captura_Obra!$A$5:$A$1000=E4)*(Captura_Obra!$B$5:$B$1000=F4)*(Captura_Obra!$D$5:$D$1000=G4)), Captura_Obra!$N$5:$N$1000), "No Reportado")) | D4: =IF(Captura_Pegaso!A5="", "", IF(J4=0, "✅ Cuadrado", IF(I4=0, "❌ Falta en Obra", "⚠️ Dif"))) | E4: =IF(Captura_Pegaso!A5="", "", Captura_Pegaso!A5) | F4: =IF(Captura_Pegaso!A5="", "", Captura_Pegaso!D5) | G4: =IF(Captura_Pegaso!A5="", "", Captura_Pegaso!E5) | H4: =IF(Captura_Pegaso!A5="", "", Captura_Pegaso!H5) | I4: =IF(Captura_Pegaso!A5="", "", SUMIFS(Captura_Obra!$F:$F, Captura_Obra!$A:$A, E4, Captura_Obra!$B:$B, F4, Captura_Obra!$D:$D, G4)) | J4: =IF(Captura_Pegaso!A5="", "", H4 - I4)
A5: =IF(Captura_Pegaso!A6="", "", "Pegaso") | B5: =IF(Captura_Pegaso!A6="", "", Captura_Pegaso!N6) | C5: =IF(Captura_Pegaso!A6="", "", IFERROR(LOOKUP(2, 1/((Captura_Obra!$A$5:$A$1000=E5)*(Captura_Obra!$B$5:$B$1000=F5)*(Captura_Obra!$D$5:$D$1000=G5)), Captura_Obra!$N$5:$N$1000), "No Reportado")) | D5: =IF(Captura_Pegaso!A6="", "", IF(J5=0, "✅ Cuadrado", IF(I5=0, "❌ Falta en Obra", "⚠️ Dif"))) | E5: =IF(Captura_Pegaso!A6="", "", Captura_Pegaso!A6) | F5: =IF(Captura_Pegaso!A6="", "", Captura_Pegaso!D6) | G5: =IF(Captura_Pegaso!A6="", "", Captura_Pegaso!E6) | H5: =IF(Captura_Pegaso!A6="", "", Captura_Pegaso!H6) | I5: =IF(Captura_Pegaso!A6="", "", SUMIFS(Captura_Obra!$F:$F, Captura_Obra!$A:$A, E5, Captura_Obra!$B:$B, F5, Captura_Obra!$D:$D, G5)) | J5: =IF(Captura_Pegaso!A6="", "", H5 - I5)
A6: =IF(Captura_Pegaso!A7="", "", "Pegaso") | B6: =IF(Captura_Pegaso!A7="", "", Captura_Pegaso!N7) | C6: =IF(Captura_Pegaso!A7="", "", IFERROR(LOOKUP(2, 1/((Captura_Obra!$A$5:$A$1000=E6)*(Captura_Obra!$B$5:$B$1000=F6)*(Captura_Obra!$D$5:$D$1000=G6)), Captura_Obra!$N$5:$N$1000), "No Reportado")) | D6: =IF(Captura_Pegaso!A7="", "", IF(J6=0, "✅ Cuadrado", IF(I6=0, "❌ Falta en Obra", "⚠️ Dif"))) | E6: =IF(Captura_Pegaso!A7="", "", Captura_Pegaso!A7) | F6: =IF(Captura_Pegaso!A7="", "", Captura_Pegaso!D7) | G6: =IF(Captura_Pegaso!A7="", "", Captura_Pegaso!E7) | H6: =IF(Captura_Pegaso!A7="", "", Captura_Pegaso!H7) | I6: =IF(Captura_Pegaso!A7="", "", SUMIFS(Captura_Obra!$F:$F, Captura_Obra!$A:$A, E6, Captura_Obra!$B:$B, F6, Captura_Obra!$D:$D, G6)) | J6: =IF(Captura_Pegaso!A7="", "", H6 - I6)
A7: =IF(Captura_Pegaso!A8="", "", "Pegaso") | B7: =IF(Captura_Pegaso!A8="", "", Captura_Pegaso!N8) | C7: =IF(Captura_Pegaso!A8="", "", IFERROR(LOOKUP(2, 1/((Captura_Obra!$A$5:$A$1000=E7)*(Captura_Obra!$B$5:$B$1000=F7)*(Captura_Obra!$D$5:$D$1000=G7)), Captura_Obra!$N$5:$N$1000), "No Reportado")) | D7: =IF(Captura_Pegaso!A8="", "", IF(J7=0, "✅ Cuadrado", IF(I7=0, "❌ Falta en Obra", "⚠️ Dif"))) | E7: =IF(Captura_Pegaso!A8="", "", Captura_Pegaso!A8) | F7: =IF(Captura_Pegaso!A8="", "", Captura_Pegaso!D8) | G7: =IF(Captura_Pegaso!A8="", "", Captura_Pegaso!E8) | H7: =IF(Captura_Pegaso!A8="", "", Captura_Pegaso!H8) | I7: =IF(Captura_Pegaso!A8="", "", SUMIFS(Captura_Obra!$F:$F, Captura_Obra!$A:$A, E7, Captura_Obra!$B:$B, F7, Captura_Obra!$D:$D, G7)) | J7: =IF(Captura_Pegaso!A8="", "", H7 - I7)
A8: =IF(Captura_Pegaso!A9="", "", "Pegaso") | B8: =IF(Captura_Pegaso!A9="", "", Captura_Pegaso!N9) | C8: =IF(Captura_Pegaso!A9="", "", IFERROR(LOOKUP(2, 1/((Captura_Obra!$A$5:$A$1000=E8)*(Captura_Obra!$B$5:$B$1000=F8)*(Captura_Obra!$D$5:$D$1000=G8)), Captura_Obra!$N$5:$N$1000), "No Reportado")) | D8: =IF(Captura_Pegaso!A9="", "", IF(J8=0, "✅ Cuadrado", IF(I8=0, "❌ Falta en Obra", "⚠️ Dif"))) | E8: =IF(Captura_Pegaso!A9="", "", Captura_Pegaso!A9) | F8: =IF(Captura_Pegaso!A9="", "", Captura_Pegaso!D9) | G8: =IF(Captura_Pegaso!A9="", "", Captura_Pegaso!E9) | H8: =IF(Captura_Pegaso!A9="", "", Captura_Pegaso!H9) | I8: =IF(Captura_Pegaso!A9="", "", SUMIFS(Captura_Obra!$F:$F, Captura_Obra!$A:$A, E8, Captura_Obra!$B:$B, F8, Captura_Obra!$D:$D, G8)) | J8: =IF(Captura_Pegaso!A9="", "", H8 - I8)
A9: =IF(Captura_Pegaso!A10="", "", "Pegaso") | B9: =IF(Captura_Pegaso!A10="", "", Captura_Pegaso!N10) | C9: =IF(Captura_Pegaso!A10="", "", IFERROR(LOOKUP(2, 1/((Captura_Obra!$A$5:$A$1000=E9)*(Captura_Obra!$B$5:$B$1000=F9)*(Captura_Obra!$D$5:$D$1000=G9)), Captura_Obra!$N$5:$N$1000), "No Reportado")) | D9: =IF(Captura_Pegaso!A10="", "", IF(J9=0, "✅ Cuadrado", IF(I9=0, "❌ Falta en Obra", "⚠️ Dif"))) | E9: =IF(Captura_Pegaso!A10="", "", Captura_Pegaso!A10) | F9: =IF(Captura_Pegaso!A10="", "", Captura_Pegaso!D10) | G9: =IF(Captura_Pegaso!A10="", "", Captura_Pegaso!E10) | H9: =IF(Captura_Pegaso!A10="", "", Captura_Pegaso!H10) | I9: =IF(Captura_Pegaso!A10="", "", SUMIFS(Captura_Obra!$F:$F, Captura_Obra!$A:$A, E9, Captura_Obra!$B:$B, F9, Captura_Obra!$D:$D, G9)) | J9: =IF(Captura_Pegaso!A10="", "", H9 - I9)
A10: =IF(Captura_Pegaso!A11="", "", "Pegaso") | B10: =IF(Captura_Pegaso!A11="", "", Captura_Pegaso!N11) | C10: =IF(Captura_Pegaso!A11="", "", IFERROR(LOOKUP(2, 1/((Captura_Obra!$A$5:$A$1000=E10)*(Captura_Obra!$B$5:$B$1000=F10)*(Captura_Obra!$D$5:$D$1000=G10)), Captura_Obra!$N$5:$N$1000), "No Reportado")) | D10: =IF(Captura_Pegaso!A11="", "", IF(J10=0, "✅ Cuadrado", IF(I10=0, "❌ Falta en Obra", "⚠️ Dif"))) | E10: =IF(Captura_Pegaso!A11="", "", Captura_Pegaso!A11) | F10: =IF(Captura_Pegaso!A11="", "", Captura_Pegaso!D11) | G10: =IF(Captura_Pegaso!A11="", "", Captura_Pegaso!E11) | H10: =IF(Captura_Pegaso!A11="", "", Captura_Pegaso!H11) | I10: =IF(Captura_Pegaso!A11="", "", SUMIFS(Captura_Obra!$F:$F, Captura_Obra!$A:$A, E10, Captura_Obra!$B:$B, F10, Captura_Obra!$D:$D, G10)) | J10: =IF(Captura_Pegaso!A11="", "", H10 - I10)
A11: =IF(Captura_Pegaso!A12="", "", "Pegaso") | B11: =IF(Captura_Pegaso!A12="", "", Captura_Pegaso!N12) | C11: =IF(Captura_Pegaso!A12="", "", IFERROR(LOOKUP(2, 1/((Captura_Obra!$A$5:$A$1000=E11)*(Captura_Obra!$B$5:$B$1000=F11)*(Captura_Obra!$D$5:$D$1000=G11)), Captura_Obra!$N$5:$N$1000), "No Reportado")) | D11: =IF(Captura_Pegaso!A12="", "", IF(J11=0, "✅ Cuadrado", IF(I11=0, "❌ Falta en Obra", "⚠️ Dif"))) | E11: =IF(Captura_Pegaso!A12="", "", Captura_Pegaso!A12) | F11: =IF(Captura_Pegaso!A12="", "", Captura_Pegaso!D12) | G11: =IF(Captura_Pegaso!A12="", "", Captura_Pegaso!E12) | H11: =IF(Captura_Pegaso!A12="", "", Captura_Pegaso!H12) | I11: =IF(Captura_Pegaso!A12="", "", SUMIFS(Captura_Obra!$F:$F, Captura_Obra!$A:$A, E11, Captura_Obra!$B:$B, F11, Captura_Obra!$D:$D, G11)) | J11: =IF(Captura_Pegaso!A12="", "", H11 - I11)
A12: =IF(Captura_Pegaso!A13="", "", "Pegaso") | B12: =IF(Captura_Pegaso!A13="", "", Captura_Pegaso!N13) | C12: =IF(Captura_Pegaso!A13="", "", IFERROR(LOOKUP(2, 1/((Captura_Obra!$A$5:$A$1000=E12)*(Captura_Obra!$B$5:$B$1000=F12)*(Captura_Obra!$D$5:$D$1000=G12)), Captura_Obra!$N$5:$N$1000), "No Reportado")) | D12: =IF(Captura_Pegaso!A13="", "", IF(J12=0, "✅ Cuadrado", IF(I12=0, "❌ Falta en Obra", "⚠️ Dif"))) | E12: =IF(Captura_Pegaso!A13="", "", Captura_Pegaso!A13) | F12: =IF(Captura_Pegaso!A13="", "", Captura_Pegaso!D13) | G12: =IF(Captura_Pegaso!A13="", "", Captura_Pegaso!E13) | H12: =IF(Captura_Pegaso!A13="", "", Captura_Pegaso!H13) | I12: =IF(Captura_Pegaso!A13="", "", SUMIFS(Captura_Obra!$F:$F, Captura_Obra!$A:$A, E12, Captura_Obra!$B:$B, F12, Captura_Obra!$D:$D, G12)) | J12: =IF(Captura_Pegaso!A13="", "", H12 - I12)
A13: =IF(Captura_Pegaso!A14="", "", "Pegaso") | B13: =IF(Captura_Pegaso!A14="", "", Captura_Pegaso!N14) | C13: =IF(Captura_Pegaso!A14="", "", IFERROR(LOOKUP(2, 1/((Captura_Obra!$A$5:$A$1000=E13)*(Captura_Obra!$B$5:$B$1000=F13)*(Captura_Obra!$D$5:$D$1000=G13)), Captura_Obra!$N$5:$N$1000), "No Reportado")) | D13: =IF(Captura_Pegaso!A14="", "", IF(J13=0, "✅ Cuadrado", IF(I13=0, "❌ Falta en Obra", "⚠️ Dif"))) | E13: =IF(Captura_Pegaso!A14="", "", Captura_Pegaso!A14) | F13: =IF(Captura_Pegaso!A14="", "", Captura_Pegaso!D14) | G13: =IF(Captura_Pegaso!A14="", "", Captura_Pegaso!E14) | H13: =IF(Captura_Pegaso!A14="", "", Captura_Pegaso!H14) | I13: =IF(Captura_Pegaso!A14="", "", SUMIFS(Captura_Obra!$F:$F, Captura_Obra!$A:$A, E13, Captura_Obra!$B:$B, F13, Captura_Obra!$D:$D, G13)) | J13: =IF(Captura_Pegaso!A14="", "", H13 - I13)
A14: =IF(Captura_Pegaso!A15="", "", "Pegaso") | B14: =IF(Captura_Pegaso!A15="", "", Captura_Pegaso!N15) | C14: =IF(Captura_Pegaso!A15="", "", IFERROR(LOOKUP(2, 1/((Captura_Obra!$A$5:$A$1000=E14)*(Captura_Obra!$B$5:$B$1000=F14)*(Captura_Obra!$D$5:$D$1000=G14)), Captura_Obra!$N$5:$N$1000), "No Reportado")) | D14: =IF(Captura_Pegaso!A15="", "", IF(J14=0, "✅ Cuadrado", IF(I14=0, "❌ Falta en Obra", "⚠️ Dif"))) | E14: =IF(Captura_Pegaso!A15="", "", Captura_Pegaso!A15) | F14: =IF(Captura_Pegaso!A15="", "", Captura_Pegaso!D15) | G14: =IF(Captura_Pegaso!A15="", "", Captura_Pegaso!E15) | H14: =IF(Captura_Pegaso!A15="", "", Captura_Pegaso!H15) | I14: =IF(Captura_Pegaso!A15="", "", SUMIFS(Captura_Obra!$F:$F, Captura_Obra!$A:$A, E14, Captura_Obra!$B:$B, F14, Captura_Obra!$D:$D, G14)) | J14: =IF(Captura_Pegaso!A15="", "", H14 - I14)
A15: =IF(Captura_Pegaso!A16="", "", "Pegaso") | B15: =IF(Captura_Pegaso!A16="", "", Captura_Pegaso!N16) | C15: =IF(Captura_Pegaso!A16="", "", IFERROR(LOOKUP(2, 1/((Captura_Obra!$A$5:$A$1000=E15)*(Captura_Obra!$B$5:$B$1000=F15)*(Captura_Obra!$D$5:$D$1000=G15)), Captura_Obra!$N$5:$N$1000), "No Reportado")) | D15: =IF(Captura_Pegaso!A16="", "", IF(J15=0, "✅ Cuadrado", IF(I15=0, "❌ Falta en Obra", "⚠️ Dif"))) | E15: =IF(Captura_Pegaso!A16="", "", Captura_Pegaso!A16) | F15: =IF(Captura_Pegaso!A16="", "", Captura_Pegaso!D16) | G15: =IF(Captura_Pegaso!A16="", "", Captura_Pegaso!E16) | H15: =IF(Captura_Pegaso!A16="", "", Captura_Pegaso!H16) | I15: =IF(Captura_Pegaso!A16="", "", SUMIFS(Captura_Obra!$F:$F, Captura_Obra!$A:$A, E15, Captura_Obra!$B:$B, F15, Captura_Obra!$D:$D, G15)) | J15: =IF(Captura_Pegaso!A16="", "", H15 - I15)
... A150: =IF(Captura_Pegaso!A151="", "", "Pegaso") | B150: =IF(Captura_Pegaso!A151="", "", Captura_Pegaso!N151) | C150: =IF(Captura_Pegaso!A151="", "", IFERROR(LOOKUP(2, 1/((Captura_Obra!$A$5:$A$1000=E150)*(Captura_Obra!$B$5:$B$1000=F150)*(Captura_Obra!$D$5:$D$1000=G150)), Captura_Obra!$N$5:$N$1000), "No Reportado")) | D150: =IF(Captura_Pegaso!A151="", "", IF(J150=0, "✅ Cuadrado", IF(I150=0, "❌ Falta en Obra", "⚠️ Dif"))) | E150: =IF(Captura_Pegaso!A151="", "", Captura_Pegaso!A151) | F150: =IF(Captura_Pegaso!A151="", "", Captura_Pegaso!D151) | G150: =IF(Captura_Pegaso!A151="", "", Captura_Pegaso!E151) | H150: =IF(Captura_Pegaso!A151="", "", Captura_Pegaso!H151) | I150: =IF(Captura_Pegaso!A151="", "", SUMIFS(Captura_Obra!$F:$F, Captura_Obra!$A:$A, E150, Captura_Obra!$B:$B, F150, Captura_Obra!$D:$D, G150)) | J150: =IF(Captura_Pegaso!A151="", "", H150 - I150)
A151: =IF(Captura_Marimba_M01!A5="", "", "Marimba") | B151: =IF(Captura_Marimba_M01!A5="", "", Captura_Marimba_M01!N5) | C151: =IF(Captura_Marimba_M01!A5="", "", IFERROR(LOOKUP(2, 1/((Captura_Obra!$A$5:$A$1000=E151)*(Captura_Obra!$B$5:$B$1000=F151)*(Captura_Obra!$D$5:$D$1000=G151)), Captura_Obra!$N$5:$N$1000), "No Reportado")) | D151: =IF(Captura_Marimba_M01!A5="", "", IF(J151=0, "✅ Cuadrado", IF(I151=0, "❌ Falta en Obra", "⚠️ Dif"))) | E151: =IF(Captura_Marimba_M01!A5="", "", Captura_Marimba_M01!A5) | F151: =IF(Captura_Marimba_M01!A5="", "", Captura_Marimba_M01!C5) | G151: =IF(Captura_Marimba_M01!A5="", "", Captura_Marimba_M01!D5) | H151: =IF(Captura_Marimba_M01!A5="", "", Captura_Marimba_M01!G5) | I151: =IF(Captura_Marimba_M01!A5="", "", SUMIFS(Captura_Obra!$F:$F, Captura_Obra!$A:$A, E151, Captura_Obra!$B:$B, F151, Captura_Obra!$D:$D, G151)) | J151: =IF(Captura_Marimba_M01!A5="", "", H151 - I151)
A152: =IF(Captura_Marimba_M01!A6="", "", "Marimba") | B152: =IF(Captura_Marimba_M01!A6="", "", Captura_Marimba_M01!N6) | C152: =IF(Captura_Marimba_M01!A6="", "", IFERROR(LOOKUP(2, 1/((Captura_Obra!$A$5:$A$1000=E152)*(Captura_Obra!$B$5:$B$1000=F152)*(Captura_Obra!$D$5:$D$1000=G152)), Captura_Obra!$N$5:$N$1000), "No Reportado")) | D152: =IF(Captura_Marimba_M01!A6="", "", IF(J152=0, "✅ Cuadrado", IF(I152=0, "❌ Falta en Obra", "⚠️ Dif"))) | E152: =IF(Captura_Marimba_M01!A6="", "", Captura_Marimba_M01!A6) | F152: =IF(Captura_Marimba_M01!A6="", "", Captura_Marimba_M01!C6) | G152: =IF(Captura_Marimba_M01!A6="", "", Captura_Marimba_M01!D6) | H152: =IF(Captura_Marimba_M01!A6="", "", Captura_Marimba_M01!G6) | I152: =IF(Captura_Marimba_M01!A6="", "", SUMIFS(Captura_Obra!$F:$F, Captura_Obra!$A:$A, E152, Captura_Obra!$B:$B, F152, Captura_Obra!$D:$D, G152)) | J152: =IF(Captura_Marimba_M01!A6="", "", H152 - I152)
A153: =IF(Captura_Marimba_M01!A7="", "", "Marimba") | B153: =IF(Captura_Marimba_M01!A7="", "", Captura_Marimba_M01!N7) | C153: =IF(Captura_Marimba_M01!A7="", "", IFERROR(LOOKUP(2, 1/((Captura_Obra!$A$5:$A$1000=E153)*(Captura_Obra!$B$5:$B$1000=F153)*(Captura_Obra!$D$5:$D$1000=G153)), Captura_Obra!$N$5:$N$1000), "No Reportado")) | D153: =IF(Captura_Marimba_M01!A7="", "", IF(J153=0, "✅ Cuadrado", IF(I153=0, "❌ Falta en Obra", "⚠️ Dif"))) | E153: =IF(Captura_Marimba_M01!A7="", "", Captura_Marimba_M01!A7) | F153: =IF(Captura_Marimba_M01!A7="", "", Captura_Marimba_M01!C7) | G153: =IF(Captura_Marimba_M01!A7="", "", Captura_Marimba_M01!D7) | H153: =IF(Captura_Marimba_M01!A7="", "", Captura_Marimba_M01!G7) | I153: =IF(Captura_Marimba_M01!A7="", "", SUMIFS(Captura_Obra!$F:$F, Captura_Obra!$A:$A, E153, Captura_Obra!$B:$B, F153, Captura_Obra!$D:$D, G153)) | J153: =IF(Captura_Marimba_M01!A7="", "", H153 - I153)
A154: =IF(Captura_Marimba_M01!A8="", "", "Marimba") | B154: =IF(Captura_Marimba_M01!A8="", "", Captura_Marimba_M01!N8) | C154: =IF(Captura_Marimba_M01!A8="", "", IFERROR(LOOKUP(2, 1/((Captura_Obra!$A$5:$A$1000=E154)*(Captura_Obra!$B$5:$B$1000=F154)*(Captura_Obra!$D$5:$D$1000=G154)), Captura_Obra!$N$5:$N$1000), "No Reportado")) | D154: =IF(Captura_Marimba_M01!A8="", "", IF(J154=0, "✅ Cuadrado", IF(I154=0, "❌ Falta en Obra", "⚠️ Dif"))) | E154: =IF(Captura_Marimba_M01!A8="", "", Captura_Marimba_M01!A8) | F154: =IF(Captura_Marimba_M01!A8="", "", Captura_Marimba_M01!C8) | G154: =IF(Captura_Marimba_M01!A8="", "", Captura_Marimba_M01!D8) | H154: =IF(Captura_Marimba_M01!A8="", "", Captura_Marimba_M01!G8) | I154: =IF(Captura_Marimba_M01!A8="", "", SUMIFS(Captura_Obra!$F:$F, Captura_Obra!$A:$A, E154, Captura_Obra!$B:$B, F154, Captura_Obra!$D:$D, G154)) | J154: =IF(Captura_Marimba_M01!A8="", "", H154 - I154)
A155: =IF(Captura_Marimba_M01!A9="", "", "Marimba") | B155: =IF(Captura_Marimba_M01!A9="", "", Captura_Marimba_M01!N9) | C155: =IF(Captura_Marimba_M01!A9="", "", IFERROR(LOOKUP(2, 1/((Captura_Obra!$A$5:$A$1000=E155)*(Captura_Obra!$B$5:$B$1000=F155)*(Captura_Obra!$D$5:$D$1000=G155)), Captura_Obra!$N$5:$N$1000), "No Reportado")) | D155: =IF(Captura_Marimba_M01!A9="", "", IF(J155=0, "✅ Cuadrado", IF(I155=0, "❌ Falta en Obra", "⚠️ Dif"))) | E155: =IF(Captura_Marimba_M01!A9="", "", Captura_Marimba_M01!A9) | F155: =IF(Captura_Marimba_M01!A9="", "", Captura_Marimba_M01!C9) | G155: =IF(Captura_Marimba_M01!A9="", "", Captura_Marimba_M01!D9) | H155: =IF(Captura_Marimba_M01!A9="", "", Captura_Marimba_M01!G9) | I155: =IF(Captura_Marimba_M01!A9="", "", SUMIFS(Captura_Obra!$F:$F, Captura_Obra!$A:$A, E155, Captura_Obra!$B:$B, F155, Captura_Obra!$D:$D, G155)) | J155: =IF(Captura_Marimba_M01!A9="", "", H155 - I155)
A156: =IF(Captura_Marimba_M01!A10="", "", "Marimba") | B156: =IF(Captura_Marimba_M01!A10="", "", Captura_Marimba_M01!N10) | C156: =IF(Captura_Marimba_M01!A10="", "", IFERROR(LOOKUP(2, 1/((Captura_Obra!$A$5:$A$1000=E156)*(Captura_Obra!$B$5:$B$1000=F156)*(Captura_Obra!$D$5:$D$1000=G156)), Captura_Obra!$N$5:$N$1000), "No Reportado")) | D156: =IF(Captura_Marimba_M01!A10="", "", IF(J156=0, "✅ Cuadrado", IF(I156=0, "❌ Falta en Obra", "⚠️ Dif"))) | E156: =IF(Captura_Marimba_M01!A10="", "", Captura_Marimba_M01!A10) | F156: =IF(Captura_Marimba_M01!A10="", "", Captura_Marimba_M01!C10) | G156: =IF(Captura_Marimba_M01!A10="", "", Captura_Marimba_M01!D10) | H156: =IF(Captura_Marimba_M01!A10="", "", Captura_Marimba_M01!G10) | I156: =IF(Captura_Marimba_M01!A10="", "", SUMIFS(Captura_Obra!$F:$F, Captura_Obra!$A:$A, E156, Captura_Obra!$B:$B, F156, Captura_Obra!$D:$D, G156)) | J156: =IF(Captura_Marimba_M01!A10="", "", H156 - I156)
A157: =IF(Captura_Marimba_M01!A11="", "", "Marimba") | B157: =IF(Captura_Marimba_M01!A11="", "", Captura_Marimba_M01!N11) | C157: =IF(Captura_Marimba_M01!A11="", "", IFERROR(LOOKUP(2, 1/((Captura_Obra!$A$5:$A$1000=E157)*(Captura_Obra!$B$5:$B$1000=F157)*(Captura_Obra!$D$5:$D$1000=G157)), Captura_Obra!$N$5:$N$1000), "No Reportado")) | D157: =IF(Captura_Marimba_M01!A11="", "", IF(J157=0, "✅ Cuadrado", IF(I157=0, "❌ Falta en Obra", "⚠️ Dif"))) | E157: =IF(Captura_Marimba_M01!A11="", "", Captura_Marimba_M01!A11) | F157: =IF(Captura_Marimba_M01!A11="", "", Captura_Marimba_M01!C11) | G157: =IF(Captura_Marimba_M01!A11="", "", Captura_Marimba_M01!D11) | H157: =IF(Captura_Marimba_M01!A11="", "", Captura_Marimba_M01!G11) | I157: =IF(Captura_Marimba_M01!A11="", "", SUMIFS(Captura_Obra!$F:$F, Captura_Obra!$A:$A, E157, Captura_Obra!$B:$B, F157, Captura_Obra!$D:$D, G157)) | J157: =IF(Captura_Marimba_M01!A11="", "", H157 - I157)
A158: =IF(Captura_Marimba_M01!A12="", "", "Marimba") | B158: =IF(Captura_Marimba_M01!A12="", "", Captura_Marimba_M01!N12) | C158: =IF(Captura_Marimba_M01!A12="", "", IFERROR(LOOKUP(2, 1/((Captura_Obra!$A$5:$A$1000=E158)*(Captura_Obra!$B$5:$B$1000=F158)*(Captura_Obra!$D$5:$D$1000=G158)), Captura_Obra!$N$5:$N$1000), "No Reportado")) | D158: =IF(Captura_Marimba_M01!A12="", "", IF(J158=0, "✅ Cuadrado", IF(I158=0, "❌ Falta en Obra", "⚠️ Dif"))) | E158: =IF(Captura_Marimba_M01!A12="", "", Captura_Marimba_M01!A12) | F158: =IF(Captura_Marimba_M01!A12="", "", Captura_Marimba_M01!C12) | G158: =IF(Captura_Marimba_M01!A12="", "", Captura_Marimba_M01!D12) | H158: =IF(Captura_Marimba_M01!A12="", "", Captura_Marimba_M01!G12) | I158: =IF(Captura_Marimba_M01!A12="", "", SUMIFS(Captura_Obra!$F:$F, Captura_Obra!$A:$A, E158, Captura_Obra!$B:$B, F158, Captura_Obra!$D:$D, G158)) | J158: =IF(Captura_Marimba_M01!A12="", "", H158 - I158)
A159: =IF(Captura_Marimba_M01!A13="", "", "Marimba") | B159: =IF(Captura_Marimba_M01!A13="", "", Captura_Marimba_M01!N13) | C159: =IF(Captura_Marimba_M01!A13="", "", IFERROR(LOOKUP(2, 1/((Captura_Obra!$A$5:$A$1000=E159)*(Captura_Obra!$B$5:$B$1000=F159)*(Captura_Obra!$D$5:$D$1000=G159)), Captura_Obra!$N$5:$N$1000), "No Reportado")) | D159: =IF(Captura_Marimba_M01!A13="", "", IF(J159=0, "✅ Cuadrado", IF(I159=0, "❌ Falta en Obra", "⚠️ Dif"))) | E159: =IF(Captura_Marimba_M01!A13="", "", Captura_Marimba_M01!A13) | F159: =IF(Captura_Marimba_M01!A13="", "", Captura_Marimba_M01!C13) | G159: =IF(Captura_Marimba_M01!A13="", "", Captura_Marimba_M01!D13) | H159: =IF(Captura_Marimba_M01!A13="", "", Captura_Marimba_M01!G13) | I159: =IF(Captura_Marimba_M01!A13="", "", SUMIFS(Captura_Obra!$F:$F, Captura_Obra!$A:$A, E159, Captura_Obra!$B:$B, F159, Captura_Obra!$D:$D, G159)) | J159: =IF(Captura_Marimba_M01!A13="", "", H159 - I159)
A160: =IF(Captura_Marimba_M01!A14="", "", "Marimba") | B160: =IF(Captura_Marimba_M01!A14="", "", Captura_Marimba_M01!N14) | C160: =IF(Captura_Marimba_M01!A14="", "", IFERROR(LOOKUP(2, 1/((Captura_Obra!$A$5:$A$1000=E160)*(Captura_Obra!$B$5:$B$1000=F160)*(Captura_Obra!$D$5:$D$1000=G160)), Captura_Obra!$N$5:$N$1000), "No Reportado")) | D160: =IF(Captura_Marimba_M01!A14="", "", IF(J160=0, "✅ Cuadrado", IF(I160=0, "❌ Falta en Obra", "⚠️ Dif"))) | E160: =IF(Captura_Marimba_M01!A14="", "", Captura_Marimba_M01!A14) | F160: =IF(Captura_Marimba_M01!A14="", "", Captura_Marimba_M01!C14) | G160: =IF(Captura_Marimba_M01!A14="", "", Captura_Marimba_M01!D14) | H160: =IF(Captura_Marimba_M01!A14="", "", Captura_Marimba_M01!G14) | I160: =IF(Captura_Marimba_M01!A14="", "", SUMIFS(Captura_Obra!$F:$F, Captura_Obra!$A:$A, E160, Captura_Obra!$B:$B, F160, Captura_Obra!$D:$D, G160)) | J160: =IF(Captura_Marimba_M01!A14="", "", H160 - I160)
A161: =IF(Captura_Marimba_M01!A15="", "", "Marimba") | B161: =IF(Captura_Marimba_M01!A15="", "", Captura_Marimba_M01!N15) | C161: =IF(Captura_Marimba_M01!A15="", "", IFERROR(LOOKUP(2, 1/((Captura_Obra!$A$5:$A$1000=E161)*(Captura_Obra!$B$5:$B$1000=F161)*(Captura_Obra!$D$5:$D$1000=G161)), Captura_Obra!$N$5:$N$1000), "No Reportado")) | D161: =IF(Captura_Marimba_M01!A15="", "", IF(J161=0, "✅ Cuadrado", IF(I161=0, "❌ Falta en Obra", "⚠️ Dif"))) | E161: =IF(Captura_Marimba_M01!A15="", "", Captura_Marimba_M01!A15) | F161: =IF(Captura_Marimba_M01!A15="", "", Captura_Marimba_M01!C15) | G161: =IF(Captura_Marimba_M01!A15="", "", Captura_Marimba_M01!D15) | H161: =IF(Captura_Marimba_M01!A15="", "", Captura_Marimba_M01!G15) | I161: =IF(Captura_Marimba_M01!A15="", "", SUMIFS(Captura_Obra!$F:$F, Captura_Obra!$A:$A, E161, Captura_Obra!$B:$B, F161, Captura_Obra!$D:$D, G161)) | J161: =IF(Captura_Marimba_M01!A15="", "", H161 - I161)
A162: =IF(Captura_Marimba_M01!A16="", "", "Marimba") | B162: =IF(Captura_Marimba_M01!A16="", "", Captura_Marimba_M01!N16) | C162: =IF(Captura_Marimba_M01!A16="", "", IFERROR(LOOKUP(2, 1/((Captura_Obra!$A$5:$A$1000=E162)*(Captura_Obra!$B$5:$B$1000=F162)*(Captura_Obra!$D$5:$D$1000=G162)), Captura_Obra!$N$5:$N$1000), "No Reportado")) | D162: =IF(Captura_Marimba_M01!A16="", "", IF(J162=0, "✅ Cuadrado", IF(I162=0, "❌ Falta en Obra", "⚠️ Dif"))) | E162: =IF(Captura_Marimba_M01!A16="", "", Captura_Marimba_M01!A16) | F162: =IF(Captura_Marimba_M01!A16="", "", Captura_Marimba_M01!C16) | G162: =IF(Captura_Marimba_M01!A16="", "", Captura_Marimba_M01!D16) | H162: =IF(Captura_Marimba_M01!A16="", "", Captura_Marimba_M01!G16) | I162: =IF(Captura_Marimba_M01!A16="", "", SUMIFS(Captura_Obra!$F:$F, Captura_Obra!$A:$A, E162, Captura_Obra!$B:$B, F162, Captura_Obra!$D:$D, G162)) | J162: =IF(Captura_Marimba_M01!A16="", "", H162 - I162)
... A300: =IF(Captura_Marimba_M01!A154="", "", "Marimba") | B300: =IF(Captura_Marimba_M01!A154="", "", Captura_Marimba_M01!N154) | C300: =IF(Captura_Marimba_M01!A154="", "", IFERROR(LOOKUP(2, 1/((Captura_Obra!$A$5:$A$1000=E300)*(Captura_Obra!$B$5:$B$1000=F300)*(Captura_Obra!$D$5:$D$1000=G300)), Captura_Obra!$N$5:$N$1000), "No Reportado")) | D300: =IF(Captura_Marimba_M01!A154="", "", IF(J300=0, "✅ Cuadrado", IF(I300=0, "❌ Falta en Obra", "⚠️ Dif"))) | E300: =IF(Captura_Marimba_M01!A154="", "", Captura_Marimba_M01!A154) | F300: =IF(Captura_Marimba_M01!A154="", "", Captura_Marimba_M01!C154) | G300: =IF(Captura_Marimba_M01!A154="", "", Captura_Marimba_M01!D154) | H300: =IF(Captura_Marimba_M01!A154="", "", Captura_Marimba_M01!G154) | I300: =IF(Captura_Marimba_M01!A154="", "", SUMIFS(Captura_Obra!$F:$F, Captura_Obra!$A:$A, E300, Captura_Obra!$B:$B, F300, Captura_Obra!$D:$D, G300)) | J300: =IF(Captura_Marimba_M01!A154="", "", H300 - I300)
A301: =IF(OR(Captura_Obra!A5="", (SUMIFS(Captura_Pegaso!$H:$H, Captura_Pegaso!$A:$A, Captura_Obra!A5, Captura_Pegaso!$D:$D, Captura_Obra!B5, Captura_Pegaso!$E:$E, Captura_Obra!D5) + SUMIFS(Captura_Marimba_M01!$G:$G, Captura_Marimba_M01!$A:$A, Captura_Obra!A5, Captura_Marimba_M01!$C:$C, Captura_Obra!B5, Captura_Marimba_M01!$D:$D, Captura_Obra!D5))>0), "", "Huérfano Obra") | B301: =IF(OR(Captura_Obra!A5="", (SUMIFS(Captura_Pegaso!$H:$H, Captura_Pegaso!$A:$A, Captura_Obra!A5, Captura_Pegaso!$D:$D, Captura_Obra!B5, Captura_Pegaso!$E:$E, Captura_Obra!D5) + SUMIFS(Captura_Marimba_M01!$G:$G, Captura_Marimba_M01!$A:$A, Captura_Obra!A5, Captura_Marimba_M01!$C:$C, Captura_Obra!B5, Captura_Marimba_M01!$D:$D, Captura_Obra!D5))>0), "", "No Reportado") | C301: =IF(OR(Captura_Obra!A5="", (SUMIFS(Captura_Pegaso!$H:$H, Captura_Pegaso!$A:$A, Captura_Obra!A5, Captura_Pegaso!$D:$D, Captura_Obra!B5, Captura_Pegaso!$E:$E, Captura_Obra!D5) + SUMIFS(Captura_Marimba_M01!$G:$G, Captura_Marimba_M01!$A:$A, Captura_Obra!A5, Captura_Marimba_M01!$C:$C, Captura_Obra!B5, Captura_Marimba_M01!$D:$D, Captura_Obra!D5))>0), "", Captura_Obra!N5) | D301: =IF(OR(Captura_Obra!A5="", (SUMIFS(Captura_Pegaso!$H:$H, Captura_Pegaso!$A:$A, Captura_Obra!A5, Captura_Pegaso!$D:$D, Captura_Obra!B5, Captura_Pegaso!$E:$E, Captura_Obra!D5) + SUMIFS(Captura_Marimba_M01!$G:$G, Captura_Marimba_M01!$A:$A, Captura_Obra!A5, Captura_Marimba_M01!$C:$C, Captura_Obra!B5, Captura_Marimba_M01!$D:$D, Captura_Obra!D5))>0), "", "❌ Falta en Pipa") | E301: =IF(OR(Captura_Obra!A5="", (SUMIFS(Captura_Pegaso!$H:$H, Captura_Pegaso!$A:$A, Captura_Obra!A5, Captura_Pegaso!$D:$D, Captura_Obra!B5, Captura_Pegaso!$E:$E, Captura_Obra!D5) + SUMIFS(Captura_Marimba_M01!$G:$G, Captura_Marimba_M01!$A:$A, Captura_Obra!A5, Captura_Marimba_M01!$C:$C, Captura_Obra!B5, Captura_Marimba_M01!$D:$D, Captura_Obra!D5))>0), "", Captura_Obra!A5) | F301: =IF(OR(Captura_Obra!A5="", (SUMIFS(Captura_Pegaso!$H:$H, Captura_Pegaso!$A:$A, Captura_Obra!A5, Captura_Pegaso!$D:$D, Captura_Obra!B5, Captura_Pegaso!$E:$E, Captura_Obra!D5) + SUMIFS(Captura_Marimba_M01!$G:$G, Captura_Marimba_M01!$A:$A, Captura_Obra!A5, Captura_Marimba_M01!$C:$C, Captura_Obra!B5, Captura_Marimba_M01!$D:$D, Captura_Obra!D5))>0), "", Captura_Obra!B5) | G301: =IF(OR(Captura_Obra!A5="", (SUMIFS(Captura_Pegaso!$H:$H, Captura_Pegaso!$A:$A, Captura_Obra!A5, Captura_Pegaso!$D:$D, Captura_Obra!B5, Captura_Pegaso!$E:$E, Captura_Obra!D5) + SUMIFS(Captura_Marimba_M01!$G:$G, Captura_Marimba_M01!$A:$A, Captura_Obra!A5, Captura_Marimba_M01!$C:$C, Captura_Obra!B5, Captura_Marimba_M01!$D:$D, Captura_Obra!D5))>0), "", Captura_Obra!D5) | H301: =IF(OR(Captura_Obra!A5="", (SUMIFS(Captura_Pegaso!$H:$H, Captura_Pegaso!$A:$A, Captura_Obra!A5, Captura_Pegaso!$D:$D, Captura_Obra!B5, Captura_Pegaso!$E:$E, Captura_Obra!D5) + SUMIFS(Captura_Marimba_M01!$G:$G, Captura_Marimba_M01!$A:$A, Captura_Obra!A5, Captura_Marimba_M01!$C:$C, Captura_Obra!B5, Captura_Marimba_M01!$D:$D, Captura_Obra!D5))>0), "", 0) | I301: =IF(OR(Captura_Obra!A5="", (SUMIFS(Captura_Pegaso!$H:$H, Captura_Pegaso!$A:$A, Captura_Obra!A5, Captura_Pegaso!$D:$D, Captura_Obra!B5, Captura_Pegaso!$E:$E, Captura_Obra!D5) + SUMIFS(Captura_Marimba_M01!$G:$G, Captura_Marimba_M01!$A:$A, Captura_Obra!A5, Captura_Marimba_M01!$C:$C, Captura_Obra!B5, Captura_Marimba_M01!$D:$D, Captura_Obra!D5))>0), "", Captura_Obra!F5) | J301: =IF(OR(Captura_Obra!A5="", (SUMIFS(Captura_Pegaso!$H:$H, Captura_Pegaso!$A:$A, Captura_Obra!A5, Captura_Pegaso!$D:$D, Captura_Obra!B5, Captura_Pegaso!$E:$E, Captura_Obra!D5) + SUMIFS(Captura_Marimba_M01!$G:$G, Captura_Marimba_M01!$A:$A, Captura_Obra!A5, Captura_Marimba_M01!$C:$C, Captura_Obra!B5, Captura_Marimba_M01!$D:$D, Captura_Obra!D5))>0), "", H301 - I301)
A302: =IF(OR(Captura_Obra!A6="", (SUMIFS(Captura_Pegaso!$H:$H, Captura_Pegaso!$A:$A, Captura_Obra!A6, Captura_Pegaso!$D:$D, Captura_Obra!B6, Captura_Pegaso!$E:$E, Captura_Obra!D6) + SUMIFS(Captura_Marimba_M01!$G:$G, Captura_Marimba_M01!$A:$A, Captura_Obra!A6, Captura_Marimba_M01!$C:$C, Captura_Obra!B6, Captura_Marimba_M01!$D:$D, Captura_Obra!D6))>0), "", "Huérfano Obra") | B302: =IF(OR(Captura_Obra!A6="", (SUMIFS(Captura_Pegaso!$H:$H, Captura_Pegaso!$A:$A, Captura_Obra!A6, Captura_Pegaso!$D:$D, Captura_Obra!B6, Captura_Pegaso!$E:$E, Captura_Obra!D6) + SUMIFS(Captura_Marimba_M01!$G:$G, Captura_Marimba_M01!$A:$A, Captura_Obra!A6, Captura_Marimba_M01!$C:$C, Captura_Obra!B6, Captura_Marimba_M01!$D:$D, Captura_Obra!D6))>0), "", "No Reportado") | C302: =IF(OR(Captura_Obra!A6="", (SUMIFS(Captura_Pegaso!$H:$H, Captura_Pegaso!$A:$A, Captura_Obra!A6, Captura_Pegaso!$D:$D, Captura_Obra!B6, Captura_Pegaso!$E:$E, Captura_Obra!D6) + SUMIFS(Captura_Marimba_M01!$G:$G, Captura_Marimba_M01!$A:$A, Captura_Obra!A6, Captura_Marimba_M01!$C:$C, Captura_Obra!B6, Captura_Marimba_M01!$D:$D, Captura_Obra!D6))>0), "", Captura_Obra!N6) | D302: =IF(OR(Captura_Obra!A6="", (SUMIFS(Captura_Pegaso!$H:$H, Captura_Pegaso!$A:$A, Captura_Obra!A6, Captura_Pegaso!$D:$D, Captura_Obra!B6, Captura_Pegaso!$E:$E, Captura_Obra!D6) + SUMIFS(Captura_Marimba_M01!$G:$G, Captura_Marimba_M01!$A:$A, Captura_Obra!A6, Captura_Marimba_M01!$C:$C, Captura_Obra!B6, Captura_Marimba_M01!$D:$D, Captura_Obra!D6))>0), "", "❌ Falta en Pipa") | E302: =IF(OR(Captura_Obra!A6="", (SUMIFS(Captura_Pegaso!$H:$H, Captura_Pegaso!$A:$A, Captura_Obra!A6, Captura_Pegaso!$D:$D, Captura_Obra!B6, Captura_Pegaso!$E:$E, Captura_Obra!D6) + SUMIFS(Captura_Marimba_M01!$G:$G, Captura_Marimba_M01!$A:$A, Captura_Obra!A6, Captura_Marimba_M01!$C:$C, Captura_Obra!B6, Captura_Marimba_M01!$D:$D, Captura_Obra!D6))>0), "", Captura_Obra!A6) | F302: =IF(OR(Captura_Obra!A6="", (SUMIFS(Captura_Pegaso!$H:$H, Captura_Pegaso!$A:$A, Captura_Obra!A6, Captura_Pegaso!$D:$D, Captura_Obra!B6, Captura_Pegaso!$E:$E, Captura_Obra!D6) + SUMIFS(Captura_Marimba_M01!$G:$G, Captura_Marimba_M01!$A:$A, Captura_Obra!A6, Captura_Marimba_M01!$C:$C, Captura_Obra!B6, Captura_Marimba_M01!$D:$D, Captura_Obra!D6))>0), "", Captura_Obra!B6) | G302: =IF(OR(Captura_Obra!A6="", (SUMIFS(Captura_Pegaso!$H:$H, Captura_Pegaso!$A:$A, Captura_Obra!A6, Captura_Pegaso!$D:$D, Captura_Obra!B6, Captura_Pegaso!$E:$E, Captura_Obra!D6) + SUMIFS(Captura_Marimba_M01!$G:$G, Captura_Marimba_M01!$A:$A, Captura_Obra!A6, Captura_Marimba_M01!$C:$C, Captura_Obra!B6, Captura_Marimba_M01!$D:$D, Captura_Obra!D6))>0), "", Captura_Obra!D6) | H302: =IF(OR(Captura_Obra!A6="", (SUMIFS(Captura_Pegaso!$H:$H, Captura_Pegaso!$A:$A, Captura_Obra!A6, Captura_Pegaso!$D:$D, Captura_Obra!B6, Captura_Pegaso!$E:$E, Captura_Obra!D6) + SUMIFS(Captura_Marimba_M01!$G:$G, Captura_Marimba_M01!$A:$A, Captura_Obra!A6, Captura_Marimba_M01!$C:$C, Captura_Obra!B6, Captura_Marimba_M01!$D:$D, Captura_Obra!D6))>0), "", 0) | I302: =IF(OR(Captura_Obra!A6="", (SUMIFS(Captura_Pegaso!$H:$H, Captura_Pegaso!$A:$A, Captura_Obra!A6, Captura_Pegaso!$D:$D, Captura_Obra!B6, Captura_Pegaso!$E:$E, Captura_Obra!D6) + SUMIFS(Captura_Marimba_M01!$G:$G, Captura_Marimba_M01!$A:$A, Captura_Obra!A6, Captura_Marimba_M01!$C:$C, Captura_Obra!B6, Captura_Marimba_M01!$D:$D, Captura_Obra!D6))>0), "", Captura_Obra!F6) | J302: =IF(OR(Captura_Obra!A6="", (SUMIFS(Captura_Pegaso!$H:$H, Captura_Pegaso!$A:$A, Captura_Obra!A6, Captura_Pegaso!$D:$D, Captura_Obra!B6, Captura_Pegaso!$E:$E, Captura_Obra!D6) + SUMIFS(Captura_Marimba_M01!$G:$G, Captura_Marimba_M01!$A:$A, Captura_Obra!A6, Captura_Marimba_M01!$C:$C, Captura_Obra!B6, Captura_Marimba_M01!$D:$D, Captura_Obra!D6))>0), "", H302 - I302)
A303: =IF(OR(Captura_Obra!A7="", (SUMIFS(Captura_Pegaso!$H:$H, Captura_Pegaso!$A:$A, Captura_Obra!A7, Captura_Pegaso!$D:$D, Captura_Obra!B7, Captura_Pegaso!$E:$E, Captura_Obra!D7) + SUMIFS(Captura_Marimba_M01!$G:$G, Captura_Marimba_M01!$A:$A, Captura_Obra!A7, Captura_Marimba_M01!$C:$C, Captura_Obra!B7, Captura_Marimba_M01!$D:$D, Captura_Obra!D7))>0), "", "Huérfano Obra") | B303: =IF(OR(Captura_Obra!A7="", (SUMIFS(Captura_Pegaso!$H:$H, Captura_Pegaso!$A:$A, Captura_Obra!A7, Captura_Pegaso!$D:$D, Captura_Obra!B7, Captura_Pegaso!$E:$E, Captura_Obra!D7) + SUMIFS(Captura_Marimba_M01!$G:$G, Captura_Marimba_M01!$A:$A, Captura_Obra!A7, Captura_Marimba_M01!$C:$C, Captura_Obra!B7, Captura_Marimba_M01!$D:$D, Captura_Obra!D7))>0), "", "No Reportado") | C303: =IF(OR(Captura_Obra!A7="", (SUMIFS(Captura_Pegaso!$H:$H, Captura_Pegaso!$A:$A, Captura_Obra!A7, Captura_Pegaso!$D:$D, Captura_Obra!B7, Captura_Pegaso!$E:$E, Captura_Obra!D7) + SUMIFS(Captura_Marimba_M01!$G:$G, Captura_Marimba_M01!$A:$A, Captura_Obra!A7, Captura_Marimba_M01!$C:$C, Captura_Obra!B7, Captura_Marimba_M01!$D:$D, Captura_Obra!D7))>0), "", Captura_Obra!N7) | D303: =IF(OR(Captura_Obra!A7="", (SUMIFS(Captura_Pegaso!$H:$H, Captura_Pegaso!$A:$A, Captura_Obra!A7, Captura_Pegaso!$D:$D, Captura_Obra!B7, Captura_Pegaso!$E:$E, Captura_Obra!D7) + SUMIFS(Captura_Marimba_M01!$G:$G, Captura_Marimba_M01!$A:$A, Captura_Obra!A7, Captura_Marimba_M01!$C:$C, Captura_Obra!B7, Captura_Marimba_M01!$D:$D, Captura_Obra!D7))>0), "", "❌ Falta en Pipa") | E303: =IF(OR(Captura_Obra!A7="", (SUMIFS(Captura_Pegaso!$H:$H, Captura_Pegaso!$A:$A, Captura_Obra!A7, Captura_Pegaso!$D:$D, Captura_Obra!B7, Captura_Pegaso!$E:$E, Captura_Obra!D7) + SUMIFS(Captura_Marimba_M01!$G:$G, Captura_Marimba_M01!$A:$A, Captura_Obra!A7, Captura_Marimba_M01!$C:$C, Captura_Obra!B7, Captura_Marimba_M01!$D:$D, Captura_Obra!D7))>0), "", Captura_Obra!A7) | F303: =IF(OR(Captura_Obra!A7="", (SUMIFS(Captura_Pegaso!$H:$H, Captura_Pegaso!$A:$A, Captura_Obra!A7, Captura_Pegaso!$D:$D, Captura_Obra!B7, Captura_Pegaso!$E:$E, Captura_Obra!D7) + SUMIFS(Captura_Marimba_M01!$G:$G, Captura_Marimba_M01!$A:$A, Captura_Obra!A7, Captura_Marimba_M01!$C:$C, Captura_Obra!B7, Captura_Marimba_M01!$D:$D, Captura_Obra!D7))>0), "", Captura_Obra!B7) | G303: =IF(OR(Captura_Obra!A7="", (SUMIFS(Captura_Pegaso!$H:$H, Captura_Pegaso!$A:$A, Captura_Obra!A7, Captura_Pegaso!$D:$D, Captura_Obra!B7, Captura_Pegaso!$E:$E, Captura_Obra!D7) + SUMIFS(Captura_Marimba_M01!$G:$G, Captura_Marimba_M01!$A:$A, Captura_Obra!A7, Captura_Marimba_M01!$C:$C, Captura_Obra!B7, Captura_Marimba_M01!$D:$D, Captura_Obra!D7))>0), "", Captura_Obra!D7) | H303: =IF(OR(Captura_Obra!A7="", (SUMIFS(Captura_Pegaso!$H:$H, Captura_Pegaso!$A:$A, Captura_Obra!A7, Captura_Pegaso!$D:$D, Captura_Obra!B7, Captura_Pegaso!$E:$E, Captura_Obra!D7) + SUMIFS(Captura_Marimba_M01!$G:$G, Captura_Marimba_M01!$A:$A, Captura_Obra!A7, Captura_Marimba_M01!$C:$C, Captura_Obra!B7, Captura_Marimba_M01!$D:$D, Captura_Obra!D7))>0), "", 0) | I303: =IF(OR(Captura_Obra!A7="", (SUMIFS(Captura_Pegaso!$H:$H, Captura_Pegaso!$A:$A, Captura_Obra!A7, Captura_Pegaso!$D:$D, Captura_Obra!B7, Captura_Pegaso!$E:$E, Captura_Obra!D7) + SUMIFS(Captura_Marimba_M01!$G:$G, Captura_Marimba_M01!$A:$A, Captura_Obra!A7, Captura_Marimba_M01!$C:$C, Captura_Obra!B7, Captura_Marimba_M01!$D:$D, Captura_Obra!D7))>0), "", Captura_Obra!F7) | J303: =IF(OR(Captura_Obra!A7="", (SUMIFS(Captura_Pegaso!$H:$H, Captura_Pegaso!$A:$A, Captura_Obra!A7, Captura_Pegaso!$D:$D, Captura_Obra!B7, Captura_Pegaso!$E:$E, Captura_Obra!D7) + SUMIFS(Captura_Marimba_M01!$G:$G, Captura_Marimba_M01!$A:$A, Captura_Obra!A7, Captura_Marimba_M01!$C:$C, Captura_Obra!B7, Captura_Marimba_M01!$D:$D, Captura_Obra!D7))>0), "", H303 - I303)
A304: =IF(OR(Captura_Obra!A8="", (SUMIFS(Captura_Pegaso!$H:$H, Captura_Pegaso!$A:$A, Captura_Obra!A8, Captura_Pegaso!$D:$D, Captura_Obra!B8, Captura_Pegaso!$E:$E, Captura_Obra!D8) + SUMIFS(Captura_Marimba_M01!$G:$G, Captura_Marimba_M01!$A:$A, Captura_Obra!A8, Captura_Marimba_M01!$C:$C, Captura_Obra!B8, Captura_Marimba_M01!$D:$D, Captura_Obra!D8))>0), "", "Huérfano Obra") | B304: =IF(OR(Captura_Obra!A8="", (SUMIFS(Captura_Pegaso!$H:$H, Captura_Pegaso!$A:$A, Captura_Obra!A8, Captura_Pegaso!$D:$D, Captura_Obra!B8, Captura_Pegaso!$E:$E, Captura_Obra!D8) + SUMIFS(Captura_Marimba_M01!$G:$G, Captura_Marimba_M01!$A:$A, Captura_Obra!A8, Captura_Marimba_M01!$C:$C, Captura_Obra!B8, Captura_Marimba_M01!$D:$D, Captura_Obra!D8))>0), "", "No Reportado") | C304: =IF(OR(Captura_Obra!A8="", (SUMIFS(Captura_Pegaso!$H:$H, Captura_Pegaso!$A:$A, Captura_Obra!A8, Captura_Pegaso!$D:$D, Captura_Obra!B8, Captura_Pegaso!$E:$E, Captura_Obra!D8) + SUMIFS(Captura_Marimba_M01!$G:$G, Captura_Marimba_M01!$A:$A, Captura_Obra!A8, Captura_Marimba_M01!$C:$C, Captura_Obra!B8, Captura_Marimba_M01!$D:$D, Captura_Obra!D8))>0), "", Captura_Obra!N8) | D304: =IF(OR(Captura_Obra!A8="", (SUMIFS(Captura_Pegaso!$H:$H, Captura_Pegaso!$A:$A, Captura_Obra!A8, Captura_Pegaso!$D:$D, Captura_Obra!B8, Captura_Pegaso!$E:$E, Captura_Obra!D8) + SUMIFS(Captura_Marimba_M01!$G:$G, Captura_Marimba_M01!$A:$A, Captura_Obra!A8, Captura_Marimba_M01!$C:$C, Captura_Obra!B8, Captura_Marimba_M01!$D:$D, Captura_Obra!D8))>0), "", "❌ Falta en Pipa") | E304: =IF(OR(Captura_Obra!A8="", (SUMIFS(Captura_Pegaso!$H:$H, Captura_Pegaso!$A:$A, Captura_Obra!A8, Captura_Pegaso!$D:$D, Captura_Obra!B8, Captura_Pegaso!$E:$E, Captura_Obra!D8) + SUMIFS(Captura_Marimba_M01!$G:$G, Captura_Marimba_M01!$A:$A, Captura_Obra!A8, Captura_Marimba_M01!$C:$C, Captura_Obra!B8, Captura_Marimba_M01!$D:$D, Captura_Obra!D8))>0), "", Captura_Obra!A8) | F304: =IF(OR(Captura_Obra!A8="", (SUMIFS(Captura_Pegaso!$H:$H, Captura_Pegaso!$A:$A, Captura_Obra!A8, Captura_Pegaso!$D:$D, Captura_Obra!B8, Captura_Pegaso!$E:$E, Captura_Obra!D8) + SUMIFS(Captura_Marimba_M01!$G:$G, Captura_Marimba_M01!$A:$A, Captura_Obra!A8, Captura_Marimba_M01!$C:$C, Captura_Obra!B8, Captura_Marimba_M01!$D:$D, Captura_Obra!D8))>0), "", Captura_Obra!B8) | G304: =IF(OR(Captura_Obra!A8="", (SUMIFS(Captura_Pegaso!$H:$H, Captura_Pegaso!$A:$A, Captura_Obra!A8, Captura_Pegaso!$D:$D, Captura_Obra!B8, Captura_Pegaso!$E:$E, Captura_Obra!D8) + SUMIFS(Captura_Marimba_M01!$G:$G, Captura_Marimba_M01!$A:$A, Captura_Obra!A8, Captura_Marimba_M01!$C:$C, Captura_Obra!B8, Captura_Marimba_M01!$D:$D, Captura_Obra!D8))>0), "", Captura_Obra!D8) | H304: =IF(OR(Captura_Obra!A8="", (SUMIFS(Captura_Pegaso!$H:$H, Captura_Pegaso!$A:$A, Captura_Obra!A8, Captura_Pegaso!$D:$D, Captura_Obra!B8, Captura_Pegaso!$E:$E, Captura_Obra!D8) + SUMIFS(Captura_Marimba_M01!$G:$G, Captura_Marimba_M01!$A:$A, Captura_Obra!A8, Captura_Marimba_M01!$C:$C, Captura_Obra!B8, Captura_Marimba_M01!$D:$D, Captura_Obra!D8))>0), "", 0) | I304: =IF(OR(Captura_Obra!A8="", (SUMIFS(Captura_Pegaso!$H:$H, Captura_Pegaso!$A:$A, Captura_Obra!A8, Captura_Pegaso!$D:$D, Captura_Obra!B8, Captura_Pegaso!$E:$E, Captura_Obra!D8) + SUMIFS(Captura_Marimba_M01!$G:$G, Captura_Marimba_M01!$A:$A, Captura_Obra!A8, Captura_Marimba_M01!$C:$C, Captura_Obra!B8, Captura_Marimba_M01!$D:$D, Captura_Obra!D8))>0), "", Captura_Obra!F8) | J304: =IF(OR(Captura_Obra!A8="", (SUMIFS(Captura_Pegaso!$H:$H, Captura_Pegaso!$A:$A, Captura_Obra!A8, Captura_Pegaso!$D:$D, Captura_Obra!B8, Captura_Pegaso!$E:$E, Captura_Obra!D8) + SUMIFS(Captura_Marimba_M01!$G:$G, Captura_Marimba_M01!$A:$A, Captura_Obra!A8, Captura_Marimba_M01!$C:$C, Captura_Obra!B8, Captura_Marimba_M01!$D:$D, Captura_Obra!D8))>0), "", H304 - I304)
A305: =IF(OR(Captura_Obra!A9="", (SUMIFS(Captura_Pegaso!$H:$H, Captura_Pegaso!$A:$A, Captura_Obra!A9, Captura_Pegaso!$D:$D, Captura_Obra!B9, Captura_Pegaso!$E:$E, Captura_Obra!D9) + SUMIFS(Captura_Marimba_M01!$G:$G, Captura_Marimba_M01!$A:$A, Captura_Obra!A9, Captura_Marimba_M01!$C:$C, Captura_Obra!B9, Captura_Marimba_M01!$D:$D, Captura_Obra!D9))>0), "", "Huérfano Obra") | B305: =IF(OR(Captura_Obra!A9="", (SUMIFS(Captura_Pegaso!$H:$H, Captura_Pegaso!$A:$A, Captura_Obra!A9, Captura_Pegaso!$D:$D, Captura_Obra!B9, Captura_Pegaso!$E:$E, Captura_Obra!D9) + SUMIFS(Captura_Marimba_M01!$G:$G, Captura_Marimba_M01!$A:$A, Captura_Obra!A9, Captura_Marimba_M01!$C:$C, Captura_Obra!B9, Captura_Marimba_M01!$D:$D, Captura_Obra!D9))>0), "", "No Reportado") | C305: =IF(OR(Captura_Obra!A9="", (SUMIFS(Captura_Pegaso!$H:$H, Captura_Pegaso!$A:$A, Captura_Obra!A9, Captura_Pegaso!$D:$D, Captura_Obra!B9, Captura_Pegaso!$E:$E, Captura_Obra!D9) + SUMIFS(Captura_Marimba_M01!$G:$G, Captura_Marimba_M01!$A:$A, Captura_Obra!A9, Captura_Marimba_M01!$C:$C, Captura_Obra!B9, Captura_Marimba_M01!$D:$D, Captura_Obra!D9))>0), "", Captura_Obra!N9) | D305: =IF(OR(Captura_Obra!A9="", (SUMIFS(Captura_Pegaso!$H:$H, Captura_Pegaso!$A:$A, Captura_Obra!A9, Captura_Pegaso!$D:$D, Captura_Obra!B9, Captura_Pegaso!$E:$E, Captura_Obra!D9) + SUMIFS(Captura_Marimba_M01!$G:$G, Captura_Marimba_M01!$A:$A, Captura_Obra!A9, Captura_Marimba_M01!$C:$C, Captura_Obra!B9, Captura_Marimba_M01!$D:$D, Captura_Obra!D9))>0), "", "❌ Falta en Pipa") | E305: =IF(OR(Captura_Obra!A9="", (SUMIFS(Captura_Pegaso!$H:$H, Captura_Pegaso!$A:$A, Captura_Obra!A9, Captura_Pegaso!$D:$D, Captura_Obra!B9, Captura_Pegaso!$E:$E, Captura_Obra!D9) + SUMIFS(Captura_Marimba_M01!$G:$G, Captura_Marimba_M01!$A:$A, Captura_Obra!A9, Captura_Marimba_M01!$C:$C, Captura_Obra!B9, Captura_Marimba_M01!$D:$D, Captura_Obra!D9))>0), "", Captura_Obra!A9) | F305: =IF(OR(Captura_Obra!A9="", (SUMIFS(Captura_Pegaso!$H:$H, Captura_Pegaso!$A:$A, Captura_Obra!A9, Captura_Pegaso!$D:$D, Captura_Obra!B9, Captura_Pegaso!$E:$E, Captura_Obra!D9) + SUMIFS(Captura_Marimba_M01!$G:$G, Captura_Marimba_M01!$A:$A, Captura_Obra!A9, Captura_Marimba_M01!$C:$C, Captura_Obra!B9, Captura_Marimba_M01!$D:$D, Captura_Obra!D9))>0), "", Captura_Obra!B9) | G305: =IF(OR(Captura_Obra!A9="", (SUMIFS(Captura_Pegaso!$H:$H, Captura_Pegaso!$A:$A, Captura_Obra!A9, Captura_Pegaso!$D:$D, Captura_Obra!B9, Captura_Pegaso!$E:$E, Captura_Obra!D9) + SUMIFS(Captura_Marimba_M01!$G:$G, Captura_Marimba_M01!$A:$A, Captura_Obra!A9, Captura_Marimba_M01!$C:$C, Captura_Obra!B9, Captura_Marimba_M01!$D:$D, Captura_Obra!D9))>0), "", Captura_Obra!D9) | H305: =IF(OR(Captura_Obra!A9="", (SUMIFS(Captura_Pegaso!$H:$H, Captura_Pegaso!$A:$A, Captura_Obra!A9, Captura_Pegaso!$D:$D, Captura_Obra!B9, Captura_Pegaso!$E:$E, Captura_Obra!D9) + SUMIFS(Captura_Marimba_M01!$G:$G, Captura_Marimba_M01!$A:$A, Captura_Obra!A9, Captura_Marimba_M01!$C:$C, Captura_Obra!B9, Captura_Marimba_M01!$D:$D, Captura_Obra!D9))>0), "", 0) | I305: =IF(OR(Captura_Obra!A9="", (SUMIFS(Captura_Pegaso!$H:$H, Captura_Pegaso!$A:$A, Captura_Obra!A9, Captura_Pegaso!$D:$D, Captura_Obra!B9, Captura_Pegaso!$E:$E, Captura_Obra!D9) + SUMIFS(Captura_Marimba_M01!$G:$G, Captura_Marimba_M01!$A:$A, Captura_Obra!A9, Captura_Marimba_M01!$C:$C, Captura_Obra!B9, Captura_Marimba_M01!$D:$D, Captura_Obra!D9))>0), "", Captura_Obra!F9) | J305: =IF(OR(Captura_Obra!A9="", (SUMIFS(Captura_Pegaso!$H:$H, Captura_Pegaso!$A:$A, Captura_Obra!A9, Captura_Pegaso!$D:$D, Captura_Obra!B9, Captura_Pegaso!$E:$E, Captura_Obra!D9) + SUMIFS(Captura_Marimba_M01!$G:$G, Captura_Marimba_M01!$A:$A, Captura_Obra!A9, Captura_Marimba_M01!$C:$C, Captura_Obra!B9, Captura_Marimba_M01!$D:$D, Captura_Obra!D9))>0), "", H305 - I305)
A306: =IF(OR(Captura_Obra!A10="", (SUMIFS(Captura_Pegaso!$H:$H, Captura_Pegaso!$A:$A, Captura_Obra!A10, Captura_Pegaso!$D:$D, Captura_Obra!B10, Captura_Pegaso!$E:$E, Captura_Obra!D10) + SUMIFS(Captura_Marimba_M01!$G:$G, Captura_Marimba_M01!$A:$A, Captura_Obra!A10, Captura_Marimba_M01!$C:$C, Captura_Obra!B10, Captura_Marimba_M01!$D:$D, Captura_Obra!D10))>0), "", "Huérfano Obra") | B306: =IF(OR(Captura_Obra!A10="", (SUMIFS(Captura_Pegaso!$H:$H, Captura_Pegaso!$A:$A, Captura_Obra!A10, Captura_Pegaso!$D:$D, Captura_Obra!B10, Captura_Pegaso!$E:$E, Captura_Obra!D10) + SUMIFS(Captura_Marimba_M01!$G:$G, Captura_Marimba_M01!$A:$A, Captura_Obra!A10, Captura_Marimba_M01!$C:$C, Captura_Obra!B10, Captura_Marimba_M01!$D:$D, Captura_Obra!D10))>0), "", "No Reportado") | C306: =IF(OR(Captura_Obra!A10="", (SUMIFS(Captura_Pegaso!$H:$H, Captura_Pegaso!$A:$A, Captura_Obra!A10, Captura_Pegaso!$D:$D, Captura_Obra!B10, Captura_Pegaso!$E:$E, Captura_Obra!D10) + SUMIFS(Captura_Marimba_M01!$G:$G, Captura_Marimba_M01!$A:$A, Captura_Obra!A10, Captura_Marimba_M01!$C:$C, Captura_Obra!B10, Captura_Marimba_M01!$D:$D, Captura_Obra!D10))>0), "", Captura_Obra!N10) | D306: =IF(OR(Captura_Obra!A10="", (SUMIFS(Captura_Pegaso!$H:$H, Captura_Pegaso!$A:$A, Captura_Obra!A10, Captura_Pegaso!$D:$D, Captura_Obra!B10, Captura_Pegaso!$E:$E, Captura_Obra!D10) + SUMIFS(Captura_Marimba_M01!$G:$G, Captura_Marimba_M01!$A:$A, Captura_Obra!A10, Captura_Marimba_M01!$C:$C, Captura_Obra!B10, Captura_Marimba_M01!$D:$D, Captura_Obra!D10))>0), "", "❌ Falta en Pipa") | E306: =IF(OR(Captura_Obra!A10="", (SUMIFS(Captura_Pegaso!$H:$H, Captura_Pegaso!$A:$A, Captura_Obra!A10, Captura_Pegaso!$D:$D, Captura_Obra!B10, Captura_Pegaso!$E:$E, Captura_Obra!D10) + SUMIFS(Captura_Marimba_M01!$G:$G, Captura_Marimba_M01!$A:$A, Captura_Obra!A10, Captura_Marimba_M01!$C:$C, Captura_Obra!B10, Captura_Marimba_M01!$D:$D, Captura_Obra!D10))>0), "", Captura_Obra!A10) | F306: =IF(OR(Captura_Obra!A10="", (SUMIFS(Captura_Pegaso!$H:$H, Captura_Pegaso!$A:$A, Captura_Obra!A10, Captura_Pegaso!$D:$D, Captura_Obra!B10, Captura_Pegaso!$E:$E, Captura_Obra!D10) + SUMIFS(Captura_Marimba_M01!$G:$G, Captura_Marimba_M01!$A:$A, Captura_Obra!A10, Captura_Marimba_M01!$C:$C, Captura_Obra!B10, Captura_Marimba_M01!$D:$D, Captura_Obra!D10))>0), "", Captura_Obra!B10) | G306: =IF(OR(Captura_Obra!A10="", (SUMIFS(Captura_Pegaso!$H:$H, Captura_Pegaso!$A:$A, Captura_Obra!A10, Captura_Pegaso!$D:$D, Captura_Obra!B10, Captura_Pegaso!$E:$E, Captura_Obra!D10) + SUMIFS(Captura_Marimba_M01!$G:$G, Captura_Marimba_M01!$A:$A, Captura_Obra!A10, Captura_Marimba_M01!$C:$C, Captura_Obra!B10, Captura_Marimba_M01!$D:$D, Captura_Obra!D10))>0), "", Captura_Obra!D10) | H306: =IF(OR(Captura_Obra!A10="", (SUMIFS(Captura_Pegaso!$H:$H, Captura_Pegaso!$A:$A, Captura_Obra!A10, Captura_Pegaso!$D:$D, Captura_Obra!B10, Captura_Pegaso!$E:$E, Captura_Obra!D10) + SUMIFS(Captura_Marimba_M01!$G:$G, Captura_Marimba_M01!$A:$A, Captura_Obra!A10, Captura_Marimba_M01!$C:$C, Captura_Obra!B10, Captura_Marimba_M01!$D:$D, Captura_Obra!D10))>0), "", 0) | I306: =IF(OR(Captura_Obra!A10="", (SUMIFS(Captura_Pegaso!$H:$H, Captura_Pegaso!$A:$A, Captura_Obra!A10, Captura_Pegaso!$D:$D, Captura_Obra!B10, Captura_Pegaso!$E:$E, Captura_Obra!D10) + SUMIFS(Captura_Marimba_M01!$G:$G, Captura_Marimba_M01!$A:$A, Captura_Obra!A10, Captura_Marimba_M01!$C:$C, Captura_Obra!B10, Captura_Marimba_M01!$D:$D, Captura_Obra!D10))>0), "", Captura_Obra!F10) | J306: =IF(OR(Captura_Obra!A10="", (SUMIFS(Captura_Pegaso!$H:$H, Captura_Pegaso!$A:$A, Captura_Obra!A10, Captura_Pegaso!$D:$D, Captura_Obra!B10, Captura_Pegaso!$E:$E, Captura_Obra!D10) + SUMIFS(Captura_Marimba_M01!$G:$G, Captura_Marimba_M01!$A:$A, Captura_Obra!A10, Captura_Marimba_M01!$C:$C, Captura_Obra!B10, Captura_Marimba_M01!$D:$D, Captura_Obra!D10))>0), "", H306 - I306)
A307: =IF(OR(Captura_Obra!A11="", (SUMIFS(Captura_Pegaso!$H:$H, Captura_Pegaso!$A:$A, Captura_Obra!A11, Captura_Pegaso!$D:$D, Captura_Obra!B11, Captura_Pegaso!$E:$E, Captura_Obra!D11) + SUMIFS(Captura_Marimba_M01!$G:$G, Captura_Marimba_M01!$A:$A, Captura_Obra!A11, Captura_Marimba_M01!$C:$C, Captura_Obra!B11, Captura_Marimba_M01!$D:$D, Captura_Obra!D11))>0), "", "Huérfano Obra") | B307: =IF(OR(Captura_Obra!A11="", (SUMIFS(Captura_Pegaso!$H:$H, Captura_Pegaso!$A:$A, Captura_Obra!A11, Captura_Pegaso!$D:$D, Captura_Obra!B11, Captura_Pegaso!$E:$E, Captura_Obra!D11) + SUMIFS(Captura_Marimba_M01!$G:$G, Captura_Marimba_M01!$A:$A, Captura_Obra!A11, Captura_Marimba_M01!$C:$C, Captura_Obra!B11, Captura_Marimba_M01!$D:$D, Captura_Obra!D11))>0), "", "No Reportado") | C307: =IF(OR(Captura_Obra!A11="", (SUMIFS(Captura_Pegaso!$H:$H, Captura_Pegaso!$A:$A, Captura_Obra!A11, Captura_Pegaso!$D:$D, Captura_Obra!B11, Captura_Pegaso!$E:$E, Captura_Obra!D11) + SUMIFS(Captura_Marimba_M01!$G:$G, Captura_Marimba_M01!$A:$A, Captura_Obra!A11, Captura_Marimba_M01!$C:$C, Captura_Obra!B11, Captura_Marimba_M01!$D:$D, Captura_Obra!D11))>0), "", Captura_Obra!N11) | D307: =IF(OR(Captura_Obra!A11="", (SUMIFS(Captura_Pegaso!$H:$H, Captura_Pegaso!$A:$A, Captura_Obra!A11, Captura_Pegaso!$D:$D, Captura_Obra!B11, Captura_Pegaso!$E:$E, Captura_Obra!D11) + SUMIFS(Captura_Marimba_M01!$G:$G, Captura_Marimba_M01!$A:$A, Captura_Obra!A11, Captura_Marimba_M01!$C:$C, Captura_Obra!B11, Captura_Marimba_M01!$D:$D, Captura_Obra!D11))>0), "", "❌ Falta en Pipa") | E307: =IF(OR(Captura_Obra!A11="", (SUMIFS(Captura_Pegaso!$H:$H, Captura_Pegaso!$A:$A, Captura_Obra!A11, Captura_Pegaso!$D:$D, Captura_Obra!B11, Captura_Pegaso!$E:$E, Captura_Obra!D11) + SUMIFS(Captura_Marimba_M01!$G:$G, Captura_Marimba_M01!$A:$A, Captura_Obra!A11, Captura_Marimba_M01!$C:$C, Captura_Obra!B11, Captura_Marimba_M01!$D:$D, Captura_Obra!D11))>0), "", Captura_Obra!A11) | F307: =IF(OR(Captura_Obra!A11="", (SUMIFS(Captura_Pegaso!$H:$H, Captura_Pegaso!$A:$A, Captura_Obra!A11, Captura_Pegaso!$D:$D, Captura_Obra!B11, Captura_Pegaso!$E:$E, Captura_Obra!D11) + SUMIFS(Captura_Marimba_M01!$G:$G, Captura_Marimba_M01!$A:$A, Captura_Obra!A11, Captura_Marimba_M01!$C:$C, Captura_Obra!B11, Captura_Marimba_M01!$D:$D, Captura_Obra!D11))>0), "", Captura_Obra!B11) | G307: =IF(OR(Captura_Obra!A11="", (SUMIFS(Captura_Pegaso!$H:$H, Captura_Pegaso!$A:$A, Captura_Obra!A11, Captura_Pegaso!$D:$D, Captura_Obra!B11, Captura_Pegaso!$E:$E, Captura_Obra!D11) + SUMIFS(Captura_Marimba_M01!$G:$G, Captura_Marimba_M01!$A:$A, Captura_Obra!A11, Captura_Marimba_M01!$C:$C, Captura_Obra!B11, Captura_Marimba_M01!$D:$D, Captura_Obra!D11))>0), "", Captura_Obra!D11) | H307: =IF(OR(Captura_Obra!A11="", (SUMIFS(Captura_Pegaso!$H:$H, Captura_Pegaso!$A:$A, Captura_Obra!A11, Captura_Pegaso!$D:$D, Captura_Obra!B11, Captura_Pegaso!$E:$E, Captura_Obra!D11) + SUMIFS(Captura_Marimba_M01!$G:$G, Captura_Marimba_M01!$A:$A, Captura_Obra!A11, Captura_Marimba_M01!$C:$C, Captura_Obra!B11, Captura_Marimba_M01!$D:$D, Captura_Obra!D11))>0), "", 0) | I307: =IF(OR(Captura_Obra!A11="", (SUMIFS(Captura_Pegaso!$H:$H, Captura_Pegaso!$A:$A, Captura_Obra!A11, Captura_Pegaso!$D:$D, Captura_Obra!B11, Captura_Pegaso!$E:$E, Captura_Obra!D11) + SUMIFS(Captura_Marimba_M01!$G:$G, Captura_Marimba_M01!$A:$A, Captura_Obra!A11, Captura_Marimba_M01!$C:$C, Captura_Obra!B11, Captura_Marimba_M01!$D:$D, Captura_Obra!D11))>0), "", Captura_Obra!F11) | J307: =IF(OR(Captura_Obra!A11="", (SUMIFS(Captura_Pegaso!$H:$H, Captura_Pegaso!$A:$A, Captura_Obra!A11, Captura_Pegaso!$D:$D, Captura_Obra!B11, Captura_Pegaso!$E:$E, Captura_Obra!D11) + SUMIFS(Captura_Marimba_M01!$G:$G, Captura_Marimba_M01!$A:$A, Captura_Obra!A11, Captura_Marimba_M01!$C:$C, Captura_Obra!B11, Captura_Marimba_M01!$D:$D, Captura_Obra!D11))>0), "", H307 - I307)
A308: =IF(OR(Captura_Obra!A12="", (SUMIFS(Captura_Pegaso!$H:$H, Captura_Pegaso!$A:$A, Captura_Obra!A12, Captura_Pegaso!$D:$D, Captura_Obra!B12, Captura_Pegaso!$E:$E, Captura_Obra!D12) + SUMIFS(Captura_Marimba_M01!$G:$G, Captura_Marimba_M01!$A:$A, Captura_Obra!A12, Captura_Marimba_M01!$C:$C, Captura_Obra!B12, Captura_Marimba_M01!$D:$D, Captura_Obra!D12))>0), "", "Huérfano Obra") | B308: =IF(OR(Captura_Obra!A12="", (SUMIFS(Captura_Pegaso!$H:$H, Captura_Pegaso!$A:$A, Captura_Obra!A12, Captura_Pegaso!$D:$D, Captura_Obra!B12, Captura_Pegaso!$E:$E, Captura_Obra!D12) + SUMIFS(Captura_Marimba_M01!$G:$G, Captura_Marimba_M01!$A:$A, Captura_Obra!A12, Captura_Marimba_M01!$C:$C, Captura_Obra!B12, Captura_Marimba_M01!$D:$D, Captura_Obra!D12))>0), "", "No Reportado") | C308: =IF(OR(Captura_Obra!A12="", (SUMIFS(Captura_Pegaso!$H:$H, Captura_Pegaso!$A:$A, Captura_Obra!A12, Captura_Pegaso!$D:$D, Captura_Obra!B12, Captura_Pegaso!$E:$E, Captura_Obra!D12) + SUMIFS(Captura_Marimba_M01!$G:$G, Captura_Marimba_M01!$A:$A, Captura_Obra!A12, Captura_Marimba_M01!$C:$C, Captura_Obra!B12, Captura_Marimba_M01!$D:$D, Captura_Obra!D12))>0), "", Captura_Obra!N12) | D308: =IF(OR(Captura_Obra!A12="", (SUMIFS(Captura_Pegaso!$H:$H, Captura_Pegaso!$A:$A, Captura_Obra!A12, Captura_Pegaso!$D:$D, Captura_Obra!B12, Captura_Pegaso!$E:$E, Captura_Obra!D12) + SUMIFS(Captura_Marimba_M01!$G:$G, Captura_Marimba_M01!$A:$A, Captura_Obra!A12, Captura_Marimba_M01!$C:$C, Captura_Obra!B12, Captura_Marimba_M01!$D:$D, Captura_Obra!D12))>0), "", "❌ Falta en Pipa") | E308: =IF(OR(Captura_Obra!A12="", (SUMIFS(Captura_Pegaso!$H:$H, Captura_Pegaso!$A:$A, Captura_Obra!A12, Captura_Pegaso!$D:$D, Captura_Obra!B12, Captura_Pegaso!$E:$E, Captura_Obra!D12) + SUMIFS(Captura_Marimba_M01!$G:$G, Captura_Marimba_M01!$A:$A, Captura_Obra!A12, Captura_Marimba_M01!$C:$C, Captura_Obra!B12, Captura_Marimba_M01!$D:$D, Captura_Obra!D12))>0), "", Captura_Obra!A12) | F308: =IF(OR(Captura_Obra!A12="", (SUMIFS(Captura_Pegaso!$H:$H, Captura_Pegaso!$A:$A, Captura_Obra!A12, Captura_Pegaso!$D:$D, Captura_Obra!B12, Captura_Pegaso!$E:$E, Captura_Obra!D12) + SUMIFS(Captura_Marimba_M01!$G:$G, Captura_Marimba_M01!$A:$A, Captura_Obra!A12, Captura_Marimba_M01!$C:$C, Captura_Obra!B12, Captura_Marimba_M01!$D:$D, Captura_Obra!D12))>0), "", Captura_Obra!B12) | G308: =IF(OR(Captura_Obra!A12="", (SUMIFS(Captura_Pegaso!$H:$H, Captura_Pegaso!$A:$A, Captura_Obra!A12, Captura_Pegaso!$D:$D, Captura_Obra!B12, Captura_Pegaso!$E:$E, Captura_Obra!D12) + SUMIFS(Captura_Marimba_M01!$G:$G, Captura_Marimba_M01!$A:$A, Captura_Obra!A12, Captura_Marimba_M01!$C:$C, Captura_Obra!B12, Captura_Marimba_M01!$D:$D, Captura_Obra!D12))>0), "", Captura_Obra!D12) | H308: =IF(OR(Captura_Obra!A12="", (SUMIFS(Captura_Pegaso!$H:$H, Captura_Pegaso!$A:$A, Captura_Obra!A12, Captura_Pegaso!$D:$D, Captura_Obra!B12, Captura_Pegaso!$E:$E, Captura_Obra!D12) + SUMIFS(Captura_Marimba_M01!$G:$G, Captura_Marimba_M01!$A:$A, Captura_Obra!A12, Captura_Marimba_M01!$C:$C, Captura_Obra!B12, Captura_Marimba_M01!$D:$D, Captura_Obra!D12))>0), "", 0) | I308: =IF(OR(Captura_Obra!A12="", (SUMIFS(Captura_Pegaso!$H:$H, Captura_Pegaso!$A:$A, Captura_Obra!A12, Captura_Pegaso!$D:$D, Captura_Obra!B12, Captura_Pegaso!$E:$E, Captura_Obra!D12) + SUMIFS(Captura_Marimba_M01!$G:$G, Captura_Marimba_M01!$A:$A, Captura_Obra!A12, Captura_Marimba_M01!$C:$C, Captura_Obra!B12, Captura_Marimba_M01!$D:$D, Captura_Obra!D12))>0), "", Captura_Obra!F12) | J308: =IF(OR(Captura_Obra!A12="", (SUMIFS(Captura_Pegaso!$H:$H, Captura_Pegaso!$A:$A, Captura_Obra!A12, Captura_Pegaso!$D:$D, Captura_Obra!B12, Captura_Pegaso!$E:$E, Captura_Obra!D12) + SUMIFS(Captura_Marimba_M01!$G:$G, Captura_Marimba_M01!$A:$A, Captura_Obra!A12, Captura_Marimba_M01!$C:$C, Captura_Obra!B12, Captura_Marimba_M01!$D:$D, Captura_Obra!D12))>0), "", H308 - I308)
A309: =IF(OR(Captura_Obra!A13="", (SUMIFS(Captura_Pegaso!$H:$H, Captura_Pegaso!$A:$A, Captura_Obra!A13, Captura_Pegaso!$D:$D, Captura_Obra!B13, Captura_Pegaso!$E:$E, Captura_Obra!D13) + SUMIFS(Captura_Marimba_M01!$G:$G, Captura_Marimba_M01!$A:$A, Captura_Obra!A13, Captura_Marimba_M01!$C:$C, Captura_Obra!B13, Captura_Marimba_M01!$D:$D, Captura_Obra!D13))>0), "", "Huérfano Obra") | B309: =IF(OR(Captura_Obra!A13="", (SUMIFS(Captura_Pegaso!$H:$H, Captura_Pegaso!$A:$A, Captura_Obra!A13, Captura_Pegaso!$D:$D, Captura_Obra!B13, Captura_Pegaso!$E:$E, Captura_Obra!D13) + SUMIFS(Captura_Marimba_M01!$G:$G, Captura_Marimba_M01!$A:$A, Captura_Obra!A13, Captura_Marimba_M01!$C:$C, Captura_Obra!B13, Captura_Marimba_M01!$D:$D, Captura_Obra!D13))>0), "", "No Reportado") | C309: =IF(OR(Captura_Obra!A13="", (SUMIFS(Captura_Pegaso!$H:$H, Captura_Pegaso!$A:$A, Captura_Obra!A13, Captura_Pegaso!$D:$D, Captura_Obra!B13, Captura_Pegaso!$E:$E, Captura_Obra!D13) + SUMIFS(Captura_Marimba_M01!$G:$G, Captura_Marimba_M01!$A:$A, Captura_Obra!A13, Captura_Marimba_M01!$C:$C, Captura_Obra!B13, Captura_Marimba_M01!$D:$D, Captura_Obra!D13))>0), "", Captura_Obra!N13) | D309: =IF(OR(Captura_Obra!A13="", (SUMIFS(Captura_Pegaso!$H:$H, Captura_Pegaso!$A:$A, Captura_Obra!A13, Captura_Pegaso!$D:$D, Captura_Obra!B13, Captura_Pegaso!$E:$E, Captura_Obra!D13) + SUMIFS(Captura_Marimba_M01!$G:$G, Captura_Marimba_M01!$A:$A, Captura_Obra!A13, Captura_Marimba_M01!$C:$C, Captura_Obra!B13, Captura_Marimba_M01!$D:$D, Captura_Obra!D13))>0), "", "❌ Falta en Pipa") | E309: =IF(OR(Captura_Obra!A13="", (SUMIFS(Captura_Pegaso!$H:$H, Captura_Pegaso!$A:$A, Captura_Obra!A13, Captura_Pegaso!$D:$D, Captura_Obra!B13, Captura_Pegaso!$E:$E, Captura_Obra!D13) + SUMIFS(Captura_Marimba_M01!$G:$G, Captura_Marimba_M01!$A:$A, Captura_Obra!A13, Captura_Marimba_M01!$C:$C, Captura_Obra!B13, Captura_Marimba_M01!$D:$D, Captura_Obra!D13))>0), "", Captura_Obra!A13) | F309: =IF(OR(Captura_Obra!A13="", (SUMIFS(Captura_Pegaso!$H:$H, Captura_Pegaso!$A:$A, Captura_Obra!A13, Captura_Pegaso!$D:$D, Captura_Obra!B13, Captura_Pegaso!$E:$E, Captura_Obra!D13) + SUMIFS(Captura_Marimba_M01!$G:$G, Captura_Marimba_M01!$A:$A, Captura_Obra!A13, Captura_Marimba_M01!$C:$C, Captura_Obra!B13, Captura_Marimba_M01!$D:$D, Captura_Obra!D13))>0), "", Captura_Obra!B13) | G309: =IF(OR(Captura_Obra!A13="", (SUMIFS(Captura_Pegaso!$H:$H, Captura_Pegaso!$A:$A, Captura_Obra!A13, Captura_Pegaso!$D:$D, Captura_Obra!B13, Captura_Pegaso!$E:$E, Captura_Obra!D13) + SUMIFS(Captura_Marimba_M01!$G:$G, Captura_Marimba_M01!$A:$A, Captura_Obra!A13, Captura_Marimba_M01!$C:$C, Captura_Obra!B13, Captura_Marimba_M01!$D:$D, Captura_Obra!D13))>0), "", Captura_Obra!D13) | H309: =IF(OR(Captura_Obra!A13="", (SUMIFS(Captura_Pegaso!$H:$H, Captura_Pegaso!$A:$A, Captura_Obra!A13, Captura_Pegaso!$D:$D, Captura_Obra!B13, Captura_Pegaso!$E:$E, Captura_Obra!D13) + SUMIFS(Captura_Marimba_M01!$G:$G, Captura_Marimba_M01!$A:$A, Captura_Obra!A13, Captura_Marimba_M01!$C:$C, Captura_Obra!B13, Captura_Marimba_M01!$D:$D, Captura_Obra!D13))>0), "", 0) | I309: =IF(OR(Captura_Obra!A13="", (SUMIFS(Captura_Pegaso!$H:$H, Captura_Pegaso!$A:$A, Captura_Obra!A13, Captura_Pegaso!$D:$D, Captura_Obra!B13, Captura_Pegaso!$E:$E, Captura_Obra!D13) + SUMIFS(Captura_Marimba_M01!$G:$G, Captura_Marimba_M01!$A:$A, Captura_Obra!A13, Captura_Marimba_M01!$C:$C, Captura_Obra!B13, Captura_Marimba_M01!$D:$D, Captura_Obra!D13))>0), "", Captura_Obra!F13) | J309: =IF(OR(Captura_Obra!A13="", (SUMIFS(Captura_Pegaso!$H:$H, Captura_Pegaso!$A:$A, Captura_Obra!A13, Captura_Pegaso!$D:$D, Captura_Obra!B13, Captura_Pegaso!$E:$E, Captura_Obra!D13) + SUMIFS(Captura_Marimba_M01!$G:$G, Captura_Marimba_M01!$A:$A, Captura_Obra!A13, Captura_Marimba_M01!$C:$C, Captura_Obra!B13, Captura_Marimba_M01!$D:$D, Captura_Obra!D13))>0), "", H309 - I309)
A310: =IF(OR(Captura_Obra!A14="", (SUMIFS(Captura_Pegaso!$H:$H, Captura_Pegaso!$A:$A, Captura_Obra!A14, Captura_Pegaso!$D:$D, Captura_Obra!B14, Captura_Pegaso!$E:$E, Captura_Obra!D14) + SUMIFS(Captura_Marimba_M01!$G:$G, Captura_Marimba_M01!$A:$A, Captura_Obra!A14, Captura_Marimba_M01!$C:$C, Captura_Obra!B14, Captura_Marimba_M01!$D:$D, Captura_Obra!D14))>0), "", "Huérfano Obra") | B310: =IF(OR(Captura_Obra!A14="", (SUMIFS(Captura_Pegaso!$H:$H, Captura_Pegaso!$A:$A, Captura_Obra!A14, Captura_Pegaso!$D:$D, Captura_Obra!B14, Captura_Pegaso!$E:$E, Captura_Obra!D14) + SUMIFS(Captura_Marimba_M01!$G:$G, Captura_Marimba_M01!$A:$A, Captura_Obra!A14, Captura_Marimba_M01!$C:$C, Captura_Obra!B14, Captura_Marimba_M01!$D:$D, Captura_Obra!D14))>0), "", "No Reportado") | C310: =IF(OR(Captura_Obra!A14="", (SUMIFS(Captura_Pegaso!$H:$H, Captura_Pegaso!$A:$A, Captura_Obra!A14, Captura_Pegaso!$D:$D, Captura_Obra!B14, Captura_Pegaso!$E:$E, Captura_Obra!D14) + SUMIFS(Captura_Marimba_M01!$G:$G, Captura_Marimba_M01!$A:$A, Captura_Obra!A14, Captura_Marimba_M01!$C:$C, Captura_Obra!B14, Captura_Marimba_M01!$D:$D, Captura_Obra!D14))>0), "", Captura_Obra!N14) | D310: =IF(OR(Captura_Obra!A14="", (SUMIFS(Captura_Pegaso!$H:$H, Captura_Pegaso!$A:$A, Captura_Obra!A14, Captura_Pegaso!$D:$D, Captura_Obra!B14, Captura_Pegaso!$E:$E, Captura_Obra!D14) + SUMIFS(Captura_Marimba_M01!$G:$G, Captura_Marimba_M01!$A:$A, Captura_Obra!A14, Captura_Marimba_M01!$C:$C, Captura_Obra!B14, Captura_Marimba_M01!$D:$D, Captura_Obra!D14))>0), "", "❌ Falta en Pipa") | E310: =IF(OR(Captura_Obra!A14="", (SUMIFS(Captura_Pegaso!$H:$H, Captura_Pegaso!$A:$A, Captura_Obra!A14, Captura_Pegaso!$D:$D, Captura_Obra!B14, Captura_Pegaso!$E:$E, Captura_Obra!D14) + SUMIFS(Captura_Marimba_M01!$G:$G, Captura_Marimba_M01!$A:$A, Captura_Obra!A14, Captura_Marimba_M01!$C:$C, Captura_Obra!B14, Captura_Marimba_M01!$D:$D, Captura_Obra!D14))>0), "", Captura_Obra!A14) | F310: =IF(OR(Captura_Obra!A14="", (SUMIFS(Captura_Pegaso!$H:$H, Captura_Pegaso!$A:$A, Captura_Obra!A14, Captura_Pegaso!$D:$D, Captura_Obra!B14, Captura_Pegaso!$E:$E, Captura_Obra!D14) + SUMIFS(Captura_Marimba_M01!$G:$G, Captura_Marimba_M01!$A:$A, Captura_Obra!A14, Captura_Marimba_M01!$C:$C, Captura_Obra!B14, Captura_Marimba_M01!$D:$D, Captura_Obra!D14))>0), "", Captura_Obra!B14) | G310: =IF(OR(Captura_Obra!A14="", (SUMIFS(Captura_Pegaso!$H:$H, Captura_Pegaso!$A:$A, Captura_Obra!A14, Captura_Pegaso!$D:$D, Captura_Obra!B14, Captura_Pegaso!$E:$E, Captura_Obra!D14) + SUMIFS(Captura_Marimba_M01!$G:$G, Captura_Marimba_M01!$A:$A, Captura_Obra!A14, Captura_Marimba_M01!$C:$C, Captura_Obra!B14, Captura_Marimba_M01!$D:$D, Captura_Obra!D14))>0), "", Captura_Obra!D14) | H310: =IF(OR(Captura_Obra!A14="", (SUMIFS(Captura_Pegaso!$H:$H, Captura_Pegaso!$A:$A, Captura_Obra!A14, Captura_Pegaso!$D:$D, Captura_Obra!B14, Captura_Pegaso!$E:$E, Captura_Obra!D14) + SUMIFS(Captura_Marimba_M01!$G:$G, Captura_Marimba_M01!$A:$A, Captura_Obra!A14, Captura_Marimba_M01!$C:$C, Captura_Obra!B14, Captura_Marimba_M01!$D:$D, Captura_Obra!D14))>0), "", 0) | I310: =IF(OR(Captura_Obra!A14="", (SUMIFS(Captura_Pegaso!$H:$H, Captura_Pegaso!$A:$A, Captura_Obra!A14, Captura_Pegaso!$D:$D, Captura_Obra!B14, Captura_Pegaso!$E:$E, Captura_Obra!D14) + SUMIFS(Captura_Marimba_M01!$G:$G, Captura_Marimba_M01!$A:$A, Captura_Obra!A14, Captura_Marimba_M01!$C:$C, Captura_Obra!B14, Captura_Marimba_M01!$D:$D, Captura_Obra!D14))>0), "", Captura_Obra!F14) | J310: =IF(OR(Captura_Obra!A14="", (SUMIFS(Captura_Pegaso!$H:$H, Captura_Pegaso!$A:$A, Captura_Obra!A14, Captura_Pegaso!$D:$D, Captura_Obra!B14, Captura_Pegaso!$E:$E, Captura_Obra!D14) + SUMIFS(Captura_Marimba_M01!$G:$G, Captura_Marimba_M01!$A:$A, Captura_Obra!A14, Captura_Marimba_M01!$C:$C, Captura_Obra!B14, Captura_Marimba_M01!$D:$D, Captura_Obra!D14))>0), "", H310 - I310)
A311: =IF(OR(Captura_Obra!A15="", (SUMIFS(Captura_Pegaso!$H:$H, Captura_Pegaso!$A:$A, Captura_Obra!A15, Captura_Pegaso!$D:$D, Captura_Obra!B15, Captura_Pegaso!$E:$E, Captura_Obra!D15) + SUMIFS(Captura_Marimba_M01!$G:$G, Captura_Marimba_M01!$A:$A, Captura_Obra!A15, Captura_Marimba_M01!$C:$C, Captura_Obra!B15, Captura_Marimba_M01!$D:$D, Captura_Obra!D15))>0), "", "Huérfano Obra") | B311: =IF(OR(Captura_Obra!A15="", (SUMIFS(Captura_Pegaso!$H:$H, Captura_Pegaso!$A:$A, Captura_Obra!A15, Captura_Pegaso!$D:$D, Captura_Obra!B15, Captura_Pegaso!$E:$E, Captura_Obra!D15) + SUMIFS(Captura_Marimba_M01!$G:$G, Captura_Marimba_M01!$A:$A, Captura_Obra!A15, Captura_Marimba_M01!$C:$C, Captura_Obra!B15, Captura_Marimba_M01!$D:$D, Captura_Obra!D15))>0), "", "No Reportado") | C311: =IF(OR(Captura_Obra!A15="", (SUMIFS(Captura_Pegaso!$H:$H, Captura_Pegaso!$A:$A, Captura_Obra!A15, Captura_Pegaso!$D:$D, Captura_Obra!B15, Captura_Pegaso!$E:$E, Captura_Obra!D15) + SUMIFS(Captura_Marimba_M01!$G:$G, Captura_Marimba_M01!$A:$A, Captura_Obra!A15, Captura_Marimba_M01!$C:$C, Captura_Obra!B15, Captura_Marimba_M01!$D:$D, Captura_Obra!D15))>0), "", Captura_Obra!N15) | D311: =IF(OR(Captura_Obra!A15="", (SUMIFS(Captura_Pegaso!$H:$H, Captura_Pegaso!$A:$A, Captura_Obra!A15, Captura_Pegaso!$D:$D, Captura_Obra!B15, Captura_Pegaso!$E:$E, Captura_Obra!D15) + SUMIFS(Captura_Marimba_M01!$G:$G, Captura_Marimba_M01!$A:$A, Captura_Obra!A15, Captura_Marimba_M01!$C:$C, Captura_Obra!B15, Captura_Marimba_M01!$D:$D, Captura_Obra!D15))>0), "", "❌ Falta en Pipa") | E311: =IF(OR(Captura_Obra!A15="", (SUMIFS(Captura_Pegaso!$H:$H, Captura_Pegaso!$A:$A, Captura_Obra!A15, Captura_Pegaso!$D:$D, Captura_Obra!B15, Captura_Pegaso!$E:$E, Captura_Obra!D15) + SUMIFS(Captura_Marimba_M01!$G:$G, Captura_Marimba_M01!$A:$A, Captura_Obra!A15, Captura_Marimba_M01!$C:$C, Captura_Obra!B15, Captura_Marimba_M01!$D:$D, Captura_Obra!D15))>0), "", Captura_Obra!A15) | F311: =IF(OR(Captura_Obra!A15="", (SUMIFS(Captura_Pegaso!$H:$H, Captura_Pegaso!$A:$A, Captura_Obra!A15, Captura_Pegaso!$D:$D, Captura_Obra!B15, Captura_Pegaso!$E:$E, Captura_Obra!D15) + SUMIFS(Captura_Marimba_M01!$G:$G, Captura_Marimba_M01!$A:$A, Captura_Obra!A15, Captura_Marimba_M01!$C:$C, Captura_Obra!B15, Captura_Marimba_M01!$D:$D, Captura_Obra!D15))>0), "", Captura_Obra!B15) | G311: =IF(OR(Captura_Obra!A15="", (SUMIFS(Captura_Pegaso!$H:$H, Captura_Pegaso!$A:$A, Captura_Obra!A15, Captura_Pegaso!$D:$D, Captura_Obra!B15, Captura_Pegaso!$E:$E, Captura_Obra!D15) + SUMIFS(Captura_Marimba_M01!$G:$G, Captura_Marimba_M01!$A:$A, Captura_Obra!A15, Captura_Marimba_M01!$C:$C, Captura_Obra!B15, Captura_Marimba_M01!$D:$D, Captura_Obra!D15))>0), "", Captura_Obra!D15) | H311: =IF(OR(Captura_Obra!A15="", (SUMIFS(Captura_Pegaso!$H:$H, Captura_Pegaso!$A:$A, Captura_Obra!A15, Captura_Pegaso!$D:$D, Captura_Obra!B15, Captura_Pegaso!$E:$E, Captura_Obra!D15) + SUMIFS(Captura_Marimba_M01!$G:$G, Captura_Marimba_M01!$A:$A, Captura_Obra!A15, Captura_Marimba_M01!$C:$C, Captura_Obra!B15, Captura_Marimba_M01!$D:$D, Captura_Obra!D15))>0), "", 0) | I311: =IF(OR(Captura_Obra!A15="", (SUMIFS(Captura_Pegaso!$H:$H, Captura_Pegaso!$A:$A, Captura_Obra!A15, Captura_Pegaso!$D:$D, Captura_Obra!B15, Captura_Pegaso!$E:$E, Captura_Obra!D15) + SUMIFS(Captura_Marimba_M01!$G:$G, Captura_Marimba_M01!$A:$A, Captura_Obra!A15, Captura_Marimba_M01!$C:$C, Captura_Obra!B15, Captura_Marimba_M01!$D:$D, Captura_Obra!D15))>0), "", Captura_Obra!F15) | J311: =IF(OR(Captura_Obra!A15="", (SUMIFS(Captura_Pegaso!$H:$H, Captura_Pegaso!$A:$A, Captura_Obra!A15, Captura_Pegaso!$D:$D, Captura_Obra!B15, Captura_Pegaso!$E:$E, Captura_Obra!D15) + SUMIFS(Captura_Marimba_M01!$G:$G, Captura_Marimba_M01!$A:$A, Captura_Obra!A15, Captura_Marimba_M01!$C:$C, Captura_Obra!B15, Captura_Marimba_M01!$D:$D, Captura_Obra!D15))>0), "", H311 - I311)
A312: =IF(OR(Captura_Obra!A16="", (SUMIFS(Captura_Pegaso!$H:$H, Captura_Pegaso!$A:$A, Captura_Obra!A16, Captura_Pegaso!$D:$D, Captura_Obra!B16, Captura_Pegaso!$E:$E, Captura_Obra!D16) + SUMIFS(Captura_Marimba_M01!$G:$G, Captura_Marimba_M01!$A:$A, Captura_Obra!A16, Captura_Marimba_M01!$C:$C, Captura_Obra!B16, Captura_Marimba_M01!$D:$D, Captura_Obra!D16))>0), "", "Huérfano Obra") | B312: =IF(OR(Captura_Obra!A16="", (SUMIFS(Captura_Pegaso!$H:$H, Captura_Pegaso!$A:$A, Captura_Obra!A16, Captura_Pegaso!$D:$D, Captura_Obra!B16, Captura_Pegaso!$E:$E, Captura_Obra!D16) + SUMIFS(Captura_Marimba_M01!$G:$G, Captura_Marimba_M01!$A:$A, Captura_Obra!A16, Captura_Marimba_M01!$C:$C, Captura_Obra!B16, Captura_Marimba_M01!$D:$D, Captura_Obra!D16))>0), "", "No Reportado") | C312: =IF(OR(Captura_Obra!A16="", (SUMIFS(Captura_Pegaso!$H:$H, Captura_Pegaso!$A:$A, Captura_Obra!A16, Captura_Pegaso!$D:$D, Captura_Obra!B16, Captura_Pegaso!$E:$E, Captura_Obra!D16) + SUMIFS(Captura_Marimba_M01!$G:$G, Captura_Marimba_M01!$A:$A, Captura_Obra!A16, Captura_Marimba_M01!$C:$C, Captura_Obra!B16, Captura_Marimba_M01!$D:$D, Captura_Obra!D16))>0), "", Captura_Obra!N16) | D312: =IF(OR(Captura_Obra!A16="", (SUMIFS(Captura_Pegaso!$H:$H, Captura_Pegaso!$A:$A, Captura_Obra!A16, Captura_Pegaso!$D:$D, Captura_Obra!B16, Captura_Pegaso!$E:$E, Captura_Obra!D16) + SUMIFS(Captura_Marimba_M01!$G:$G, Captura_Marimba_M01!$A:$A, Captura_Obra!A16, Captura_Marimba_M01!$C:$C, Captura_Obra!B16, Captura_Marimba_M01!$D:$D, Captura_Obra!D16))>0), "", "❌ Falta en Pipa") | E312: =IF(OR(Captura_Obra!A16="", (SUMIFS(Captura_Pegaso!$H:$H, Captura_Pegaso!$A:$A, Captura_Obra!A16, Captura_Pegaso!$D:$D, Captura_Obra!B16, Captura_Pegaso!$E:$E, Captura_Obra!D16) + SUMIFS(Captura_Marimba_M01!$G:$G, Captura_Marimba_M01!$A:$A, Captura_Obra!A16, Captura_Marimba_M01!$C:$C, Captura_Obra!B16, Captura_Marimba_M01!$D:$D, Captura_Obra!D16))>0), "", Captura_Obra!A16) | F312: =IF(OR(Captura_Obra!A16="", (SUMIFS(Captura_Pegaso!$H:$H, Captura_Pegaso!$A:$A, Captura_Obra!A16, Captura_Pegaso!$D:$D, Captura_Obra!B16, Captura_Pegaso!$E:$E, Captura_Obra!D16) + SUMIFS(Captura_Marimba_M01!$G:$G, Captura_Marimba_M01!$A:$A, Captura_Obra!A16, Captura_Marimba_M01!$C:$C, Captura_Obra!B16, Captura_Marimba_M01!$D:$D, Captura_Obra!D16))>0), "", Captura_Obra!B16) | G312: =IF(OR(Captura_Obra!A16="", (SUMIFS(Captura_Pegaso!$H:$H, Captura_Pegaso!$A:$A, Captura_Obra!A16, Captura_Pegaso!$D:$D, Captura_Obra!B16, Captura_Pegaso!$E:$E, Captura_Obra!D16) + SUMIFS(Captura_Marimba_M01!$G:$G, Captura_Marimba_M01!$A:$A, Captura_Obra!A16, Captura_Marimba_M01!$C:$C, Captura_Obra!B16, Captura_Marimba_M01!$D:$D, Captura_Obra!D16))>0), "", Captura_Obra!D16) | H312: =IF(OR(Captura_Obra!A16="", (SUMIFS(Captura_Pegaso!$H:$H, Captura_Pegaso!$A:$A, Captura_Obra!A16, Captura_Pegaso!$D:$D, Captura_Obra!B16, Captura_Pegaso!$E:$E, Captura_Obra!D16) + SUMIFS(Captura_Marimba_M01!$G:$G, Captura_Marimba_M01!$A:$A, Captura_Obra!A16, Captura_Marimba_M01!$C:$C, Captura_Obra!B16, Captura_Marimba_M01!$D:$D, Captura_Obra!D16))>0), "", 0) | I312: =IF(OR(Captura_Obra!A16="", (SUMIFS(Captura_Pegaso!$H:$H, Captura_Pegaso!$A:$A, Captura_Obra!A16, Captura_Pegaso!$D:$D, Captura_Obra!B16, Captura_Pegaso!$E:$E, Captura_Obra!D16) + SUMIFS(Captura_Marimba_M01!$G:$G, Captura_Marimba_M01!$A:$A, Captura_Obra!A16, Captura_Marimba_M01!$C:$C, Captura_Obra!B16, Captura_Marimba_M01!$D:$D, Captura_Obra!D16))>0), "", Captura_Obra!F16) | J312: =IF(OR(Captura_Obra!A16="", (SUMIFS(Captura_Pegaso!$H:$H, Captura_Pegaso!$A:$A, Captura_Obra!A16, Captura_Pegaso!$D:$D, Captura_Obra!B16, Captura_Pegaso!$E:$E, Captura_Obra!D16) + SUMIFS(Captura_Marimba_M01!$G:$G, Captura_Marimba_M01!$A:$A, Captura_Obra!A16, Captura_Marimba_M01!$C:$C, Captura_Obra!B16, Captura_Marimba_M01!$D:$D, Captura_Obra!D16))>0), "", H312 - I312)
... A482: =IF(OR(Captura_Obra!A186="", (SUMIFS(Captura_Pegaso!$H:$H, Captura_Pegaso!$A:$A, Captura_Obra!A186, Captura_Pegaso!$D:$D, Captura_Obra!B186, Captura_Pegaso!$E:$E, Captura_Obra!D186) + SUMIFS(Captura_Marimba_M01!$G:$G, Captura_Marimba_M01!$A:$A, Captura_Obra!A186, Captura_Marimba_M01!$C:$C, Captura_Obra!B186, Captura_Marimba_M01!$D:$D, Captura_Obra!D186))>0), "", "Huérfano Obra") | B482: =IF(OR(Captura_Obra!A186="", (SUMIFS(Captura_Pegaso!$H:$H, Captura_Pegaso!$A:$A, Captura_Obra!A186, Captura_Pegaso!$D:$D, Captura_Obra!B186, Captura_Pegaso!$E:$E, Captura_Obra!D186) + SUMIFS(Captura_Marimba_M01!$G:$G, Captura_Marimba_M01!$A:$A, Captura_Obra!A186, Captura_Marimba_M01!$C:$C, Captura_Obra!B186, Captura_Marimba_M01!$D:$D, Captura_Obra!D186))>0), "", "No Reportado") | C482: =IF(OR(Captura_Obra!A186="", (SUMIFS(Captura_Pegaso!$H:$H, Captura_Pegaso!$A:$A, Captura_Obra!A186, Captura_Pegaso!$D:$D, Captura_Obra!B186, Captura_Pegaso!$E:$E, Captura_Obra!D186) + SUMIFS(Captura_Marimba_M01!$G:$G, Captura_Marimba_M01!$A:$A, Captura_Obra!A186, Captura_Marimba_M01!$C:$C, Captura_Obra!B186, Captura_Marimba_M01!$D:$D, Captura_Obra!D186))>0), "", Captura_Obra!N186) | D482: =IF(OR(Captura_Obra!A186="", (SUMIFS(Captura_Pegaso!$H:$H, Captura_Pegaso!$A:$A, Captura_Obra!A186, Captura_Pegaso!$D:$D, Captura_Obra!B186, Captura_Pegaso!$E:$E, Captura_Obra!D186) + SUMIFS(Captura_Marimba_M01!$G:$G, Captura_Marimba_M01!$A:$A, Captura_Obra!A186, Captura_Marimba_M01!$C:$C, Captura_Obra!B186, Captura_Marimba_M01!$D:$D, Captura_Obra!D186))>0), "", "❌ Falta en Pipa") | E482: =IF(OR(Captura_Obra!A186="", (SUMIFS(Captura_Pegaso!$H:$H, Captura_Pegaso!$A:$A, Captura_Obra!A186, Captura_Pegaso!$D:$D, Captura_Obra!B186, Captura_Pegaso!$E:$E, Captura_Obra!D186) + SUMIFS(Captura_Marimba_M01!$G:$G, Captura_Marimba_M01!$A:$A, Captura_Obra!A186, Captura_Marimba_M01!$C:$C, Captura_Obra!B186, Captura_Marimba_M01!$D:$D, Captura_Obra!D186))>0), "", Captura_Obra!A186) | F482: =IF(OR(Captura_Obra!A186="", (SUMIFS(Captura_Pegaso!$H:$H, Captura_Pegaso!$A:$A, Captura_Obra!A186, Captura_Pegaso!$D:$D, Captura_Obra!B186, Captura_Pegaso!$E:$E, Captura_Obra!D186) + SUMIFS(Captura_Marimba_M01!$G:$G, Captura_Marimba_M01!$A:$A, Captura_Obra!A186, Captura_Marimba_M01!$C:$C, Captura_Obra!B186, Captura_Marimba_M01!$D:$D, Captura_Obra!D186))>0), "", Captura_Obra!B186) | G482: =IF(OR(Captura_Obra!A186="", (SUMIFS(Captura_Pegaso!$H:$H, Captura_Pegaso!$A:$A, Captura_Obra!A186, Captura_Pegaso!$D:$D, Captura_Obra!B186, Captura_Pegaso!$E:$E, Captura_Obra!D186) + SUMIFS(Captura_Marimba_M01!$G:$G, Captura_Marimba_M01!$A:$A, Captura_Obra!A186, Captura_Marimba_M01!$C:$C, Captura_Obra!B186, Captura_Marimba_M01!$D:$D, Captura_Obra!D186))>0), "", Captura_Obra!D186) | H482: =IF(OR(Captura_Obra!A186="", (SUMIFS(Captura_Pegaso!$H:$H, Captura_Pegaso!$A:$A, Captura_Obra!A186, Captura_Pegaso!$D:$D, Captura_Obra!B186, Captura_Pegaso!$E:$E, Captura_Obra!D186) + SUMIFS(Captura_Marimba_M01!$G:$G, Captura_Marimba_M01!$A:$A, Captura_Obra!A186, Captura_Marimba_M01!$C:$C, Captura_Obra!B186, Captura_Marimba_M01!$D:$D, Captura_Obra!D186))>0), "", 0) | I482: =IF(OR(Captura_Obra!A186="", (SUMIFS(Captura_Pegaso!$H:$H, Captura_Pegaso!$A:$A, Captura_Obra!A186, Captura_Pegaso!$D:$D, Captura_Obra!B186, Captura_Pegaso!$E:$E, Captura_Obra!D186) + SUMIFS(Captura_Marimba_M01!$G:$G, Captura_Marimba_M01!$A:$A, Captura_Obra!A186, Captura_Marimba_M01!$C:$C, Captura_Obra!B186, Captura_Marimba_M01!$D:$D, Captura_Obra!D186))>0), "", Captura_Obra!F186) | J482: =IF(OR(Captura_Obra!A186="", (SUMIFS(Captura_Pegaso!$H:$H, Captura_Pegaso!$A:$A, Captura_Obra!A186, Captura_Pegaso!$D:$D, Captura_Obra!B186, Captura_Pegaso!$E:$E, Captura_Obra!D186) + SUMIFS(Captura_Marimba_M01!$G:$G, Captura_Marimba_M01!$A:$A, Captura_Obra!A186, Captura_Marimba_M01!$C:$C, Captura_Obra!B186, Captura_Marimba_M01!$D:$D, Captura_Obra!D186))>0), "", H482 - I482)
A483: =IF(OR(Captura_Obra!#REF!="", (SUMIFS(Captura_Pegaso!$H:$H, Captura_Pegaso!$A:$A, Captura_Obra!#REF!, Captura_Pegaso!$D:$D, Captura_Obra!#REF!, Captura_Pegaso!$E:$E, Captura_Obra!#REF!) + SUMIFS(Captura_Marimba_M01!$G:$G, Captura_Marimba_M01!$A:$A, Captura_Obra!#REF!, Captura_Marimba_M01!$C:$C, Captura_Obra!#REF!, Captura_Marimba_M01!$D:$D, Captura_Obra!#REF!))>0), "", "Huérfano Obra") | B483: =IF(OR(Captura_Obra!#REF!="", (SUMIFS(Captura_Pegaso!$H:$H, Captura_Pegaso!$A:$A, Captura_Obra!#REF!, Captura_Pegaso!$D:$D, Captura_Obra!#REF!, Captura_Pegaso!$E:$E, Captura_Obra!#REF!) + SUMIFS(Captura_Marimba_M01!$G:$G, Captura_Marimba_M01!$A:$A, Captura_Obra!#REF!, Captura_Marimba_M01!$C:$C, Captura_Obra!#REF!, Captura_Marimba_M01!$D:$D, Captura_Obra!#REF!))>0), "", "No Reportado") | C483: =IF(OR(Captura_Obra!#REF!="", (SUMIFS(Captura_Pegaso!$H:$H, Captura_Pegaso!$A:$A, Captura_Obra!#REF!, Captura_Pegaso!$D:$D, Captura_Obra!#REF!, Captura_Pegaso!$E:$E, Captura_Obra!#REF!) + SUMIFS(Captura_Marimba_M01!$G:$G, Captura_Marimba_M01!$A:$A, Captura_Obra!#REF!, Captura_Marimba_M01!$C:$C, Captura_Obra!#REF!, Captura_Marimba_M01!$D:$D, Captura_Obra!#REF!))>0), "", Captura_Obra!N187) | D483: =IF(OR(Captura_Obra!#REF!="", (SUMIFS(Captura_Pegaso!$H:$H, Captura_Pegaso!$A:$A, Captura_Obra!#REF!, Captura_Pegaso!$D:$D, Captura_Obra!#REF!, Captura_Pegaso!$E:$E, Captura_Obra!#REF!) + SUMIFS(Captura_Marimba_M01!$G:$G, Captura_Marimba_M01!$A:$A, Captura_Obra!#REF!, Captura_Marimba_M01!$C:$C, Captura_Obra!#REF!, Captura_Marimba_M01!$D:$D, Captura_Obra!#REF!))>0), "", "❌ Falta en Pipa") | E483: =IF(OR(Captura_Obra!#REF!="", (SUMIFS(Captura_Pegaso!$H:$H, Captura_Pegaso!$A:$A, Captura_Obra!#REF!, Captura_Pegaso!$D:$D, Captura_Obra!#REF!, Captura_Pegaso!$E:$E, Captura_Obra!#REF!) + SUMIFS(Captura_Marimba_M01!$G:$G, Captura_Marimba_M01!$A:$A, Captura_Obra!#REF!, Captura_Marimba_M01!$C:$C, Captura_Obra!#REF!, Captura_Marimba_M01!$D:$D, Captura_Obra!#REF!))>0), "", Captura_Obra!#REF!) | F483: =IF(OR(Captura_Obra!#REF!="", (SUMIFS(Captura_Pegaso!$H:$H, Captura_Pegaso!$A:$A, Captura_Obra!#REF!, Captura_Pegaso!$D:$D, Captura_Obra!#REF!, Captura_Pegaso!$E:$E, Captura_Obra!#REF!) + SUMIFS(Captura_Marimba_M01!$G:$G, Captura_Marimba_M01!$A:$A, Captura_Obra!#REF!, Captura_Marimba_M01!$C:$C, Captura_Obra!#REF!, Captura_Marimba_M01!$D:$D, Captura_Obra!#REF!))>0), "", Captura_Obra!#REF!) | G483: =IF(OR(Captura_Obra!#REF!="", (SUMIFS(Captura_Pegaso!$H:$H, Captura_Pegaso!$A:$A, Captura_Obra!#REF!, Captura_Pegaso!$D:$D, Captura_Obra!#REF!, Captura_Pegaso!$E:$E, Captura_Obra!#REF!) + SUMIFS(Captura_Marimba_M01!$G:$G, Captura_Marimba_M01!$A:$A, Captura_Obra!#REF!, Captura_Marimba_M01!$C:$C, Captura_Obra!#REF!, Captura_Marimba_M01!$D:$D, Captura_Obra!#REF!))>0), "", Captura_Obra!#REF!) | H483: =IF(OR(Captura_Obra!#REF!="", (SUMIFS(Captura_Pegaso!$H:$H, Captura_Pegaso!$A:$A, Captura_Obra!#REF!, Captura_Pegaso!$D:$D, Captura_Obra!#REF!, Captura_Pegaso!$E:$E, Captura_Obra!#REF!) + SUMIFS(Captura_Marimba_M01!$G:$G, Captura_Marimba_M01!$A:$A, Captura_Obra!#REF!, Captura_Marimba_M01!$C:$C, Captura_Obra!#REF!, Captura_Marimba_M01!$D:$D, Captura_Obra!#REF!))>0), "", 0) | I483: =IF(OR(Captura_Obra!#REF!="", (SUMIFS(Captura_Pegaso!$H:$H, Captura_Pegaso!$A:$A, Captura_Obra!#REF!, Captura_Pegaso!$D:$D, Captura_Obra!#REF!, Captura_Pegaso!$E:$E, Captura_Obra!#REF!) + SUMIFS(Captura_Marimba_M01!$G:$G, Captura_Marimba_M01!$A:$A, Captura_Obra!#REF!, Captura_Marimba_M01!$C:$C, Captura_Obra!#REF!, Captura_Marimba_M01!$D:$D, Captura_Obra!#REF!))>0), "", Captura_Obra!#REF!) | J483: =IF(OR(Captura_Obra!#REF!="", (SUMIFS(Captura_Pegaso!$H:$H, Captura_Pegaso!$A:$A, Captura_Obra!#REF!, Captura_Pegaso!$D:$D, Captura_Obra!#REF!, Captura_Pegaso!$E:$E, Captura_Obra!#REF!) + SUMIFS(Captura_Marimba_M01!$G:$G, Captura_Marimba_M01!$A:$A, Captura_Obra!#REF!, Captura_Marimba_M01!$C:$C, Captura_Obra!#REF!, Captura_Marimba_M01!$D:$D, Captura_Obra!#REF!))>0), "", H483 - I483)
A484: =IF(OR(Captura_Obra!#REF!="", (SUMIFS(Captura_Pegaso!$H:$H, Captura_Pegaso!$A:$A, Captura_Obra!#REF!, Captura_Pegaso!$D:$D, Captura_Obra!#REF!, Captura_Pegaso!$E:$E, Captura_Obra!#REF!) + SUMIFS(Captura_Marimba_M01!$G:$G, Captura_Marimba_M01!$A:$A, Captura_Obra!#REF!, Captura_Marimba_M01!$C:$C, Captura_Obra!#REF!, Captura_Marimba_M01!$D:$D, Captura_Obra!#REF!))>0), "", "Huérfano Obra") | B484: =IF(OR(Captura_Obra!#REF!="", (SUMIFS(Captura_Pegaso!$H:$H, Captura_Pegaso!$A:$A, Captura_Obra!#REF!, Captura_Pegaso!$D:$D, Captura_Obra!#REF!, Captura_Pegaso!$E:$E, Captura_Obra!#REF!) + SUMIFS(Captura_Marimba_M01!$G:$G, Captura_Marimba_M01!$A:$A, Captura_Obra!#REF!, Captura_Marimba_M01!$C:$C, Captura_Obra!#REF!, Captura_Marimba_M01!$D:$D, Captura_Obra!#REF!))>0), "", "No Reportado") | C484: =IF(OR(Captura_Obra!#REF!="", (SUMIFS(Captura_Pegaso!$H:$H, Captura_Pegaso!$A:$A, Captura_Obra!#REF!, Captura_Pegaso!$D:$D, Captura_Obra!#REF!, Captura_Pegaso!$E:$E, Captura_Obra!#REF!) + SUMIFS(Captura_Marimba_M01!$G:$G, Captura_Marimba_M01!$A:$A, Captura_Obra!#REF!, Captura_Marimba_M01!$C:$C, Captura_Obra!#REF!, Captura_Marimba_M01!$D:$D, Captura_Obra!#REF!))>0), "", Captura_Obra!N188) | D484: =IF(OR(Captura_Obra!#REF!="", (SUMIFS(Captura_Pegaso!$H:$H, Captura_Pegaso!$A:$A, Captura_Obra!#REF!, Captura_Pegaso!$D:$D, Captura_Obra!#REF!, Captura_Pegaso!$E:$E, Captura_Obra!#REF!) + SUMIFS(Captura_Marimba_M01!$G:$G, Captura_Marimba_M01!$A:$A, Captura_Obra!#REF!, Captura_Marimba_M01!$C:$C, Captura_Obra!#REF!, Captura_Marimba_M01!$D:$D, Captura_Obra!#REF!))>0), "", "❌ Falta en Pipa") | E484: =IF(OR(Captura_Obra!#REF!="", (SUMIFS(Captura_Pegaso!$H:$H, Captura_Pegaso!$A:$A, Captura_Obra!#REF!, Captura_Pegaso!$D:$D, Captura_Obra!#REF!, Captura_Pegaso!$E:$E, Captura_Obra!#REF!) + SUMIFS(Captura_Marimba_M01!$G:$G, Captura_Marimba_M01!$A:$A, Captura_Obra!#REF!, Captura_Marimba_M01!$C:$C, Captura_Obra!#REF!, Captura_Marimba_M01!$D:$D, Captura_Obra!#REF!))>0), "", Captura_Obra!#REF!) | F484: =IF(OR(Captura_Obra!#REF!="", (SUMIFS(Captura_Pegaso!$H:$H, Captura_Pegaso!$A:$A, Captura_Obra!#REF!, Captura_Pegaso!$D:$D, Captura_Obra!#REF!, Captura_Pegaso!$E:$E, Captura_Obra!#REF!) + SUMIFS(Captura_Marimba_M01!$G:$G, Captura_Marimba_M01!$A:$A, Captura_Obra!#REF!, Captura_Marimba_M01!$C:$C, Captura_Obra!#REF!, Captura_Marimba_M01!$D:$D, Captura_Obra!#REF!))>0), "", Captura_Obra!#REF!) | G484: =IF(OR(Captura_Obra!#REF!="", (SUMIFS(Captura_Pegaso!$H:$H, Captura_Pegaso!$A:$A, Captura_Obra!#REF!, Captura_Pegaso!$D:$D, Captura_Obra!#REF!, Captura_Pegaso!$E:$E, Captura_Obra!#REF!) + SUMIFS(Captura_Marimba_M01!$G:$G, Captura_Marimba_M01!$A:$A, Captura_Obra!#REF!, Captura_Marimba_M01!$C:$C, Captura_Obra!#REF!, Captura_Marimba_M01!$D:$D, Captura_Obra!#REF!))>0), "", Captura_Obra!#REF!) | H484: =IF(OR(Captura_Obra!#REF!="", (SUMIFS(Captura_Pegaso!$H:$H, Captura_Pegaso!$A:$A, Captura_Obra!#REF!, Captura_Pegaso!$D:$D, Captura_Obra!#REF!, Captura_Pegaso!$E:$E, Captura_Obra!#REF!) + SUMIFS(Captura_Marimba_M01!$G:$G, Captura_Marimba_M01!$A:$A, Captura_Obra!#REF!, Captura_Marimba_M01!$C:$C, Captura_Obra!#REF!, Captura_Marimba_M01!$D:$D, Captura_Obra!#REF!))>0), "", 0) | I484: =IF(OR(Captura_Obra!#REF!="", (SUMIFS(Captura_Pegaso!$H:$H, Captura_Pegaso!$A:$A, Captura_Obra!#REF!, Captura_Pegaso!$D:$D, Captura_Obra!#REF!, Captura_Pegaso!$E:$E, Captura_Obra!#REF!) + SUMIFS(Captura_Marimba_M01!$G:$G, Captura_Marimba_M01!$A:$A, Captura_Obra!#REF!, Captura_Marimba_M01!$C:$C, Captura_Obra!#REF!, Captura_Marimba_M01!$D:$D, Captura_Obra!#REF!))>0), "", Captura_Obra!#REF!) | J484: =IF(OR(Captura_Obra!#REF!="", (SUMIFS(Captura_Pegaso!$H:$H, Captura_Pegaso!$A:$A, Captura_Obra!#REF!, Captura_Pegaso!$D:$D, Captura_Obra!#REF!, Captura_Pegaso!$E:$E, Captura_Obra!#REF!) + SUMIFS(Captura_Marimba_M01!$G:$G, Captura_Marimba_M01!$A:$A, Captura_Obra!#REF!, Captura_Marimba_M01!$C:$C, Captura_Obra!#REF!, Captura_Marimba_M01!$D:$D, Captura_Obra!#REF!))>0), "", H484 - I484)
A485: =IF(OR(Captura_Obra!A189="", (SUMIFS(Captura_Pegaso!$H:$H, Captura_Pegaso!$A:$A, Captura_Obra!A189, Captura_Pegaso!$D:$D, Captura_Obra!B189, Captura_Pegaso!$E:$E, Captura_Obra!D189) + SUMIFS(Captura_Marimba_M01!$G:$G, Captura_Marimba_M01!$A:$A, Captura_Obra!A189, Captura_Marimba_M01!$C:$C, Captura_Obra!B189, Captura_Marimba_M01!$D:$D, Captura_Obra!D189))>0), "", "Huérfano Obra") | B485: =IF(OR(Captura_Obra!A189="", (SUMIFS(Captura_Pegaso!$H:$H, Captura_Pegaso!$A:$A, Captura_Obra!A189, Captura_Pegaso!$D:$D, Captura_Obra!B189, Captura_Pegaso!$E:$E, Captura_Obra!D189) + SUMIFS(Captura_Marimba_M01!$G:$G, Captura_Marimba_M01!$A:$A, Captura_Obra!A189, Captura_Marimba_M01!$C:$C, Captura_Obra!B189, Captura_Marimba_M01!$D:$D, Captura_Obra!D189))>0), "", "No Reportado") | C485: =IF(OR(Captura_Obra!A189="", (SUMIFS(Captura_Pegaso!$H:$H, Captura_Pegaso!$A:$A, Captura_Obra!A189, Captura_Pegaso!$D:$D, Captura_Obra!B189, Captura_Pegaso!$E:$E, Captura_Obra!D189) + SUMIFS(Captura_Marimba_M01!$G:$G, Captura_Marimba_M01!$A:$A, Captura_Obra!A189, Captura_Marimba_M01!$C:$C, Captura_Obra!B189, Captura_Marimba_M01!$D:$D, Captura_Obra!D189))>0), "", Captura_Obra!N189) | D485: =IF(OR(Captura_Obra!A189="", (SUMIFS(Captura_Pegaso!$H:$H, Captura_Pegaso!$A:$A, Captura_Obra!A189, Captura_Pegaso!$D:$D, Captura_Obra!B189, Captura_Pegaso!$E:$E, Captura_Obra!D189) + SUMIFS(Captura_Marimba_M01!$G:$G, Captura_Marimba_M01!$A:$A, Captura_Obra!A189, Captura_Marimba_M01!$C:$C, Captura_Obra!B189, Captura_Marimba_M01!$D:$D, Captura_Obra!D189))>0), "", "❌ Falta en Pipa") | E485: =IF(OR(Captura_Obra!A189="", (SUMIFS(Captura_Pegaso!$H:$H, Captura_Pegaso!$A:$A, Captura_Obra!A189, Captura_Pegaso!$D:$D, Captura_Obra!B189, Captura_Pegaso!$E:$E, Captura_Obra!D189) + SUMIFS(Captura_Marimba_M01!$G:$G, Captura_Marimba_M01!$A:$A, Captura_Obra!A189, Captura_Marimba_M01!$C:$C, Captura_Obra!B189, Captura_Marimba_M01!$D:$D, Captura_Obra!D189))>0), "", Captura_Obra!A189) | F485: =IF(OR(Captura_Obra!A189="", (SUMIFS(Captura_Pegaso!$H:$H, Captura_Pegaso!$A:$A, Captura_Obra!A189, Captura_Pegaso!$D:$D, Captura_Obra!B189, Captura_Pegaso!$E:$E, Captura_Obra!D189) + SUMIFS(Captura_Marimba_M01!$G:$G, Captura_Marimba_M01!$A:$A, Captura_Obra!A189, Captura_Marimba_M01!$C:$C, Captura_Obra!B189, Captura_Marimba_M01!$D:$D, Captura_Obra!D189))>0), "", Captura_Obra!B189) | G485: =IF(OR(Captura_Obra!A189="", (SUMIFS(Captura_Pegaso!$H:$H, Captura_Pegaso!$A:$A, Captura_Obra!A189, Captura_Pegaso!$D:$D, Captura_Obra!B189, Captura_Pegaso!$E:$E, Captura_Obra!D189) + SUMIFS(Captura_Marimba_M01!$G:$G, Captura_Marimba_M01!$A:$A, Captura_Obra!A189, Captura_Marimba_M01!$C:$C, Captura_Obra!B189, Captura_Marimba_M01!$D:$D, Captura_Obra!D189))>0), "", Captura_Obra!D189) | H485: =IF(OR(Captura_Obra!A189="", (SUMIFS(Captura_Pegaso!$H:$H, Captura_Pegaso!$A:$A, Captura_Obra!A189, Captura_Pegaso!$D:$D, Captura_Obra!B189, Captura_Pegaso!$E:$E, Captura_Obra!D189) + SUMIFS(Captura_Marimba_M01!$G:$G, Captura_Marimba_M01!$A:$A, Captura_Obra!A189, Captura_Marimba_M01!$C:$C, Captura_Obra!B189, Captura_Marimba_M01!$D:$D, Captura_Obra!D189))>0), "", 0) | I485: =IF(OR(Captura_Obra!A189="", (SUMIFS(Captura_Pegaso!$H:$H, Captura_Pegaso!$A:$A, Captura_Obra!A189, Captura_Pegaso!$D:$D, Captura_Obra!B189, Captura_Pegaso!$E:$E, Captura_Obra!D189) + SUMIFS(Captura_Marimba_M01!$G:$G, Captura_Marimba_M01!$A:$A, Captura_Obra!A189, Captura_Marimba_M01!$C:$C, Captura_Obra!B189, Captura_Marimba_M01!$D:$D, Captura_Obra!D189))>0), "", Captura_Obra!F189) | J485: =IF(OR(Captura_Obra!A189="", (SUMIFS(Captura_Pegaso!$H:$H, Captura_Pegaso!$A:$A, Captura_Obra!A189, Captura_Pegaso!$D:$D, Captura_Obra!B189, Captura_Pegaso!$E:$E, Captura_Obra!D189) + SUMIFS(Captura_Marimba_M01!$G:$G, Captura_Marimba_M01!$A:$A, Captura_Obra!A189, Captura_Marimba_M01!$C:$C, Captura_Obra!B189, Captura_Marimba_M01!$D:$D, Captura_Obra!D189))>0), "", H485 - I485)
A486: =IF(OR(Captura_Obra!A190="", (SUMIFS(Captura_Pegaso!$H:$H, Captura_Pegaso!$A:$A, Captura_Obra!A190, Captura_Pegaso!$D:$D, Captura_Obra!B190, Captura_Pegaso!$E:$E, Captura_Obra!D190) + SUMIFS(Captura_Marimba_M01!$G:$G, Captura_Marimba_M01!$A:$A, Captura_Obra!A190, Captura_Marimba_M01!$C:$C, Captura_Obra!B190, Captura_Marimba_M01!$D:$D, Captura_Obra!D190))>0), "", "Huérfano Obra") | B486: =IF(OR(Captura_Obra!A190="", (SUMIFS(Captura_Pegaso!$H:$H, Captura_Pegaso!$A:$A, Captura_Obra!A190, Captura_Pegaso!$D:$D, Captura_Obra!B190, Captura_Pegaso!$E:$E, Captura_Obra!D190) + SUMIFS(Captura_Marimba_M01!$G:$G, Captura_Marimba_M01!$A:$A, Captura_Obra!A190, Captura_Marimba_M01!$C:$C, Captura_Obra!B190, Captura_Marimba_M01!$D:$D, Captura_Obra!D190))>0), "", "No Reportado") | C486: =IF(OR(Captura_Obra!A190="", (SUMIFS(Captura_Pegaso!$H:$H, Captura_Pegaso!$A:$A, Captura_Obra!A190, Captura_Pegaso!$D:$D, Captura_Obra!B190, Captura_Pegaso!$E:$E, Captura_Obra!D190) + SUMIFS(Captura_Marimba_M01!$G:$G, Captura_Marimba_M01!$A:$A, Captura_Obra!A190, Captura_Marimba_M01!$C:$C, Captura_Obra!B190, Captura_Marimba_M01!$D:$D, Captura_Obra!D190))>0), "", Captura_Obra!N190) | D486: =IF(OR(Captura_Obra!A190="", (SUMIFS(Captura_Pegaso!$H:$H, Captura_Pegaso!$A:$A, Captura_Obra!A190, Captura_Pegaso!$D:$D, Captura_Obra!B190, Captura_Pegaso!$E:$E, Captura_Obra!D190) + SUMIFS(Captura_Marimba_M01!$G:$G, Captura_Marimba_M01!$A:$A, Captura_Obra!A190, Captura_Marimba_M01!$C:$C, Captura_Obra!B190, Captura_Marimba_M01!$D:$D, Captura_Obra!D190))>0), "", "❌ Falta en Pipa") | E486: =IF(OR(Captura_Obra!A190="", (SUMIFS(Captura_Pegaso!$H:$H, Captura_Pegaso!$A:$A, Captura_Obra!A190, Captura_Pegaso!$D:$D, Captura_Obra!B190, Captura_Pegaso!$E:$E, Captura_Obra!D190) + SUMIFS(Captura_Marimba_M01!$G:$G, Captura_Marimba_M01!$A:$A, Captura_Obra!A190, Captura_Marimba_M01!$C:$C, Captura_Obra!B190, Captura_Marimba_M01!$D:$D, Captura_Obra!D190))>0), "", Captura_Obra!A190) | F486: =IF(OR(Captura_Obra!A190="", (SUMIFS(Captura_Pegaso!$H:$H, Captura_Pegaso!$A:$A, Captura_Obra!A190, Captura_Pegaso!$D:$D, Captura_Obra!B190, Captura_Pegaso!$E:$E, Captura_Obra!D190) + SUMIFS(Captura_Marimba_M01!$G:$G, Captura_Marimba_M01!$A:$A, Captura_Obra!A190, Captura_Marimba_M01!$C:$C, Captura_Obra!B190, Captura_Marimba_M01!$D:$D, Captura_Obra!D190))>0), "", Captura_Obra!B190) | G486: =IF(OR(Captura_Obra!A190="", (SUMIFS(Captura_Pegaso!$H:$H, Captura_Pegaso!$A:$A, Captura_Obra!A190, Captura_Pegaso!$D:$D, Captura_Obra!B190, Captura_Pegaso!$E:$E, Captura_Obra!D190) + SUMIFS(Captura_Marimba_M01!$G:$G, Captura_Marimba_M01!$A:$A, Captura_Obra!A190, Captura_Marimba_M01!$C:$C, Captura_Obra!B190, Captura_Marimba_M01!$D:$D, Captura_Obra!D190))>0), "", Captura_Obra!D190) | H486: =IF(OR(Captura_Obra!A190="", (SUMIFS(Captura_Pegaso!$H:$H, Captura_Pegaso!$A:$A, Captura_Obra!A190, Captura_Pegaso!$D:$D, Captura_Obra!B190, Captura_Pegaso!$E:$E, Captura_Obra!D190) + SUMIFS(Captura_Marimba_M01!$G:$G, Captura_Marimba_M01!$A:$A, Captura_Obra!A190, Captura_Marimba_M01!$C:$C, Captura_Obra!B190, Captura_Marimba_M01!$D:$D, Captura_Obra!D190))>0), "", 0) | I486: =IF(OR(Captura_Obra!A190="", (SUMIFS(Captura_Pegaso!$H:$H, Captura_Pegaso!$A:$A, Captura_Obra!A190, Captura_Pegaso!$D:$D, Captura_Obra!B190, Captura_Pegaso!$E:$E, Captura_Obra!D190) + SUMIFS(Captura_Marimba_M01!$G:$G, Captura_Marimba_M01!$A:$A, Captura_Obra!A190, Captura_Marimba_M01!$C:$C, Captura_Obra!B190, Captura_Marimba_M01!$D:$D, Captura_Obra!D190))>0), "", Captura_Obra!F190) | J486: =IF(OR(Captura_Obra!A190="", (SUMIFS(Captura_Pegaso!$H:$H, Captura_Pegaso!$A:$A, Captura_Obra!A190, Captura_Pegaso!$D:$D, Captura_Obra!B190, Captura_Pegaso!$E:$E, Captura_Obra!D190) + SUMIFS(Captura_Marimba_M01!$G:$G, Captura_Marimba_M01!$A:$A, Captura_Obra!A190, Captura_Marimba_M01!$C:$C, Captura_Obra!B190, Captura_Marimba_M01!$D:$D, Captura_Obra!D190))>0), "", H486 - I486)
A487: =IF(OR(Captura_Obra!A191="", (SUMIFS(Captura_Pegaso!$H:$H, Captura_Pegaso!$A:$A, Captura_Obra!A191, Captura_Pegaso!$D:$D, Captura_Obra!B191, Captura_Pegaso!$E:$E, Captura_Obra!D191) + SUMIFS(Captura_Marimba_M01!$G:$G, Captura_Marimba_M01!$A:$A, Captura_Obra!A191, Captura_Marimba_M01!$C:$C, Captura_Obra!B191, Captura_Marimba_M01!$D:$D, Captura_Obra!D191))>0), "", "Huérfano Obra") | B487: =IF(OR(Captura_Obra!A191="", (SUMIFS(Captura_Pegaso!$H:$H, Captura_Pegaso!$A:$A, Captura_Obra!A191, Captura_Pegaso!$D:$D, Captura_Obra!B191, Captura_Pegaso!$E:$E, Captura_Obra!D191) + SUMIFS(Captura_Marimba_M01!$G:$G, Captura_Marimba_M01!$A:$A, Captura_Obra!A191, Captura_Marimba_M01!$C:$C, Captura_Obra!B191, Captura_Marimba_M01!$D:$D, Captura_Obra!D191))>0), "", "No Reportado") | C487: =IF(OR(Captura_Obra!A191="", (SUMIFS(Captura_Pegaso!$H:$H, Captura_Pegaso!$A:$A, Captura_Obra!A191, Captura_Pegaso!$D:$D, Captura_Obra!B191, Captura_Pegaso!$E:$E, Captura_Obra!D191) + SUMIFS(Captura_Marimba_M01!$G:$G, Captura_Marimba_M01!$A:$A, Captura_Obra!A191, Captura_Marimba_M01!$C:$C, Captura_Obra!B191, Captura_Marimba_M01!$D:$D, Captura_Obra!D191))>0), "", Captura_Obra!N191) | D487: =IF(OR(Captura_Obra!A191="", (SUMIFS(Captura_Pegaso!$H:$H, Captura_Pegaso!$A:$A, Captura_Obra!A191, Captura_Pegaso!$D:$D, Captura_Obra!B191, Captura_Pegaso!$E:$E, Captura_Obra!D191) + SUMIFS(Captura_Marimba_M01!$G:$G, Captura_Marimba_M01!$A:$A, Captura_Obra!A191, Captura_Marimba_M01!$C:$C, Captura_Obra!B191, Captura_Marimba_M01!$D:$D, Captura_Obra!D191))>0), "", "❌ Falta en Pipa") | E487: =IF(OR(Captura_Obra!A191="", (SUMIFS(Captura_Pegaso!$H:$H, Captura_Pegaso!$A:$A, Captura_Obra!A191, Captura_Pegaso!$D:$D, Captura_Obra!B191, Captura_Pegaso!$E:$E, Captura_Obra!D191) + SUMIFS(Captura_Marimba_M01!$G:$G, Captura_Marimba_M01!$A:$A, Captura_Obra!A191, Captura_Marimba_M01!$C:$C, Captura_Obra!B191, Captura_Marimba_M01!$D:$D, Captura_Obra!D191))>0), "", Captura_Obra!A191) | F487: =IF(OR(Captura_Obra!A191="", (SUMIFS(Captura_Pegaso!$H:$H, Captura_Pegaso!$A:$A, Captura_Obra!A191, Captura_Pegaso!$D:$D, Captura_Obra!B191, Captura_Pegaso!$E:$E, Captura_Obra!D191) + SUMIFS(Captura_Marimba_M01!$G:$G, Captura_Marimba_M01!$A:$A, Captura_Obra!A191, Captura_Marimba_M01!$C:$C, Captura_Obra!B191, Captura_Marimba_M01!$D:$D, Captura_Obra!D191))>0), "", Captura_Obra!B191) | G487: =IF(OR(Captura_Obra!A191="", (SUMIFS(Captura_Pegaso!$H:$H, Captura_Pegaso!$A:$A, Captura_Obra!A191, Captura_Pegaso!$D:$D, Captura_Obra!B191, Captura_Pegaso!$E:$E, Captura_Obra!D191) + SUMIFS(Captura_Marimba_M01!$G:$G, Captura_Marimba_M01!$A:$A, Captura_Obra!A191, Captura_Marimba_M01!$C:$C, Captura_Obra!B191, Captura_Marimba_M01!$D:$D, Captura_Obra!D191))>0), "", Captura_Obra!D191) | H487: =IF(OR(Captura_Obra!A191="", (SUMIFS(Captura_Pegaso!$H:$H, Captura_Pegaso!$A:$A, Captura_Obra!A191, Captura_Pegaso!$D:$D, Captura_Obra!B191, Captura_Pegaso!$E:$E, Captura_Obra!D191) + SUMIFS(Captura_Marimba_M01!$G:$G, Captura_Marimba_M01!$A:$A, Captura_Obra!A191, Captura_Marimba_M01!$C:$C, Captura_Obra!B191, Captura_Marimba_M01!$D:$D, Captura_Obra!D191))>0), "", 0) | I487: =IF(OR(Captura_Obra!A191="", (SUMIFS(Captura_Pegaso!$H:$H, Captura_Pegaso!$A:$A, Captura_Obra!A191, Captura_Pegaso!$D:$D, Captura_Obra!B191, Captura_Pegaso!$E:$E, Captura_Obra!D191) + SUMIFS(Captura_Marimba_M01!$G:$G, Captura_Marimba_M01!$A:$A, Captura_Obra!A191, Captura_Marimba_M01!$C:$C, Captura_Obra!B191, Captura_Marimba_M01!$D:$D, Captura_Obra!D191))>0), "", Captura_Obra!F191) | J487: =IF(OR(Captura_Obra!A191="", (SUMIFS(Captura_Pegaso!$H:$H, Captura_Pegaso!$A:$A, Captura_Obra!A191, Captura_Pegaso!$D:$D, Captura_Obra!B191, Captura_Pegaso!$E:$E, Captura_Obra!D191) + SUMIFS(Captura_Marimba_M01!$G:$G, Captura_Marimba_M01!$A:$A, Captura_Obra!A191, Captura_Marimba_M01!$C:$C, Captura_Obra!B191, Captura_Marimba_M01!$D:$D, Captura_Obra!D191))>0), "", H487 - I487)
A488: =IF(OR(Captura_Obra!A192="", (SUMIFS(Captura_Pegaso!$H:$H, Captura_Pegaso!$A:$A, Captura_Obra!A192, Captura_Pegaso!$D:$D, Captura_Obra!B192, Captura_Pegaso!$E:$E, Captura_Obra!D192) + SUMIFS(Captura_Marimba_M01!$G:$G, Captura_Marimba_M01!$A:$A, Captura_Obra!A192, Captura_Marimba_M01!$C:$C, Captura_Obra!B192, Captura_Marimba_M01!$D:$D, Captura_Obra!D192))>0), "", "Huérfano Obra") | B488: =IF(OR(Captura_Obra!A192="", (SUMIFS(Captura_Pegaso!$H:$H, Captura_Pegaso!$A:$A, Captura_Obra!A192, Captura_Pegaso!$D:$D, Captura_Obra!B192, Captura_Pegaso!$E:$E, Captura_Obra!D192) + SUMIFS(Captura_Marimba_M01!$G:$G, Captura_Marimba_M01!$A:$A, Captura_Obra!A192, Captura_Marimba_M01!$C:$C, Captura_Obra!B192, Captura_Marimba_M01!$D:$D, Captura_Obra!D192))>0), "", "No Reportado") | C488: =IF(OR(Captura_Obra!A192="", (SUMIFS(Captura_Pegaso!$H:$H, Captura_Pegaso!$A:$A, Captura_Obra!A192, Captura_Pegaso!$D:$D, Captura_Obra!B192, Captura_Pegaso!$E:$E, Captura_Obra!D192) + SUMIFS(Captura_Marimba_M01!$G:$G, Captura_Marimba_M01!$A:$A, Captura_Obra!A192, Captura_Marimba_M01!$C:$C, Captura_Obra!B192, Captura_Marimba_M01!$D:$D, Captura_Obra!D192))>0), "", Captura_Obra!N192) | D488: =IF(OR(Captura_Obra!A192="", (SUMIFS(Captura_Pegaso!$H:$H, Captura_Pegaso!$A:$A, Captura_Obra!A192, Captura_Pegaso!$D:$D, Captura_Obra!B192, Captura_Pegaso!$E:$E, Captura_Obra!D192) + SUMIFS(Captura_Marimba_M01!$G:$G, Captura_Marimba_M01!$A:$A, Captura_Obra!A192, Captura_Marimba_M01!$C:$C, Captura_Obra!B192, Captura_Marimba_M01!$D:$D, Captura_Obra!D192))>0), "", "❌ Falta en Pipa") | E488: =IF(OR(Captura_Obra!A192="", (SUMIFS(Captura_Pegaso!$H:$H, Captura_Pegaso!$A:$A, Captura_Obra!A192, Captura_Pegaso!$D:$D, Captura_Obra!B192, Captura_Pegaso!$E:$E, Captura_Obra!D192) + SUMIFS(Captura_Marimba_M01!$G:$G, Captura_Marimba_M01!$A:$A, Captura_Obra!A192, Captura_Marimba_M01!$C:$C, Captura_Obra!B192, Captura_Marimba_M01!$D:$D, Captura_Obra!D192))>0), "", Captura_Obra!A192) | F488: =IF(OR(Captura_Obra!A192="", (SUMIFS(Captura_Pegaso!$H:$H, Captura_Pegaso!$A:$A, Captura_Obra!A192, Captura_Pegaso!$D:$D, Captura_Obra!B192, Captura_Pegaso!$E:$E, Captura_Obra!D192) + SUMIFS(Captura_Marimba_M01!$G:$G, Captura_Marimba_M01!$A:$A, Captura_Obra!A192, Captura_Marimba_M01!$C:$C, Captura_Obra!B192, Captura_Marimba_M01!$D:$D, Captura_Obra!D192))>0), "", Captura_Obra!B192) | G488: =IF(OR(Captura_Obra!A192="", (SUMIFS(Captura_Pegaso!$H:$H, Captura_Pegaso!$A:$A, Captura_Obra!A192, Captura_Pegaso!$D:$D, Captura_Obra!B192, Captura_Pegaso!$E:$E, Captura_Obra!D192) + SUMIFS(Captura_Marimba_M01!$G:$G, Captura_Marimba_M01!$A:$A, Captura_Obra!A192, Captura_Marimba_M01!$C:$C, Captura_Obra!B192, Captura_Marimba_M01!$D:$D, Captura_Obra!D192))>0), "", Captura_Obra!D192) | H488: =IF(OR(Captura_Obra!A192="", (SUMIFS(Captura_Pegaso!$H:$H, Captura_Pegaso!$A:$A, Captura_Obra!A192, Captura_Pegaso!$D:$D, Captura_Obra!B192, Captura_Pegaso!$E:$E, Captura_Obra!D192) + SUMIFS(Captura_Marimba_M01!$G:$G, Captura_Marimba_M01!$A:$A, Captura_Obra!A192, Captura_Marimba_M01!$C:$C, Captura_Obra!B192, Captura_Marimba_M01!$D:$D, Captura_Obra!D192))>0), "", 0) | I488: =IF(OR(Captura_Obra!A192="", (SUMIFS(Captura_Pegaso!$H:$H, Captura_Pegaso!$A:$A, Captura_Obra!A192, Captura_Pegaso!$D:$D, Captura_Obra!B192, Captura_Pegaso!$E:$E, Captura_Obra!D192) + SUMIFS(Captura_Marimba_M01!$G:$G, Captura_Marimba_M01!$A:$A, Captura_Obra!A192, Captura_Marimba_M01!$C:$C, Captura_Obra!B192, Captura_Marimba_M01!$D:$D, Captura_Obra!D192))>0), "", Captura_Obra!F192) | J488: =IF(OR(Captura_Obra!A192="", (SUMIFS(Captura_Pegaso!$H:$H, Captura_Pegaso!$A:$A, Captura_Obra!A192, Captura_Pegaso!$D:$D, Captura_Obra!B192, Captura_Pegaso!$E:$E, Captura_Obra!D192) + SUMIFS(Captura_Marimba_M01!$G:$G, Captura_Marimba_M01!$A:$A, Captura_Obra!A192, Captura_Marimba_M01!$C:$C, Captura_Obra!B192, Captura_Marimba_M01!$D:$D, Captura_Obra!D192))>0), "", H488 - I488)
A489: =IF(OR(Captura_Obra!A193="", (SUMIFS(Captura_Pegaso!$H:$H, Captura_Pegaso!$A:$A, Captura_Obra!A193, Captura_Pegaso!$D:$D, Captura_Obra!B193, Captura_Pegaso!$E:$E, Captura_Obra!D193) + SUMIFS(Captura_Marimba_M01!$G:$G, Captura_Marimba_M01!$A:$A, Captura_Obra!A193, Captura_Marimba_M01!$C:$C, Captura_Obra!B193, Captura_Marimba_M01!$D:$D, Captura_Obra!D193))>0), "", "Huérfano Obra") | B489: =IF(OR(Captura_Obra!A193="", (SUMIFS(Captura_Pegaso!$H:$H, Captura_Pegaso!$A:$A, Captura_Obra!A193, Captura_Pegaso!$D:$D, Captura_Obra!B193, Captura_Pegaso!$E:$E, Captura_Obra!D193) + SUMIFS(Captura_Marimba_M01!$G:$G, Captura_Marimba_M01!$A:$A, Captura_Obra!A193, Captura_Marimba_M01!$C:$C, Captura_Obra!B193, Captura_Marimba_M01!$D:$D, Captura_Obra!D193))>0), "", "No Reportado") | C489: =IF(OR(Captura_Obra!A193="", (SUMIFS(Captura_Pegaso!$H:$H, Captura_Pegaso!$A:$A, Captura_Obra!A193, Captura_Pegaso!$D:$D, Captura_Obra!B193, Captura_Pegaso!$E:$E, Captura_Obra!D193) + SUMIFS(Captura_Marimba_M01!$G:$G, Captura_Marimba_M01!$A:$A, Captura_Obra!A193, Captura_Marimba_M01!$C:$C, Captura_Obra!B193, Captura_Marimba_M01!$D:$D, Captura_Obra!D193))>0), "", Captura_Obra!N193) | D489: =IF(OR(Captura_Obra!A193="", (SUMIFS(Captura_Pegaso!$H:$H, Captura_Pegaso!$A:$A, Captura_Obra!A193, Captura_Pegaso!$D:$D, Captura_Obra!B193, Captura_Pegaso!$E:$E, Captura_Obra!D193) + SUMIFS(Captura_Marimba_M01!$G:$G, Captura_Marimba_M01!$A:$A, Captura_Obra!A193, Captura_Marimba_M01!$C:$C, Captura_Obra!B193, Captura_Marimba_M01!$D:$D, Captura_Obra!D193))>0), "", "❌ Falta en Pipa") | E489: =IF(OR(Captura_Obra!A193="", (SUMIFS(Captura_Pegaso!$H:$H, Captura_Pegaso!$A:$A, Captura_Obra!A193, Captura_Pegaso!$D:$D, Captura_Obra!B193, Captura_Pegaso!$E:$E, Captura_Obra!D193) + SUMIFS(Captura_Marimba_M01!$G:$G, Captura_Marimba_M01!$A:$A, Captura_Obra!A193, Captura_Marimba_M01!$C:$C, Captura_Obra!B193, Captura_Marimba_M01!$D:$D, Captura_Obra!D193))>0), "", Captura_Obra!A193) | F489: =IF(OR(Captura_Obra!A193="", (SUMIFS(Captura_Pegaso!$H:$H, Captura_Pegaso!$A:$A, Captura_Obra!A193, Captura_Pegaso!$D:$D, Captura_Obra!B193, Captura_Pegaso!$E:$E, Captura_Obra!D193) + SUMIFS(Captura_Marimba_M01!$G:$G, Captura_Marimba_M01!$A:$A, Captura_Obra!A193, Captura_Marimba_M01!$C:$C, Captura_Obra!B193, Captura_Marimba_M01!$D:$D, Captura_Obra!D193))>0), "", Captura_Obra!B193) | G489: =IF(OR(Captura_Obra!A193="", (SUMIFS(Captura_Pegaso!$H:$H, Captura_Pegaso!$A:$A, Captura_Obra!A193, Captura_Pegaso!$D:$D, Captura_Obra!B193, Captura_Pegaso!$E:$E, Captura_Obra!D193) + SUMIFS(Captura_Marimba_M01!$G:$G, Captura_Marimba_M01!$A:$A, Captura_Obra!A193, Captura_Marimba_M01!$C:$C, Captura_Obra!B193, Captura_Marimba_M01!$D:$D, Captura_Obra!D193))>0), "", Captura_Obra!D193) | H489: =IF(OR(Captura_Obra!A193="", (SUMIFS(Captura_Pegaso!$H:$H, Captura_Pegaso!$A:$A, Captura_Obra!A193, Captura_Pegaso!$D:$D, Captura_Obra!B193, Captura_Pegaso!$E:$E, Captura_Obra!D193) + SUMIFS(Captura_Marimba_M01!$G:$G, Captura_Marimba_M01!$A:$A, Captura_Obra!A193, Captura_Marimba_M01!$C:$C, Captura_Obra!B193, Captura_Marimba_M01!$D:$D, Captura_Obra!D193))>0), "", 0) | I489: =IF(OR(Captura_Obra!A193="", (SUMIFS(Captura_Pegaso!$H:$H, Captura_Pegaso!$A:$A, Captura_Obra!A193, Captura_Pegaso!$D:$D, Captura_Obra!B193, Captura_Pegaso!$E:$E, Captura_Obra!D193) + SUMIFS(Captura_Marimba_M01!$G:$G, Captura_Marimba_M01!$A:$A, Captura_Obra!A193, Captura_Marimba_M01!$C:$C, Captura_Obra!B193, Captura_Marimba_M01!$D:$D, Captura_Obra!D193))>0), "", Captura_Obra!F193) | J489: =IF(OR(Captura_Obra!A193="", (SUMIFS(Captura_Pegaso!$H:$H, Captura_Pegaso!$A:$A, Captura_Obra!A193, Captura_Pegaso!$D:$D, Captura_Obra!B193, Captura_Pegaso!$E:$E, Captura_Obra!D193) + SUMIFS(Captura_Marimba_M01!$G:$G, Captura_Marimba_M01!$A:$A, Captura_Obra!A193, Captura_Marimba_M01!$C:$C, Captura_Obra!B193, Captura_Marimba_M01!$D:$D, Captura_Obra!D193))>0), "", H489 - I489)
A490: =IF(OR(Captura_Obra!A194="", (SUMIFS(Captura_Pegaso!$H:$H, Captura_Pegaso!$A:$A, Captura_Obra!A194, Captura_Pegaso!$D:$D, Captura_Obra!B194, Captura_Pegaso!$E:$E, Captura_Obra!D194) + SUMIFS(Captura_Marimba_M01!$G:$G, Captura_Marimba_M01!$A:$A, Captura_Obra!A194, Captura_Marimba_M01!$C:$C, Captura_Obra!B194, Captura_Marimba_M01!$D:$D, Captura_Obra!D194))>0), "", "Huérfano Obra") | B490: =IF(OR(Captura_Obra!A194="", (SUMIFS(Captura_Pegaso!$H:$H, Captura_Pegaso!$A:$A, Captura_Obra!A194, Captura_Pegaso!$D:$D, Captura_Obra!B194, Captura_Pegaso!$E:$E, Captura_Obra!D194) + SUMIFS(Captura_Marimba_M01!$G:$G, Captura_Marimba_M01!$A:$A, Captura_Obra!A194, Captura_Marimba_M01!$C:$C, Captura_Obra!B194, Captura_Marimba_M01!$D:$D, Captura_Obra!D194))>0), "", "No Reportado") | C490: =IF(OR(Captura_Obra!A194="", (SUMIFS(Captura_Pegaso!$H:$H, Captura_Pegaso!$A:$A, Captura_Obra!A194, Captura_Pegaso!$D:$D, Captura_Obra!B194, Captura_Pegaso!$E:$E, Captura_Obra!D194) + SUMIFS(Captura_Marimba_M01!$G:$G, Captura_Marimba_M01!$A:$A, Captura_Obra!A194, Captura_Marimba_M01!$C:$C, Captura_Obra!B194, Captura_Marimba_M01!$D:$D, Captura_Obra!D194))>0), "", Captura_Obra!N194) | D490: =IF(OR(Captura_Obra!A194="", (SUMIFS(Captura_Pegaso!$H:$H, Captura_Pegaso!$A:$A, Captura_Obra!A194, Captura_Pegaso!$D:$D, Captura_Obra!B194, Captura_Pegaso!$E:$E, Captura_Obra!D194) + SUMIFS(Captura_Marimba_M01!$G:$G, Captura_Marimba_M01!$A:$A, Captura_Obra!A194, Captura_Marimba_M01!$C:$C, Captura_Obra!B194, Captura_Marimba_M01!$D:$D, Captura_Obra!D194))>0), "", "❌ Falta en Pipa") | E490: =IF(OR(Captura_Obra!A194="", (SUMIFS(Captura_Pegaso!$H:$H, Captura_Pegaso!$A:$A, Captura_Obra!A194, Captura_Pegaso!$D:$D, Captura_Obra!B194, Captura_Pegaso!$E:$E, Captura_Obra!D194) + SUMIFS(Captura_Marimba_M01!$G:$G, Captura_Marimba_M01!$A:$A, Captura_Obra!A194, Captura_Marimba_M01!$C:$C, Captura_Obra!B194, Captura_Marimba_M01!$D:$D, Captura_Obra!D194))>0), "", Captura_Obra!A194) | F490: =IF(OR(Captura_Obra!A194="", (SUMIFS(Captura_Pegaso!$H:$H, Captura_Pegaso!$A:$A, Captura_Obra!A194, Captura_Pegaso!$D:$D, Captura_Obra!B194, Captura_Pegaso!$E:$E, Captura_Obra!D194) + SUMIFS(Captura_Marimba_M01!$G:$G, Captura_Marimba_M01!$A:$A, Captura_Obra!A194, Captura_Marimba_M01!$C:$C, Captura_Obra!B194, Captura_Marimba_M01!$D:$D, Captura_Obra!D194))>0), "", Captura_Obra!B194) | G490: =IF(OR(Captura_Obra!A194="", (SUMIFS(Captura_Pegaso!$H:$H, Captura_Pegaso!$A:$A, Captura_Obra!A194, Captura_Pegaso!$D:$D, Captura_Obra!B194, Captura_Pegaso!$E:$E, Captura_Obra!D194) + SUMIFS(Captura_Marimba_M01!$G:$G, Captura_Marimba_M01!$A:$A, Captura_Obra!A194, Captura_Marimba_M01!$C:$C, Captura_Obra!B194, Captura_Marimba_M01!$D:$D, Captura_Obra!D194))>0), "", Captura_Obra!D194) | H490: =IF(OR(Captura_Obra!A194="", (SUMIFS(Captura_Pegaso!$H:$H, Captura_Pegaso!$A:$A, Captura_Obra!A194, Captura_Pegaso!$D:$D, Captura_Obra!B194, Captura_Pegaso!$E:$E, Captura_Obra!D194) + SUMIFS(Captura_Marimba_M01!$G:$G, Captura_Marimba_M01!$A:$A, Captura_Obra!A194, Captura_Marimba_M01!$C:$C, Captura_Obra!B194, Captura_Marimba_M01!$D:$D, Captura_Obra!D194))>0), "", 0) | I490: =IF(OR(Captura_Obra!A194="", (SUMIFS(Captura_Pegaso!$H:$H, Captura_Pegaso!$A:$A, Captura_Obra!A194, Captura_Pegaso!$D:$D, Captura_Obra!B194, Captura_Pegaso!$E:$E, Captura_Obra!D194) + SUMIFS(Captura_Marimba_M01!$G:$G, Captura_Marimba_M01!$A:$A, Captura_Obra!A194, Captura_Marimba_M01!$C:$C, Captura_Obra!B194, Captura_Marimba_M01!$D:$D, Captura_Obra!D194))>0), "", Captura_Obra!F194) | J490: =IF(OR(Captura_Obra!A194="", (SUMIFS(Captura_Pegaso!$H:$H, Captura_Pegaso!$A:$A, Captura_Obra!A194, Captura_Pegaso!$D:$D, Captura_Obra!B194, Captura_Pegaso!$E:$E, Captura_Obra!D194) + SUMIFS(Captura_Marimba_M01!$G:$G, Captura_Marimba_M01!$A:$A, Captura_Obra!A194, Captura_Marimba_M01!$C:$C, Captura_Obra!B194, Captura_Marimba_M01!$D:$D, Captura_Obra!D194))>0), "", H490 - I490)
A491: =IF(OR(Captura_Obra!A195="", (SUMIFS(Captura_Pegaso!$H:$H, Captura_Pegaso!$A:$A, Captura_Obra!A195, Captura_Pegaso!$D:$D, Captura_Obra!B195, Captura_Pegaso!$E:$E, Captura_Obra!D195) + SUMIFS(Captura_Marimba_M01!$G:$G, Captura_Marimba_M01!$A:$A, Captura_Obra!A195, Captura_Marimba_M01!$C:$C, Captura_Obra!B195, Captura_Marimba_M01!$D:$D, Captura_Obra!D195))>0), "", "Huérfano Obra") | B491: =IF(OR(Captura_Obra!A195="", (SUMIFS(Captura_Pegaso!$H:$H, Captura_Pegaso!$A:$A, Captura_Obra!A195, Captura_Pegaso!$D:$D, Captura_Obra!B195, Captura_Pegaso!$E:$E, Captura_Obra!D195) + SUMIFS(Captura_Marimba_M01!$G:$G, Captura_Marimba_M01!$A:$A, Captura_Obra!A195, Captura_Marimba_M01!$C:$C, Captura_Obra!B195, Captura_Marimba_M01!$D:$D, Captura_Obra!D195))>0), "", "No Reportado") | C491: =IF(OR(Captura_Obra!A195="", (SUMIFS(Captura_Pegaso!$H:$H, Captura_Pegaso!$A:$A, Captura_Obra!A195, Captura_Pegaso!$D:$D, Captura_Obra!B195, Captura_Pegaso!$E:$E, Captura_Obra!D195) + SUMIFS(Captura_Marimba_M01!$G:$G, Captura_Marimba_M01!$A:$A, Captura_Obra!A195, Captura_Marimba_M01!$C:$C, Captura_Obra!B195, Captura_Marimba_M01!$D:$D, Captura_Obra!D195))>0), "", Captura_Obra!N195) | D491: =IF(OR(Captura_Obra!A195="", (SUMIFS(Captura_Pegaso!$H:$H, Captura_Pegaso!$A:$A, Captura_Obra!A195, Captura_Pegaso!$D:$D, Captura_Obra!B195, Captura_Pegaso!$E:$E, Captura_Obra!D195) + SUMIFS(Captura_Marimba_M01!$G:$G, Captura_Marimba_M01!$A:$A, Captura_Obra!A195, Captura_Marimba_M01!$C:$C, Captura_Obra!B195, Captura_Marimba_M01!$D:$D, Captura_Obra!D195))>0), "", "❌ Falta en Pipa") | E491: =IF(OR(Captura_Obra!A195="", (SUMIFS(Captura_Pegaso!$H:$H, Captura_Pegaso!$A:$A, Captura_Obra!A195, Captura_Pegaso!$D:$D, Captura_Obra!B195, Captura_Pegaso!$E:$E, Captura_Obra!D195) + SUMIFS(Captura_Marimba_M01!$G:$G, Captura_Marimba_M01!$A:$A, Captura_Obra!A195, Captura_Marimba_M01!$C:$C, Captura_Obra!B195, Captura_Marimba_M01!$D:$D, Captura_Obra!D195))>0), "", Captura_Obra!A195) | F491: =IF(OR(Captura_Obra!A195="", (SUMIFS(Captura_Pegaso!$H:$H, Captura_Pegaso!$A:$A, Captura_Obra!A195, Captura_Pegaso!$D:$D, Captura_Obra!B195, Captura_Pegaso!$E:$E, Captura_Obra!D195) + SUMIFS(Captura_Marimba_M01!$G:$G, Captura_Marimba_M01!$A:$A, Captura_Obra!A195, Captura_Marimba_M01!$C:$C, Captura_Obra!B195, Captura_Marimba_M01!$D:$D, Captura_Obra!D195))>0), "", Captura_Obra!B195) | G491: =IF(OR(Captura_Obra!A195="", (SUMIFS(Captura_Pegaso!$H:$H, Captura_Pegaso!$A:$A, Captura_Obra!A195, Captura_Pegaso!$D:$D, Captura_Obra!B195, Captura_Pegaso!$E:$E, Captura_Obra!D195) + SUMIFS(Captura_Marimba_M01!$G:$G, Captura_Marimba_M01!$A:$A, Captura_Obra!A195, Captura_Marimba_M01!$C:$C, Captura_Obra!B195, Captura_Marimba_M01!$D:$D, Captura_Obra!D195))>0), "", Captura_Obra!D195) | H491: =IF(OR(Captura_Obra!A195="", (SUMIFS(Captura_Pegaso!$H:$H, Captura_Pegaso!$A:$A, Captura_Obra!A195, Captura_Pegaso!$D:$D, Captura_Obra!B195, Captura_Pegaso!$E:$E, Captura_Obra!D195) + SUMIFS(Captura_Marimba_M01!$G:$G, Captura_Marimba_M01!$A:$A, Captura_Obra!A195, Captura_Marimba_M01!$C:$C, Captura_Obra!B195, Captura_Marimba_M01!$D:$D, Captura_Obra!D195))>0), "", 0) | I491: =IF(OR(Captura_Obra!A195="", (SUMIFS(Captura_Pegaso!$H:$H, Captura_Pegaso!$A:$A, Captura_Obra!A195, Captura_Pegaso!$D:$D, Captura_Obra!B195, Captura_Pegaso!$E:$E, Captura_Obra!D195) + SUMIFS(Captura_Marimba_M01!$G:$G, Captura_Marimba_M01!$A:$A, Captura_Obra!A195, Captura_Marimba_M01!$C:$C, Captura_Obra!B195, Captura_Marimba_M01!$D:$D, Captura_Obra!D195))>0), "", Captura_Obra!F195) | J491: =IF(OR(Captura_Obra!A195="", (SUMIFS(Captura_Pegaso!$H:$H, Captura_Pegaso!$A:$A, Captura_Obra!A195, Captura_Pegaso!$D:$D, Captura_Obra!B195, Captura_Pegaso!$E:$E, Captura_Obra!D195) + SUMIFS(Captura_Marimba_M01!$G:$G, Captura_Marimba_M01!$A:$A, Captura_Obra!A195, Captura_Marimba_M01!$C:$C, Captura_Obra!B195, Captura_Marimba_M01!$D:$D, Captura_Obra!D195))>0), "", H491 - I491)
A492: =IF(OR(Captura_Obra!A196="", (SUMIFS(Captura_Pegaso!$H:$H, Captura_Pegaso!$A:$A, Captura_Obra!A196, Captura_Pegaso!$D:$D, Captura_Obra!B196, Captura_Pegaso!$E:$E, Captura_Obra!D196) + SUMIFS(Captura_Marimba_M01!$G:$G, Captura_Marimba_M01!$A:$A, Captura_Obra!A196, Captura_Marimba_M01!$C:$C, Captura_Obra!B196, Captura_Marimba_M01!$D:$D, Captura_Obra!D196))>0), "", "Huérfano Obra") | B492: =IF(OR(Captura_Obra!A196="", (SUMIFS(Captura_Pegaso!$H:$H, Captura_Pegaso!$A:$A, Captura_Obra!A196, Captura_Pegaso!$D:$D, Captura_Obra!B196, Captura_Pegaso!$E:$E, Captura_Obra!D196) + SUMIFS(Captura_Marimba_M01!$G:$G, Captura_Marimba_M01!$A:$A, Captura_Obra!A196, Captura_Marimba_M01!$C:$C, Captura_Obra!B196, Captura_Marimba_M01!$D:$D, Captura_Obra!D196))>0), "", "No Reportado") | C492: =IF(OR(Captura_Obra!A196="", (SUMIFS(Captura_Pegaso!$H:$H, Captura_Pegaso!$A:$A, Captura_Obra!A196, Captura_Pegaso!$D:$D, Captura_Obra!B196, Captura_Pegaso!$E:$E, Captura_Obra!D196) + SUMIFS(Captura_Marimba_M01!$G:$G, Captura_Marimba_M01!$A:$A, Captura_Obra!A196, Captura_Marimba_M01!$C:$C, Captura_Obra!B196, Captura_Marimba_M01!$D:$D, Captura_Obra!D196))>0), "", Captura_Obra!N196) | D492: =IF(OR(Captura_Obra!A196="", (SUMIFS(Captura_Pegaso!$H:$H, Captura_Pegaso!$A:$A, Captura_Obra!A196, Captura_Pegaso!$D:$D, Captura_Obra!B196, Captura_Pegaso!$E:$E, Captura_Obra!D196) + SUMIFS(Captura_Marimba_M01!$G:$G, Captura_Marimba_M01!$A:$A, Captura_Obra!A196, Captura_Marimba_M01!$C:$C, Captura_Obra!B196, Captura_Marimba_M01!$D:$D, Captura_Obra!D196))>0), "", "❌ Falta en Pipa") | E492: =IF(OR(Captura_Obra!A196="", (SUMIFS(Captura_Pegaso!$H:$H, Captura_Pegaso!$A:$A, Captura_Obra!A196, Captura_Pegaso!$D:$D, Captura_Obra!B196, Captura_Pegaso!$E:$E, Captura_Obra!D196) + SUMIFS(Captura_Marimba_M01!$G:$G, Captura_Marimba_M01!$A:$A, Captura_Obra!A196, Captura_Marimba_M01!$C:$C, Captura_Obra!B196, Captura_Marimba_M01!$D:$D, Captura_Obra!D196))>0), "", Captura_Obra!A196) | F492: =IF(OR(Captura_Obra!A196="", (SUMIFS(Captura_Pegaso!$H:$H, Captura_Pegaso!$A:$A, Captura_Obra!A196, Captura_Pegaso!$D:$D, Captura_Obra!B196, Captura_Pegaso!$E:$E, Captura_Obra!D196) + SUMIFS(Captura_Marimba_M01!$G:$G, Captura_Marimba_M01!$A:$A, Captura_Obra!A196, Captura_Marimba_M01!$C:$C, Captura_Obra!B196, Captura_Marimba_M01!$D:$D, Captura_Obra!D196))>0), "", Captura_Obra!B196) | G492: =IF(OR(Captura_Obra!A196="", (SUMIFS(Captura_Pegaso!$H:$H, Captura_Pegaso!$A:$A, Captura_Obra!A196, Captura_Pegaso!$D:$D, Captura_Obra!B196, Captura_Pegaso!$E:$E, Captura_Obra!D196) + SUMIFS(Captura_Marimba_M01!$G:$G, Captura_Marimba_M01!$A:$A, Captura_Obra!A196, Captura_Marimba_M01!$C:$C, Captura_Obra!B196, Captura_Marimba_M01!$D:$D, Captura_Obra!D196))>0), "", Captura_Obra!D196) | H492: =IF(OR(Captura_Obra!A196="", (SUMIFS(Captura_Pegaso!$H:$H, Captura_Pegaso!$A:$A, Captura_Obra!A196, Captura_Pegaso!$D:$D, Captura_Obra!B196, Captura_Pegaso!$E:$E, Captura_Obra!D196) + SUMIFS(Captura_Marimba_M01!$G:$G, Captura_Marimba_M01!$A:$A, Captura_Obra!A196, Captura_Marimba_M01!$C:$C, Captura_Obra!B196, Captura_Marimba_M01!$D:$D, Captura_Obra!D196))>0), "", 0) | I492: =IF(OR(Captura_Obra!A196="", (SUMIFS(Captura_Pegaso!$H:$H, Captura_Pegaso!$A:$A, Captura_Obra!A196, Captura_Pegaso!$D:$D, Captura_Obra!B196, Captura_Pegaso!$E:$E, Captura_Obra!D196) + SUMIFS(Captura_Marimba_M01!$G:$G, Captura_Marimba_M01!$A:$A, Captura_Obra!A196, Captura_Marimba_M01!$C:$C, Captura_Obra!B196, Captura_Marimba_M01!$D:$D, Captura_Obra!D196))>0), "", Captura_Obra!F196) | J492: =IF(OR(Captura_Obra!A196="", (SUMIFS(Captura_Pegaso!$H:$H, Captura_Pegaso!$A:$A, Captura_Obra!A196, Captura_Pegaso!$D:$D, Captura_Obra!B196, Captura_Pegaso!$E:$E, Captura_Obra!D196) + SUMIFS(Captura_Marimba_M01!$G:$G, Captura_Marimba_M01!$A:$A, Captura_Obra!A196, Captura_Marimba_M01!$C:$C, Captura_Obra!B196, Captura_Marimba_M01!$D:$D, Captura_Obra!D196))>0), "", H492 - I492)
A493: =IF(OR(Captura_Obra!A197="", (SUMIFS(Captura_Pegaso!$H:$H, Captura_Pegaso!$A:$A, Captura_Obra!A197, Captura_Pegaso!$D:$D, Captura_Obra!B197, Captura_Pegaso!$E:$E, Captura_Obra!D197) + SUMIFS(Captura_Marimba_M01!$G:$G, Captura_Marimba_M01!$A:$A, Captura_Obra!A197, Captura_Marimba_M01!$C:$C, Captura_Obra!B197, Captura_Marimba_M01!$D:$D, Captura_Obra!D197))>0), "", "Huérfano Obra") | B493: =IF(OR(Captura_Obra!A197="", (SUMIFS(Captura_Pegaso!$H:$H, Captura_Pegaso!$A:$A, Captura_Obra!A197, Captura_Pegaso!$D:$D, Captura_Obra!B197, Captura_Pegaso!$E:$E, Captura_Obra!D197) + SUMIFS(Captura_Marimba_M01!$G:$G, Captura_Marimba_M01!$A:$A, Captura_Obra!A197, Captura_Marimba_M01!$C:$C, Captura_Obra!B197, Captura_Marimba_M01!$D:$D, Captura_Obra!D197))>0), "", "No Reportado") | C493: =IF(OR(Captura_Obra!A197="", (SUMIFS(Captura_Pegaso!$H:$H, Captura_Pegaso!$A:$A, Captura_Obra!A197, Captura_Pegaso!$D:$D, Captura_Obra!B197, Captura_Pegaso!$E:$E, Captura_Obra!D197) + SUMIFS(Captura_Marimba_M01!$G:$G, Captura_Marimba_M01!$A:$A, Captura_Obra!A197, Captura_Marimba_M01!$C:$C, Captura_Obra!B197, Captura_Marimba_M01!$D:$D, Captura_Obra!D197))>0), "", Captura_Obra!N197) | D493: =IF(OR(Captura_Obra!A197="", (SUMIFS(Captura_Pegaso!$H:$H, Captura_Pegaso!$A:$A, Captura_Obra!A197, Captura_Pegaso!$D:$D, Captura_Obra!B197, Captura_Pegaso!$E:$E, Captura_Obra!D197) + SUMIFS(Captura_Marimba_M01!$G:$G, Captura_Marimba_M01!$A:$A, Captura_Obra!A197, Captura_Marimba_M01!$C:$C, Captura_Obra!B197, Captura_Marimba_M01!$D:$D, Captura_Obra!D197))>0), "", "❌ Falta en Pipa") | E493: =IF(OR(Captura_Obra!A197="", (SUMIFS(Captura_Pegaso!$H:$H, Captura_Pegaso!$A:$A, Captura_Obra!A197, Captura_Pegaso!$D:$D, Captura_Obra!B197, Captura_Pegaso!$E:$E, Captura_Obra!D197) + SUMIFS(Captura_Marimba_M01!$G:$G, Captura_Marimba_M01!$A:$A, Captura_Obra!A197, Captura_Marimba_M01!$C:$C, Captura_Obra!B197, Captura_Marimba_M01!$D:$D, Captura_Obra!D197))>0), "", Captura_Obra!A197) | F493: =IF(OR(Captura_Obra!A197="", (SUMIFS(Captura_Pegaso!$H:$H, Captura_Pegaso!$A:$A, Captura_Obra!A197, Captura_Pegaso!$D:$D, Captura_Obra!B197, Captura_Pegaso!$E:$E, Captura_Obra!D197) + SUMIFS(Captura_Marimba_M01!$G:$G, Captura_Marimba_M01!$A:$A, Captura_Obra!A197, Captura_Marimba_M01!$C:$C, Captura_Obra!B197, Captura_Marimba_M01!$D:$D, Captura_Obra!D197))>0), "", Captura_Obra!B197) | G493: =IF(OR(Captura_Obra!A197="", (SUMIFS(Captura_Pegaso!$H:$H, Captura_Pegaso!$A:$A, Captura_Obra!A197, Captura_Pegaso!$D:$D, Captura_Obra!B197, Captura_Pegaso!$E:$E, Captura_Obra!D197) + SUMIFS(Captura_Marimba_M01!$G:$G, Captura_Marimba_M01!$A:$A, Captura_Obra!A197, Captura_Marimba_M01!$C:$C, Captura_Obra!B197, Captura_Marimba_M01!$D:$D, Captura_Obra!D197))>0), "", Captura_Obra!D197) | H493: =IF(OR(Captura_Obra!A197="", (SUMIFS(Captura_Pegaso!$H:$H, Captura_Pegaso!$A:$A, Captura_Obra!A197, Captura_Pegaso!$D:$D, Captura_Obra!B197, Captura_Pegaso!$E:$E, Captura_Obra!D197) + SUMIFS(Captura_Marimba_M01!$G:$G, Captura_Marimba_M01!$A:$A, Captura_Obra!A197, Captura_Marimba_M01!$C:$C, Captura_Obra!B197, Captura_Marimba_M01!$D:$D, Captura_Obra!D197))>0), "", 0) | I493: =IF(OR(Captura_Obra!A197="", (SUMIFS(Captura_Pegaso!$H:$H, Captura_Pegaso!$A:$A, Captura_Obra!A197, Captura_Pegaso!$D:$D, Captura_Obra!B197, Captura_Pegaso!$E:$E, Captura_Obra!D197) + SUMIFS(Captura_Marimba_M01!$G:$G, Captura_Marimba_M01!$A:$A, Captura_Obra!A197, Captura_Marimba_M01!$C:$C, Captura_Obra!B197, Captura_Marimba_M01!$D:$D, Captura_Obra!D197))>0), "", Captura_Obra!F197) | J493: =IF(OR(Captura_Obra!A197="", (SUMIFS(Captura_Pegaso!$H:$H, Captura_Pegaso!$A:$A, Captura_Obra!A197, Captura_Pegaso!$D:$D, Captura_Obra!B197, Captura_Pegaso!$E:$E, Captura_Obra!D197) + SUMIFS(Captura_Marimba_M01!$G:$G, Captura_Marimba_M01!$A:$A, Captura_Obra!A197, Captura_Marimba_M01!$C:$C, Captura_Obra!B197, Captura_Marimba_M01!$D:$D, Captura_Obra!D197))>0), "", H493 - I493)
A494: =IF(OR(Captura_Obra!A198="", (SUMIFS(Captura_Pegaso!$H:$H, Captura_Pegaso!$A:$A, Captura_Obra!A198, Captura_Pegaso!$D:$D, Captura_Obra!B198, Captura_Pegaso!$E:$E, Captura_Obra!D198) + SUMIFS(Captura_Marimba_M01!$G:$G, Captura_Marimba_M01!$A:$A, Captura_Obra!A198, Captura_Marimba_M01!$C:$C, Captura_Obra!B198, Captura_Marimba_M01!$D:$D, Captura_Obra!D198))>0), "", "Huérfano Obra") | B494: =IF(OR(Captura_Obra!A198="", (SUMIFS(Captura_Pegaso!$H:$H, Captura_Pegaso!$A:$A, Captura_Obra!A198, Captura_Pegaso!$D:$D, Captura_Obra!B198, Captura_Pegaso!$E:$E, Captura_Obra!D198) + SUMIFS(Captura_Marimba_M01!$G:$G, Captura_Marimba_M01!$A:$A, Captura_Obra!A198, Captura_Marimba_M01!$C:$C, Captura_Obra!B198, Captura_Marimba_M01!$D:$D, Captura_Obra!D198))>0), "", "No Reportado") | C494: =IF(OR(Captura_Obra!A198="", (SUMIFS(Captura_Pegaso!$H:$H, Captura_Pegaso!$A:$A, Captura_Obra!A198, Captura_Pegaso!$D:$D, Captura_Obra!B198, Captura_Pegaso!$E:$E, Captura_Obra!D198) + SUMIFS(Captura_Marimba_M01!$G:$G, Captura_Marimba_M01!$A:$A, Captura_Obra!A198, Captura_Marimba_M01!$C:$C, Captura_Obra!B198, Captura_Marimba_M01!$D:$D, Captura_Obra!D198))>0), "", Captura_Obra!N198) | D494: =IF(OR(Captura_Obra!A198="", (SUMIFS(Captura_Pegaso!$H:$H, Captura_Pegaso!$A:$A, Captura_Obra!A198, Captura_Pegaso!$D:$D, Captura_Obra!B198, Captura_Pegaso!$E:$E, Captura_Obra!D198) + SUMIFS(Captura_Marimba_M01!$G:$G, Captura_Marimba_M01!$A:$A, Captura_Obra!A198, Captura_Marimba_M01!$C:$C, Captura_Obra!B198, Captura_Marimba_M01!$D:$D, Captura_Obra!D198))>0), "", "❌ Falta en Pipa") | E494: =IF(OR(Captura_Obra!A198="", (SUMIFS(Captura_Pegaso!$H:$H, Captura_Pegaso!$A:$A, Captura_Obra!A198, Captura_Pegaso!$D:$D, Captura_Obra!B198, Captura_Pegaso!$E:$E, Captura_Obra!D198) + SUMIFS(Captura_Marimba_M01!$G:$G, Captura_Marimba_M01!$A:$A, Captura_Obra!A198, Captura_Marimba_M01!$C:$C, Captura_Obra!B198, Captura_Marimba_M01!$D:$D, Captura_Obra!D198))>0), "", Captura_Obra!A198) | F494: =IF(OR(Captura_Obra!A198="", (SUMIFS(Captura_Pegaso!$H:$H, Captura_Pegaso!$A:$A, Captura_Obra!A198, Captura_Pegaso!$D:$D, Captura_Obra!B198, Captura_Pegaso!$E:$E, Captura_Obra!D198) + SUMIFS(Captura_Marimba_M01!$G:$G, Captura_Marimba_M01!$A:$A, Captura_Obra!A198, Captura_Marimba_M01!$C:$C, Captura_Obra!B198, Captura_Marimba_M01!$D:$D, Captura_Obra!D198))>0), "", Captura_Obra!B198) | G494: =IF(OR(Captura_Obra!A198="", (SUMIFS(Captura_Pegaso!$H:$H, Captura_Pegaso!$A:$A, Captura_Obra!A198, Captura_Pegaso!$D:$D, Captura_Obra!B198, Captura_Pegaso!$E:$E, Captura_Obra!D198) + SUMIFS(Captura_Marimba_M01!$G:$G, Captura_Marimba_M01!$A:$A, Captura_Obra!A198, Captura_Marimba_M01!$C:$C, Captura_Obra!B198, Captura_Marimba_M01!$D:$D, Captura_Obra!D198))>0), "", Captura_Obra!D198) | H494: =IF(OR(Captura_Obra!A198="", (SUMIFS(Captura_Pegaso!$H:$H, Captura_Pegaso!$A:$A, Captura_Obra!A198, Captura_Pegaso!$D:$D, Captura_Obra!B198, Captura_Pegaso!$E:$E, Captura_Obra!D198) + SUMIFS(Captura_Marimba_M01!$G:$G, Captura_Marimba_M01!$A:$A, Captura_Obra!A198, Captura_Marimba_M01!$C:$C, Captura_Obra!B198, Captura_Marimba_M01!$D:$D, Captura_Obra!D198))>0), "", 0) | I494: =IF(OR(Captura_Obra!A198="", (SUMIFS(Captura_Pegaso!$H:$H, Captura_Pegaso!$A:$A, Captura_Obra!A198, Captura_Pegaso!$D:$D, Captura_Obra!B198, Captura_Pegaso!$E:$E, Captura_Obra!D198) + SUMIFS(Captura_Marimba_M01!$G:$G, Captura_Marimba_M01!$A:$A, Captura_Obra!A198, Captura_Marimba_M01!$C:$C, Captura_Obra!B198, Captura_Marimba_M01!$D:$D, Captura_Obra!D198))>0), "", Captura_Obra!F198) | J494: =IF(OR(Captura_Obra!A198="", (SUMIFS(Captura_Pegaso!$H:$H, Captura_Pegaso!$A:$A, Captura_Obra!A198, Captura_Pegaso!$D:$D, Captura_Obra!B198, Captura_Pegaso!$E:$E, Captura_Obra!D198) + SUMIFS(Captura_Marimba_M01!$G:$G, Captura_Marimba_M01!$A:$A, Captura_Obra!A198, Captura_Marimba_M01!$C:$C, Captura_Obra!B198, Captura_Marimba_M01!$D:$D, Captura_Obra!D198))>0), "", H494 - I494)
A495: =IF(OR(Captura_Obra!A199="", (SUMIFS(Captura_Pegaso!$H:$H, Captura_Pegaso!$A:$A, Captura_Obra!A199, Captura_Pegaso!$D:$D, Captura_Obra!B199, Captura_Pegaso!$E:$E, Captura_Obra!D199) + SUMIFS(Captura_Marimba_M01!$G:$G, Captura_Marimba_M01!$A:$A, Captura_Obra!A199, Captura_Marimba_M01!$C:$C, Captura_Obra!B199, Captura_Marimba_M01!$D:$D, Captura_Obra!D199))>0), "", "Huérfano Obra") | B495: =IF(OR(Captura_Obra!A199="", (SUMIFS(Captura_Pegaso!$H:$H, Captura_Pegaso!$A:$A, Captura_Obra!A199, Captura_Pegaso!$D:$D, Captura_Obra!B199, Captura_Pegaso!$E:$E, Captura_Obra!D199) + SUMIFS(Captura_Marimba_M01!$G:$G, Captura_Marimba_M01!$A:$A, Captura_Obra!A199, Captura_Marimba_M01!$C:$C, Captura_Obra!B199, Captura_Marimba_M01!$D:$D, Captura_Obra!D199))>0), "", "No Reportado") | C495: =IF(OR(Captura_Obra!A199="", (SUMIFS(Captura_Pegaso!$H:$H, Captura_Pegaso!$A:$A, Captura_Obra!A199, Captura_Pegaso!$D:$D, Captura_Obra!B199, Captura_Pegaso!$E:$E, Captura_Obra!D199) + SUMIFS(Captura_Marimba_M01!$G:$G, Captura_Marimba_M01!$A:$A, Captura_Obra!A199, Captura_Marimba_M01!$C:$C, Captura_Obra!B199, Captura_Marimba_M01!$D:$D, Captura_Obra!D199))>0), "", Captura_Obra!N199) | D495: =IF(OR(Captura_Obra!A199="", (SUMIFS(Captura_Pegaso!$H:$H, Captura_Pegaso!$A:$A, Captura_Obra!A199, Captura_Pegaso!$D:$D, Captura_Obra!B199, Captura_Pegaso!$E:$E, Captura_Obra!D199) + SUMIFS(Captura_Marimba_M01!$G:$G, Captura_Marimba_M01!$A:$A, Captura_Obra!A199, Captura_Marimba_M01!$C:$C, Captura_Obra!B199, Captura_Marimba_M01!$D:$D, Captura_Obra!D199))>0), "", "❌ Falta en Pipa") | E495: =IF(OR(Captura_Obra!A199="", (SUMIFS(Captura_Pegaso!$H:$H, Captura_Pegaso!$A:$A, Captura_Obra!A199, Captura_Pegaso!$D:$D, Captura_Obra!B199, Captura_Pegaso!$E:$E, Captura_Obra!D199) + SUMIFS(Captura_Marimba_M01!$G:$G, Captura_Marimba_M01!$A:$A, Captura_Obra!A199, Captura_Marimba_M01!$C:$C, Captura_Obra!B199, Captura_Marimba_M01!$D:$D, Captura_Obra!D199))>0), "", Captura_Obra!A199) | F495: =IF(OR(Captura_Obra!A199="", (SUMIFS(Captura_Pegaso!$H:$H, Captura_Pegaso!$A:$A, Captura_Obra!A199, Captura_Pegaso!$D:$D, Captura_Obra!B199, Captura_Pegaso!$E:$E, Captura_Obra!D199) + SUMIFS(Captura_Marimba_M01!$G:$G, Captura_Marimba_M01!$A:$A, Captura_Obra!A199, Captura_Marimba_M01!$C:$C, Captura_Obra!B199, Captura_Marimba_M01!$D:$D, Captura_Obra!D199))>0), "", Captura_Obra!B199) | G495: =IF(OR(Captura_Obra!A199="", (SUMIFS(Captura_Pegaso!$H:$H, Captura_Pegaso!$A:$A, Captura_Obra!A199, Captura_Pegaso!$D:$D, Captura_Obra!B199, Captura_Pegaso!$E:$E, Captura_Obra!D199) + SUMIFS(Captura_Marimba_M01!$G:$G, Captura_Marimba_M01!$A:$A, Captura_Obra!A199, Captura_Marimba_M01!$C:$C, Captura_Obra!B199, Captura_Marimba_M01!$D:$D, Captura_Obra!D199))>0), "", Captura_Obra!D199) | H495: =IF(OR(Captura_Obra!A199="", (SUMIFS(Captura_Pegaso!$H:$H, Captura_Pegaso!$A:$A, Captura_Obra!A199, Captura_Pegaso!$D:$D, Captura_Obra!B199, Captura_Pegaso!$E:$E, Captura_Obra!D199) + SUMIFS(Captura_Marimba_M01!$G:$G, Captura_Marimba_M01!$A:$A, Captura_Obra!A199, Captura_Marimba_M01!$C:$C, Captura_Obra!B199, Captura_Marimba_M01!$D:$D, Captura_Obra!D199))>0), "", 0) | I495: =IF(OR(Captura_Obra!A199="", (SUMIFS(Captura_Pegaso!$H:$H, Captura_Pegaso!$A:$A, Captura_Obra!A199, Captura_Pegaso!$D:$D, Captura_Obra!B199, Captura_Pegaso!$E:$E, Captura_Obra!D199) + SUMIFS(Captura_Marimba_M01!$G:$G, Captura_Marimba_M01!$A:$A, Captura_Obra!A199, Captura_Marimba_M01!$C:$C, Captura_Obra!B199, Captura_Marimba_M01!$D:$D, Captura_Obra!D199))>0), "", Captura_Obra!F199) | J495: =IF(OR(Captura_Obra!A199="", (SUMIFS(Captura_Pegaso!$H:$H, Captura_Pegaso!$A:$A, Captura_Obra!A199, Captura_Pegaso!$D:$D, Captura_Obra!B199, Captura_Pegaso!$E:$E, Captura_Obra!D199) + SUMIFS(Captura_Marimba_M01!$G:$G, Captura_Marimba_M01!$A:$A, Captura_Obra!A199, Captura_Marimba_M01!$C:$C, Captura_Obra!B199, Captura_Marimba_M01!$D:$D, Captura_Obra!D199))>0), "", H495 - I495)
A496: =IF(OR(Captura_Obra!A200="", (SUMIFS(Captura_Pegaso!$H:$H, Captura_Pegaso!$A:$A, Captura_Obra!A200, Captura_Pegaso!$D:$D, Captura_Obra!B200, Captura_Pegaso!$E:$E, Captura_Obra!D200) + SUMIFS(Captura_Marimba_M01!$G:$G, Captura_Marimba_M01!$A:$A, Captura_Obra!A200, Captura_Marimba_M01!$C:$C, Captura_Obra!B200, Captura_Marimba_M01!$D:$D, Captura_Obra!D200))>0), "", "Huérfano Obra") | B496: =IF(OR(Captura_Obra!A200="", (SUMIFS(Captura_Pegaso!$H:$H, Captura_Pegaso!$A:$A, Captura_Obra!A200, Captura_Pegaso!$D:$D, Captura_Obra!B200, Captura_Pegaso!$E:$E, Captura_Obra!D200) + SUMIFS(Captura_Marimba_M01!$G:$G, Captura_Marimba_M01!$A:$A, Captura_Obra!A200, Captura_Marimba_M01!$C:$C, Captura_Obra!B200, Captura_Marimba_M01!$D:$D, Captura_Obra!D200))>0), "", "No Reportado") | C496: =IF(OR(Captura_Obra!A200="", (SUMIFS(Captura_Pegaso!$H:$H, Captura_Pegaso!$A:$A, Captura_Obra!A200, Captura_Pegaso!$D:$D, Captura_Obra!B200, Captura_Pegaso!$E:$E, Captura_Obra!D200) + SUMIFS(Captura_Marimba_M01!$G:$G, Captura_Marimba_M01!$A:$A, Captura_Obra!A200, Captura_Marimba_M01!$C:$C, Captura_Obra!B200, Captura_Marimba_M01!$D:$D, Captura_Obra!D200))>0), "", Captura_Obra!N200) | D496: =IF(OR(Captura_Obra!A200="", (SUMIFS(Captura_Pegaso!$H:$H, Captura_Pegaso!$A:$A, Captura_Obra!A200, Captura_Pegaso!$D:$D, Captura_Obra!B200, Captura_Pegaso!$E:$E, Captura_Obra!D200) + SUMIFS(Captura_Marimba_M01!$G:$G, Captura_Marimba_M01!$A:$A, Captura_Obra!A200, Captura_Marimba_M01!$C:$C, Captura_Obra!B200, Captura_Marimba_M01!$D:$D, Captura_Obra!D200))>0), "", "❌ Falta en Pipa") | E496: =IF(OR(Captura_Obra!A200="", (SUMIFS(Captura_Pegaso!$H:$H, Captura_Pegaso!$A:$A, Captura_Obra!A200, Captura_Pegaso!$D:$D, Captura_Obra!B200, Captura_Pegaso!$E:$E, Captura_Obra!D200) + SUMIFS(Captura_Marimba_M01!$G:$G, Captura_Marimba_M01!$A:$A, Captura_Obra!A200, Captura_Marimba_M01!$C:$C, Captura_Obra!B200, Captura_Marimba_M01!$D:$D, Captura_Obra!D200))>0), "", Captura_Obra!A200) | F496: =IF(OR(Captura_Obra!A200="", (SUMIFS(Captura_Pegaso!$H:$H, Captura_Pegaso!$A:$A, Captura_Obra!A200, Captura_Pegaso!$D:$D, Captura_Obra!B200, Captura_Pegaso!$E:$E, Captura_Obra!D200) + SUMIFS(Captura_Marimba_M01!$G:$G, Captura_Marimba_M01!$A:$A, Captura_Obra!A200, Captura_Marimba_M01!$C:$C, Captura_Obra!B200, Captura_Marimba_M01!$D:$D, Captura_Obra!D200))>0), "", Captura_Obra!B200) | G496: =IF(OR(Captura_Obra!A200="", (SUMIFS(Captura_Pegaso!$H:$H, Captura_Pegaso!$A:$A, Captura_Obra!A200, Captura_Pegaso!$D:$D, Captura_Obra!B200, Captura_Pegaso!$E:$E, Captura_Obra!D200) + SUMIFS(Captura_Marimba_M01!$G:$G, Captura_Marimba_M01!$A:$A, Captura_Obra!A200, Captura_Marimba_M01!$C:$C, Captura_Obra!B200, Captura_Marimba_M01!$D:$D, Captura_Obra!D200))>0), "", Captura_Obra!D200) | H496: =IF(OR(Captura_Obra!A200="", (SUMIFS(Captura_Pegaso!$H:$H, Captura_Pegaso!$A:$A, Captura_Obra!A200, Captura_Pegaso!$D:$D, Captura_Obra!B200, Captura_Pegaso!$E:$E, Captura_Obra!D200) + SUMIFS(Captura_Marimba_M01!$G:$G, Captura_Marimba_M01!$A:$A, Captura_Obra!A200, Captura_Marimba_M01!$C:$C, Captura_Obra!B200, Captura_Marimba_M01!$D:$D, Captura_Obra!D200))>0), "", 0) | I496: =IF(OR(Captura_Obra!A200="", (SUMIFS(Captura_Pegaso!$H:$H, Captura_Pegaso!$A:$A, Captura_Obra!A200, Captura_Pegaso!$D:$D, Captura_Obra!B200, Captura_Pegaso!$E:$E, Captura_Obra!D200) + SUMIFS(Captura_Marimba_M01!$G:$G, Captura_Marimba_M01!$A:$A, Captura_Obra!A200, Captura_Marimba_M01!$C:$C, Captura_Obra!B200, Captura_Marimba_M01!$D:$D, Captura_Obra!D200))>0), "", Captura_Obra!F200) | J496: =IF(OR(Captura_Obra!A200="", (SUMIFS(Captura_Pegaso!$H:$H, Captura_Pegaso!$A:$A, Captura_Obra!A200, Captura_Pegaso!$D:$D, Captura_Obra!B200, Captura_Pegaso!$E:$E, Captura_Obra!D200) + SUMIFS(Captura_Marimba_M01!$G:$G, Captura_Marimba_M01!$A:$A, Captura_Obra!A200, Captura_Marimba_M01!$C:$C, Captura_Obra!B200, Captura_Marimba_M01!$D:$D, Captura_Obra!D200))>0), "", H496 - I496)
... A500: =IF(OR(Captura_Obra!A204="", (SUMIFS(Captura_Pegaso!$H:$H, Captura_Pegaso!$A:$A, Captura_Obra!A204, Captura_Pegaso!$D:$D, Captura_Obra!B204, Captura_Pegaso!$E:$E, Captura_Obra!D204) + SUMIFS(Captura_Marimba_M01!$G:$G, Captura_Marimba_M01!$A:$A, Captura_Obra!A204, Captura_Marimba_M01!$C:$C, Captura_Obra!B204, Captura_Marimba_M01!$D:$D, Captura_Obra!D204))>0), "", "Huérfano Obra") | B500: =IF(OR(Captura_Obra!A204="", (SUMIFS(Captura_Pegaso!$H:$H, Captura_Pegaso!$A:$A, Captura_Obra!A204, Captura_Pegaso!$D:$D, Captura_Obra!B204, Captura_Pegaso!$E:$E, Captura_Obra!D204) + SUMIFS(Captura_Marimba_M01!$G:$G, Captura_Marimba_M01!$A:$A, Captura_Obra!A204, Captura_Marimba_M01!$C:$C, Captura_Obra!B204, Captura_Marimba_M01!$D:$D, Captura_Obra!D204))>0), "", "No Reportado") | C500: =IF(OR(Captura_Obra!A204="", (SUMIFS(Captura_Pegaso!$H:$H, Captura_Pegaso!$A:$A, Captura_Obra!A204, Captura_Pegaso!$D:$D, Captura_Obra!B204, Captura_Pegaso!$E:$E, Captura_Obra!D204) + SUMIFS(Captura_Marimba_M01!$G:$G, Captura_Marimba_M01!$A:$A, Captura_Obra!A204, Captura_Marimba_M01!$C:$C, Captura_Obra!B204, Captura_Marimba_M01!$D:$D, Captura_Obra!D204))>0), "", Captura_Obra!N204) | D500: =IF(OR(Captura_Obra!A204="", (SUMIFS(Captura_Pegaso!$H:$H, Captura_Pegaso!$A:$A, Captura_Obra!A204, Captura_Pegaso!$D:$D, Captura_Obra!B204, Captura_Pegaso!$E:$E, Captura_Obra!D204) + SUMIFS(Captura_Marimba_M01!$G:$G, Captura_Marimba_M01!$A:$A, Captura_Obra!A204, Captura_Marimba_M01!$C:$C, Captura_Obra!B204, Captura_Marimba_M01!$D:$D, Captura_Obra!D204))>0), "", "❌ Falta en Pipa") | E500: =IF(OR(Captura_Obra!A204="", (SUMIFS(Captura_Pegaso!$H:$H, Captura_Pegaso!$A:$A, Captura_Obra!A204, Captura_Pegaso!$D:$D, Captura_Obra!B204, Captura_Pegaso!$E:$E, Captura_Obra!D204) + SUMIFS(Captura_Marimba_M01!$G:$G, Captura_Marimba_M01!$A:$A, Captura_Obra!A204, Captura_Marimba_M01!$C:$C, Captura_Obra!B204, Captura_Marimba_M01!$D:$D, Captura_Obra!D204))>0), "", Captura_Obra!A204) | F500: =IF(OR(Captura_Obra!A204="", (SUMIFS(Captura_Pegaso!$H:$H, Captura_Pegaso!$A:$A, Captura_Obra!A204, Captura_Pegaso!$D:$D, Captura_Obra!B204, Captura_Pegaso!$E:$E, Captura_Obra!D204) + SUMIFS(Captura_Marimba_M01!$G:$G, Captura_Marimba_M01!$A:$A, Captura_Obra!A204, Captura_Marimba_M01!$C:$C, Captura_Obra!B204, Captura_Marimba_M01!$D:$D, Captura_Obra!D204))>0), "", Captura_Obra!B204) | G500: =IF(OR(Captura_Obra!A204="", (SUMIFS(Captura_Pegaso!$H:$H, Captura_Pegaso!$A:$A, Captura_Obra!A204, Captura_Pegaso!$D:$D, Captura_Obra!B204, Captura_Pegaso!$E:$E, Captura_Obra!D204) + SUMIFS(Captura_Marimba_M01!$G:$G, Captura_Marimba_M01!$A:$A, Captura_Obra!A204, Captura_Marimba_M01!$C:$C, Captura_Obra!B204, Captura_Marimba_M01!$D:$D, Captura_Obra!D204))>0), "", Captura_Obra!D204) | H500: =IF(OR(Captura_Obra!A204="", (SUMIFS(Captura_Pegaso!$H:$H, Captura_Pegaso!$A:$A, Captura_Obra!A204, Captura_Pegaso!$D:$D, Captura_Obra!B204, Captura_Pegaso!$E:$E, Captura_Obra!D204) + SUMIFS(Captura_Marimba_M01!$G:$G, Captura_Marimba_M01!$A:$A, Captura_Obra!A204, Captura_Marimba_M01!$C:$C, Captura_Obra!B204, Captura_Marimba_M01!$D:$D, Captura_Obra!D204))>0), "", 0) | I500: =IF(OR(Captura_Obra!A204="", (SUMIFS(Captura_Pegaso!$H:$H, Captura_Pegaso!$A:$A, Captura_Obra!A204, Captura_Pegaso!$D:$D, Captura_Obra!B204, Captura_Pegaso!$E:$E, Captura_Obra!D204) + SUMIFS(Captura_Marimba_M01!$G:$G, Captura_Marimba_M01!$A:$A, Captura_Obra!A204, Captura_Marimba_M01!$C:$C, Captura_Obra!B204, Captura_Marimba_M01!$D:$D, Captura_Obra!D204))>0), "", Captura_Obra!F204) | J500: =IF(OR(Captura_Obra!A204="", (SUMIFS(Captura_Pegaso!$H:$H, Captura_Pegaso!$A:$A, Captura_Obra!A204, Captura_Pegaso!$D:$D, Captura_Obra!B204, Captura_Pegaso!$E:$E, Captura_Obra!D204) + SUMIFS(Captura_Marimba_M01!$G:$G, Captura_Marimba_M01!$A:$A, Captura_Obra!A204, Captura_Marimba_M01!$C:$C, Captura_Obra!B204, Captura_Marimba_M01!$D:$D, Captura_Obra!D204))>0), "", H500 - I500)

Sheet Captura_Pegaso
A1: GC-COMB-001 | BITÁCORA DE INVENTARIO PEGASO
A2: Responsable: | C2: Semana: | F2: Fecha entrega: | H2: Tanque: | I2: Pegaso | J2: Costo por litro base:
A4: Fecha | B4: Tipo Movimiento | C4: Origen/Destino | D4: Obra | E4: Equipo | F4: Economico | G4: Entrada (L) | H4: Salida (L) | I4: Existencia Teórica | J4: Costo/L | K4: Importe | L4: Observaciones | M4: Semana (Helper) | N4: Folio Ticket (Auto)
A5: 46181 | B5: Salida | C5: Otro | D5: Bacheo Toluca | E5: Bidones | F5: =VLOOKUP(TablaPegaso[[#This Row],[Equipo]],Catalogos!$V$4:$W$85,2,FALSE) | H5: 100 | I5: =IF(ROW()=5,G5-H5,I4+G5-H5) | J5: 28.3 | K5: =IFERROR((G5+H5)*J5,0) | M5: 24 | N5: =IF(A5="","", "CP-" & IFERROR(VLOOKUP(D5, Catalogos!$Z$4:$AA$20, 2, FALSE), "FOL") & "-" & WEEKNUM(A5,2) & "-" & TEXT(ROW(A1),"000"))
A6: 46181 | B6: Salida | C6: Planta Asfalto Pegaso | D6: Planta Asfalto Pegaso | E6: Bidones | F6: =VLOOKUP(TablaPegaso[[#This Row],[Equipo]],Catalogos!$V$4:$W$85,2,FALSE) | H6: 200 | I6: =IF(ROW()=5,G6-H6,I5+G6-H6) | J6: 28.3 | K6: =IFERROR((G6+H6)*J6,0) | M6: 24 | N6: =IF(A6="","", "CP-" & IFERROR(VLOOKUP(D6, Catalogos!$Z$4:$AA$20, 2, FALSE), "FOL") & "-" & WEEKNUM(A6,2) & "-" & TEXT(ROW(A2),"000"))
A7: 46181 | B7: Salida | C7: Planta Asfaltos | D7: Planta Asfalto Pegaso | E7: Bidones | F7: =VLOOKUP(TablaPegaso[[#This Row],[Equipo]],Catalogos!$V$4:$W$85,2,FALSE) | H7: 209 | I7: =IF(ROW()=5,G7-H7,I6+G7-H7) | J7: 28.3 | K7: =IFERROR((G7+H7)*J7,0) | M7: 24 | N7: =IF(A7="","", "CP-" & IFERROR(VLOOKUP(D7, Catalogos!$Z$4:$AA$20, 2, FALSE), "FOL") & "-" & WEEKNUM(A7,2) & "-" & TEXT(ROW(A3),"000"))
A8: 46181 | B8: Entrada | F8: =VLOOKUP(TablaPegaso[[#This Row],[Equipo]],Catalogos!$V$4:$W$85,2,FALSE) | G8: 2800 | I8: =IF(ROW()=5,G8-H8,I7+G8-H8) | J8: 28.3 | K8: =IFERROR((G8+H8)*J8,0) | M8: 24 | N8: =IF(A8="","", "CP-" & IFERROR(VLOOKUP(D8, Catalogos!$Z$4:$AA$20, 2, FALSE), "FOL") & "-" & WEEKNUM(A8,2) & "-" & TEXT(ROW(A4),"000"))
A9: 46181 | B9: Salida | C9: Carga directa | D9: Bacheo Toluca | E9: Bidones | F9: =VLOOKUP(TablaPegaso[[#This Row],[Equipo]],Catalogos!$V$4:$W$85,2,FALSE) | H9: 80 | I9: =IF(ROW()=5,G9-H9,I8+G9-H9) | J9: 28.3 | K9: =IFERROR((G9+H9)*J9,0) | M9: 24 | N9: =IF(A9="","", "CP-" & IFERROR(VLOOKUP(D9, Catalogos!$Z$4:$AA$20, 2, FALSE), "FOL") & "-" & WEEKNUM(A9,2) & "-" & TEXT(ROW(A5),"000"))
A10: 46182 | B10: Salida | C10: Carga directa | D10: Lerma - Tres Marías | E10: Retroexcavadora | F10: =VLOOKUP(TablaPegaso[[#This Row],[Equipo]],Catalogos!$V$4:$W$85,2,FALSE) | H10: 70 | I10: =IF(ROW()=5,G10-H10,I9+G10-H10) | J10: 28.3 | K10: =IFERROR((G10+H10)*J10,0) | M10: 24 | N10: =IF(A10="","", "CP-" & IFERROR(VLOOKUP(D10, Catalogos!$Z$4:$AA$20, 2, FALSE), "FOL") & "-" & WEEKNUM(A10,2) & "-" & TEXT(ROW(A6),"000"))
A11: 46182 | B11: Salida | C11: Carga directa | D11: Lerma - Tres Marías | E11: Doble Rodillo | F11: =VLOOKUP(TablaPegaso[[#This Row],[Equipo]],Catalogos!$V$4:$W$85,2,FALSE) | H11: 50 | I11: =IF(ROW()=5,G11-H11,I10+G11-H11) | J11: 28.3 | K11: =IFERROR((G11+H11)*J11,0) | M11: 24 | N11: =IF(A11="","", "CP-" & IFERROR(VLOOKUP(D11, Catalogos!$Z$4:$AA$20, 2, FALSE), "FOL") & "-" & WEEKNUM(A11,2) & "-" & TEXT(ROW(A7),"000"))
A12: 46182 | B12: Salida | C12: Carga directa | D12: Lerma - Tres Marías | E12: Petrolizadora | F12: =VLOOKUP(TablaPegaso[[#This Row],[Equipo]],Catalogos!$V$4:$W$85,2,FALSE) | H12: 60 | I12: =IF(ROW()=5,G12-H12,I11+G12-H12) | J12: 28.3 | K12: =IFERROR((G12+H12)*J12,0) | M12: 24 | N12: =IF(A12="","", "CP-" & IFERROR(VLOOKUP(D12, Catalogos!$Z$4:$AA$20, 2, FALSE), "FOL") & "-" & WEEKNUM(A12,2) & "-" & TEXT(ROW(A8),"000"))
A13: 46183 | B13: Salida | C13: Otro | D13: Bacheo Toluca | E13: Bidones | F13: =VLOOKUP(TablaPegaso[[#This Row],[Equipo]],Catalogos!$V$4:$W$85,2,FALSE) | H13: 100 | I13: =IF(ROW()=5,G13-H13,I12+G13-H13) | J13: 28.3 | K13: =IFERROR((G13+H13)*J13,0) | M13: 24 | N13: =IF(A13="","", "CP-" & IFERROR(VLOOKUP(D13, Catalogos!$Z$4:$AA$20, 2, FALSE), "FOL") & "-" & WEEKNUM(A13,2) & "-" & TEXT(ROW(A9),"000"))
A14: 46184 | B14: Salida | C14: Planta Asfalto Pegaso | D14: Planta Asfalto Pegaso | E14: PayLoder | F14: =VLOOKUP(TablaPegaso[[#This Row],[Equipo]],Catalogos!$V$4:$W$85,2,FALSE) | H14: 238 | I14: =IF(ROW()=5,G14-H14,I13+G14-H14) | J14: 28.3 | K14: =IFERROR((G14+H14)*J14,0) | M14: 24 | N14: =IF(A14="","", "CP-" & IFERROR(VLOOKUP(D14, Catalogos!$Z$4:$AA$20, 2, FALSE), "FOL") & "-" & WEEKNUM(A14,2) & "-" & TEXT(ROW(A10),"000"))
A15: 46184 | B15: Salida | C15: Carga directa | D15: Lerma - Tres Marías | E15: Petrolizadora | F15: =VLOOKUP(TablaPegaso[[#This Row],[Equipo]],Catalogos!$V$4:$W$85,2,FALSE) | H15: 80 | I15: =IF(ROW()=5,G15-H15,I14+G15-H15) | J15: 28.3 | K15: =IFERROR((G15+H15)*J15,0) | M15: 24 | N15: =IF(A15="","", "CP-" & IFERROR(VLOOKUP(D15, Catalogos!$Z$4:$AA$20, 2, FALSE), "FOL") & "-" & WEEKNUM(A15,2) & "-" & TEXT(ROW(A11),"000"))
A16: 46184 | B16: Salida | C16: Carga directa | D16: Lerma - Tres Marías | E16: Compresor | F16: =VLOOKUP(TablaPegaso[[#This Row],[Equipo]],Catalogos!$V$4:$W$85,2,FALSE) | H16: 50 | I16: =IF(ROW()=5,G16-H16,I15+G16-H16) | J16: 28.3 | K16: =IFERROR((G16+H16)*J16,0) | M16: 24 | N16: =IF(A16="","", "CP-" & IFERROR(VLOOKUP(D16, Catalogos!$Z$4:$AA$20, 2, FALSE), "FOL") & "-" & WEEKNUM(A16,2) & "-" & TEXT(ROW(A12),"000"))
A17: 46184 | B17: Salida | C17: Carga directa | D17: Lerma - Tres Marías | E17: Retroexcavadora | F17: =VLOOKUP(TablaPegaso[[#This Row],[Equipo]],Catalogos!$V$4:$W$85,2,FALSE) | H17: 70 | I17: =IF(ROW()=5,G17-H17,I16+G17-H17) | J17: 28.3 | K17: =IFERROR((G17+H17)*J17,0) | M17: 24 | N17: =IF(A17="","", "CP-" & IFERROR(VLOOKUP(D17, Catalogos!$Z$4:$AA$20, 2, FALSE), "FOL") & "-" & WEEKNUM(A17,2) & "-" & TEXT(ROW(A13),"000"))
A18: 46184 | B18: Salida | C18: Carga directa | D18: Lerma - Tres Marías | E18: Camion de Impacto | F18: =VLOOKUP(TablaPegaso[[#This Row],[Equipo]],Catalogos!$V$4:$W$85,2,FALSE) | H18: 80 | I18: =IF(ROW()=5,G18-H18,I17+G18-H18) | J18: 28.3 | K18: =IFERROR((G18+H18)*J18,0) | M18: 24 | N18: =IF(A18="","", "CP-" & IFERROR(VLOOKUP(D18, Catalogos!$Z$4:$AA$20, 2, FALSE), "FOL") & "-" & WEEKNUM(A18,2) & "-" & TEXT(ROW(A14),"000"))
A19: 46184 | B19: Salida | C19: Carga directa | D19: Lerma - Tres Marías | E19: Vogel | F19: =VLOOKUP(TablaPegaso[[#This Row],[Equipo]],Catalogos!$V$4:$W$85,2,FALSE) | H19: 185 | I19: =IF(ROW()=5,G19-H19,I18+G19-H19) | J19: 28.3 | K19: =IFERROR((G19+H19)*J19,0) | M19: 24 | N19: =IF(A19="","", "CP-" & IFERROR(VLOOKUP(D19, Catalogos!$Z$4:$AA$20, 2, FALSE), "FOL") & "-" & WEEKNUM(A19,2) & "-" & TEXT(ROW(A15),"000"))
A20: 46184 | B20: Salida | C20: Carga directa | D20: Lerma - Tres Marías | E20: Doble Rodillo | F20: =VLOOKUP(TablaPegaso[[#This Row],[Equipo]],Catalogos!$V$4:$W$85,2,FALSE) | H20: 50 | I20: =IF(ROW()=5,G20-H20,I19+G20-H20) | J20: 28.3 | K20: =IFERROR((G20+H20)*J20,0) | M20: 24 | N20: =IF(A20="","", "CP-" & IFERROR(VLOOKUP(D20, Catalogos!$Z$4:$AA$20, 2, FALSE), "FOL") & "-" & WEEKNUM(A20,2) & "-" & TEXT(ROW(A16),"000"))
... A29: 46188 | B29: Salida | C29: Tanque Pegaso | D29: Lerma - Tres Marías | E29: BARREDORA LAYMOR SM400 | F29: =VLOOKUP(TablaPegaso[[#This Row],[Equipo]],Catalogos!$V$4:$W$85,2,FALSE) | H29: 52 | I29: =IF(ROW()=5,G29-H29,I28+G29-H29) | J29: 28.3 | K29: =IFERROR((G29+H29)*J29,0) | M29: 25 | N29: =IF(A29="","", "CP-" & IFERROR(VLOOKUP(D29, Catalogos!$Z$4:$AA$20, 2, FALSE), "FOL") & "-" & WEEKNUM(A29,2) & "-" & TEXT(ROW(A25),"000"))
A30: 46188 | B30: Salida | C30: Tanque Pegaso | D30: Lerma - Tres Marías | E30: LIMPIEZA | F30: =VLOOKUP(TablaPegaso[[#This Row],[Equipo]],Catalogos!$V$4:$W$85,2,FALSE) | H30: 25 | I30: =IF(ROW()=5,G30-H30,I29+G30-H30) | J30: 28.3 | K30: =IFERROR((G30+H30)*J30,0) | L30: LIMPIEZA | M30: 25 | N30: =IF(A30="","", "CP-" & IFERROR(VLOOKUP(D30, Catalogos!$Z$4:$AA$20, 2, FALSE), "FOL") & "-" & WEEKNUM(A30,2) & "-" & TEXT(ROW(A26),"000"))
A31: 46188 | B31: Salida | C31: Tanque Pegaso | D31: Lerma - Tres Marías | E31: RETROEXCAVADORA JHONDEREE 310SK | F31: =VLOOKUP(TablaPegaso[[#This Row],[Equipo]],Catalogos!$V$4:$W$85,2,FALSE) | H31: 55 | I31: =IF(ROW()=5,G31-H31,I30+G31-H31) | J31: 28.3 | K31: =IFERROR((G31+H31)*J31,0) | M31: 25 | N31: =IF(A31="","", "CP-" & IFERROR(VLOOKUP(D31, Catalogos!$Z$4:$AA$20, 2, FALSE), "FOL") & "-" & WEEKNUM(A31,2) & "-" & TEXT(ROW(A27),"000"))
A32: 46189 | B32: Salida | C32: Tanque Pegaso | D32: Lerma - Tres Marías | E32: PIPA DE AGUA (IMPACTO 01) FORD | F32: =VLOOKUP(TablaPegaso[[#This Row],[Equipo]],Catalogos!$V$4:$W$85,2,FALSE) | H32: 50 | I32: =IF(ROW()=5,G32-H32,I31+G32-H32) | J32: 28.3 | K32: =IFERROR((G32+H32)*J32,0) | M32: 25 | N32: =IF(A32="","", "CP-" & IFERROR(VLOOKUP(D32, Catalogos!$Z$4:$AA$20, 2, FALSE), "FOL") & "-" & WEEKNUM(A32,2) & "-" & TEXT(ROW(A28),"000"))
A33: 46189 | B33: Salida | C33: Tanque Pegaso | D33: Planta Asfalto Pegaso | E33: PETROLIZADORA (IMPACTO 04) FORD F800 | F33: =VLOOKUP(TablaPegaso[[#This Row],[Equipo]],Catalogos!$V$4:$W$85,2,FALSE) | H33: 51 | I33: =IF(ROW()=5,G33-H33,I32+G33-H33) | J33: 28.3 | K33: =IFERROR((G33+H33)*J33,0) | L33: PETROLIZADORA NUEVA AMARRILLA NO TENIA DIESEL, EL CARGO CORRE A MAQUINARIA | M33: 25 | N33: =IF(A33="","", "CP-" & IFERROR(VLOOKUP(D33, Catalogos!$Z$4:$AA$20, 2, FALSE), "FOL") & "-" & WEEKNUM(A33,2) & "-" & TEXT(ROW(A29),"000"))
A34: 46189 | B34: Salida | C34: Tanque Pegaso | D34: Planta Asfalto Pegaso | E34: BIDONES | F34: =VLOOKUP(TablaPegaso[[#This Row],[Equipo]],Catalogos!$V$4:$W$85,2,FALSE) | H34: 1001 | I34: =IF(ROW()=5,G34-H34,I33+G34-H34) | J34: 28.3 | K34: =IFERROR((G34+H34)*J34,0) | M34: 25 | N34: =IF(A34="","", "CP-" & IFERROR(VLOOKUP(D34, Catalogos!$Z$4:$AA$20, 2, FALSE), "FOL") & "-" & WEEKNUM(A34,2) & "-" & TEXT(ROW(A30),"000"))
A35: 46189 | B35: Salida | C35: Tanque Pegaso | D35: Lerma - Tres Marías | E35: PERFILADORA RODATEC RX600-4-4008 | F35: =VLOOKUP(TablaPegaso[[#This Row],[Equipo]],Catalogos!$V$4:$W$85,2,FALSE) | H35: 350 | I35: =IF(ROW()=5,G35-H35,I34+G35-H35) | J35: 28.3 | K35: =IFERROR((G35+H35)*J35,0) | M35: 25 | N35: =IF(A35="","", "CP-" & IFERROR(VLOOKUP(D35, Catalogos!$Z$4:$AA$20, 2, FALSE), "FOL") & "-" & WEEKNUM(A35,2) & "-" & TEXT(ROW(A31),"000"))
A36: 46189 | B36: Salida | C36: Tanque Pegaso | D36: Bacheo Toluca | E36: PERFILADORA RODATEC RX600-4-4008 | F36: =VLOOKUP(TablaPegaso[[#This Row],[Equipo]],Catalogos!$V$4:$W$85,2,FALSE) | H36: 200 | I36: =IF(ROW()=5,G36-H36,I35+G36-H36) | J36: 28.3 | M36: 25 | N36: =IF(A36="","", "CP-" & IFERROR(VLOOKUP(D36, Catalogos!$Z$4:$AA$20, 2, FALSE), "FOL") & "-" & WEEKNUM(A36,2) & "-" & TEXT(ROW(A32),"000"))
A37: 46189 | B37: Salida | C37: Tanque Pegaso | D37: Lerma - Tres Marías | E37: PIPA DE AGUA (IMPACTO 01) FORD | F37: =VLOOKUP(TablaPegaso[[#This Row],[Equipo]],Catalogos!$V$4:$W$85,2,FALSE) | H37: 50 | I37: =IF(ROW()=5,G37-H37,I36+G37-H37) | J37: 28.3 | K37: =IFERROR((G37+H37)*J37,0) | M37: 25 | N37: =IF(A37="","", "CP-" & IFERROR(VLOOKUP(D37, Catalogos!$Z$4:$AA$20, 2, FALSE), "FOL") & "-" & WEEKNUM(A37,2) & "-" & TEXT(ROW(A33),"000"))
A38: 46189 | B38: Salida | C38: Tanque Pegaso | D38: Lerma - Tres Marías | E38: PAVIMENTADORA VOGELE 1800-3 i | F38: =VLOOKUP(TablaPegaso[[#This Row],[Equipo]],Catalogos!$V$4:$W$85,2,FALSE) | H38: 165 | I38: =IF(ROW()=5,G38-H38,I37+G38-H38) | J38: 28.3 | K38: =IFERROR((G38+H38)*J38,0) | M38: 25 | N38: =IF(A38="","", "CP-" & IFERROR(VLOOKUP(D38, Catalogos!$Z$4:$AA$20, 2, FALSE), "FOL") & "-" & WEEKNUM(A38,2) & "-" & TEXT(ROW(A34),"000"))
A39: 46190 | B39: Salida | C39: Tanque Pegaso | D39: Lerma - Tres Marías | E39: IMPACTO FORD 4300 | F39: =VLOOKUP(TablaPegaso[[#This Row],[Equipo]],Catalogos!$V$4:$W$85,2,FALSE) | H39: 81 | I39: =IF(ROW()=5,G39-H39,I38+G39-H39) | J39: 28.3 | K39: =IFERROR((G39+H39)*J39,0) | M39: 25 | N39: =IF(A39="","", "CP-" & IFERROR(VLOOKUP(D39, Catalogos!$Z$4:$AA$20, 2, FALSE), "FOL") & "-" & WEEKNUM(A39,2) & "-" & TEXT(ROW(A35),"000"))
A40: 46192 | B40: Salida | C40: Tanque Pegaso | D40: Lerma - Tres Marías | E40: PETROLIZADORA INTERNATIONAL | F40: =VLOOKUP(TablaPegaso[[#This Row],[Equipo]],Catalogos!$V$4:$W$85,2,FALSE) | H40: 40 | I40: =IF(ROW()=5,G40-H40,I39+G40-H40) | J40: 28.3 | K40: =IFERROR((G40+H40)*J40,0) | M40: 25 | N40: =IF(A40="","", "CP-" & IFERROR(VLOOKUP(D40, Catalogos!$Z$4:$AA$20, 2, FALSE), "FOL") & "-" & WEEKNUM(A40,2) & "-" & TEXT(ROW(A36),"000"))
A41: 46192 | B41: Salida | C41: Tanque Pegaso | D41: Dragones | E41: PETROLIZADORA INTERNATIONAL | F41: =VLOOKUP(TablaPegaso[[#This Row],[Equipo]],Catalogos!$V$4:$W$85,2,FALSE) | H41: 40 | I41: =IF(ROW()=5,G41-H41,I40+G41-H41) | J41: 28.3 | K41: =IFERROR((G41+H41)*J41,0) | M41: 25 | N41: =IF(A41="","", "CP-" & IFERROR(VLOOKUP(D41, Catalogos!$Z$4:$AA$20, 2, FALSE), "FOL") & "-" & WEEKNUM(A41,2) & "-" & TEXT(ROW(A37),"000"))
A42: 46192 | B42: Salida | C42: Tanque Pegaso | D42: Lerma - Tres Marías | E42: BARREDORA LAYMOR SM400 | F42: =VLOOKUP(TablaPegaso[[#This Row],[Equipo]],Catalogos!$V$4:$W$85,2,FALSE) | H42: 43 | I42: =IF(ROW()=5,G42-H42,I40+G42-H42) | J42: 28.3 | K42: =IFERROR((G42+H42)*J42,0) | M42: 25 | N42: =IF(A42="","", "CP-" & IFERROR(VLOOKUP(D42, Catalogos!$Z$4:$AA$20, 2, FALSE), "FOL") & "-" & WEEKNUM(A42,2) & "-" & TEXT(ROW(A38),"000"))
A43: 46192 | B43: Salida | C43: Tanque Pegaso | D43: Lerma - Tres Marías | E43: TANDEM DOBLE RODILLO / VIBROCOMPACTOR RODILLO CAT CB54 | F43: =VLOOKUP(TablaPegaso[[#This Row],[Equipo]],Catalogos!$V$4:$W$85,2,FALSE) | H43: 50 | I43: =IF(ROW()=5,G43-H43,I42+G43-H43) | J43: 28.3 | K43: =IFERROR((G43+H43)*J43,0) | M43: 25 | N43: =IF(A43="","", "CP-" & IFERROR(VLOOKUP(D43, Catalogos!$Z$4:$AA$20, 2, FALSE), "FOL") & "-" & WEEKNUM(A43,2) & "-" & TEXT(ROW(A39),"000"))
A44: 46192 | B44: Salida | C44: Tanque Pegaso | D44: Lerma - Tres Marías | E44: RETROEXCAVADORA JHONDEREE 310SK | F44: =VLOOKUP(TablaPegaso[[#This Row],[Equipo]],Catalogos!$V$4:$W$85,2,FALSE) | H44: 80 | I44: =IF(ROW()=5,G44-H44,I43+G44-H44) | J44: 28.3 | K44: =IFERROR((G44+H44)*J44,0) | M44: 25 | N44: =IF(A44="","", "CP-" & IFERROR(VLOOKUP(D44, Catalogos!$Z$4:$AA$20, 2, FALSE), "FOL") & "-" & WEEKNUM(A44,2) & "-" & TEXT(ROW(A40),"000"))
A45: 46192 | B45: Salida | C45: Tanque Pegaso | D45: Lerma - Tres Marías | E45: NEUMATICO / COMPACTADOR DE NEUMATICOS DINAPAC CP271 | F45: =VLOOKUP(TablaPegaso[[#This Row],[Equipo]],Catalogos!$V$4:$W$85,2,FALSE) | H45: 30 | I45: =IF(ROW()=5,G45-H45,I44+G45-H45) | J45: 28.3 | K45: =IFERROR((G45+H45)*J45,0) | M45: 25 | N45: =IF(A45="","", "CP-" & IFERROR(VLOOKUP(D45, Catalogos!$Z$4:$AA$20, 2, FALSE), "FOL") & "-" & WEEKNUM(A45,2) & "-" & TEXT(ROW(A41),"000"))
A46: 46192 | B46: Salida | C46: Tanque Pegaso | D46: Lerma - Tres Marías | E46: PAVIMENTADORA VOGELE 1800-3 i | F46: =VLOOKUP(TablaPegaso[[#This Row],[Equipo]],Catalogos!$V$4:$W$85,2,FALSE) | H46: 160 | I46: =IF(ROW()=5,G46-H46,I45+G46-H46) | J46: 28.3 | K46: =IFERROR((G46+H46)*J46,0) | M46: 25 | N46: =IF(A46="","", "CP-" & IFERROR(VLOOKUP(D46, Catalogos!$Z$4:$AA$20, 2, FALSE), "FOL") & "-" & WEEKNUM(A46,2) & "-" & TEXT(ROW(A42),"000"))
A47: 46192 | B47: Salida | C47: Tanque Pegaso | D47: Lerma - Tres Marías | E47: PIPA DE AGUA (IMPACTO 01) FORD | F47: =VLOOKUP(TablaPegaso[[#This Row],[Equipo]],Catalogos!$V$4:$W$85,2,FALSE) | H47: 50 | I47: =IF(ROW()=5,G47-H47,I46+G47-H47) | J47: 28.3 | K47: =IFERROR((G47+H47)*J47,0) | M47: 25 | N47: =IF(A47="","", "CP-" & IFERROR(VLOOKUP(D47, Catalogos!$Z$4:$AA$20, 2, FALSE), "FOL") & "-" & WEEKNUM(A47,2) & "-" & TEXT(ROW(A43),"000"))
A48: 46192 | B48: Salida | C48: Tanque Pegaso | D48: Bacheo Toluca | E48: RETROEXCAVADORA CASE 580 N | F48: =VLOOKUP(TablaPegaso[[#This Row],[Equipo]],Catalogos!$V$4:$W$85,2,FALSE) | H48: 60 | I48: =IF(ROW()=5,G48-H48,I47+G48-H48) | J48: 28.3 | K48: =IFERROR((G48+H48)*J48,0) | M48: 25 | N48: =IF(A48="","", "CP-" & IFERROR(VLOOKUP(D48, Catalogos!$Z$4:$AA$20, 2, FALSE), "FOL") & "-" & WEEKNUM(A48,2) & "-" & TEXT(ROW(A44),"000"))
A49: 46193 | B49: Salida | C49: Tanque Pegaso | D49: Bacheo Toluca | E49: BIDONES | F49: =VLOOKUP(TablaPegaso[[#This Row],[Equipo]],Catalogos!$V$4:$W$85,2,FALSE) | H49: 70 | I49: =IF(ROW()=5,G49-H49,I48+G49-H49) | J49: 28.3 | K49: =IFERROR((G49+H49)*J49,0) | M49: 25 | N49: =IF(A49="","", "CP-" & IFERROR(VLOOKUP(D49, Catalogos!$Z$4:$AA$20, 2, FALSE), "FOL") & "-" & WEEKNUM(A49,2) & "-" & TEXT(ROW(A45),"000"))
A50: 46193 | B50: Salida | C50: Tanque Pegaso | D50: Planta Asfalto Pegaso | E50: BIDONES | F50: =VLOOKUP(TablaPegaso[[#This Row],[Equipo]],Catalogos!$V$4:$W$85,2,FALSE) | H50: 600 | I50: =IF(ROW()=5,G50-H50,I49+G50-H50) | J50: 28.3 | K50: =IFERROR((G50+H50)*J50,0) | M50: 25 | N50: =IF(A50="","", "CP-" & IFERROR(VLOOKUP(D50, Catalogos!$Z$4:$AA$20, 2, FALSE), "FOL") & "-" & WEEKNUM(A50,2) & "-" & TEXT(ROW(A46),"000"))
A51: 46188 | B51: Salida | C51: Tanque Pegaso | D51: Bacheo Toluca | E51: PERFILADORA RODATEC RX600E | F51: =VLOOKUP(TablaPegaso[[#This Row],[Equipo]],Catalogos!$V$4:$W$85,2,FALSE) | H51: 200 | I51: =IF(ROW()=5,G51-H51,I50+G51-H51) | J51: 28.3 | K51: =IFERROR((G51+H51)*J51,0) | M51: 25 | N51: =IF(A51="","", "CP-" & IFERROR(VLOOKUP(D51, Catalogos!$Z$4:$AA$20, 2, FALSE), "FOL") & "-" & WEEKNUM(A51,2) & "-" & TEXT(ROW(A47),"000"))
A52: 46195 | B52: Entrada | C52: Tanque Pegaso | F52: =VLOOKUP(TablaPegaso[[#This Row],[Equipo]],Catalogos!$V$4:$W$85,2,FALSE) | G52: 6036.51 | I52: =IF(ROW()=5,G52-H52,I51+G52-H52) | J52: 28.3 | K52: =IFERROR((G52+H52)*J52,0) | M52: 26 | N52: =IF(A52="","", "CP-" & IFERROR(VLOOKUP(D52, Catalogos!$Z$4:$AA$20, 2, FALSE), "FOL") & "-" & WEEKNUM(A52,2) & "-" & TEXT(ROW(A48),"000"))
C53: Tanque Pegaso | F53: =VLOOKUP(TablaPegaso[[#This Row],[Equipo]],Catalogos!$V$4:$W$85,2,FALSE) | I53: =IF(ROW()=5,G53-H53,I52+G53-H53) | J53: 28.3 | K53: =IFERROR((G53+H53)*J53,0) | N53: =IF(A53="","", "CP-" & IFERROR(VLOOKUP(D53, Catalogos!$Z$4:$AA$20, 2, FALSE), "FOL") & "-" & WEEKNUM(A53,2) & "-" & TEXT(ROW(A49),"000"))
C54: Tanque Pegaso | F54: =VLOOKUP(TablaPegaso[[#This Row],[Equipo]],Catalogos!$V$4:$W$85,2,FALSE) | I54: =IF(ROW()=5,G54-H54,I53+G54-H54) | J54: 28.3 | K54: =IFERROR((G54+H54)*J54,0) | N54: =IF(A54="","", "CP-" & IFERROR(VLOOKUP(D54, Catalogos!$Z$4:$AA$20, 2, FALSE), "FOL") & "-" & WEEKNUM(A54,2) & "-" & TEXT(ROW(A50),"000"))
C55: Tanque Pegaso | F55: =VLOOKUP(TablaPegaso[[#This Row],[Equipo]],Catalogos!$V$4:$W$85,2,FALSE) | I55: =IF(ROW()=5,G55-H55,I54+G55-H55) | J55: 28.3 | K55: =IFERROR((G55+H55)*J55,0) | N55: =IF(A55="","", "CP-" & IFERROR(VLOOKUP(D55, Catalogos!$Z$4:$AA$20, 2, FALSE), "FOL") & "-" & WEEKNUM(A55,2) & "-" & TEXT(ROW(A51),"000"))
C56: Tanque Pegaso | F56: =VLOOKUP(TablaPegaso[[#This Row],[Equipo]],Catalogos!$V$4:$W$85,2,FALSE) | I56: =IF(ROW()=5,G56-H56,I55+G56-H56) | J56: 28.3 | K56: =IFERROR((G56+H56)*J56,0) | N56: =IF(A56="","", "CP-" & IFERROR(VLOOKUP(D56, Catalogos!$Z$4:$AA$20, 2, FALSE), "FOL") & "-" & WEEKNUM(A56,2) & "-" & TEXT(ROW(A52),"000"))
C57: Tanque Pegaso | F57: =VLOOKUP(TablaPegaso[[#This Row],[Equipo]],Catalogos!$V$4:$W$85,2,FALSE) | I57: =IF(ROW()=5,G57-H57,I56+G57-H57) | J57: 28.3 | K57: =IFERROR((G57+H57)*J57,0) | N57: =IF(A57="","", "CP-" & IFERROR(VLOOKUP(D57, Catalogos!$Z$4:$AA$20, 2, FALSE), "FOL") & "-" & WEEKNUM(A57,2) & "-" & TEXT(ROW(A53),"000"))
C58: Tanque Pegaso | F58: =VLOOKUP(TablaPegaso[[#This Row],[Equipo]],Catalogos!$V$4:$W$85,2,FALSE) | I58: =IF(ROW()=5,G58-H58,I57+G58-H58) | J58: 28.3 | K58: =IFERROR((G58+H58)*J58,0) | N58: =IF(A58="","", "CP-" & IFERROR(VLOOKUP(D58, Catalogos!$Z$4:$AA$20, 2, FALSE), "FOL") & "-" & WEEKNUM(A58,2) & "-" & TEXT(ROW(A54),"000"))
C59: Tanque Pegaso | F59: =VLOOKUP(TablaPegaso[[#This Row],[Equipo]],Catalogos!$V$4:$W$85,2,FALSE) | I59: =IF(ROW()=5,G59-H59,I58+G59-H59) | J59: 28.3 | K59: =IFERROR((G59+H59)*J59,0) | N59: =IF(A59="","", "CP-" & IFERROR(VLOOKUP(D59, Catalogos!$Z$4:$AA$20, 2, FALSE), "FOL") & "-" & WEEKNUM(A59,2) & "-" & TEXT(ROW(A55),"000"))
C60: Tanque Pegaso | F60: =VLOOKUP(TablaPegaso[[#This Row],[Equipo]],Catalogos!$V$4:$W$85,2,FALSE) | I60: =IF(ROW()=5,G60-H60,I59+G60-H60) | J60: 28.3 | K60: =IFERROR((G60+H60)*J60,0) | N60: =IF(A60="","", "CP-" & IFERROR(VLOOKUP(D60, Catalogos!$Z$4:$AA$20, 2, FALSE), "FOL") & "-" & WEEKNUM(A60,2) & "-" & TEXT(ROW(A56),"000"))
C61: Tanque Pegaso | F61: =VLOOKUP(TablaPegaso[[#This Row],[Equipo]],Catalogos!$V$4:$W$85,2,FALSE) | I61: =IF(ROW()=5,G61-H61,I60+G61-H61) | J61: 28.3 | K61: =IFERROR((G61+H61)*J61,0) | N61: =IF(A61="","", "CP-" & IFERROR(VLOOKUP(D61, Catalogos!$Z$4:$AA$20, 2, FALSE), "FOL") & "-" & WEEKNUM(A61,2) & "-" & TEXT(ROW(A57),"000"))
C62: Tanque Pegaso | F62: =VLOOKUP(TablaPegaso[[#This Row],[Equipo]],Catalogos!$V$4:$W$85,2,FALSE) | I62: =IF(ROW()=5,G62-H62,I61+G62-H62) | J62: 28.3 | K62: =IFERROR((G62+H62)*J62,0) | N62: =IF(A62="","", "CP-" & IFERROR(VLOOKUP(D62, Catalogos!$Z$4:$AA$20, 2, FALSE), "FOL") & "-" & WEEKNUM(A62,2) & "-" & TEXT(ROW(A58),"000"))
C63: Tanque Pegaso | F63: =VLOOKUP(TablaPegaso[[#This Row],[Equipo]],Catalogos!$V$4:$W$85,2,FALSE) | I63: =IF(ROW()=5,G63-H63,I62+G63-H63) | J63: 28.3 | K63: =IFERROR((G63+H63)*J63,0) | N63: =IF(A63="","", "CP-" & IFERROR(VLOOKUP(D63, Catalogos!$Z$4:$AA$20, 2, FALSE), "FOL") & "-" & WEEKNUM(A63,2) & "-" & TEXT(ROW(A59),"000"))
C64: Tanque Pegaso | F64: =VLOOKUP(TablaPegaso[[#This Row],[Equipo]],Catalogos!$V$4:$W$85,2,FALSE) | I64: =IF(ROW()=5,G64-H64,I63+G64-H64) | J64: 28.3 | K64: =IFERROR((G64+H64)*J64,0) | N64: =IF(A64="","", "CP-" & IFERROR(VLOOKUP(D64, Catalogos!$Z$4:$AA$20, 2, FALSE), "FOL") & "-" & WEEKNUM(A64,2) & "-" & TEXT(ROW(A60),"000"))
... C68: Tanque Pegaso | F68: =VLOOKUP(TablaPegaso[[#This Row],[Equipo]],Catalogos!$V$4:$W$85,2,FALSE) | I68: =IF(ROW()=5,G68-H68,I67+G68-H68) | J68: 28.3 | K68: =IFERROR((G68+H68)*J68,0) | N68: =IF(A68="","", "CP-" & IFERROR(VLOOKUP(D68, Catalogos!$Z$4:$AA$20, 2, FALSE), "FOL") & "-" & WEEKNUM(A68,2) & "-" & TEXT(ROW(A64),"000"))
C69: Tanque Pegaso | F69: =VLOOKUP(TablaPegaso[[#This Row],[Equipo]],Catalogos!$V$4:$W$85,2,FALSE) | I69: =IF(ROW()=5,G69-H69,I68+G69-H69) | J69: 28.3 | K69: =IFERROR((G69+H69)*J69,0) | M69: =IF(A69="","", WEEKNUM(A69, 2)) | N69: =IF(A69="","", "CP-" & IFERROR(VLOOKUP(D69, Catalogos!$Z$4:$AA$20, 2, FALSE), "FOL") & "-" & WEEKNUM(A69,2) & "-" & TEXT(ROW(A65),"000"))
C70: Tanque Pegaso | F70: =VLOOKUP(TablaPegaso[[#This Row],[Equipo]],Catalogos!$V$4:$W$85,2,FALSE) | I70: =IF(ROW()=5,G70-H70,I69+G70-H70) | J70: 28.3 | K70: =IFERROR((G70+H70)*J70,0) | M70: =IF(A70="","", WEEKNUM(A70, 2)) | N70: =IF(A70="","", "CP-" & IFERROR(VLOOKUP(D70, Catalogos!$Z$4:$AA$20, 2, FALSE), "FOL") & "-" & WEEKNUM(A70,2) & "-" & TEXT(ROW(A66),"000"))
C71: Tanque Pegaso | F71: =VLOOKUP(TablaPegaso[[#This Row],[Equipo]],Catalogos!$V$4:$W$85,2,FALSE) | I71: =IF(ROW()=5,G71-H71,I70+G71-H71) | J71: 28.3 | K71: =IFERROR((G71+H71)*J71,0) | M71: =IF(A71="","", WEEKNUM(A71, 2)) | N71: =IF(A71="","", "CP-" & IFERROR(VLOOKUP(D71, Catalogos!$Z$4:$AA$20, 2, FALSE), "FOL") & "-" & WEEKNUM(A71,2) & "-" & TEXT(ROW(A67),"000"))
C72: Tanque Pegaso | F72: =VLOOKUP(TablaPegaso[[#This Row],[Equipo]],Catalogos!$V$4:$W$85,2,FALSE) | I72: =IF(ROW()=5,G72-H72,I71+G72-H72) | J72: 28.3 | K72: =IFERROR((G72+H72)*J72,0) | M72: =IF(A72="","", WEEKNUM(A72, 2)) | N72: =IF(A72="","", "CP-" & IFERROR(VLOOKUP(D72, Catalogos!$Z$4:$AA$20, 2, FALSE), "FOL") & "-" & WEEKNUM(A72,2) & "-" & TEXT(ROW(A68),"000"))
C73: Tanque Pegaso | F73: =VLOOKUP(TablaPegaso[[#This Row],[Equipo]],Catalogos!$V$4:$W$85,2,FALSE) | I73: =IF(ROW()=5,G73-H73,I72+G73-H73) | J73: 28.3 | K73: =IFERROR((G73+H73)*J73,0) | M73: =IF(A73="","", WEEKNUM(A73, 2)) | N73: =IF(A73="","", "CP-" & IFERROR(VLOOKUP(D73, Catalogos!$Z$4:$AA$20, 2, FALSE), "FOL") & "-" & WEEKNUM(A73,2) & "-" & TEXT(ROW(A69),"000"))
C74: Tanque Pegaso | F74: =VLOOKUP(TablaPegaso[[#This Row],[Equipo]],Catalogos!$V$4:$W$85,2,FALSE) | I74: =IF(ROW()=5,G74-H74,I73+G74-H74) | J74: 28.3 | K74: =IFERROR((G74+H74)*J74,0) | M74: =IF(A74="","", WEEKNUM(A74, 2)) | N74: =IF(A74="","", "CP-" & IFERROR(VLOOKUP(D74, Catalogos!$Z$4:$AA$20, 2, FALSE), "FOL") & "-" & WEEKNUM(A74,2) & "-" & TEXT(ROW(A70),"000"))
C75: Tanque Pegaso | F75: =VLOOKUP(TablaPegaso[[#This Row],[Equipo]],Catalogos!$V$4:$W$85,2,FALSE) | I75: =IF(ROW()=5,G75-H75,I74+G75-H75) | J75: 28.3 | K75: =IFERROR((G75+H75)*J75,0) | M75: =IF(A75="","", WEEKNUM(A75, 2)) | N75: =IF(A75="","", "CP-" & IFERROR(VLOOKUP(D75, Catalogos!$Z$4:$AA$20, 2, FALSE), "FOL") & "-" & WEEKNUM(A75,2) & "-" & TEXT(ROW(A71),"000"))
C76: Tanque Pegaso | F76: =VLOOKUP(TablaPegaso[[#This Row],[Equipo]],Catalogos!$V$4:$W$85,2,FALSE) | I76: =IF(ROW()=5,G76-H76,I75+G76-H76) | J76: 28.3 | K76: =IFERROR((G76+H76)*J76,0) | M76: =IF(A76="","", WEEKNUM(A76, 2)) | N76: =IF(A76="","", "CP-" & IFERROR(VLOOKUP(D76, Catalogos!$Z$4:$AA$20, 2, FALSE), "FOL") & "-" & WEEKNUM(A76,2) & "-" & TEXT(ROW(A72),"000"))
C77: Tanque Pegaso | F77: =VLOOKUP(TablaPegaso[[#This Row],[Equipo]],Catalogos!$V$4:$W$85,2,FALSE) | I77: =IF(ROW()=5,G77-H77,I76+G77-H77) | J77: 28.3 | K77: =IFERROR((G77+H77)*J77,0) | M77: =IF(A77="","", WEEKNUM(A77, 2)) | N77: =IF(A77="","", "CP-" & IFERROR(VLOOKUP(D77, Catalogos!$Z$4:$AA$20, 2, FALSE), "FOL") & "-" & WEEKNUM(A77,2) & "-" & TEXT(ROW(A73),"000"))
C78: Tanque Pegaso | F78: =VLOOKUP(TablaPegaso[[#This Row],[Equipo]],Catalogos!$V$4:$W$85,2,FALSE) | I78: =IF(ROW()=5,G78-H78,I77+G78-H78) | J78: 28.3 | K78: =IFERROR((G78+H78)*J78,0) | M78: =IF(A78="","", WEEKNUM(A78, 2)) | N78: =IF(A78="","", "CP-" & IFERROR(VLOOKUP(D78, Catalogos!$Z$4:$AA$20, 2, FALSE), "FOL") & "-" & WEEKNUM(A78,2) & "-" & TEXT(ROW(A74),"000"))
C79: Tanque Pegaso | F79: =VLOOKUP(TablaPegaso[[#This Row],[Equipo]],Catalogos!$V$4:$W$85,2,FALSE) | I79: =IF(ROW()=5,G79-H79,I78+G79-H79) | J79: 28.3 | K79: =IFERROR((G79+H79)*J79,0) | M79: =IF(A79="","", WEEKNUM(A79, 2)) | N79: =IF(A79="","", "CP-" & IFERROR(VLOOKUP(D79, Catalogos!$Z$4:$AA$20, 2, FALSE), "FOL") & "-" & WEEKNUM(A79,2) & "-" & TEXT(ROW(A75),"000"))
C80: Tanque Pegaso | F80: =VLOOKUP(TablaPegaso[[#This Row],[Equipo]],Catalogos!$V$4:$W$85,2,FALSE) | I80: =IF(ROW()=5,G80-H80,I79+G80-H80) | J80: 28.3 | K80: =IFERROR((G80+H80)*J80,0) | M80: =IF(A80="","", WEEKNUM(A80, 2)) | N80: =IF(A80="","", "CP-" & IFERROR(VLOOKUP(D80, Catalogos!$Z$4:$AA$20, 2, FALSE), "FOL") & "-" & WEEKNUM(A80,2) & "-" & TEXT(ROW(A76),"000"))
... C200: Tanque Pegaso | F200: =VLOOKUP(TablaPegaso[[#This Row],[Equipo]],Catalogos!$V$4:$W$85,2,FALSE) | I200: =IF(ROW()=5,G200-H200,I199+G200-H200) | J200: 28.3 | K200: =IFERROR((G200+H200)*J200,0) | M200: =IF(A200="","", WEEKNUM(A200, 2)) | N200: =IF(A200="","", "CP-" & IFERROR(VLOOKUP(D200, Catalogos!$Z$4:$AA$20, 2, FALSE), "FOL") & "-" & WEEKNUM(A200,2) & "-" & TEXT(ROW(A196),"000"))
C201: Tanque Pegaso | F201: =VLOOKUP(TablaPegaso[[#This Row],[Equipo]],Catalogos!$V$4:$W$85,2,FALSE) | I201: =IF(ROW()=5,G201-H201,I200+G201-H201) | J201: 28.3 | K201: =IFERROR((G201+H201)*J201,0) | M201: =IF(A201="","", WEEKNUM(A201, 2))
C202: Tanque Pegaso | F202: =VLOOKUP(TablaPegaso[[#This Row],[Equipo]],Catalogos!$V$4:$W$85,2,FALSE) | I202: =IF(ROW()=5,G202-H202,I201+G202-H202) | J202: 28.3 | K202: =IFERROR((G202+H202)*J202,0) | M202: =IF(A202="","", WEEKNUM(A202, 2))
C203: Tanque Pegaso | F203: =VLOOKUP(TablaPegaso[[#This Row],[Equipo]],Catalogos!$V$4:$W$85,2,FALSE) | I203: =IF(ROW()=5,G203-H203,I202+G203-H203) | J203: 28.3 | K203: =IFERROR((G203+H203)*J203,0) | M203: =IF(A203="","", WEEKNUM(A203, 2))
C204: Tanque Pegaso | F204: =VLOOKUP(TablaPegaso[[#This Row],[Equipo]],Catalogos!$V$4:$W$85,2,FALSE) | I204: =IF(ROW()=5,G204-H204,I203+G204-H204) | J204: 28.3 | K204: =IFERROR((G204+H204)*J204,0) | M204: =IF(A204="","", WEEKNUM(A204, 2))
C205: Tanque Pegaso | F205: =VLOOKUP(TablaPegaso[[#This Row],[Equipo]],Catalogos!$V$4:$W$85,2,FALSE) | I205: =IF(ROW()=5,G205-H205,I204+G205-H205) | J205: 28.3 | K205: =IFERROR((G205+H205)*J205,0) | M205: =IF(A205="","", WEEKNUM(A205, 2))
C206: Tanque Pegaso | F206: =VLOOKUP(TablaPegaso[[#This Row],[Equipo]],Catalogos!$V$4:$W$85,2,FALSE) | I206: =IF(ROW()=5,G206-H206,I205+G206-H206) | J206: 28.3 | K206: =IFERROR((G206+H206)*J206,0) | M206: =IF(A206="","", WEEKNUM(A206, 2))
C207: Tanque Pegaso | F207: =VLOOKUP(TablaPegaso[[#This Row],[Equipo]],Catalogos!$V$4:$W$85,2,FALSE) | I207: =IF(ROW()=5,G207-H207,I206+G207-H207) | J207: 28.3 | K207: =IFERROR((G207+H207)*J207,0) | M207: =IF(A207="","", WEEKNUM(A207, 2))
C208: Tanque Pegaso | F208: =VLOOKUP(TablaPegaso[[#This Row],[Equipo]],Catalogos!$V$4:$W$85,2,FALSE) | I208: =IF(ROW()=5,G208-H208,I207+G208-H208) | J208: 28.3 | K208: =IFERROR((G208+H208)*J208,0) | M208: =IF(A208="","", WEEKNUM(A208, 2))
M209: =IF(A209="","", WEEKNUM(A209, 2))
M210: =IF(A210="","", WEEKNUM(A210, 2))
M211: =IF(A211="","", WEEKNUM(A211, 2))
M212: =IF(A212="","", WEEKNUM(A212, 2))
M213: =IF(A213="","", WEEKNUM(A213, 2))
M214: =IF(A214="","", WEEKNUM(A214, 2))
M215: =IF(A215="","", WEEKNUM(A215, 2))
M216: =IF(A216="","", WEEKNUM(A216, 2))
M217: =IF(A217="","", WEEKNUM(A217, 2))
M218: =IF(A218="","", WEEKNUM(A218, 2))
M219: =IF(A219="","", WEEKNUM(A219, 2))
M220: =IF(A220="","", WEEKNUM(A220, 2))
... M2000: =IF(A2000="","", WEEKNUM(A2000, 2))

Sheet Captura_Obra
A1: GC-COMB-003 | BITÁCORA DE CONTROL DE COMBUSTIBLE DE OBRA
A2: Ingeniero: | C2: Semana: | E2: Fecha entrega: | G2: Obra: | I2: Costo/L base:
A4: Fecha | B4: Obra | C4: Fuente | D4: Equipo | E4: Económico | F4: Litros Recibidos | G4: Costo/L | H4: Importe | I4: Actividad Ejecutada | J4: Incidencia | K4: Observaciones | M4: Semana (Helper) | N4: Folio Ticket (Auto)
A5: 46181 | B5: México-Toluca | C5: Marimba M-01 | D5: Neuomatico | E5: =VLOOKUP(TablaObra[[#This Row],[Equipo]],Catalogos!$V$4:$W$64,2,FALSE) | F5: 30 | G5: 27 | H5: =IFERROR(F5*G5,0) | M5: 24 | N5: =IF(A5="","", "CO-" & IFERROR(VLOOKUP(B5, Catalogos!$Z$4:$AA$20, 2, FALSE), "FOL") & "-" & WEEKNUM(A5,2) & "-" & TEXT(ROW(A1),"000"))
A6: 46181 | B6: México-Toluca | C6: Marimba M-01 | D6: Compactador | E6: =VLOOKUP(TablaObra[[#This Row],[Equipo]],Catalogos!$V$4:$W$64,2,FALSE) | F6: 32 | G6: 27 | H6: =IFERROR(F6*G6,0) | M6: 24 | N6: =IF(A6="","", "CO-" & IFERROR(VLOOKUP(B6, Catalogos!$Z$4:$AA$20, 2, FALSE), "FOL") & "-" & WEEKNUM(A6,2) & "-" & TEXT(ROW(A2),"000"))
A7: 46181 | B7: México-Toluca | C7: Marimba M-01 | D7: Perfiladora | E7: =VLOOKUP(TablaObra[[#This Row],[Equipo]],Catalogos!$V$4:$W$64,2,FALSE) | F7: 277 | G7: 27 | H7: =IFERROR(F7*G7,0) | M7: 24 | N7: =IF(A7="","", "CO-" & IFERROR(VLOOKUP(B7, Catalogos!$Z$4:$AA$20, 2, FALSE), "FOL") & "-" & WEEKNUM(A7,2) & "-" & TEXT(ROW(A3),"000"))
A8: 46181 | B8: México-Toluca | C8: Marimba M-01 | D8: Retroexcavadora | E8: =VLOOKUP(TablaObra[[#This Row],[Equipo]],Catalogos!$V$4:$W$64,2,FALSE) | F8: 30 | G8: 27 | H8: =IFERROR(F8*G8,0) | M8: 24 | N8: =IF(A8="","", "CO-" & IFERROR(VLOOKUP(B8, Catalogos!$Z$4:$AA$20, 2, FALSE), "FOL") & "-" & WEEKNUM(A8,2) & "-" & TEXT(ROW(A4),"000"))
A9: 46181 | B9: Lerma - Tres Marías | C9: Marimba M-01 | D9: Vogel | E9: =VLOOKUP(TablaObra[[#This Row],[Equipo]],Catalogos!$V$4:$W$64,2,FALSE) | F9: 97 | G9: 27 | H9: =IFERROR(F9*G9,0) | M9: 24 | N9: =IF(A9="","", "CO-" & IFERROR(VLOOKUP(B9, Catalogos!$Z$4:$AA$20, 2, FALSE), "FOL") & "-" & WEEKNUM(A9,2) & "-" & TEXT(ROW(A5),"000"))
A10: 46181 | B10: Chamapa-Lechería | C10: Marimba M-01 | D10: Perfiladora Wirgent | E10: =VLOOKUP(TablaObra[[#This Row],[Equipo]],Catalogos!$V$4:$W$64,2,FALSE) | F10: 198 | G10: 27 | H10: =IFERROR(F10*G10,0) | M10: 24 | N10: =IF(A10="","", "CO-" & IFERROR(VLOOKUP(B10, Catalogos!$Z$4:$AA$20, 2, FALSE), "FOL") & "-" & WEEKNUM(A10,2) & "-" & TEXT(ROW(A6),"000"))
A11: 46181 | B11: Chamapa-Lechería | C11: Marimba M-01 | D11: Maxilihgs | E11: =VLOOKUP(TablaObra[[#This Row],[Equipo]],Catalogos!$V$4:$W$64,2,FALSE) | F11: 10 | G11: 27 | H11: =IFERROR(F11*G11,0) | M11: 24 | N11: =IF(A11="","", "CO-" & IFERROR(VLOOKUP(B11, Catalogos!$Z$4:$AA$20, 2, FALSE), "FOL") & "-" & WEEKNUM(A11,2) & "-" & TEXT(ROW(A7),"000"))
A12: 46181 | B12: Chamapa-Lechería | C12: Marimba M-01 | D12: Neuomatico Dynapac | E12: =VLOOKUP(TablaObra[[#This Row],[Equipo]],Catalogos!$V$4:$W$64,2,FALSE) | F12: 27 | G12: 27 | H12: =IFERROR(F12*G12,0) | M12: 24 | N12: =IF(A12="","", "CO-" & IFERROR(VLOOKUP(B12, Catalogos!$Z$4:$AA$20, 2, FALSE), "FOL") & "-" & WEEKNUM(A12,2) & "-" & TEXT(ROW(A8),"000"))
A13: 46181 | B13: Chamapa-Lechería | C13: Marimba M-01 | D13: Compresor | E13: =VLOOKUP(TablaObra[[#This Row],[Equipo]],Catalogos!$V$4:$W$64,2,FALSE) | F13: 30 | G13: 27 | H13: =IFERROR(F13*G13,0) | M13: 24 | N13: =IF(A13="","", "CO-" & IFERROR(VLOOKUP(B13, Catalogos!$Z$4:$AA$20, 2, FALSE), "FOL") & "-" & WEEKNUM(A13,2) & "-" & TEXT(ROW(A9),"000"))
A14: 46181 | B14: Chamapa-Lechería | C14: Marimba M-01 | D14: Retroexcavadora Jonh Deere | E14: =VLOOKUP(TablaObra[[#This Row],[Equipo]],Catalogos!$V$4:$W$64,2,FALSE) | F14: 40 | G14: 27 | H14: =IFERROR(F14*G14,0) | M14: 24 | N14: =IF(A14="","", "CO-" & IFERROR(VLOOKUP(B14, Catalogos!$Z$4:$AA$20, 2, FALSE), "FOL") & "-" & WEEKNUM(A14,2) & "-" & TEXT(ROW(A10),"000"))
A15: 46181 | B15: Chamapa-Lechería | C15: Marimba M-01 | D15: Vogele Guion | E15: =VLOOKUP(TablaObra[[#This Row],[Equipo]],Catalogos!$V$4:$W$64,2,FALSE) | F15: 120 | G15: 27 | H15: =IFERROR(F15*G15,0) | M15: 24 | N15: =IF(A15="","", "CO-" & IFERROR(VLOOKUP(B15, Catalogos!$Z$4:$AA$20, 2, FALSE), "FOL") & "-" & WEEKNUM(A15,2) & "-" & TEXT(ROW(A11),"000"))
A16: 46181 | B16: Chamapa-Lechería | C16: Marimba M-01 | D16: Petrolizadora Elton | E16: =VLOOKUP(TablaObra[[#This Row],[Equipo]],Catalogos!$V$4:$W$64,2,FALSE) | F16: 30 | G16: 27 | H16: =IFERROR(F16*G16,0) | M16: 24 | N16: =IF(A16="","", "CO-" & IFERROR(VLOOKUP(B16, Catalogos!$Z$4:$AA$20, 2, FALSE), "FOL") & "-" & WEEKNUM(A16,2) & "-" & TEXT(ROW(A12),"000"))
... A37: 46183 | B37: Bacheo Toluca | C37: Tanque Pegaso | D37: Bidones | E37: =VLOOKUP(TablaObra[[#This Row],[Equipo]],Catalogos!$V$4:$W$64,2,FALSE) | F37: 100 | G37: 27 | H37: =IFERROR(F37*G37,0) | M37: 24 | N37: =IF(A37="","", "CO-" & IFERROR(VLOOKUP(B37, Catalogos!$Z$4:$AA$20, 2, FALSE), "FOL") & "-" & WEEKNUM(A37,2) & "-" & TEXT(ROW(A33),"000"))
A38: 46184 | B38: México-Toluca | C38: Marimba M-01 | D38: Compactador | E38: =VLOOKUP(TablaObra[[#This Row],[Equipo]],Catalogos!$V$4:$W$64,2,FALSE) | F38: 30 | G38: 27 | H38: =IFERROR(F38*G38,0) | K38: Cuerpo a (Pausada) | M38: 24 | N38: =IF(A38="","", "CO-" & IFERROR(VLOOKUP(B38, Catalogos!$Z$4:$AA$20, 2, FALSE), "FOL") & "-" & WEEKNUM(A38,2) & "-" & TEXT(ROW(A34),"000"))
A39: 46184 | B39: México-Toluca | C39: Marimba M-01 | D39: Neuomatico | E39: =VLOOKUP(TablaObra[[#This Row],[Equipo]],Catalogos!$V$4:$W$64,2,FALSE) | F39: 30 | G39: 27 | H39: =IFERROR(F39*G39,0) | K39: Cuerpo a (Pausada) | M39: 24 | N39: =IF(A39="","", "CO-" & IFERROR(VLOOKUP(B39, Catalogos!$Z$4:$AA$20, 2, FALSE), "FOL") & "-" & WEEKNUM(A39,2) & "-" & TEXT(ROW(A35),"000"))
A40: 46184 | B40: México-Toluca | C40: Marimba M-01 | D40: Vogel | E40: =VLOOKUP(TablaObra[[#This Row],[Equipo]],Catalogos!$V$4:$W$64,2,FALSE) | F40: 136 | G40: 27 | H40: =IFERROR(F40*G40,0) | K40: Cuerpo a (Pausada) | M40: 24 | N40: =IF(A40="","", "CO-" & IFERROR(VLOOKUP(B40, Catalogos!$Z$4:$AA$20, 2, FALSE), "FOL") & "-" & WEEKNUM(A40,2) & "-" & TEXT(ROW(A36),"000"))
A41: 46184 | B41: México-Toluca | C41: Marimba M-01 | D41: Barredora | E41: =VLOOKUP(TablaObra[[#This Row],[Equipo]],Catalogos!$V$4:$W$64,2,FALSE) | F41: 20 | G41: 27 | H41: =IFERROR(F41*G41,0) | K41: Cuerpo a (Pausada) | M41: 24 | N41: =IF(A41="","", "CO-" & IFERROR(VLOOKUP(B41, Catalogos!$Z$4:$AA$20, 2, FALSE), "FOL") & "-" & WEEKNUM(A41,2) & "-" & TEXT(ROW(A37),"000"))
A42: 46184 | B42: México-Toluca | C42: Marimba M-01 | D42: Retroexcavadora | E42: =VLOOKUP(TablaObra[[#This Row],[Equipo]],Catalogos!$V$4:$W$64,2,FALSE) | F42: 20 | G42: 27 | H42: =IFERROR(F42*G42,0) | K42: Cuerpo a (Pausada) | M42: 24 | N42: =IF(A42="","", "CO-" & IFERROR(VLOOKUP(B42, Catalogos!$Z$4:$AA$20, 2, FALSE), "FOL") & "-" & WEEKNUM(A42,2) & "-" & TEXT(ROW(A38),"000"))
A43: 46184 | B43: México-Toluca | C43: Marimba M-01 | D43: Maxilihgs | E43: =VLOOKUP(TablaObra[[#This Row],[Equipo]],Catalogos!$V$4:$W$64,2,FALSE) | F43: 20 | G43: 27 | H43: =IFERROR(F43*G43,0) | K43: Cuerpo a (Pausada) | M43: 24 | N43: =IF(A43="","", "CO-" & IFERROR(VLOOKUP(B43, Catalogos!$Z$4:$AA$20, 2, FALSE), "FOL") & "-" & WEEKNUM(A43,2) & "-" & TEXT(ROW(A39),"000"))
A44: 46184 | B44: Maquinaria Pegaso | C44: Tanque Pegaso | D44: PayLoder | E44: =VLOOKUP(TablaObra[[#This Row],[Equipo]],Catalogos!$V$4:$W$64,2,FALSE) | F44: 238 | G44: 27 | H44: =IFERROR(F44*G44,0) | M44: 24 | N44: =IF(A44="","", "CO-" & IFERROR(VLOOKUP(B44, Catalogos!$Z$4:$AA$20, 2, FALSE), "FOL") & "-" & WEEKNUM(A44,2) & "-" & TEXT(ROW(A40),"000"))
A45: 46184 | B45: Lerma - Tres Marías | C45: Tanque Pegaso | D45: Petrolizadora | E45: =VLOOKUP(TablaObra[[#This Row],[Equipo]],Catalogos!$V$4:$W$64,2,FALSE) | F45: 80 | G45: 27 | H45: =IFERROR(F45*G45,0) | M45: 24 | N45: =IF(A45="","", "CO-" & IFERROR(VLOOKUP(B45, Catalogos!$Z$4:$AA$20, 2, FALSE), "FOL") & "-" & WEEKNUM(A45,2) & "-" & TEXT(ROW(A41),"000"))
A46: 46184 | B46: Lerma - Tres Marías | C46: Tanque Pegaso | D46: Compresor | E46: =VLOOKUP(TablaObra[[#This Row],[Equipo]],Catalogos!$V$4:$W$64,2,FALSE) | F46: 50 | G46: 27 | H46: =IFERROR(F46*G46,0) | M46: 24 | N46: =IF(A46="","", "CO-" & IFERROR(VLOOKUP(B46, Catalogos!$Z$4:$AA$20, 2, FALSE), "FOL") & "-" & WEEKNUM(A46,2) & "-" & TEXT(ROW(A42),"000"))
A47: 46184 | B47: Lerma - Tres Marías | C47: Tanque Pegaso | D47: Retroexcavadora | E47: =VLOOKUP(TablaObra[[#This Row],[Equipo]],Catalogos!$V$4:$W$64,2,FALSE) | F47: 70 | G47: 27 | H47: =IFERROR(F47*G47,0) | M47: 24 | N47: =IF(A47="","", "CO-" & IFERROR(VLOOKUP(B47, Catalogos!$Z$4:$AA$20, 2, FALSE), "FOL") & "-" & WEEKNUM(A47,2) & "-" & TEXT(ROW(A43),"000"))
A48: 46184 | B48: Lerma - Tres Marías | C48: Tanque Pegaso | D48: Camion de Impacto | E48: =VLOOKUP(TablaObra[[#This Row],[Equipo]],Catalogos!$V$4:$W$64,2,FALSE) | F48: 80 | G48: 27 | H48: =IFERROR(F48*G48,0) | M48: 24 | N48: =IF(A48="","", "CO-" & IFERROR(VLOOKUP(B48, Catalogos!$Z$4:$AA$20, 2, FALSE), "FOL") & "-" & WEEKNUM(A48,2) & "-" & TEXT(ROW(A44),"000"))
A49: 46184 | B49: Lerma - Tres Marías | C49: Tanque Pegaso | D49: Vogel | E49: =VLOOKUP(TablaObra[[#This Row],[Equipo]],Catalogos!$V$4:$W$64,2,FALSE) | F49: 185 | G49: 27 | H49: =IFERROR(F49*G49,0) | M49: 24 | N49: =IF(A49="","", "CO-" & IFERROR(VLOOKUP(B49, Catalogos!$Z$4:$AA$20, 2, FALSE), "FOL") & "-" & WEEKNUM(A49,2) & "-" & TEXT(ROW(A45),"000"))
A50: 46184 | B50: Lerma - Tres Marías | C50: Tanque Pegaso | D50: Doble Rodillo | E50: =VLOOKUP(TablaObra[[#This Row],[Equipo]],Catalogos!$V$4:$W$64,2,FALSE) | F50: 50 | G50: 27 | H50: =IFERROR(F50*G50,0) | M50: 24 | N50: =IF(A50="","", "CO-" & IFERROR(VLOOKUP(B50, Catalogos!$Z$4:$AA$20, 2, FALSE), "FOL") & "-" & WEEKNUM(A50,2) & "-" & TEXT(ROW(A46),"000"))
A51: 46184 | B51: Lerma - Tres Marías | C51: Tanque Pegaso | D51: Doble Rodillo | E51: =VLOOKUP(TablaObra[[#This Row],[Equipo]],Catalogos!$V$4:$W$64,2,FALSE) | F51: 40 | G51: 27 | H51: =IFERROR(F51*G51,0) | M51: 24 | N51: =IF(A51="","", "CO-" & IFERROR(VLOOKUP(B51, Catalogos!$Z$4:$AA$20, 2, FALSE), "FOL") & "-" & WEEKNUM(A51,2) & "-" & TEXT(ROW(A47),"000"))
A52: 46184 | B52: Lerma - Tres Marías | C52: Tanque Pegaso | D52: Neuomatico | E52: =VLOOKUP(TablaObra[[#This Row],[Equipo]],Catalogos!$V$4:$W$64,2,FALSE) | F52: 40 | G52: 27 | H52: =IFERROR(F52*G52,0) | M52: 24 | N52: =IF(A52="","", "CO-" & IFERROR(VLOOKUP(B52, Catalogos!$Z$4:$AA$20, 2, FALSE), "FOL") & "-" & WEEKNUM(A52,2) & "-" & TEXT(ROW(A48),"000"))
A53: 46185 | B53: Chamapa-Lechería | C53: Marimba M-01 | D53: Tandem Hamm | E53: =VLOOKUP(TablaObra[[#This Row],[Equipo]],Catalogos!$V$4:$W$64,2,FALSE) | F53: 32 | G53: 27 | H53: =IFERROR(F53*G53,0) | M53: 24 | N53: =IF(A53="","", "CO-" & IFERROR(VLOOKUP(B53, Catalogos!$Z$4:$AA$20, 2, FALSE), "FOL") & "-" & WEEKNUM(A53,2) & "-" & TEXT(ROW(A49),"000"))
A54: 46185 | B54: Chamapa-Lechería | C54: Marimba M-01 | D54: Neuomatico Dynapac | E54: =VLOOKUP(TablaObra[[#This Row],[Equipo]],Catalogos!$V$4:$W$64,2,FALSE) | F54: 30 | G54: 27 | H54: =IFERROR(F54*G54,0) | M54: 24 | N54: =IF(A54="","", "CO-" & IFERROR(VLOOKUP(B54, Catalogos!$Z$4:$AA$20, 2, FALSE), "FOL") & "-" & WEEKNUM(A54,2) & "-" & TEXT(ROW(A50),"000"))
A55: 46185 | B55: Chamapa-Lechería | C55: Marimba M-01 | D55: Barredora Broce | E55: =VLOOKUP(TablaObra[[#This Row],[Equipo]],Catalogos!$V$4:$W$64,2,FALSE) | F55: 30 | G55: 27 | H55: =IFERROR(F55*G55,0) | M55: 24 | N55: =IF(A55="","", "CO-" & IFERROR(VLOOKUP(B55, Catalogos!$Z$4:$AA$20, 2, FALSE), "FOL") & "-" & WEEKNUM(A55,2) & "-" & TEXT(ROW(A51),"000"))
... A68: 46188 | B68: México-Toluca | C68: Marimba M-01 | D68: NEUMATICO VOLVO PT-240R | E68: =VLOOKUP(TablaObra[[#This Row],[Equipo]],Catalogos!$V$4:$W$64,2,FALSE) | F68: 50 | G68: 27 | H68: =IFERROR(F68*G68,0) | M68: 25 | N68: =IF(A68="","", "CO-" & IFERROR(VLOOKUP(B68, Catalogos!$Z$4:$AA$20, 2, FALSE), "FOL") & "-" & WEEKNUM(A68,2) & "-" & TEXT(ROW(A64),"000"))
A69: 46188 | B69: Lerma - Tres Marías | C69: Marimba M-01 | D69: PAVIMENTADORA VOGELE 1800-3 i | E69: =VLOOKUP(TablaObra[[#This Row],[Equipo]],Catalogos!$V$4:$W$64,2,FALSE) | F69: 73 | G69: 27 | H69: =IFERROR(F69*G69,0) | K69: * | M69: 25 | N69: =IF(A69="","", "CO-" & IFERROR(VLOOKUP(B69, Catalogos!$Z$4:$AA$20, 2, FALSE), "FOL") & "-" & WEEKNUM(A69,2) & "-" & TEXT(ROW(A65),"000"))
A70: 46188 | B70: México-Toluca | C70: Marimba M-01 | D70: PAVIMENTADORA VOGELE SJ 1800-3 | E70: =VLOOKUP(TablaObra[[#This Row],[Equipo]],Catalogos!$V$4:$W$64,2,FALSE) | F70: 99 | G70: 27 | H70: =IFERROR(F70*G70,0) | M70: 25 | N70: =IF(A70="","", "CO-" & IFERROR(VLOOKUP(B70, Catalogos!$Z$4:$AA$20, 2, FALSE), "FOL") & "-" & WEEKNUM(A70,2) & "-" & TEXT(ROW(A66),"000"))
A71: 46188 | B71: México-Toluca | C71: Marimba M-01 | D71: PETROLIZADORA INTERNATIONAL | E71: =VLOOKUP(TablaObra[[#This Row],[Equipo]],Catalogos!$V$4:$W$64,2,FALSE) | F71: 50 | G71: 27 | H71: =IFERROR(F71*G71,0) | M71: 25 | N71: =IF(A71="","", "CO-" & IFERROR(VLOOKUP(B71, Catalogos!$Z$4:$AA$20, 2, FALSE), "FOL") & "-" & WEEKNUM(A71,2) & "-" & TEXT(ROW(A67),"000"))
A72: 46188 | B72: Bacheo Toluca | C72: Tanque Pegaso | D72: Bidones | E72: =VLOOKUP(TablaObra[[#This Row],[Equipo]],Catalogos!$V$4:$W$64,2,FALSE) | F72: 70 | G72: 27 | H72: =IFERROR(F72*G72,0) | M72: 25 | N72: =IF(A72="","", "CO-" & IFERROR(VLOOKUP(B72, Catalogos!$Z$4:$AA$20, 2, FALSE), "FOL") & "-" & WEEKNUM(A72,2) & "-" & TEXT(ROW(A68),"000"))
