Workbook

Sheet Dashboard
A1: DASHBOARD EJECUTIVO DE CONTROL DE COMBUSTIBLE | GRUPO TRUJANO
A3: FILTROS DEL DASHBOARD (Celdas en amarillo editables en Excel) | E3: ESTADO DE LA CONCILIACIÓN SEMANAL
B4: Obra Seleccionada: | C4: México-Toluca | E4: =IF(I28=0, "🟢 TODO COINCIDE (0 L)", "🔴 DISCREPANCIA: " & I28 & " L")
B5: Fecha Inicio (Lunes): | C5: 46181
B6: Fecha Fin (Rango): | C6: 46188
B7: Precio Diésel ($/L): | C7: 28.3
B8: Período Resumen: | C8: Semana Seleccionada
A10: COMPARATIVA: SOLICITADO (PETICIONES) VS ENTREGADO EN OBRA
A11: Día | B11: Fecha | C11: Lts Solicitados | D11: Lts Recibidos Obra | E11: Dif. Litros (Obra-Sol) | F11: Costo Solicitado | G11: Costo Real Obra | H11: Dif. Costo (Real-Sol)
A12: Lunes | B12: =C$5 | C12: =IF(C$4="Todas", SUMIFS(Solicitudes!F:F, Solicitudes!C:C, B12), SUMIFS(Solicitudes!F:F, Solicitudes!B:B, C$4, Solicitudes!C:C, B12)) | D12: =IF(C$4="Jalisco", SUMIFS(Captura_Jalisco!G:G, Captura_Jalisco!A:A, B12, Captura_Jalisco!B:B, "Salida"), IF(C$4="Todas", SUMIFS(Captura_Obra!F:F, Captura_Obra!A:A, B12) + SUMIFS(Captura_Jalisco!G:G, Captura_Jalisco!A:A, B12, Captura_Jalisco!B:B, "Salida"), SUMIFS(Captura_Obra!F:F, Captura_Obra!B:B, C$4, Captura_Obra!A:A, B12))) | E12: =D12-C12 | F12: =C12*C$7 | G12: =D12*C$7 | H12: =G12-F12
A13: Martes | B13: =B12+1 | C13: =IF(C$4="Todas", SUMIFS(Solicitudes!F:F, Solicitudes!C:C, B13), SUMIFS(Solicitudes!F:F, Solicitudes!B:B, C$4, Solicitudes!C:C, B13)) | D13: =IF(C$4="Jalisco", SUMIFS(Captura_Jalisco!G:G, Captura_Jalisco!A:A, B13, Captura_Jalisco!B:B, "Salida"), IF(C$4="Todas", SUMIFS(Captura_Obra!F:F, Captura_Obra!A:A, B13) + SUMIFS(Captura_Jalisco!G:G, Captura_Jalisco!A:A, B13, Captura_Jalisco!B:B, "Salida"), SUMIFS(Captura_Obra!F:F, Captura_Obra!B:B, C$4, Captura_Obra!A:A, B13))) | E13: =D13-C13 | F13: =C13*C$7 | G13: =D13*C$7 | H13: =G13-F13
A14: Miércoles | B14: =B13+1 | C14: =IF(C$4="Todas", SUMIFS(Solicitudes!F:F, Solicitudes!C:C, B14), SUMIFS(Solicitudes!F:F, Solicitudes!B:B, C$4, Solicitudes!C:C, B14)) | D14: =IF(C$4="Jalisco", SUMIFS(Captura_Jalisco!G:G, Captura_Jalisco!A:A, B14, Captura_Jalisco!B:B, "Salida"), IF(C$4="Todas", SUMIFS(Captura_Obra!F:F, Captura_Obra!A:A, B14) + SUMIFS(Captura_Jalisco!G:G, Captura_Jalisco!A:A, B14, Captura_Jalisco!B:B, "Salida"), SUMIFS(Captura_Obra!F:F, Captura_Obra!B:B, C$4, Captura_Obra!A:A, B14))) | E14: =D14-C14 | F14: =C14*C$7 | G14: =D14*C$7 | H14: =G14-F14
A15: Jueves | B15: =B14+1 | C15: =IF(C$4="Todas", SUMIFS(Solicitudes!F:F, Solicitudes!C:C, B15), SUMIFS(Solicitudes!F:F, Solicitudes!B:B, C$4, Solicitudes!C:C, B15)) | D15: =IF(C$4="Jalisco", SUMIFS(Captura_Jalisco!G:G, Captura_Jalisco!A:A, B15, Captura_Jalisco!B:B, "Salida"), IF(C$4="Todas", SUMIFS(Captura_Obra!F:F, Captura_Obra!A:A, B15) + SUMIFS(Captura_Jalisco!G:G, Captura_Jalisco!A:A, B15, Captura_Jalisco!B:B, "Salida"), SUMIFS(Captura_Obra!F:F, Captura_Obra!B:B, C$4, Captura_Obra!A:A, B15))) | E15: =D15-C15 | F15: =C15*C$7 | G15: =D15*C$7 | H15: =G15-F15
A16: Viernes | B16: =B15+1 | C16: =IF(C$4="Todas", SUMIFS(Solicitudes!F:F, Solicitudes!C:C, B16), SUMIFS(Solicitudes!F:F, Solicitudes!B:B, C$4, Solicitudes!C:C, B16)) | D16: =IF(C$4="Jalisco", SUMIFS(Captura_Jalisco!G:G, Captura_Jalisco!A:A, B16, Captura_Jalisco!B:B, "Salida"), IF(C$4="Todas", SUMIFS(Captura_Obra!F:F, Captura_Obra!A:A, B16) + SUMIFS(Captura_Jalisco!G:G, Captura_Jalisco!A:A, B16, Captura_Jalisco!B:B, "Salida"), SUMIFS(Captura_Obra!F:F, Captura_Obra!B:B, C$4, Captura_Obra!A:A, B16))) | E16: =D16-C16 | F16: =C16*C$7 | G16: =D16*C$7 | H16: =G16-F16
A17: Sábado | B17: =B16+1 | C17: =IF(C$4="Todas", SUMIFS(Solicitudes!F:F, Solicitudes!C:C, B17), SUMIFS(Solicitudes!F:F, Solicitudes!B:B, C$4, Solicitudes!C:C, B17)) | D17: =IF(C$4="Jalisco", SUMIFS(Captura_Jalisco!G:G, Captura_Jalisco!A:A, B17, Captura_Jalisco!B:B, "Salida"), IF(C$4="Todas", SUMIFS(Captura_Obra!F:F, Captura_Obra!A:A, B17) + SUMIFS(Captura_Jalisco!G:G, Captura_Jalisco!A:A, B17, Captura_Jalisco!B:B, "Salida"), SUMIFS(Captura_Obra!F:F, Captura_Obra!B:B, C$4, Captura_Obra!A:A, B17))) | E17: =D17-C17 | F17: =C17*C$7 | G17: =D17*C$7 | H17: =G17-F17
A18: TOTAL SEMANAL | C18: =SUM(C12:C17) | D18: =SUM(D12:D17) | E18: =SUM(E12:E17) | F18: =SUM(F12:F17) | G18: =SUM(G12:G17) | H18: =SUM(H12:H17)
A20: CONCILIACIÓN FÍSICA Y DISCREPANCIAS (OBRA VS MARIMBA Y PEGASO)
A21: Día | B21: Fecha | C21: Obra Recibió (M) | D21: Marimba Despachó | E21: Dif. Marimba | F21: Obra Recibió (P) | G21: Pegaso Despachó | H21: Dif. Pegaso | I21: Dif. Total (L) | J21: Observaciones / Justificación
A22: Lunes | B22: =B12 | C22: =IF(C$4="Todas", SUMIFS(Captura_Obra!F:F, Captura_Obra!A:A, B22, Captura_Obra!C:C, "Marimba M-01"), SUMIFS(Captura_Obra!F:F, Captura_Obra!B:B, C$4, Captura_Obra!A:A, B22, Captura_Obra!C:C, "Marimba M-01")) | D22: =IF(C$4="Todas", SUMIFS(Captura_Marimba_M01!G:G, Captura_Marimba_M01!A:A, B22, Captura_Marimba_M01!B:B, "Salida"), SUMIFS(Captura_Marimba_M01!G:G, Captura_Marimba_M01!C:C, C$4, Captura_Marimba_M01!A:A, B22, Captura_Marimba_M01!B:B, "Salida")) | E22: =C22-D22 | F22: =IF(C$4="Todas", SUMIFS(Captura_Obra!F:F, Captura_Obra!A:A, B22, Captura_Obra!C:C, "Pegaso Directo"), SUMIFS(Captura_Obra!F:F, Captura_Obra!B:B, C$4, Captura_Obra!A:A, B22, Captura_Obra!C:C, "Pegaso Directo")) | G22: =IF(C$4="Todas", SUMIFS(Captura_Pegaso!H:H, Captura_Pegaso!A:A, B22, Captura_Pegaso!B:B, "Salida"), SUMIFS(Captura_Pegaso!H:H, Captura_Pegaso!D:D, C$4, Captura_Pegaso!A:A, B22, Captura_Pegaso!B:B, "Salida")) | H22: =F22-G22 | I22: =E22+H22
A23: Martes | B23: =B13 | C23: =IF(C$4="Todas", SUMIFS(Captura_Obra!F:F, Captura_Obra!A:A, B23, Captura_Obra!C:C, "Marimba M-01"), SUMIFS(Captura_Obra!F:F, Captura_Obra!B:B, C$4, Captura_Obra!A:A, B23, Captura_Obra!C:C, "Marimba M-01")) | D23: =IF(C$4="Todas", SUMIFS(Captura_Marimba_M01!G:G, Captura_Marimba_M01!A:A, B23, Captura_Marimba_M01!B:B, "Salida"), SUMIFS(Captura_Marimba_M01!G:G, Captura_Marimba_M01!C:C, C$4, Captura_Marimba_M01!A:A, B23, Captura_Marimba_M01!B:B, "Salida")) | E23: =C23-D23 | F23: =IF(C$4="Todas", SUMIFS(Captura_Obra!F:F, Captura_Obra!A:A, B23, Captura_Obra!C:C, "Pegaso Directo"), SUMIFS(Captura_Obra!F:F, Captura_Obra!B:B, C$4, Captura_Obra!A:A, B23, Captura_Obra!C:C, "Pegaso Directo")) | G23: =IF(C$4="Todas", SUMIFS(Captura_Pegaso!H:H, Captura_Pegaso!A:A, B23, Captura_Pegaso!B:B, "Salida"), SUMIFS(Captura_Pegaso!H:H, Captura_Pegaso!D:D, C$4, Captura_Pegaso!A:A, B23, Captura_Pegaso!B:B, "Salida")) | H23: =F23-G23 | I23: =E23+H23
A24: Miércoles | B24: =B14 | C24: =IF(C$4="Todas", SUMIFS(Captura_Obra!F:F, Captura_Obra!A:A, B24, Captura_Obra!C:C, "Marimba M-01"), SUMIFS(Captura_Obra!F:F, Captura_Obra!B:B, C$4, Captura_Obra!A:A, B24, Captura_Obra!C:C, "Marimba M-01")) | D24: =IF(C$4="Todas", SUMIFS(Captura_Marimba_M01!G:G, Captura_Marimba_M01!A:A, B24, Captura_Marimba_M01!B:B, "Salida"), SUMIFS(Captura_Marimba_M01!G:G, Captura_Marimba_M01!C:C, C$4, Captura_Marimba_M01!A:A, B24, Captura_Marimba_M01!B:B, "Salida")) | E24: =C24-D24 | F24: =IF(C$4="Todas", SUMIFS(Captura_Obra!F:F, Captura_Obra!A:A, B24, Captura_Obra!C:C, "Pegaso Directo"), SUMIFS(Captura_Obra!F:F, Captura_Obra!B:B, C$4, Captura_Obra!A:A, B24, Captura_Obra!C:C, "Pegaso Directo")) | G24: =IF(C$4="Todas", SUMIFS(Captura_Pegaso!H:H, Captura_Pegaso!A:A, B24, Captura_Pegaso!B:B, "Salida"), SUMIFS(Captura_Pegaso!H:H, Captura_Pegaso!D:D, C$4, Captura_Pegaso!A:A, B24, Captura_Pegaso!B:B, "Salida")) | H24: =F24-G24 | I24: =E24+H24
A25: Jueves | B25: =B15 | C25: =IF(C$4="Todas", SUMIFS(Captura_Obra!F:F, Captura_Obra!A:A, B25, Captura_Obra!C:C, "Marimba M-01"), SUMIFS(Captura_Obra!F:F, Captura_Obra!B:B, C$4, Captura_Obra!A:A, B25, Captura_Obra!C:C, "Marimba M-01")) | D25: =IF(C$4="Todas", SUMIFS(Captura_Marimba_M01!G:G, Captura_Marimba_M01!A:A, B25, Captura_Marimba_M01!B:B, "Salida"), SUMIFS(Captura_Marimba_M01!G:G, Captura_Marimba_M01!C:C, C$4, Captura_Marimba_M01!A:A, B25, Captura_Marimba_M01!B:B, "Salida")) | E25: =C25-D25 | F25: =IF(C$4="Todas", SUMIFS(Captura_Obra!F:F, Captura_Obra!A:A, B25, Captura_Obra!C:C, "Pegaso Directo"), SUMIFS(Captura_Obra!F:F, Captura_Obra!B:B, C$4, Captura_Obra!A:A, B25, Captura_Obra!C:C, "Pegaso Directo")) | G25: =IF(C$4="Todas", SUMIFS(Captura_Pegaso!H:H, Captura_Pegaso!A:A, B25, Captura_Pegaso!B:B, "Salida"), SUMIFS(Captura_Pegaso!H:H, Captura_Pegaso!D:D, C$4, Captura_Pegaso!A:A, B25, Captura_Pegaso!B:B, "Salida")) | H25: =F25-G25 | I25: =E25+H25
A26: Viernes | B26: =B16 | C26: =IF(C$4="Todas", SUMIFS(Captura_Obra!F:F, Captura_Obra!A:A, B26, Captura_Obra!C:C, "Marimba M-01"), SUMIFS(Captura_Obra!F:F, Captura_Obra!B:B, C$4, Captura_Obra!A:A, B26, Captura_Obra!C:C, "Marimba M-01")) | D26: =IF(C$4="Todas", SUMIFS(Captura_Marimba_M01!G:G, Captura_Marimba_M01!A:A, B26, Captura_Marimba_M01!B:B, "Salida"), SUMIFS(Captura_Marimba_M01!G:G, Captura_Marimba_M01!C:C, C$4, Captura_Marimba_M01!A:A, B26, Captura_Marimba_M01!B:B, "Salida")) | E26: =C26-D26 | F26: =IF(C$4="Todas", SUMIFS(Captura_Obra!F:F, Captura_Obra!A:A, B26, Captura_Obra!C:C, "Pegaso Directo"), SUMIFS(Captura_Obra!F:F, Captura_Obra!B:B, C$4, Captura_Obra!A:A, B26, Captura_Obra!C:C, "Pegaso Directo")) | G26: =IF(C$4="Todas", SUMIFS(Captura_Pegaso!H:H, Captura_Pegaso!A:A, B26, Captura_Pegaso!B:B, "Salida"), SUMIFS(Captura_Pegaso!H:H, Captura_Pegaso!D:D, C$4, Captura_Pegaso!A:A, B26, Captura_Pegaso!B:B, "Salida")) | H26: =F26-G26 | I26: =E26+H26
A27: Sábado | B27: =B17 | C27: =IF(C$4="Todas", SUMIFS(Captura_Obra!F:F, Captura_Obra!A:A, B27, Captura_Obra!C:C, "Marimba M-01"), SUMIFS(Captura_Obra!F:F, Captura_Obra!B:B, C$4, Captura_Obra!A:A, B27, Captura_Obra!C:C, "Marimba M-01")) | D27: =IF(C$4="Todas", SUMIFS(Captura_Marimba_M01!G:G, Captura_Marimba_M01!A:A, B27, Captura_Marimba_M01!B:B, "Salida"), SUMIFS(Captura_Marimba_M01!G:G, Captura_Marimba_M01!C:C, C$4, Captura_Marimba_M01!A:A, B27, Captura_Marimba_M01!B:B, "Salida")) | E27: =C27-D27 | F27: =IF(C$4="Todas", SUMIFS(Captura_Obra!F:F, Captura_Obra!A:A, B27, Captura_Obra!C:C, "Pegaso Directo"), SUMIFS(Captura_Obra!F:F, Captura_Obra!B:B, C$4, Captura_Obra!A:A, B27, Captura_Obra!C:C, "Pegaso Directo")) | G27: =IF(C$4="Todas", SUMIFS(Captura_Pegaso!H:H, Captura_Pegaso!A:A, B27, Captura_Pegaso!B:B, "Salida"), SUMIFS(Captura_Pegaso!H:H, Captura_Pegaso!D:D, C$4, Captura_Pegaso!A:A, B27, Captura_Pegaso!B:B, "Salida")) | H27: =F27-G27 | I27: =E27+H27
A28: TOTAL CONCILIADO | C28: =SUM(C22:C27) | D28: =SUM(D22:D27) | E28: =SUM(E22:E27) | F28: =SUM(F22:F27) | G28: =SUM(G22:G27) | H28: =SUM(H22:H27) | I28: =SUM(I22:I27)
A31: RESUMEN ACUMULADO POR OBRA / PERÍODO SELECCIONADO
A32: Obra | B32: Total Litros Suministrados | C32: Costo Total Acumulado
A33: México-Toluca | B33: =IF(C$8="Acumulado Histórico", SUMIFS(Captura_Obra!F:F, Captura_Obra!B:B, A33), IF(C$8="Rango de Fechas", SUMIFS(Captura_Obra!F:F, Captura_Obra!B:B, A33, Captura_Obra!A:A, ">="&C$5, Captura_Obra!A:A, "<="&(C$6+5)), SUMIFS(Captura_Obra!F:F, Captura_Obra!B:B, A33, Captura_Obra!A:A, ">="&C$5, Captura_Obra!A:A, "<="&(C$5+5)))) | C33: =B33*C$7
A34: Lerma - Tres Marías | B34: =IF(C$8="Acumulado Histórico", SUMIFS(Captura_Obra!F:F, Captura_Obra!B:B, A34), IF(C$8="Rango de Fechas", SUMIFS(Captura_Obra!F:F, Captura_Obra!B:B, A34, Captura_Obra!A:A, ">="&C$5, Captura_Obra!A:A, "<="&(C$6+5)), SUMIFS(Captura_Obra!F:F, Captura_Obra!B:B, A34, Captura_Obra!A:A, ">="&C$5, Captura_Obra!A:A, "<="&(C$5+5)))) | C34: =B34*C$7
A35: Chamapa-Lechería | B35: =IF(C$8="Acumulado Histórico", SUMIFS(Captura_Obra!F:F, Captura_Obra!B:B, A35), IF(C$8="Rango de Fechas", SUMIFS(Captura_Obra!F:F, Captura_Obra!B:B, A35, Captura_Obra!A:A, ">="&C$5, Captura_Obra!A:A, "<="&(C$6+5)), SUMIFS(Captura_Obra!F:F, Captura_Obra!B:B, A35, Captura_Obra!A:A, ">="&C$5, Captura_Obra!A:A, "<="&(C$5+5)))) | C35: =B35*C$7
A36: Bacheo Toluca | B36: =IF(C$8="Acumulado Histórico", SUMIFS(Captura_Obra!F:F, Captura_Obra!B:B, A36), IF(C$8="Rango de Fechas", SUMIFS(Captura_Obra!F:F, Captura_Obra!B:B, A36, Captura_Obra!A:A, ">="&C$5, Captura_Obra!A:A, "<="&(C$6+5)), SUMIFS(Captura_Obra!F:F, Captura_Obra!B:B, A36, Captura_Obra!A:A, ">="&C$5, Captura_Obra!A:A, "<="&(C$5+5)))) | C36: =B36*C$7
A37: Planta Asfalto Pegaso | B37: =IF(C$8="Acumulado Histórico", SUMIFS(Captura_Obra!F:F, Captura_Obra!B:B, A37), IF(C$8="Rango de Fechas", SUMIFS(Captura_Obra!F:F, Captura_Obra!B:B, A37, Captura_Obra!A:A, ">="&C$5, Captura_Obra!A:A, "<="&(C$6+5)), SUMIFS(Captura_Obra!F:F, Captura_Obra!B:B, A37, Captura_Obra!A:A, ">="&C$5, Captura_Obra!A:A, "<="&(C$5+5)))) | C37: =B37*C$7
A38: Planta Asflato Huixquilucan | B38: =IF(C$8="Acumulado Histórico", SUMIFS(Captura_Obra!F:F, Captura_Obra!B:B, A38), IF(C$8="Rango de Fechas", SUMIFS(Captura_Obra!F:F, Captura_Obra!B:B, A38, Captura_Obra!A:A, ">="&C$5, Captura_Obra!A:A, "<="&(C$6+5)), SUMIFS(Captura_Obra!F:F, Captura_Obra!B:B, A38, Captura_Obra!A:A, ">="&C$5, Captura_Obra!A:A, "<="&(C$5+5)))) | C38: =B38*C$7
A39: Dragones | B39: =IF(C$8="Acumulado Histórico", SUMIFS(Captura_Obra!F:F, Captura_Obra!B:B, A39), IF(C$8="Rango de Fechas", SUMIFS(Captura_Obra!F:F, Captura_Obra!B:B, A39, Captura_Obra!A:A, ">="&C$5, Captura_Obra!A:A, "<="&(C$6+5)), SUMIFS(Captura_Obra!F:F, Captura_Obra!B:B, A39, Captura_Obra!A:A, ">="&C$5, Captura_Obra!A:A, "<="&(C$5+5)))) | C39: =B39*C$7
A40: Jalisco | B40: =IF(C$8="Acumulado Histórico", SUMIFS(Captura_Jalisco!G:G, Captura_Jalisco!B:B, "Salida"), IF(C$8="Rango de Fechas", SUMIFS(Captura_Jalisco!G:G, Captura_Jalisco!B:B, "Salida", Captura_Jalisco!A:A, ">="&C$5, Captura_Jalisco!A:A, "<="&(C$6+5)), SUMIFS(Captura_Jalisco!G:G, Captura_Jalisco!B:B, "Salida", Captura_Jalisco!A:A, ">="&C$5, Captura_Jalisco!A:A, "<="&(C$5+5)))) | C40: =B40*C$7
A41: TOTAL GENERAL | B41: =SUM(B33:B40) | C41: =SUM(C33:C40)
A43: RESUMEN DE CONSUMO SEMANAL POR OBRA (DETALLE HISTÓRICO POR SEMANA)
B44: Obra (Tabla Semanal): | C44: Jalisco
B45: Precio Diésel ($/L): | C45: 28.3
A47: Semana (Lunes) | B47: Litros Despachados | C47: Costo/L ($) | D47: Costo Combustible ($) | E47: Acumulado Semanal ($)
A48: 46167 | B48: =IF(C$44="Jalisco", SUMIFS(Captura_Jalisco!G:G, Captura_Jalisco!B:B, "Salida", Captura_Jalisco!A:A, ">="&A48, Captura_Jalisco!A:A, "<="&(A48+5)), IF(C$44="Todas", SUMIFS(Captura_Obra!F:F, Captura_Obra!A:A, ">="&A48, Captura_Obra!A:A, "<="&(A48+5)) + SUMIFS(Captura_Jalisco!G:G, Captura_Jalisco!B:B, "Salida", Captura_Jalisco!A:A, ">="&A48, Captura_Jalisco!A:A, "<="&(A48+5)), SUMIFS(Captura_Obra!F:F, Captura_Obra!B:B, C$44, Captura_Obra!A:A, ">="&A48, Captura_Obra!A:A, "<="&(A48+5)))) | C48: =C$45 | D48: =B48*C48 | E48: =D48
A49: 46174 | B49: =IF(C$44="Jalisco", SUMIFS(Captura_Jalisco!G:G, Captura_Jalisco!B:B, "Salida", Captura_Jalisco!A:A, ">="&A49, Captura_Jalisco!A:A, "<="&(A49+5)), IF(C$44="Todas", SUMIFS(Captura_Obra!F:F, Captura_Obra!A:A, ">="&A49, Captura_Obra!A:A, "<="&(A49+5)) + SUMIFS(Captura_Jalisco!G:G, Captura_Jalisco!B:B, "Salida", Captura_Jalisco!A:A, ">="&A49, Captura_Jalisco!A:A, "<="&(A49+5)), SUMIFS(Captura_Obra!F:F, Captura_Obra!B:B, C$44, Captura_Obra!A:A, ">="&A49, Captura_Obra!A:A, "<="&(A49+5)))) | C49: =C$45 | D49: =B49*C49 | E49: =E48+D49
A50: 46181 | B50: =IF(C$44="Jalisco", SUMIFS(Captura_Jalisco!G:G, Captura_Jalisco!B:B, "Salida", Captura_Jalisco!A:A, ">="&A50, Captura_Jalisco!A:A, "<="&(A50+5)), IF(C$44="Todas", SUMIFS(Captura_Obra!F:F, Captura_Obra!A:A, ">="&A50, Captura_Obra!A:A, "<="&(A50+5)) + SUMIFS(Captura_Jalisco!G:G, Captura_Jalisco!B:B, "Salida", Captura_Jalisco!A:A, ">="&A50, Captura_Jalisco!A:A, "<="&(A50+5)), SUMIFS(Captura_Obra!F:F, Captura_Obra!B:B, C$44, Captura_Obra!A:A, ">="&A50, Captura_Obra!A:A, "<="&(A50+5)))) | C50: =C$45 | D50: =B50*C50 | E50: =E49+D50
A51: 46188 | B51: =IF(C$44="Jalisco", SUMIFS(Captura_Jalisco!G:G, Captura_Jalisco!B:B, "Salida", Captura_Jalisco!A:A, ">="&A51, Captura_Jalisco!A:A, "<="&(A51+5)), IF(C$44="Todas", SUMIFS(Captura_Obra!F:F, Captura_Obra!A:A, ">="&A51, Captura_Obra!A:A, "<="&(A51+5)) + SUMIFS(Captura_Jalisco!G:G, Captura_Jalisco!B:B, "Salida", Captura_Jalisco!A:A, ">="&A51, Captura_Jalisco!A:A, "<="&(A51+5)), SUMIFS(Captura_Obra!F:F, Captura_Obra!B:B, C$44, Captura_Obra!A:A, ">="&A51, Captura_Obra!A:A, "<="&(A51+5)))) | C51: =C$45 | D51: =B51*C51 | E51: =E50+D51
A52: TOTAL ACUMULADO | B52: =SUM(B48:B51) | D52: =SUM(D48:D51)

Sheet Dashboard_Ejecutivo
B2: Peticiones por Día y Obra | G2: Salidas Marimba por Día y Obra | L2: Salidas Pegaso a Obra | Q2: Consumo Total en Obra | V2: Resumen Semanal por Obra
B4: Fecha | C4: Obra | D4: Litros Solicitados | E4: Costo Estimado ($) | G4: Fecha | H4: Obra | I4: Salida (L) | J4: Costo Surtido ($) | L4: Fecha | M4: Obra | N4: Salida (L) | O4: Costo Surtido ($) | Q4: Fecha | R4: Obra | S4: Litros Recibidos | T4: Costo Surtido ($) | V4: Obra | W4: Litros Recibidos | X4: Costo Surtido ($)
B5: 2026-06-07 | C5: Lerma - Tres Marías | D5: 160 | E5: 4528 | G5: 2026-06-08 | H5: Chamapa-Lechería | I5: 455 | J5: 12876.5 | L5: 2026-06-08 | M5: Bacheo Toluca | N5: 180 | O5: 5094 | Q5: 2026-06-08 | R5: Bacheo Toluca | S5: 100 | T5: 2830 | V5: Bacheo Toluca | W5: 200 | X5: 5660
B6: 2026-06-07 | C6: México-Toluca | D6: 640 | E6: 18112 | G6: 2026-06-08 | H6: Lerma - Tres Marías | I6: 97 | J6: 2745.1 | L6: 2026-06-08 | M6: Planta Asfalto Pegaso | N6: 409 | O6: 11574.7 | Q6: 2026-06-08 | R6: Chamapa-Lechería | S6: 455 | T6: 12876.5 | V6: Chamapa-Lechería | W6: 1693 | X6: 47911.9
B7: 2026-06-08 | C7: Bacheo Toluca | D7: 100 | E7: 2830 | G7: 2026-06-08 | H7: México-Toluca | I7: 369 | J7: 10442.7 | L7: 2026-06-09 | M7: Lerma - Tres Marías | N7: 180 | O7: 5094 | Q7: 2026-06-08 | R7: Lerma - Tres Marías | S7: 97 | T7: 2745.1 | V7: Lerma - Tres Marías | W7: 872 | X7: 24677.6
B8: 2026-06-08 | C8: Chamapa-Lechería | D8: 990 | E8: 28017 | G8: 2026-06-09 | H8: Chamapa-Lechería | I8: 736 | J8: 20828.8 | L8: 2026-06-10 | M8: Bacheo Toluca | N8: 100 | O8: 2830 | Q8: 2026-06-08 | R8: México-Toluca | S8: 369 | T8: 10442.7 | V8: México-Toluca | W8: 1285 | X8: 36365.5
B9: 2026-06-09 | C9: Bacheo Toluca | D9: 100 | E9: 2830 | G9: 2026-06-10 | H9: México-Toluca | I9: 300 | J9: 8490 | L9: 2026-06-11 | M9: Lerma - Tres Marías | N9: 595 | O9: 16838.5 | Q9: 2026-06-08 | R9: Planta Asfalto Pegaso | S9: 409 | T9: 11574.7 | V9: Planta Asfalto Pegaso | W9: 647 | X9: 18310.1
B10: 2026-06-09 | C10: Chamapa-Lechería | D10: 790 | E10: 22357 | G10: 2026-06-11 | H10: México-Toluca | I10: 256 | J10: 7244.8 | L10: 2026-06-11 | M10: Planta Asfalto Pegaso | N10: 238 | O10: 6735.4 | Q10: 2026-06-09 | R10: Chamapa-Lechería | S10: 736 | T10: 20828.8 | X10: =SUM(X5:X9)
B11: 2026-06-09 | C11: Lerma - Tres Marías | D11: 210 | E11: 5943 | G11: 2026-06-12 | H11: Chamapa-Lechería | I11: 502 | J11: 14206.6 | L11: 2026-06-12 | M11: Bacheo Toluca | N11: 70 | O11: 1981 | Q11: 2026-06-09 | R11: Lerma - Tres Marías | S11: 180 | T11: 5094
B12: 2026-06-10 | C12: México-Toluca | D12: 320 | E12: 9056 | G12: 2026-06-12 | H12: México-Toluca | I12: 360 | J12: 10188 | Q12: 2026-06-10 | R12: Bacheo Toluca | S12: 100 | T12: 2830
B13: 2026-06-11 | C13: Bacheo Toluca | D13: 70 | E13: 1981 | Q13: 2026-06-10 | R13: México-Toluca | S13: 300 | T13: 8490
B14: 2026-06-11 | C14: Lerma - Tres Marías | D14: 460 | E14: 13018 | Q14: 2026-06-11 | R14: Lerma - Tres Marías | S14: 595 | T14: 16838.5
B15: 2026-06-12 | C15: Chamapa-Lechería | D15: 620 | E15: 17546 | Q15: 2026-06-11 | R15: México-Toluca | S15: 256 | T15: 7244.8
B16: 2026-06-12 | C16: México-Toluca | D16: 540 | E16: 15282 | Q16: 2026-06-11 | R16: Planta Asfalto Pegaso | S16: 238 | T16: 6735.4
Q17: 2026-06-12 | R17: Chamapa-Lechería | S17: 502 | T17: 14206.6
Q18: 2026-06-12 | R18: México-Toluca | S18: 360 | T18: 10188
B35: Costos por Día (Petición vs Surtido) | G35: Costos por Obra (Petición vs Surtido) | L35: Totales Generales por Día | Q35: Totales Generales por Obra | V35: Reporte de Discrepancias (Faltantes/Sobrantes)
B37: Fecha | C37: Costo Solicitado ($) | D37: Costo Surtido ($) | G37: Obra | H37: Costo Solicitado ($) | I37: Costo Surtido ($) | L37: Fecha | M37: Litros Totales | N37: Costo Total ($) | Q37: Obra | R37: Litros Totales | S37: Costo Total ($) | V37: Fecha | W37: Obra | X37: Litros Surtidos | Y37: Litros Recibidos | Z37: Discrepancia (L)
B38: 2026-06-07 | C38: 22640 | D38: 0 | G38: Bacheo Toluca | H38: 7641 | I38: 9905 | L38: 2026-06-08 | M38: 1510 | N38: 42733 | Q38: Bacheo Toluca | R38: 350 | S38: 9905 | V38: 2026-06-08 | W38: Bacheo Toluca | X38: 180 | Y38: 100 | Z38: 80
B39: 2026-06-08 | C39: 30847 | D39: 42733 | G39: Chamapa-Lechería | H39: 67920 | I39: 47911.9 | L39: 2026-06-09 | M39: 916 | N39: 25922.8 | Q39: Chamapa-Lechería | R39: 1693 | S39: 47911.9 | V39: 2026-06-12 | W39: Bacheo Toluca | X39: 70 | Y39: 0 | Z39: 70
B40: 2026-06-09 | C40: 31130 | D40: 25922.8 | G40: Lerma - Tres Marías | H40: 23489 | I40: 24677.6 | L40: 2026-06-10 | M40: 400 | N40: 11320 | Q40: Lerma - Tres Marías | R40: 872 | S40: 24677.6
B41: 2026-06-10 | C41: 9056 | D41: 11320 | G41: México-Toluca | H41: 42450 | I41: 36365.5 | L41: 2026-06-11 | M41: 1089 | N41: 30818.7 | Q41: México-Toluca | R41: 1285 | S41: 36365.5
B42: 2026-06-11 | C42: 14999 | D42: 30818.7 | G42: Planta Asfalto Pegaso | H42: 0 | I42: 18310.1 | L42: 2026-06-12 | M42: 932 | N42: 26375.6 | Q42: Planta Asfalto Pegaso | R42: 647 | S42: 18310.1
B43: 2026-06-12 | C43: 32828 | D43: 26375.6

Sheet Captura_Pegaso
A1: GC-COMB-001 | BITÁCORA DE INVENTARIO PEGASO
A2: Responsable: | C2: Semana: | F2: Fecha entrega: | H2: Tanque: | I2: Pegaso | J2: Costo por litro base:
A4: Fecha | B4: Tipo Movimiento | C4: Origen/Destino | D4: Obra | E4: Equipo | F4: Economico | G4: Entrada (L) | H4: Salida (L) | I4: Existencia Teórica | J4: Costo/L | K4: Importe | L4: Observaciones
A5: 46181 | B5: Salida | C5: Otro | D5: Bacheo Toluca | E5: Bidones | F5: =VLOOKUP(TablaPegaso[[#This Row],[Equipo]],Catalogos!$I$4:$J$34,2,FALSE) | H5: 100 | I5: =IF(ROW()=5,G5-H5,I4+G5-H5) | J5: 28.3 | K5: =IFERROR((G5+H5)*J5,0)
A6: 46181 | B6: Salida | C6: Planta Asfalto Pegaso | D6: Planta Asfalto Pegaso | E6: Bidones | F6: =VLOOKUP(TablaPegaso[[#This Row],[Equipo]],Catalogos!$I$4:$J$34,2,FALSE) | H6: 200 | I6: =IF(ROW()=5,G6-H6,I5+G6-H6) | J6: 28.3 | K6: =IFERROR((G6+H6)*J6,0)
A7: 46181 | B7: Salida | C7: Planta Asfaltos | D7: Planta Asfalto Pegaso | E7: Bidones | F7: =VLOOKUP(TablaPegaso[[#This Row],[Equipo]],Catalogos!$I$4:$J$34,2,FALSE) | H7: 209 | I7: =IF(ROW()=5,G7-H7,I6+G7-H7) | J7: 28.3 | K7: =IFERROR((G7+H7)*J7,0)
A8: 46181 | B8: Entrada | F8: =VLOOKUP(TablaPegaso[[#This Row],[Equipo]],Catalogos!$I$4:$J$34,2,FALSE) | G8: 2800 | I8: =IF(ROW()=5,G8-H8,I7+G8-H8) | J8: 28.3 | K8: =IFERROR((G8+H8)*J8,0)
A9: 46181 | B9: Salida | C9: Carga directa | D9: Bacheo Toluca | E9: Bidones | F9: =VLOOKUP(TablaPegaso[[#This Row],[Equipo]],Catalogos!$I$4:$J$34,2,FALSE) | H9: 80 | I9: =IF(ROW()=5,G9-H9,I8+G9-H9) | J9: 28.3 | K9: =IFERROR((G9+H9)*J9,0)
A10: 46182 | B10: Salida | C10: Carga directa | D10: Lerma - Tres Marías | E10: Retroexcavadora | F10: =VLOOKUP(TablaPegaso[[#This Row],[Equipo]],Catalogos!$I$4:$J$34,2,FALSE) | H10: 70 | I10: =IF(ROW()=5,G10-H10,I9+G10-H10) | J10: 28.3 | K10: =IFERROR((G10+H10)*J10,0)
A11: 46182 | B11: Salida | C11: Carga directa | D11: Lerma - Tres Marías | E11: Doble Rodillo | F11: =VLOOKUP(TablaPegaso[[#This Row],[Equipo]],Catalogos!$I$4:$J$34,2,FALSE) | H11: 50 | I11: =IF(ROW()=5,G11-H11,I10+G11-H11) | J11: 28.3 | K11: =IFERROR((G11+H11)*J11,0)
A12: 46182 | B12: Salida | C12: Carga directa | D12: Lerma - Tres Marías | E12: Petrolizadora | F12: =VLOOKUP(TablaPegaso[[#This Row],[Equipo]],Catalogos!$I$4:$J$34,2,FALSE) | H12: 60 | I12: =IF(ROW()=5,G12-H12,I11+G12-H12) | J12: 28.3 | K12: =IFERROR((G12+H12)*J12,0)
A13: 46183 | B13: Salida | C13: Otro | D13: Bacheo Toluca | E13: Bidones | F13: =VLOOKUP(TablaPegaso[[#This Row],[Equipo]],Catalogos!$I$4:$J$34,2,FALSE) | H13: 100 | I13: =IF(ROW()=5,G13-H13,I12+G13-H13) | J13: 28.3 | K13: =IFERROR((G13+H13)*J13,0)
A14: 46184 | B14: Salida | C14: Planta Asfalto Pegaso | D14: Planta Asfalto Pegaso | E14: PayLoder | F14: =VLOOKUP(TablaPegaso[[#This Row],[Equipo]],Catalogos!$I$4:$J$34,2,FALSE) | H14: 238 | I14: =IF(ROW()=5,G14-H14,I13+G14-H14) | J14: 28.3 | K14: =IFERROR((G14+H14)*J14,0)
A15: 46184 | B15: Salida | C15: Carga directa | D15: Lerma - Tres Marías | E15: Petrolizadora | F15: =VLOOKUP(TablaPegaso[[#This Row],[Equipo]],Catalogos!$I$4:$J$34,2,FALSE) | H15: 80 | I15: =IF(ROW()=5,G15-H15,I14+G15-H15) | J15: 28.3 | K15: =IFERROR((G15+H15)*J15,0)
A16: 46184 | B16: Salida | C16: Carga directa | D16: Lerma - Tres Marías | E16: Compresor | F16: =VLOOKUP(TablaPegaso[[#This Row],[Equipo]],Catalogos!$I$4:$J$34,2,FALSE) | H16: 50 | I16: =IF(ROW()=5,G16-H16,I15+G16-H16) | J16: 28.3 | K16: =IFERROR((G16+H16)*J16,0)
A17: 46184 | B17: Salida | C17: Carga directa | D17: Lerma - Tres Marías | E17: Retroexcavadora | F17: =VLOOKUP(TablaPegaso[[#This Row],[Equipo]],Catalogos!$I$4:$J$34,2,FALSE) | H17: 70 | I17: =IF(ROW()=5,G17-H17,I16+G17-H17) | J17: 28.3 | K17: =IFERROR((G17+H17)*J17,0)
A18: 46184 | B18: Salida | C18: Carga directa | D18: Lerma - Tres Marías | E18: Camion de Impacto | F18: =VLOOKUP(TablaPegaso[[#This Row],[Equipo]],Catalogos!$I$4:$J$34,2,FALSE) | H18: 80 | I18: =IF(ROW()=5,G18-H18,I17+G18-H18) | J18: 28.3 | K18: =IFERROR((G18+H18)*J18,0)
A19: 46184 | B19: Salida | C19: Carga directa | D19: Lerma - Tres Marías | E19: Vogel | F19: =VLOOKUP(TablaPegaso[[#This Row],[Equipo]],Catalogos!$I$4:$J$34,2,FALSE) | H19: 185 | I19: =IF(ROW()=5,G19-H19,I18+G19-H19) | J19: 28.3 | K19: =IFERROR((G19+H19)*J19,0)
A20: 46184 | B20: Salida | C20: Carga directa | D20: Lerma - Tres Marías | E20: Doble Rodillo | F20: =VLOOKUP(TablaPegaso[[#This Row],[Equipo]],Catalogos!$I$4:$J$34,2,FALSE) | H20: 50 | I20: =IF(ROW()=5,G20-H20,I19+G20-H20) | J20: 28.3 | K20: =IFERROR((G20+H20)*J20,0)
... A23: 46185 | B23: Salida | C23: Carga directa | D23: Bacheo Toluca | E23: Barredora Broce | F23: =VLOOKUP(TablaPegaso[[#This Row],[Equipo]],Catalogos!$I$4:$J$34,2,FALSE) | H23: 70 | I23: =IF(ROW()=5,G23-H23,I22+G23-H23) | J23: 28.3 | K23: =IFERROR((G23+H23)*J23,0)
F24: =VLOOKUP(TablaPegaso[[#This Row],[Equipo]],Catalogos!$I$4:$J$34,2,FALSE) | I24: =IF(ROW()=5,G24-H24,I23+G24-H24) | K24: =IFERROR((G24+H24)*J24,0)
F25: =VLOOKUP(TablaPegaso[[#This Row],[Equipo]],Catalogos!$I$4:$J$34,2,FALSE) | I25: =IF(ROW()=5,G25-H25,I24+G25-H25) | K25: =IFERROR((G25+H25)*J25,0)
F26: =VLOOKUP(TablaPegaso[[#This Row],[Equipo]],Catalogos!$I$4:$J$34,2,FALSE) | I26: =IF(ROW()=5,G26-H26,I25+G26-H26) | K26: =IFERROR((G26+H26)*J26,0)
F27: =VLOOKUP(TablaPegaso[[#This Row],[Equipo]],Catalogos!$I$4:$J$34,2,FALSE) | I27: =IF(ROW()=5,G27-H27,I26+G27-H27) | K27: =IFERROR((G27+H27)*J27,0)
F28: =VLOOKUP(TablaPegaso[[#This Row],[Equipo]],Catalogos!$I$4:$J$34,2,FALSE) | I28: =IF(ROW()=5,G28-H28,I27+G28-H28) | K28: =IFERROR((G28+H28)*J28,0)
F29: =VLOOKUP(TablaPegaso[[#This Row],[Equipo]],Catalogos!$I$4:$J$34,2,FALSE) | I29: =IF(ROW()=5,G29-H29,I28+G29-H29) | K29: =IFERROR((G29+H29)*J29,0)
F30: =VLOOKUP(TablaPegaso[[#This Row],[Equipo]],Catalogos!$I$4:$J$34,2,FALSE) | I30: =IF(ROW()=5,G30-H30,I29+G30-H30) | K30: =IFERROR((G30+H30)*J30,0)
F31: =VLOOKUP(TablaPegaso[[#This Row],[Equipo]],Catalogos!$I$4:$J$34,2,FALSE) | I31: =IF(ROW()=5,G31-H31,I30+G31-H31) | K31: =IFERROR((G31+H31)*J31,0)
F32: =VLOOKUP(TablaPegaso[[#This Row],[Equipo]],Catalogos!$I$4:$J$34,2,FALSE) | I32: =IF(ROW()=5,G32-H32,I31+G32-H32) | K32: =IFERROR((G32+H32)*J32,0)
F33: =VLOOKUP(TablaPegaso[[#This Row],[Equipo]],Catalogos!$I$4:$J$34,2,FALSE) | I33: =IF(ROW()=5,G33-H33,I32+G33-H33) | K33: =IFERROR((G33+H33)*J33,0)
F34: =VLOOKUP(TablaPegaso[[#This Row],[Equipo]],Catalogos!$I$4:$J$34,2,FALSE) | I34: =IF(ROW()=5,G34-H34,I33+G34-H34) | K34: =IFERROR((G34+H34)*J34,0)
F35: =VLOOKUP(TablaPegaso[[#This Row],[Equipo]],Catalogos!$I$4:$J$34,2,FALSE) | I35: =IF(ROW()=5,G35-H35,I34+G35-H35) | K35: =IFERROR((G35+H35)*J35,0)
... F206: =VLOOKUP(TablaPegaso[[#This Row],[Equipo]],Catalogos!$I$4:$J$34,2,FALSE) | I206: =IF(ROW()=5,G206-H206,I205+G206-H206) | K206: =IFERROR((G206+H206)*J206,0)

Sheet Captura_Marimba_M01
A1: GC-COMB-002 | BITÁCORA DE SUMINISTRO DE MARIMBA M-01
A2: Operador: | C2: Semana: | E2: Fecha entrega: | G2: Marimba: | H2: M-01 | I2: Costo/L base:
A4: Fecha | B4: Movimiento | C4: Origen/Obra | D4: Equipo | E4: Económico | F4: Entrada (L) | G4: Salida (L) | H4: Existencia Teórica | I4: Costo/L | J4: Importe | K4: Firma/Validación | L4: Observaciones
A5: 46181 | B5: Salida | C5: México-Toluca | D5: Neuomatico | E5: =VLOOKUP(TablaMarimba[[#This Row],[Equipo]],Catalogos!$I$4:$J$35,2,FALSE) | F5: 0 | G5: 30 | H5: =IF(ROW()=5,F5-G5,H4+F5-G5) | I5: 28.3 | J5: =IFERROR((F5+G5)*I5,0)
A6: 46181 | B6: Salida | C6: México-Toluca | D6: Compactador | E6: =VLOOKUP(TablaMarimba[[#This Row],[Equipo]],Catalogos!$I$4:$J$35,2,FALSE) | G6: 32 | H6: =IF(ROW()=5,F6-G6,H5+F6-G6) | I6: 28.3 | J6: =IFERROR((F6+G6)*I6,0)
A7: 46181 | B7: Salida | C7: México-Toluca | D7: Perfiladora | E7: =VLOOKUP(TablaMarimba[[#This Row],[Equipo]],Catalogos!$I$4:$J$35,2,FALSE) | G7: 277 | H7: =IF(ROW()=5,F7-G7,H6+F7-G7) | I7: 28.3 | J7: =IFERROR((F7+G7)*I7,0)
A8: 46181 | B8: Salida | C8: México-Toluca | D8: Retroexcavadora | E8: =VLOOKUP(TablaMarimba[[#This Row],[Equipo]],Catalogos!$I$4:$J$35,2,FALSE) | G8: 30 | H8: =IF(ROW()=5,F8-G8,H7+F8-G8) | I8: 28.3 | J8: =IFERROR((F8+G8)*I8,0)
A9: 46181 | B9: Salida | C9: Lerma - Tres Marías | D9: Vogel | E9: =VLOOKUP(TablaMarimba[[#This Row],[Equipo]],Catalogos!$I$4:$J$35,2,FALSE) | G9: 97 | H9: =IF(ROW()=5,F9-G9,H8+F9-G9) | I9: 28.3 | J9: =IFERROR((F9+G9)*I9,0)
A10: 46181 | B10: Salida | C10: Chamapa-Lechería | D10: Perfiladora Wirgent | E10: =VLOOKUP(TablaMarimba[[#This Row],[Equipo]],Catalogos!$I$4:$J$35,2,FALSE) | G10: 198 | H10: =IF(ROW()=5,F10-G10,H9+F10-G10) | I10: 28.3 | J10: =IFERROR((F10+G10)*I10,0)
A11: 46181 | B11: Salida | C11: Chamapa-Lechería | D11: Maxilihgs | E11: =VLOOKUP(TablaMarimba[[#This Row],[Equipo]],Catalogos!$I$4:$J$35,2,FALSE) | G11: 10 | H11: =IF(ROW()=5,F11-G11,H10+F11-G11) | I11: 28.3 | J11: =IFERROR((F11+G11)*I11,0)
A12: 46181 | B12: Salida | C12: Chamapa-Lechería | D12: Neuomatico Dynapac | E12: =VLOOKUP(TablaMarimba[[#This Row],[Equipo]],Catalogos!$I$4:$J$35,2,FALSE) | G12: 27 | H12: =IF(ROW()=5,F12-G12,H11+F12-G12) | I12: 28.3 | J12: =IFERROR((F12+G12)*I12,0)
A13: 46181 | B13: Salida | C13: Chamapa-Lechería | D13: Compresor | E13: =VLOOKUP(TablaMarimba[[#This Row],[Equipo]],Catalogos!$I$4:$J$35,2,FALSE) | G13: 30 | H13: =IF(ROW()=5,F13-G13,H12+F13-G13) | I13: 28.3 | J13: =IFERROR((F13+G13)*I13,0)
A14: 46181 | B14: Salida | C14: Chamapa-Lechería | D14: Retroexcavadora Jonh Deere | E14: =VLOOKUP(TablaMarimba[[#This Row],[Equipo]],Catalogos!$I$4:$J$35,2,FALSE) | G14: 40 | H14: =IF(ROW()=5,F14-G14,H13+F14-G14) | I14: 28.3 | J14: =IFERROR((F14+G14)*I14,0)
A15: 46181 | B15: Salida | C15: Chamapa-Lechería | D15: Vogele Guion | E15: =VLOOKUP(TablaMarimba[[#This Row],[Equipo]],Catalogos!$I$4:$J$35,2,FALSE) | G15: 120 | H15: =IF(ROW()=5,F15-G15,H14+F15-G15) | I15: 28.3 | J15: =IFERROR((F15+G15)*I15,0)
A16: 46181 | B16: Salida | C16: Chamapa-Lechería | D16: Petrolizadora Elton | E16: =VLOOKUP(TablaMarimba[[#This Row],[Equipo]],Catalogos!$I$4:$J$35,2,FALSE) | G16: 30 | H16: =IF(ROW()=5,F16-G16,H15+F16-G16) | I16: 28.3 | J16: =IFERROR((F16+G16)*I16,0)
A17: 46182 | B17: Salida | C17: Chamapa-Lechería | D17: Barredora Broce | E17: =VLOOKUP(TablaMarimba[[#This Row],[Equipo]],Catalogos!$I$4:$J$35,2,FALSE) | G17: 30 | H17: =IF(ROW()=5,F17-G17,H16+F17-G17) | I17: 28.3 | J17: =IFERROR((F17+G17)*I17,0)
... A42: 46185 | B42: Salida | C42: Chamapa-Lechería | D42: Petrolizadora Elton | E42: =VLOOKUP(TablaMarimba[[#This Row],[Equipo]],Catalogos!$I$4:$J$35,2,FALSE) | G42: 40 | H42: =IF(ROW()=5,F42-G42,H41+F42-G42) | I42: 28.3 | J42: =IFERROR((F42+G42)*I42,0)
A43: 46185 | B43: Salida | C43: Chamapa-Lechería | D43: Perfiladora Wirgent | E43: =VLOOKUP(TablaMarimba[[#This Row],[Equipo]],Catalogos!$I$4:$J$35,2,FALSE) | G43: 200 | H43: =IF(ROW()=5,F43-G43,H42+F43-G43) | I43: 28.3 | J43: =IFERROR((F43+G43)*I43,0) | N43: =SUM(G5:G48)
A44: 46185 | B44: Salida | C44: México-Toluca | D44: Barredora | E44: =VLOOKUP(TablaMarimba[[#This Row],[Equipo]],Catalogos!$I$4:$J$35,2,FALSE) | G44: 20 | H44: =IF(ROW()=5,F44-G44,H43+F44-G44) | I44: 28.3 | J44: =IFERROR((F44+G44)*I44,0)
A45: 46185 | B45: Salida | C45: México-Toluca | D45: Neuomatico | E45: =VLOOKUP(TablaMarimba[[#This Row],[Equipo]],Catalogos!$I$4:$J$35,2,FALSE) | G45: 30 | H45: =IF(ROW()=5,F45-G45,H44+F45-G45) | I45: 28.3 | J45: =IFERROR((F45+G45)*I45,0)
A46: 46185 | B46: Salida | C46: México-Toluca | D46: Maxilihgs | E46: =VLOOKUP(TablaMarimba[[#This Row],[Equipo]],Catalogos!$I$4:$J$35,2,FALSE) | G46: 20 | H46: =IF(ROW()=5,F46-G46,H45+F46-G46) | I46: 28.3 | J46: =IFERROR((F46+G46)*I46,0)
A47: 46185 | B47: Salida | C47: México-Toluca | D47: Compactador | E47: =VLOOKUP(TablaMarimba[[#This Row],[Equipo]],Catalogos!$I$4:$J$35,2,FALSE) | G47: 40 | H47: =IF(ROW()=5,F47-G47,H46+F47-G47) | I47: 28.3 | J47: =IFERROR((F47+G47)*I47,0)
A48: 46185 | B48: Salida | C48: México-Toluca | D48: Perfiladora | E48: =VLOOKUP(TablaMarimba[[#This Row],[Equipo]],Catalogos!$I$4:$J$35,2,FALSE) | G48: 250 | H48: 0 | I48: 28.3 | J48: =IFERROR((F48+G48)*I48,0)
A49: 46188 | B49: Entrada | C49: No aplica | D49: Marimba | E49: =VLOOKUP(TablaMarimba[[#This Row],[Equipo]],Catalogos!$I$4:$J$35,2,FALSE) | F49: 500 | H49: =IF(ROW()=5,F49-G49,H48+F49-G49)
A50: 46188 | B50: Salida | C50: México-Toluca | D50: Perfiladora Wirgent | E50: =VLOOKUP(TablaMarimba[[#This Row],[Equipo]],Catalogos!$I$4:$J$35,2,FALSE) | G50: 200 | H50: =IF(ROW()=5,F50-G50,H49+F50-G50) | I50: 28.3 | J50: =IFERROR((F50+G50)*I50,0)
A51: 46188 | B51: Salida | C51: México-Toluca | D51: Retroexcavadora | E51: =VLOOKUP(TablaMarimba[[#This Row],[Equipo]],Catalogos!$I$4:$J$35,2,FALSE) | G51: 40 | H51: =IF(ROW()=5,F51-G51,H50+F51-G51) | I51: 28.3 | J51: =IFERROR((F51+G51)*I51,0)
A52: 46188 | B52: Salida | C52: México-Toluca | D52: Tandem Hamm | E52: =VLOOKUP(TablaMarimba[[#This Row],[Equipo]],Catalogos!$I$4:$J$35,2,FALSE) | G52: 30 | H52: =IF(ROW()=5,F52-G52,H51+F52-G52) | I52: 28.3 | J52: =IFERROR((F52+G52)*I52,0)
A53: 46188 | B53: Salida | C53: México-Toluca | D53: Neuomatico | E53: =VLOOKUP(TablaMarimba[[#This Row],[Equipo]],Catalogos!$I$4:$J$35,2,FALSE) | G53: 50 | H53: =IF(ROW()=5,F53-G53,H52+F53-G53) | I53: 28.3 | J53: =IFERROR((F53+G53)*I53,0)
A54: 46188 | B54: Salida | C54: Lerma - Tres Marías | D54: Vogel | E54: =VLOOKUP(TablaMarimba[[#This Row],[Equipo]],Catalogos!$I$4:$J$35,2,FALSE) | G54: 99 | H54: =IF(ROW()=5,F54-G54,H53+F54-G54) | I54: 28.3 | J54: =IFERROR((F54+G54)*I54,0)
A55: 46188 | B55: Salida | C55: México-Toluca | D55: Petrolizadora | E55: =VLOOKUP(TablaMarimba[[#This Row],[Equipo]],Catalogos!$I$4:$J$35,2,FALSE) | G55: 50 | H55: =IF(ROW()=5,F55-G55,H54+F55-G55) | I55: 28.3 | J55: =IFERROR((F55+G55)*I55,0)
A56: 46189 | B56: Entrada | C56: No aplica | D56: Fresadora | E56: =VLOOKUP(TablaMarimba[[#This Row],[Equipo]],Catalogos!$I$4:$J$35,2,FALSE) | F56: =TablaMarimba[[#This Row],[Existencia Teórica]]-H55 | H56: 500
A57: 46189 | B57: Salida | C57: México-Toluca | D57: Perfiladora Wirgent | E57: =VLOOKUP(TablaMarimba[[#This Row],[Equipo]],Catalogos!$I$4:$J$35,2,FALSE) | G57: 200 | H57: =IF(ROW()=5,F57-G57,H56+F57-G57) | I57: 28.3 | J57: =IFERROR((F57+G57)*I57,0)
A58: 46189 | B58: Salida | C58: México-Toluca | D58: Tandem Hamm | E58: =VLOOKUP(TablaMarimba[[#This Row],[Equipo]],Catalogos!$I$4:$J$35,2,FALSE) | G58: 32 | H58: =IF(ROW()=5,F58-G58,H57+F58-G58) | I58: 28.3 | J58: =IFERROR((F58+G58)*I58,0)
A59: 46189 | B59: Salida | C59: México-Toluca | D59: Neuomatico | E59: =VLOOKUP(TablaMarimba[[#This Row],[Equipo]],Catalogos!$I$4:$J$35,2,FALSE) | G59: 30 | H59: =IF(ROW()=5,F59-G59,H58+F59-G59) | I59: 28.3 | J59: =IFERROR((F59+G59)*I59,0)
A60: 46189 | B60: Salida | C60: México-Toluca | D60: Barredora | E60: =VLOOKUP(TablaMarimba[[#This Row],[Equipo]],Catalogos!$I$4:$J$35,2,FALSE) | G60: 30 | H60: =IF(ROW()=5,F60-G60,H59+F60-G60) | I60: 28.3 | J60: =IFERROR((F60+G60)*I60,0)
A61: 46189 | B61: Salida | C61: México-Toluca | D61: Vogel | E61: =VLOOKUP(TablaMarimba[[#This Row],[Equipo]],Catalogos!$I$4:$J$35,2,FALSE) | G61: 107 | H61: =IF(ROW()=5,F61-G61,H60+F61-G61) | I61: 28.3 | J61: =IFERROR((F61+G61)*I61,0)
A62: 46189 | B62: Salida | C62: México-Toluca | D62: Retroexcavadora | E62: =VLOOKUP(TablaMarimba[[#This Row],[Equipo]],Catalogos!$I$4:$J$35,2,FALSE) | G62: 40 | H62: =IF(ROW()=5,F62-G62,H61+F62-G62) | I62: 28.3 | J62: =IFERROR((F62+G62)*I62,0)
A63: 46189 | B63: Salida | C63: México-Toluca | D63: Petrolizadora | E63: =VLOOKUP(TablaMarimba[[#This Row],[Equipo]],Catalogos!$I$4:$J$35,2,FALSE) | G63: 50 | H63: =IF(ROW()=5,F63-G63,H62+F63-G63) | I63: 28.3 | J63: =IFERROR((F63+G63)*I63,0)
A64: 46190 | B64: Entrada | C64: No aplica | D64: Marimba | E64: =VLOOKUP(TablaMarimba[[#This Row],[Equipo]],Catalogos!$I$4:$J$35,2,FALSE) | F64: =TablaMarimba[[#This Row],[Existencia Teórica]]-H63 | H64: 520
A65: 46190 | B65: Salida | C65: México-Toluca | D65: Perfiladora Wirgent | E65: =VLOOKUP(TablaMarimba[[#This Row],[Equipo]],Catalogos!$I$4:$J$35,2,FALSE) | G65: 200 | H65: =IF(ROW()=5,F65-G65,H64+F65-G65) | I65: 28.3 | J65: =IFERROR((F65+G65)*I65,0)
A66: 46190 | B66: Salida | C66: México-Toluca | D66: Vogele Guion | E66: =VLOOKUP(TablaMarimba[[#This Row],[Equipo]],Catalogos!$I$4:$J$35,2,FALSE) | G66: 120 | H66: =IF(ROW()=5,F66-G66,H65+F66-G66) | I66: 28.3 | J66: =IFERROR((F66+G66)*I66,0)
A67: 46190 | B67: Salida | C67: México-Toluca | D67: Tandem Hamm | E67: =VLOOKUP(TablaMarimba[[#This Row],[Equipo]],Catalogos!$I$4:$J$35,2,FALSE) | G67: 32 | H67: =IF(ROW()=5,F67-G67,H66+F67-G67) | I67: 28.3 | J67: =IFERROR((F67+G67)*I67,0)
A68: 46190 | B68: Salida | C68: México-Toluca | D68: Neuomatico | E68: =VLOOKUP(TablaMarimba[[#This Row],[Equipo]],Catalogos!$I$4:$J$35,2,FALSE) | G68: 30 | H68: =IF(ROW()=5,F68-G68,H67+F68-G68) | I68: 28.3 | J68: =IFERROR((F68+G68)*I68,0)
A69: 46190 | B69: Salida | C69: México-Toluca | D69: Barredora | E69: =VLOOKUP(TablaMarimba[[#This Row],[Equipo]],Catalogos!$I$4:$J$35,2,FALSE) | G69: 28 | H69: =IF(ROW()=5,F69-G69,H68+F69-G69) | I69: 28.3 | J69: =IFERROR((F69+G69)*I69,0)
A70: 46190 | B70: Salida | C70: México-Toluca | D70: Retroexcavadora | E70: =VLOOKUP(TablaMarimba[[#This Row],[Equipo]],Catalogos!$I$4:$J$35,2,FALSE) | G70: 60 | H70: =IF(ROW()=5,F70-G70,H69+F70-G70) | I70: 28.3 | J70: =IFERROR((F70+G70)*I70,0)
A71: 46190 | B71: Salida | C71: México-Toluca | D71: Petrolizadora | E71: =VLOOKUP(TablaMarimba[[#This Row],[Equipo]],Catalogos!$I$4:$J$35,2,FALSE) | G71: 50 | H71: =IF(ROW()=5,F71-G71,H70+F71-G71) | I71: 28.3 | J71: =IFERROR((F72+G72)*I71,0)
A72: 46191 | B72: Salida | C72: México-Toluca | D72: Perfiladora Wirgent | E72: =VLOOKUP(TablaMarimba[[#This Row],[Equipo]],Catalogos!$I$4:$J$35,2,FALSE) | G72: 200 | H72: =IF(ROW()=5,F72-G72,H71+F72-G72) | I72: 28.3 | J72: =IFERROR((F73+G73)*I72,0)
A73: 46191 | B73: Salida | C73: México-Toluca | D73: Vogel | E73: =VLOOKUP(TablaMarimba[[#This Row],[Equipo]],Catalogos!$I$4:$J$35,2,FALSE) | G73: 115 | H73: =IF(ROW()=5,F73-G73,H72+F73-G73) | I73: 28.3 | J73: =IFERROR((F74+G74)*I73,0)
A74: 46191 | B74: Salida | C74: México-Toluca | D74: Neuomatico | E74: =VLOOKUP(TablaMarimba[[#This Row],[Equipo]],Catalogos!$I$4:$J$35,2,FALSE) | G74: 30 | H74: =IF(ROW()=5,F74-G74,H73+F74-G74) | I74: 28.3 | J74: =IFERROR((F75+G75)*I74,0)
A75: 46191 | B75: Salida | C75: México-Toluca | D75: Tandem Hamm | E75: =VLOOKUP(TablaMarimba[[#This Row],[Equipo]],Catalogos!$I$4:$J$35,2,FALSE) | G75: 30 | H75: =IF(ROW()=5,F75-G75,H74+F75-G75) | I75: 28.3 | J75: =IFERROR((#REF!+#REF!)*I75,0)
E76: =VLOOKUP(TablaMarimba[[#This Row],[Equipo]],Catalogos!$I$4:$J$35,2,FALSE) | H76: =IF(ROW()=5,F76-G76,H75+F76-G76) | I76: 28.3 | J76: =IFERROR((F76+G76)*I76,0)
E77: =VLOOKUP(TablaMarimba[[#This Row],[Equipo]],Catalogos!$I$4:$J$35,2,FALSE) | H77: =IF(ROW()=5,F77-G77,H76+F77-G77) | I77: 28.3 | J77: =IFERROR((F77+G77)*I77,0)
E78: =VLOOKUP(TablaMarimba[[#This Row],[Equipo]],Catalogos!$I$4:$J$35,2,FALSE) | H78: =IF(ROW()=5,F78-G78,H77+F78-G78) | I78: 28.3 | J78: =IFERROR((F78+G78)*I78,0)
E79: =VLOOKUP(TablaMarimba[[#This Row],[Equipo]],Catalogos!$I$4:$J$35,2,FALSE) | H79: =IF(ROW()=5,F79-G79,H78+F79-G79) | I79: 28.3 | J79: =IFERROR((F79+G79)*I79,0)
E80: =VLOOKUP(TablaMarimba[[#This Row],[Equipo]],Catalogos!$I$4:$J$35,2,FALSE) | H80: =IF(ROW()=5,F80-G80,H79+F80-G80) | I80: 28.3 | J80: =IFERROR((F80+G80)*I80,0)
E81: =VLOOKUP(TablaMarimba[[#This Row],[Equipo]],Catalogos!$I$4:$J$35,2,FALSE) | H81: =IF(ROW()=5,F81-G81,H80+F81-G81) | I81: 28.3 | J81: =IFERROR((F81+G81)*I81,0)
E82: =VLOOKUP(TablaMarimba[[#This Row],[Equipo]],Catalogos!$I$4:$J$35,2,FALSE) | H82: =IF(ROW()=5,F82-G82,H81+F82-G82) | I82: 28.3 | J82: =IFERROR((F82+G82)*I82,0)
E83: =VLOOKUP(TablaMarimba[[#This Row],[Equipo]],Catalogos!$I$4:$J$35,2,FALSE) | H83: =IF(ROW()=5,F83-G83,H82+F83-G83) | I83: 28.3 | J83: =IFERROR((F83+G83)*I83,0)
E84: =VLOOKUP(TablaMarimba[[#This Row],[Equipo]],Catalogos!$I$4:$J$35,2,FALSE) | H84: =IF(ROW()=5,F84-G84,H83+F84-G84) | I84: 28.3 | J84: =IFERROR((F84+G84)*I84,0)
E85: =VLOOKUP(TablaMarimba[[#This Row],[Equipo]],Catalogos!$I$4:$J$35,2,FALSE) | H85: =IF(ROW()=5,F85-G85,H84+F85-G85) | I85: 28.3 | J85: =IFERROR((F85+G85)*I85,0)
E86: =VLOOKUP(TablaMarimba[[#This Row],[Equipo]],Catalogos!$I$4:$J$35,2,FALSE) | H86: =IF(ROW()=5,F86-G86,H85+F86-G86) | I86: 28.3 | J86: =IFERROR((F86+G86)*I86,0)
E87: =VLOOKUP(TablaMarimba[[#This Row],[Equipo]],Catalogos!$I$4:$J$35,2,FALSE) | H87: =IF(ROW()=5,F87-G87,H86+F87-G87) | I87: 28.3 | J87: =IFERROR((F87+G87)*I87,0)
... E206: =VLOOKUP(TablaMarimba[[#This Row],[Equipo]],Catalogos!$I$4:$J$35,2,FALSE) | H206: =IF(ROW()=5,F206-G206,H205+F206-G206) | I206: 28.3 | J206: =IFERROR((F206+G206)*I206,0)

Sheet Captura_Jalisco
A1: GC-COMB-002 | BITÁCORA DE SUMINISTRO DE JALISCO
A2: Operador: | C2: Semana: | E2: Fecha entrega: | G2: Marimba: | H2: M-01 | I2: Costo/L base:
A4: Fecha | B4: Movimiento | C4: Origen/Obra | D4: Equipo | E4: Económico | F4: Entrada (L) | G4: Salida (L) | H4: Existencia Teórica | I4: Costo/L | J4: Importe | K4: Firma/Validación | L4: Observaciones
A5: 46168 | B5: Salida | C5: Jalisco | D5: Motoconformadora Rentada | E5: =VLOOKUP(TablaMarimba6[[#This Row],[Equipo]],Catalogos!$I$4:$J$54,2,FALSE) | G5: 89 | H5: 0 | I5: 27 | J5: =(TablaMarimba6[[#This Row],[Salida (L)]]*TablaMarimba6[[#This Row],[Costo/L]])
A6: 46169 | B6: Salida | C6: Jalisco | D6: Motoconformadora Rentada | E6: =VLOOKUP(TablaMarimba6[[#This Row],[Equipo]],Catalogos!$I$4:$J$54,2,FALSE) | G6: 89 | H6: =IF(ROW()=5,F5-G5,H5+F5-G5) | I6: 27 | J6: =(TablaMarimba6[[#This Row],[Salida (L)]]*TablaMarimba6[[#This Row],[Costo/L]])
A7: 46171 | B7: Salida | C7: Jalisco | D7: Motoconformadora Rentada | E7: =VLOOKUP(TablaMarimba6[[#This Row],[Equipo]],Catalogos!$I$4:$J$54,2,FALSE) | G7: 99 | H7: =IF(ROW()=5,F6-G6,H6+F6-G6) | I7: 27 | J7: =(TablaMarimba6[[#This Row],[Salida (L)]]*TablaMarimba6[[#This Row],[Costo/L]])
A8: 46171 | B8: Salida | C8: Jalisco | D8: Motoconformadora | E8: =VLOOKUP(TablaMarimba6[[#This Row],[Equipo]],Catalogos!$I$4:$J$54,2,FALSE) | G8: 99 | H8: =IF(ROW()=5,F7-G7,H7+F7-G7) | I8: 27 | J8: =(TablaMarimba6[[#This Row],[Salida (L)]]*TablaMarimba6[[#This Row],[Costo/L]])
A9: 46172 | B9: Salida | C9: Jalisco | D9: Motoconformadora Rentada | E9: =VLOOKUP(TablaMarimba6[[#This Row],[Equipo]],Catalogos!$I$4:$J$54,2,FALSE) | G9: 90 | H9: =IF(ROW()=5,F8-G8,H8+F8-G8) | I9: 27 | J9: =(TablaMarimba6[[#This Row],[Salida (L)]]*TablaMarimba6[[#This Row],[Costo/L]])
A10: 46172 | B10: Salida | C10: Jalisco | D10: Motoconformadora | E10: =VLOOKUP(TablaMarimba6[[#This Row],[Equipo]],Catalogos!$I$4:$J$54,2,FALSE) | G10: 90 | H10: =IF(ROW()=5,F9-G9,H9+F9-G9) | I10: 27 | J10: =(TablaMarimba6[[#This Row],[Salida (L)]]*TablaMarimba6[[#This Row],[Costo/L]])
A11: 46174 | B11: Salida | C11: Jalisco | D11: Retroexcavadora | E11: =VLOOKUP(TablaMarimba6[[#This Row],[Equipo]],Catalogos!$I$4:$J$54,2,FALSE) | G11: 50 | H11: =IF(ROW()=5,F10-G10,H10+F10-G10) | I11: 27 | J11: =(TablaMarimba6[[#This Row],[Salida (L)]]*TablaMarimba6[[#This Row],[Costo/L]])
A12: 46175 | B12: Salida | C12: Jalisco | D12: Motoconformadora Rentada | E12: =VLOOKUP(TablaMarimba6[[#This Row],[Equipo]],Catalogos!$I$4:$J$54,2,FALSE) | G12: 74 | H12: =IF(ROW()=5,F11-G11,H11+F11-G11) | I12: 27 | J12: =(TablaMarimba6[[#This Row],[Salida (L)]]*TablaMarimba6[[#This Row],[Costo/L]])
A13: 46175 | B13: Salida | C13: Jalisco | D13: Motoconformadora | E13: =VLOOKUP(TablaMarimba6[[#This Row],[Equipo]],Catalogos!$I$4:$J$54,2,FALSE) | G13: 80 | H13: =IF(ROW()=5,F12-G12,H12+F12-G12) | I13: 27 | J13: =(TablaMarimba6[[#This Row],[Salida (L)]]*TablaMarimba6[[#This Row],[Costo/L]])
A14: 46175 | B14: Salida | C14: Jalisco | D14: Vibro Compactador | E14: =VLOOKUP(TablaMarimba6[[#This Row],[Equipo]],Catalogos!$I$4:$J$54,2,FALSE) | G14: 40 | H14: =IF(ROW()=5,F13-G13,H13+F13-G13) | I14: 27 | J14: =(TablaMarimba6[[#This Row],[Salida (L)]]*TablaMarimba6[[#This Row],[Costo/L]])
A15: 46177 | B15: Salida | C15: Jalisco | D15: Motoconformadora Rentada | E15: =VLOOKUP(TablaMarimba6[[#This Row],[Equipo]],Catalogos!$I$4:$J$54,2,FALSE) | G15: 70 | H15: =IF(ROW()=5,F14-G14,H14+F14-G14) | I15: 27 | J15: =(TablaMarimba6[[#This Row],[Salida (L)]]*TablaMarimba6[[#This Row],[Costo/L]])
A16: 46177 | B16: Salida | C16: Jalisco | D16: Pipa | E16: =VLOOKUP(TablaMarimba6[[#This Row],[Equipo]],Catalogos!$I$4:$J$54,2,FALSE) | G16: 100 | H16: =IF(ROW()=5,F15-G15,H15+F15-G15) | I16: 27 | J16: =(TablaMarimba6[[#This Row],[Salida (L)]]*TablaMarimba6[[#This Row],[Costo/L]])
A17: 46178 | B17: Salida | C17: Jalisco | D17: Motoconformadora Rentada | E17: =VLOOKUP(TablaMarimba6[[#This Row],[Equipo]],Catalogos!$I$4:$J$54,2,FALSE) | G17: 60 | H17: =IF(ROW()=5,F16-G16,H16+F16-G16) | I17: 27 | J17: =(TablaMarimba6[[#This Row],[Salida (L)]]*TablaMarimba6[[#This Row],[Costo/L]])
... A33: 46191 | B33: Salida | C33: Jalisco | D33: Excavadora | E33: =VLOOKUP(TablaMarimba6[[#This Row],[Equipo]],Catalogos!$I$4:$J$54,2,FALSE) | G33: 100 | H33: =IF(ROW()=5,F32-G32,H32+F32-G32) | I33: 27 | J33: =(TablaMarimba6[[#This Row],[Salida (L)]]*TablaMarimba6[[#This Row],[Costo/L]])
H34: =IF(ROW()=5,F33-G33,H33+F33-G33) | I34: 27 | J34: =(TablaMarimba6[[#This Row],[Salida (L)]]*TablaMarimba6[[#This Row],[Costo/L]])
E35: =VLOOKUP(TablaMarimba6[[#This Row],[Equipo]],Catalogos!$I$4:$J$54,2,FALSE) | H35: =IF(ROW()=5,F35-G35,H34+F35-G35) | I35: 27 | J35: =(TablaMarimba6[[#This Row],[Salida (L)]]*TablaMarimba6[[#This Row],[Costo/L]])
E36: =VLOOKUP(TablaMarimba6[[#This Row],[Equipo]],Catalogos!$I$4:$J$54,2,FALSE) | H36: =IF(ROW()=5,F36-G36,H35+F36-G36) | I36: 27 | J36: =(TablaMarimba6[[#This Row],[Salida (L)]]*TablaMarimba6[[#This Row],[Costo/L]])
E37: =VLOOKUP(TablaMarimba6[[#This Row],[Equipo]],Catalogos!$I$4:$J$54,2,FALSE) | H37: =IF(ROW()=5,F37-G37,H36+F37-G37) | I37: 27 | J37: =(TablaMarimba6[[#This Row],[Salida (L)]]*TablaMarimba6[[#This Row],[Costo/L]])
E38: =VLOOKUP(TablaMarimba6[[#This Row],[Equipo]],Catalogos!$I$4:$J$54,2,FALSE) | H38: =IF(ROW()=5,F38-G38,H37+F38-G38) | I38: 27 | J38: =(TablaMarimba6[[#This Row],[Salida (L)]]*TablaMarimba6[[#This Row],[Costo/L]])
E39: =VLOOKUP(TablaMarimba6[[#This Row],[Equipo]],Catalogos!$I$4:$J$54,2,FALSE) | H39: =IF(ROW()=5,F39-G39,H38+F39-G39) | I39: 27 | J39: =(TablaMarimba6[[#This Row],[Salida (L)]]*TablaMarimba6[[#This Row],[Costo/L]])
E40: =VLOOKUP(TablaMarimba6[[#This Row],[Equipo]],Catalogos!$I$4:$J$54,2,FALSE) | H40: =IF(ROW()=5,F40-G40,H39+F40-G40) | I40: 27 | J40: =(TablaMarimba6[[#This Row],[Salida (L)]]*TablaMarimba6[[#This Row],[Costo/L]])
E41: =VLOOKUP(TablaMarimba6[[#This Row],[Equipo]],Catalogos!$I$4:$J$54,2,FALSE) | H41: =IF(ROW()=5,F41-G41,H40+F41-G41) | I41: 27 | J41: =(TablaMarimba6[[#This Row],[Salida (L)]]*TablaMarimba6[[#This Row],[Costo/L]])
E42: =VLOOKUP(TablaMarimba6[[#This Row],[Equipo]],Catalogos!$I$4:$J$54,2,FALSE) | H42: =IF(ROW()=5,F42-G42,H41+F42-G42) | I42: 27 | J42: =(TablaMarimba6[[#This Row],[Salida (L)]]*TablaMarimba6[[#This Row],[Costo/L]])
E43: =VLOOKUP(TablaMarimba6[[#This Row],[Equipo]],Catalogos!$I$4:$J$54,2,FALSE) | H43: =IF(ROW()=5,F43-G43,H42+F43-G43) | I43: 27 | J43: =(TablaMarimba6[[#This Row],[Salida (L)]]*TablaMarimba6[[#This Row],[Costo/L]]) | N43: =SUM(G5:G48)
E44: =VLOOKUP(TablaMarimba6[[#This Row],[Equipo]],Catalogos!$I$4:$J$54,2,FALSE) | H44: =IF(ROW()=5,F44-G44,H43+F44-G44) | I44: 27 | J44: =(TablaMarimba6[[#This Row],[Salida (L)]]*TablaMarimba6[[#This Row],[Costo/L]])
E45: =VLOOKUP(TablaMarimba6[[#This Row],[Equipo]],Catalogos!$I$4:$J$54,2,FALSE) | H45: =IF(ROW()=5,F45-G45,H44+F45-G45) | I45: 27 | J45: =(TablaMarimba6[[#This Row],[Salida (L)]]*TablaMarimba6[[#This Row],[Costo/L]])
E46: =VLOOKUP(TablaMarimba6[[#This Row],[Equipo]],Catalogos!$I$4:$J$54,2,FALSE) | H46: =IF(ROW()=5,F46-G46,H45+F46-G46) | I46: 27 | J46: =(TablaMarimba6[[#This Row],[Salida (L)]]*TablaMarimba6[[#This Row],[Costo/L]])
E47: =VLOOKUP(TablaMarimba6[[#This Row],[Equipo]],Catalogos!$I$4:$J$54,2,FALSE) | H47: =IF(ROW()=5,F47-G47,H46+F47-G47) | I47: 27 | J47: =(TablaMarimba6[[#This Row],[Salida (L)]]*TablaMarimba6[[#This Row],[Costo/L]])
E48: =VLOOKUP(TablaMarimba6[[#This Row],[Equipo]],Catalogos!$I$4:$J$54,2,FALSE) | H48: 0 | I48: 27 | J48: =(TablaMarimba6[[#This Row],[Salida (L)]]*TablaMarimba6[[#This Row],[Costo/L]])
E49: =VLOOKUP(TablaMarimba6[[#This Row],[Equipo]],Catalogos!$I$4:$J$54,2,FALSE) | H49: =IF(ROW()=5,F49-G49,H48+F49-G49)
E50: =VLOOKUP(TablaMarimba6[[#This Row],[Equipo]],Catalogos!$I$4:$J$54,2,FALSE) | H50: =IF(ROW()=5,F50-G50,H49+F50-G50) | I50: 28.3 | J50: =IFERROR((F50+G50)*I50,0)
E51: =VLOOKUP(TablaMarimba6[[#This Row],[Equipo]],Catalogos!$I$4:$J$54,2,FALSE) | H51: =IF(ROW()=5,F51-G51,H50+F51-G51) | I51: 28.3 | J51: =IFERROR((F51+G51)*I51,0)
E52: =VLOOKUP(TablaMarimba6[[#This Row],[Equipo]],Catalogos!$I$4:$J$54,2,FALSE) | H52: =IF(ROW()=5,F52-G52,H51+F52-G52) | I52: 28.3 | J52: =IFERROR((F52+G52)*I52,0)
E53: =VLOOKUP(TablaMarimba6[[#This Row],[Equipo]],Catalogos!$I$4:$J$54,2,FALSE) | H53: =IF(ROW()=5,F53-G53,H52+F53-G53) | I53: 28.3 | J53: =IFERROR((F53+G53)*I53,0)
E54: =VLOOKUP(TablaMarimba6[[#This Row],[Equipo]],Catalogos!$I$4:$J$54,2,FALSE) | H54: =IF(ROW()=5,F54-G54,H53+F54-G54) | I54: 28.3 | J54: =IFERROR((F54+G54)*I54,0)
E55: =VLOOKUP(TablaMarimba6[[#This Row],[Equipo]],Catalogos!$I$4:$J$54,2,FALSE) | H55: =IF(ROW()=5,F55-G55,H54+F55-G55) | I55: 28.3 | J55: =IFERROR((F55+G55)*I55,0)
E56: =VLOOKUP(TablaMarimba6[[#This Row],[Equipo]],Catalogos!$I$4:$J$54,2,FALSE) | H56: 500
E57: =VLOOKUP(TablaMarimba6[[#This Row],[Equipo]],Catalogos!$I$4:$J$54,2,FALSE) | H57: =IF(ROW()=5,F57-G57,H56+F57-G57) | I57: 28.3 | J57: =IFERROR((F57+G57)*I57,0)
E58: =VLOOKUP(TablaMarimba6[[#This Row],[Equipo]],Catalogos!$I$4:$J$54,2,FALSE) | H58: =IF(ROW()=5,F58-G58,H57+F58-G58) | I58: 28.3 | J58: =IFERROR((F58+G58)*I58,0)
E59: =VLOOKUP(TablaMarimba6[[#This Row],[Equipo]],Catalogos!$I$4:$J$54,2,FALSE) | H59: =IF(ROW()=5,F59-G59,H58+F59-G59) | I59: 28.3 | J59: =IFERROR((F59+G59)*I59,0)
E60: =VLOOKUP(TablaMarimba6[[#This Row],[Equipo]],Catalogos!$I$4:$J$54,2,FALSE) | H60: =IF(ROW()=5,F60-G60,H59+F60-G60) | I60: 28.3 | J60: =IFERROR((F60+G60)*I60,0)
E61: =VLOOKUP(TablaMarimba6[[#This Row],[Equipo]],Catalogos!$I$4:$J$54,2,FALSE) | H61: =IF(ROW()=5,F61-G61,H60+F61-G61) | I61: 28.3 | J61: =IFERROR((F61+G61)*I61,0)
E62: =VLOOKUP(TablaMarimba6[[#This Row],[Equipo]],Catalogos!$I$4:$J$54,2,FALSE) | H62: =IF(ROW()=5,F62-G62,H61+F62-G62) | I62: 28.3 | J62: =IFERROR((F62+G62)*I62,0)
E63: =VLOOKUP(TablaMarimba6[[#This Row],[Equipo]],Catalogos!$I$4:$J$54,2,FALSE) | H63: =IF(ROW()=5,F63-G63,H62+F63-G63) | I63: 28.3 | J63: =IFERROR((F63+G63)*I63,0)
E64: =VLOOKUP(TablaMarimba6[[#This Row],[Equipo]],Catalogos!$I$4:$J$54,2,FALSE) | H64: 520
E65: =VLOOKUP(TablaMarimba6[[#This Row],[Equipo]],Catalogos!$I$4:$J$54,2,FALSE) | H65: =IF(ROW()=5,F65-G65,H64+F65-G65) | I65: 28.3 | J65: =IFERROR((F65+G65)*I65,0)
E66: =VLOOKUP(TablaMarimba6[[#This Row],[Equipo]],Catalogos!$I$4:$J$54,2,FALSE) | H66: =IF(ROW()=5,F66-G66,H65+F66-G66) | I66: 28.3 | J66: =IFERROR((F66+G66)*I66,0)
E67: =VLOOKUP(TablaMarimba6[[#This Row],[Equipo]],Catalogos!$I$4:$J$54,2,FALSE) | H67: =IF(ROW()=5,F67-G67,H66+F67-G67) | I67: 28.3 | J67: =IFERROR((F67+G67)*I67,0)
E68: =VLOOKUP(TablaMarimba6[[#This Row],[Equipo]],Catalogos!$I$4:$J$54,2,FALSE) | H68: =IF(ROW()=5,F68-G68,H67+F68-G68) | I68: 28.3 | J68: =IFERROR((F68+G68)*I68,0)
E69: =VLOOKUP(TablaMarimba6[[#This Row],[Equipo]],Catalogos!$I$4:$J$54,2,FALSE) | H69: =IF(ROW()=5,F69-G69,H68+F69-G69) | I69: 28.3 | J69: =IFERROR((F69+G69)*I69,0)
E70: =VLOOKUP(TablaMarimba6[[#This Row],[Equipo]],Catalogos!$I$4:$J$54,2,FALSE) | H70: =IF(ROW()=5,F70-G70,H69+F70-G70) | I70: 28.3 | J70: =IFERROR((F70+G70)*I70,0)
E71: =VLOOKUP(TablaMarimba6[[#This Row],[Equipo]],Catalogos!$I$4:$J$54,2,FALSE) | H71: =IF(ROW()=5,F71-G71,H70+F71-G71) | I71: 28.3 | J71: =IFERROR((F72+G72)*I71,0)
E72: =VLOOKUP(TablaMarimba6[[#This Row],[Equipo]],Catalogos!$I$4:$J$54,2,FALSE) | H72: =IF(ROW()=5,F72-G72,H71+F72-G72) | I72: 28.3 | J72: =IFERROR((F73+G73)*I72,0)
E73: =VLOOKUP(TablaMarimba6[[#This Row],[Equipo]],Catalogos!$I$4:$J$54,2,FALSE) | H73: =IF(ROW()=5,F73-G73,H72+F73-G73) | I73: 28.3 | J73: =IFERROR((F74+G74)*I73,0)
E74: =VLOOKUP(TablaMarimba6[[#This Row],[Equipo]],Catalogos!$I$4:$J$54,2,FALSE) | H74: =IF(ROW()=5,F74-G74,H73+F74-G74) | I74: 28.3 | J74: =IFERROR((F75+G75)*I74,0)
E75: =VLOOKUP(TablaMarimba6[[#This Row],[Equipo]],Catalogos!$I$4:$J$54,2,FALSE) | H75: =IF(ROW()=5,F75-G75,H74+F75-G75) | I75: 28.3 | J75: =IFERROR((#REF!+#REF!)*I75,0)
E76: =VLOOKUP(TablaMarimba6[[#This Row],[Equipo]],Catalogos!$I$4:$J$35,2,FALSE) | H76: =IF(ROW()=5,F76-G76,H75+F76-G76) | I76: 28.3 | J76: =IFERROR((F76+G76)*I76,0)
E77: =VLOOKUP(TablaMarimba6[[#This Row],[Equipo]],Catalogos!$I$4:$J$35,2,FALSE) | H77: =IF(ROW()=5,F77-G77,H76+F77-G77) | I77: 28.3 | J77: =IFERROR((F77+G77)*I77,0)
E78: =VLOOKUP(TablaMarimba6[[#This Row],[Equipo]],Catalogos!$I$4:$J$35,2,FALSE) | H78: =IF(ROW()=5,F78-G78,H77+F78-G78) | I78: 28.3 | J78: =IFERROR((F78+G78)*I78,0)
E79: =VLOOKUP(TablaMarimba6[[#This Row],[Equipo]],Catalogos!$I$4:$J$35,2,FALSE) | H79: =IF(ROW()=5,F79-G79,H78+F79-G79) | I79: 28.3 | J79: =IFERROR((F79+G79)*I79,0)
E80: =VLOOKUP(TablaMarimba6[[#This Row],[Equipo]],Catalogos!$I$4:$J$35,2,FALSE) | H80: =IF(ROW()=5,F80-G80,H79+F80-G80) | I80: 28.3 | J80: =IFERROR((F80+G80)*I80,0)
E81: =VLOOKUP(TablaMarimba6[[#This Row],[Equipo]],Catalogos!$I$4:$J$35,2,FALSE) | H81: =IF(ROW()=5,F81-G81,H80+F81-G81) | I81: 28.3 | J81: =IFERROR((F81+G81)*I81,0)
E82: =VLOOKUP(TablaMarimba6[[#This Row],[Equipo]],Catalogos!$I$4:$J$35,2,FALSE) | H82: =IF(ROW()=5,F82-G82,H81+F82-G82) | I82: 28.3 | J82: =IFERROR((F82+G82)*I82,0)
E83: =VLOOKUP(TablaMarimba6[[#This Row],[Equipo]],Catalogos!$I$4:$J$35,2,FALSE) | H83: =IF(ROW()=5,F83-G83,H82+F83-G83) | I83: 28.3 | J83: =IFERROR((F83+G83)*I83,0)
E84: =VLOOKUP(TablaMarimba6[[#This Row],[Equipo]],Catalogos!$I$4:$J$35,2,FALSE) | H84: =IF(ROW()=5,F84-G84,H83+F84-G84) | I84: 28.3 | J84: =IFERROR((F84+G84)*I84,0)
E85: =VLOOKUP(TablaMarimba6[[#This Row],[Equipo]],Catalogos!$I$4:$J$35,2,FALSE) | H85: =IF(ROW()=5,F85-G85,H84+F85-G85) | I85: 28.3 | J85: =IFERROR((F85+G85)*I85,0)
E86: =VLOOKUP(TablaMarimba6[[#This Row],[Equipo]],Catalogos!$I$4:$J$35,2,FALSE) | H86: =IF(ROW()=5,F86-G86,H85+F86-G86) | I86: 28.3 | J86: =IFERROR((F86+G86)*I86,0)
E87: =VLOOKUP(TablaMarimba6[[#This Row],[Equipo]],Catalogos!$I$4:$J$35,2,FALSE) | H87: =IF(ROW()=5,F87-G87,H86+F87-G87) | I87: 28.3 | J87: =IFERROR((F87+G87)*I87,0)
... E206: =VLOOKUP(TablaMarimba6[[#This Row],[Equipo]],Catalogos!$I$4:$J$35,2,FALSE) | H206: =IF(ROW()=5,F206-G206,H205+F206-G206) | I206: 28.3 | J206: =IFERROR((F206+G206)*I206,0)

Sheet Captura_Obra
A1: GC-COMB-003 | BITÁCORA DE CONTROL DE COMBUSTIBLE DE OBRA
A2: Ingeniero: | C2: Semana: | E2: Fecha entrega: | G2: Obra: | I2: Costo/L base:
A4: Fecha | B4: Obra | C4: Fuente | D4: Equipo | E4: Económico | F4: Litros Recibidos | G4: Costo/L | H4: Importe | I4: Actividad Ejecutada | J4: Incidencia | K4: Observaciones
A5: 46181 | B5: México-Toluca | C5: Marimba M-01 | D5: Neuomatico | E5: =VLOOKUP(TablaObra[[#This Row],[Equipo]],Catalogos!$I$4:$J$46,2,FALSE) | F5: 30 | G5: 28.3 | H5: =IFERROR(F5*G5,0)
A6: 46181 | B6: México-Toluca | C6: Marimba M-01 | D6: Compactador | E6: =VLOOKUP(TablaObra[[#This Row],[Equipo]],Catalogos!$I$4:$J$46,2,FALSE) | F6: 32 | G6: 28.3 | H6: =IFERROR(F6*G6,0)
A7: 46181 | B7: México-Toluca | C7: Marimba M-01 | D7: Perfiladora | E7: =VLOOKUP(TablaObra[[#This Row],[Equipo]],Catalogos!$I$4:$J$46,2,FALSE) | F7: 277 | G7: 28.3 | H7: =IFERROR(F7*G7,0)
A8: 46181 | B8: México-Toluca | C8: Marimba M-01 | D8: Retroexcavadora | E8: =VLOOKUP(TablaObra[[#This Row],[Equipo]],Catalogos!$I$4:$J$46,2,FALSE) | F8: 30 | G8: 28.3 | H8: =IFERROR(F8*G8,0)
A9: 46181 | B9: Lerma - Tres Marías | C9: Marimba M-01 | D9: Vogel | E9: =VLOOKUP(TablaObra[[#This Row],[Equipo]],Catalogos!$I$4:$J$46,2,FALSE) | F9: 97 | G9: 28.3 | H9: =IFERROR(F9*G9,0)
A10: 46181 | B10: Chamapa-Lechería | C10: Marimba M-01 | D10: Perfiladora Wirgent | E10: =VLOOKUP(TablaObra[[#This Row],[Equipo]],Catalogos!$I$4:$J$46,2,FALSE) | F10: 198 | G10: 28.3 | H10: =IFERROR(F10*G10,0)
A11: 46181 | B11: Chamapa-Lechería | C11: Marimba M-01 | D11: Maxilihgs | E11: =VLOOKUP(TablaObra[[#This Row],[Equipo]],Catalogos!$I$4:$J$46,2,FALSE) | F11: 10 | G11: 28.3 | H11: =IFERROR(F11*G11,0)
A12: 46181 | B12: Chamapa-Lechería | C12: Marimba M-01 | D12: Neuomatico Dynapac | E12: =VLOOKUP(TablaObra[[#This Row],[Equipo]],Catalogos!$I$4:$J$46,2,FALSE) | F12: 27 | G12: 28.3 | H12: =IFERROR(F12*G12,0)
A13: 46181 | B13: Chamapa-Lechería | C13: Marimba M-01 | D13: Compresor | E13: =VLOOKUP(TablaObra[[#This Row],[Equipo]],Catalogos!$I$4:$J$46,2,FALSE) | F13: 30 | G13: 28.3 | H13: =IFERROR(F13*G13,0)
A14: 46181 | B14: Chamapa-Lechería | C14: Marimba M-01 | D14: Retroexcavadora Jonh Deere | E14: =VLOOKUP(TablaObra[[#This Row],[Equipo]],Catalogos!$I$4:$J$46,2,FALSE) | F14: 40 | G14: 28.3 | H14: =IFERROR(F14*G14,0) | M14: =SUM(F5:F64)
A15: 46181 | B15: Chamapa-Lechería | C15: Marimba M-01 | D15: Vogele Guion | E15: =VLOOKUP(TablaObra[[#This Row],[Equipo]],Catalogos!$I$4:$J$46,2,FALSE) | F15: 120 | G15: 28.3 | H15: =IFERROR(F15*G15,0)
A16: 46181 | B16: Chamapa-Lechería | C16: Marimba M-01 | D16: Petrolizadora Elton | E16: =VLOOKUP(TablaObra[[#This Row],[Equipo]],Catalogos!$I$4:$J$46,2,FALSE) | F16: 30 | G16: 28.3 | H16: =IFERROR(F16*G16,0)
A17: 46181 | B17: Bacheo Toluca | C17: Pegaso Directo | D17: Bidones | E17: =VLOOKUP(TablaObra[[#This Row],[Equipo]],Catalogos!$I$4:$J$46,2,FALSE) | F17: 100 | G17: 28.3 | H17: =IFERROR(F17*G17,0)
A18: 46181 | B18: Planta Asfalto Pegaso | C18: Pegaso Directo | D18: Bidones | E18: =VLOOKUP(TablaObra[[#This Row],[Equipo]],Catalogos!$I$4:$J$46,2,FALSE) | F18: 200 | G18: 28.3 | H18: =IFERROR(F18*G18,0)
A19: 46181 | B19: Planta Asfalto Pegaso | C19: Pegaso Directo | D19: Bidones | E19: =VLOOKUP(TablaObra[[#This Row],[Equipo]],Catalogos!$I$4:$J$46,2,FALSE) | F19: 209 | G19: 28.3 | H19: =IFERROR(F19*G19,0)
A20: 46182 | B20: Chamapa-Lechería | C20: Marimba M-01 | D20: Barredora Broce | E20: =VLOOKUP(TablaObra[[#This Row],[Equipo]],Catalogos!$I$4:$J$46,2,FALSE) | F20: 30 | G20: 28.3 | H20: =IFERROR(F20*G20,0)
A21: 46182 | B21: Chamapa-Lechería | C21: Marimba M-01 | D21: Buggy Trasnfer | E21: =VLOOKUP(TablaObra[[#This Row],[Equipo]],Catalogos!$I$4:$J$46,2,FALSE) | F21: 100 | G21: 28.3 | H21: =IFERROR(F21*G21,0)
A22: 46182 | B22: Chamapa-Lechería | C22: Marimba M-01 | D22: Tandem Hamm | E22: =VLOOKUP(TablaObra[[#This Row],[Equipo]],Catalogos!$I$4:$J$46,2,FALSE) | F22: 30 | G22: 28.3 | H22: =IFERROR(F22*G22,0)
A23: 46182 | B23: Chamapa-Lechería | C23: Marimba M-01 | D23: Perfiladora Wirgent | E23: =VLOOKUP(TablaObra[[#This Row],[Equipo]],Catalogos!$I$4:$J$46,2,FALSE) | F23: 150 | G23: 28.3 | H23: =IFERROR(F23*G23,0)
A24: 46182 | B24: Chamapa-Lechería | C24: Marimba M-01 | D24: Petrolizadora Elton | E24: =VLOOKUP(TablaObra[[#This Row],[Equipo]],Catalogos!$I$4:$J$46,2,FALSE) | F24: 50 | G24: 28.3 | H24: =IFERROR(F24*G24,0)
A25: 46182 | B25: Chamapa-Lechería | C25: Marimba M-01 | D25: Vogele Guion | E25: =VLOOKUP(TablaObra[[#This Row],[Equipo]],Catalogos!$I$4:$J$46,2,FALSE) | F25: 136 | G25: 28.3 | H25: =IFERROR(F25*G25,0)
A26: 46182 | B26: Chamapa-Lechería | C26: Marimba M-01 | D26: Tandem Hamm | E26: =VLOOKUP(TablaObra[[#This Row],[Equipo]],Catalogos!$I$4:$J$46,2,FALSE) | F26: 30 | G26: 28.3 | H26: =IFERROR(F26*G26,0)
... A37: 46183 | B37: Bacheo Toluca | C37: Pegaso Directo | D37: Bidones | E37: =VLOOKUP(TablaObra[[#This Row],[Equipo]],Catalogos!$I$4:$J$46,2,FALSE) | F37: 100 | G37: 28.3 | H37: =IFERROR(F37*G37,0)
A38: 46184 | B38: México-Toluca | C38: Marimba M-01 | D38: Compactador | E38: =VLOOKUP(TablaObra[[#This Row],[Equipo]],Catalogos!$I$4:$J$46,2,FALSE) | F38: 30 | G38: 28.3 | H38: =IFERROR(F38*G38,0) | K38: Cuerpo a (Pausada)
A39: 46184 | B39: México-Toluca | C39: Marimba M-01 | D39: Neuomatico | E39: =VLOOKUP(TablaObra[[#This Row],[Equipo]],Catalogos!$I$4:$J$46,2,FALSE) | F39: 30 | G39: 28.3 | H39: =IFERROR(F39*G39,0) | K39: Cuerpo a (Pausada)
A40: 46184 | B40: México-Toluca | C40: Marimba M-01 | D40: Vogel | E40: =VLOOKUP(TablaObra[[#This Row],[Equipo]],Catalogos!$I$4:$J$46,2,FALSE) | F40: 136 | G40: 28.3 | H40: =IFERROR(F40*G40,0) | K40: Cuerpo a (Pausada)
A41: 46184 | B41: México-Toluca | C41: Marimba M-01 | D41: Barredora | E41: =VLOOKUP(TablaObra[[#This Row],[Equipo]],Catalogos!$I$4:$J$46,2,FALSE) | F41: 20 | G41: 28.3 | H41: =IFERROR(F41*G41,0) | K41: Cuerpo a (Pausada)
A42: 46184 | B42: México-Toluca | C42: Marimba M-01 | D42: Retroexcavadora | E42: =VLOOKUP(TablaObra[[#This Row],[Equipo]],Catalogos!$I$4:$J$46,2,FALSE) | F42: 20 | G42: 28.3 | H42: =IFERROR(F42*G42,0) | K42: Cuerpo a (Pausada)
A43: 46184 | B43: México-Toluca | C43: Marimba M-01 | D43: Maxilihgs | E43: =VLOOKUP(TablaObra[[#This Row],[Equipo]],Catalogos!$I$4:$J$46,2,FALSE) | F43: 20 | G43: 28.3 | H43: =IFERROR(F43*G43,0) | K43: Cuerpo a (Pausada)
A44: 46184 | B44: Planta Asfalto Pegaso | C44: Pegaso Directo | D44: PayLoder | E44: =VLOOKUP(TablaObra[[#This Row],[Equipo]],Catalogos!$I$4:$J$46,2,FALSE) | F44: 238 | G44: 28.3 | H44: =IFERROR(F44*G44,0)
A45: 46184 | B45: Lerma - Tres Marías | C45: Pegaso Directo | D45: Petrolizadora | E45: =VLOOKUP(TablaObra[[#This Row],[Equipo]],Catalogos!$I$4:$J$46,2,FALSE) | F45: 80 | G45: 28.3 | H45: =IFERROR(F45*G45,0)
A46: 46184 | B46: Lerma - Tres Marías | C46: Pegaso Directo | D46: Compresor | E46: =VLOOKUP(TablaObra[[#This Row],[Equipo]],Catalogos!$I$4:$J$46,2,FALSE) | F46: 50 | G46: 28.3 | H46: =IFERROR(F46*G46,0)
A47: 46184 | B47: Lerma - Tres Marías | C47: Pegaso Directo | D47: Retroexcavadora | E47: =VLOOKUP(TablaObra[[#This Row],[Equipo]],Catalogos!$I$4:$J$46,2,FALSE) | F47: 70 | G47: 28.3 | H47: =IFERROR(F47*G47,0)
A48: 46184 | B48: Lerma - Tres Marías | C48: Pegaso Directo | D48: Camion de Impacto | E48: =VLOOKUP(TablaObra[[#This Row],[Equipo]],Catalogos!$I$4:$J$46,2,FALSE) | F48: 80 | G48: 28.3 | H48: =IFERROR(F48*G48,0)
A49: 46184 | B49: Lerma - Tres Marías | C49: Pegaso Directo | D49: Vogel | E49: =VLOOKUP(TablaObra[[#This Row],[Equipo]],Catalogos!$I$4:$J$46,2,FALSE) | F49: 185 | G49: 28.3 | H49: =IFERROR(F49*G49,0)
A50: 46184 | B50: Lerma - Tres Marías | C50: Pegaso Directo | D50: Doble Rodillo | E50: =VLOOKUP(TablaObra[[#This Row],[Equipo]],Catalogos!$I$4:$J$46,2,FALSE) | F50: 50 | G50: 28.3 | H50: =IFERROR(F50*G50,0)
A51: 46184 | B51: Lerma - Tres Marías | C51: Pegaso Directo | D51: Doble Rodillo | E51: =VLOOKUP(TablaObra[[#This Row],[Equipo]],Catalogos!$I$4:$J$46,2,FALSE) | F51: 40 | G51: 28.3 | H51: =IFERROR(F51*G51,0)
A52: 46184 | B52: Lerma - Tres Marías | C52: Pegaso Directo | D52: Neuomatico | E52: =VLOOKUP(TablaObra[[#This Row],[Equipo]],Catalogos!$I$4:$J$46,2,FALSE) | F52: 40 | G52: 28.3 | H52: =IFERROR(F52*G52,0)
A53: 46185 | B53: Chamapa-Lechería | C53: Marimba M-01 | D53: Tandem Hamm | E53: =VLOOKUP(TablaObra[[#This Row],[Equipo]],Catalogos!$I$4:$J$46,2,FALSE) | F53: 32 | G53: 28.3 | H53: =IFERROR(F53*G53,0)
A54: 46185 | B54: Chamapa-Lechería | C54: Marimba M-01 | D54: Neuomatico Dynapac | E54: =VLOOKUP(TablaObra[[#This Row],[Equipo]],Catalogos!$I$4:$J$46,2,FALSE) | F54: 30 | G54: 28.3 | H54: =IFERROR(F54*G54,0)
A55: 46185 | B55: Chamapa-Lechería | C55: Marimba M-01 | D55: Barredora Broce | E55: =VLOOKUP(TablaObra[[#This Row],[Equipo]],Catalogos!$I$4:$J$46,2,FALSE) | F55: 30 | G55: 28.3 | H55: =IFERROR(F55*G55,0)
... A88: 46189 | B88: Planta Asfalto Pegaso | C88: Pegaso Directo | D88: Petrolizadora | E88: =VLOOKUP(TablaObra[[#This Row],[Equipo]],Catalogos!$I$4:$J$46,2,FALSE) | F88: 50 | G88: 28.3 | H88: =IFERROR(F88*G88,0)
A89: 46189 | C89: Pegaso Directo | D89: Bidones | E89: =VLOOKUP(TablaObra[[#This Row],[Equipo]],Catalogos!$I$4:$J$46,2,FALSE) | F89: 1001 | G89: 28.3 | H89: =IFERROR(F89*G89,0)
A90: 46189 | B90: Lerma - Tres Marías | C90: Pegaso Directo | D90: Perfiladora | E90: =VLOOKUP(TablaObra[[#This Row],[Equipo]],Catalogos!$I$4:$J$46,2,FALSE) | F90: 550 | G90: 28.3 | H90: =IFERROR(F90*G90,0)
A91: 46189 | B91: Lerma - Tres Marías | C91: Pegaso Directo | D91: Pipa | E91: =VLOOKUP(TablaObra[[#This Row],[Equipo]],Catalogos!$I$4:$J$46,2,FALSE) | F91: 50 | G91: 28.3 | H91: =IFERROR(F91*G91,0)
A92: 46189 | B92: Lerma - Tres Marías | C92: Pegaso Directo | D92: Vogel | E92: =VLOOKUP(TablaObra[[#This Row],[Equipo]],Catalogos!$I$4:$J$46,2,FALSE) | F92: 165 | G92: 28.3 | H92: =IFERROR(F92*G92,0)
A93: 46190 | B93: México-Toluca | C93: Marimba M-01 | D93: Perfiladora Wirgent | E93: =VLOOKUP(TablaObra[[#This Row],[Equipo]],Catalogos!$I$4:$J$46,2,FALSE) | F93: 200 | G93: 28.3 | H93: =IFERROR(F93*G93,0)
A94: 46190 | B94: México-Toluca | C94: Marimba M-01 | D94: Vogele Guion | E94: =VLOOKUP(TablaObra[[#This Row],[Equipo]],Catalogos!$I$4:$J$46,2,FALSE) | F94: 120 | G94: 28.3 | H94: =IFERROR(F94*G94,0)
A95: 46190 | B95: México-Toluca | C95: Marimba M-01 | D95: Tandem Hamm | E95: =VLOOKUP(TablaObra[[#This Row],[Equipo]],Catalogos!$I$4:$J$46,2,FALSE) | F95: 30 | G95: 28.3 | H95: =IFERROR(F95*G95,0)
A96: 46190 | B96: México-Toluca | C96: Marimba M-01 | D96: Neuomatico | E96: =VLOOKUP(TablaObra[[#This Row],[Equipo]],Catalogos!$I$4:$J$46,2,FALSE) | F96: 30 | G96: 28.3 | H96: =IFERROR(F96*G96,0)
A97: 46190 | B97: México-Toluca | C97: Marimba M-01 | D97: Barredora | E97: =VLOOKUP(TablaObra[[#This Row],[Equipo]],Catalogos!$I$4:$J$46,2,FALSE) | F97: 28 | G97: 28.3 | H97: =IFERROR(F97*G97,0)
A98: 46190 | B98: México-Toluca | C98: Marimba M-01 | D98: Retroexcavadora | E98: =VLOOKUP(TablaObra[[#This Row],[Equipo]],Catalogos!$I$4:$J$46,2,FALSE) | F98: 60 | G98: 28.3 | H98: =IFERROR(F98*G98,0)
A99: 46190 | B99: Lerma - Tres Marías | C99: Pegaso Directo | D99: Camion de Impacto | E99: =VLOOKUP(TablaObra[[#This Row],[Equipo]],Catalogos!$I$4:$J$46,2,FALSE) | F99: 80 | G99: 28.3 | H99: =IFERROR(F99*G99,0)
A100: 46191 | B100: México-Toluca | C100: Marimba M-01 | D100: Perfiladora Wirgent | E100: =VLOOKUP(TablaObra[[#This Row],[Equipo]],Catalogos!$I$4:$J$46,2,FALSE) | F100: 200 | G100: 28.3 | H100: =IFERROR(F100*G100,0)
A101: 46191 | B101: México-Toluca | C101: Marimba M-01 | D101: Vogele Guion | E101: =VLOOKUP(TablaObra[[#This Row],[Equipo]],Catalogos!$I$4:$J$46,2,FALSE) | F101: 115 | G101: 28.3 | H101: =IFERROR(F101*G101,0)
... A105: 46191 | B105: México-Toluca | C105: Marimba M-01 | D105: Petrolizadora | E105: =VLOOKUP(TablaObra[[#This Row],[Equipo]],Catalogos!$I$4:$J$46,2,FALSE) | F105: 50 | G105: 28.3 | H105: =IFERROR(F105*G105,0)
A106: 46192 | B106: Lerma - Tres Marías | C106: Pegaso Directo | E106: =VLOOKUP(TablaObra[[#This Row],[Equipo]],Catalogos!$I$4:$J$46,2,FALSE) | F106: 40 | G106: 28.3 | H106: =IFERROR(F106*G106,0)
A107: 46192 | B107: Dragones | C107: Pegaso Directo | E107: =VLOOKUP(TablaObra[[#This Row],[Equipo]],Catalogos!$I$4:$J$46,2,FALSE) | F107: 40 | G107: 28.3 | H107: =IFERROR(F107*G107,0)
A108: 46192 | B108: Lerma - Tres Marías | C108: Pegaso Directo | D108: Barredora | E108: =VLOOKUP(TablaObra[[#This Row],[Equipo]],Catalogos!$I$4:$J$46,2,FALSE) | F108: 43 | G108: 28.3 | H108: =IFERROR(F108*G108,0)
A109: 46192 | B109: Lerma - Tres Marías | C109: Pegaso Directo | D109: Tandem Hamm | E109: =VLOOKUP(TablaObra[[#This Row],[Equipo]],Catalogos!$I$4:$J$46,2,FALSE) | F109: 50 | G109: 28.3 | H109: =IFERROR(F109*G109,0)
A110: 46192 | B110: Lerma - Tres Marías | C110: Pegaso Directo | D110: Retroexcavadora | E110: =VLOOKUP(TablaObra[[#This Row],[Equipo]],Catalogos!$I$4:$J$46,2,FALSE) | F110: 80 | G110: 28.3 | H110: =IFERROR(F110*G110,0)
A111: 46192 | B111: Lerma - Tres Marías | C111: Pegaso Directo | D111: Neuomatico Dynapac | E111: =VLOOKUP(TablaObra[[#This Row],[Equipo]],Catalogos!$I$4:$J$46,2,FALSE) | F111: 30 | G111: 28.3 | H111: =IFERROR(F111*G111,0)
A112: 46192 | B112: Lerma - Tres Marías | C112: Pegaso Directo | D112: Vogel | E112: =VLOOKUP(TablaObra[[#This Row],[Equipo]],Catalogos!$I$4:$J$46,2,FALSE) | F112: 160 | G112: 28.3 | H112: =IFERROR(F112*G112,0)
A113: 46192 | B113: Lerma - Tres Marías | C113: Pegaso Directo | D113: Pipa | E113: =VLOOKUP(TablaObra[[#This Row],[Equipo]],Catalogos!$I$4:$J$46,2,FALSE) | F113: 50 | G113: 28.3 | H113: =IFERROR(F113*G113,0)
E114: =VLOOKUP(TablaObra[[#This Row],[Equipo]],Catalogos!$I$4:$J$46,2,FALSE) | G114: 28.3 | H114: =IFERROR(F114*G114,0)
E115: =VLOOKUP(TablaObra[[#This Row],[Equipo]],Catalogos!$I$4:$J$46,2,FALSE) | G115: 28.3 | H115: =IFERROR(F115*G115,0)
E116: =VLOOKUP(TablaObra[[#This Row],[Equipo]],Catalogos!$I$4:$J$46,2,FALSE) | G116: 28.3 | H116: =IFERROR(F116*G116,0)
E117: =VLOOKUP(TablaObra[[#This Row],[Equipo]],Catalogos!$I$4:$J$46,2,FALSE) | G117: 28.3 | H117: =IFERROR(F117*G117,0)
E118: =VLOOKUP(TablaObra[[#This Row],[Equipo]],Catalogos!$I$4:$J$46,2,FALSE) | G118: 28.3 | H118: =IFERROR(F118*G118,0)
E119: =VLOOKUP(TablaObra[[#This Row],[Equipo]],Catalogos!$I$4:$J$46,2,FALSE) | G119: 28.3 | H119: =IFERROR(F119*G119,0)
E120: =VLOOKUP(TablaObra[[#This Row],[Equipo]],Catalogos!$I$4:$J$46,2,FALSE) | G120: 28.3 | H120: =IFERROR(F120*G120,0)
E121: =VLOOKUP(TablaObra[[#This Row],[Equipo]],Catalogos!$I$4:$J$46,2,FALSE) | G121: 28.3 | H121: =IFERROR(F121*G121,0)
E122: =VLOOKUP(TablaObra[[#This Row],[Equipo]],Catalogos!$I$4:$J$46,2,FALSE) | G122: 28.3 | H122: =IFERROR(F122*G122,0)
E123: =VLOOKUP(TablaObra[[#This Row],[Equipo]],Catalogos!$I$4:$J$46,2,FALSE) | G123: 28.3 | H123: =IFERROR(F123*G123,0)
E124: =VLOOKUP(TablaObra[[#This Row],[Equipo]],Catalogos!$I$4:$J$46,2,FALSE) | G124: 28.3 | H124: =IFERROR(F124*G124,0)
E125: =VLOOKUP(TablaObra[[#This Row],[Equipo]],Catalogos!$I$4:$J$46,2,FALSE) | G125: 28.3 | H125: =IFERROR(F125*G125,0)
... E145: =VLOOKUP(TablaObra[[#This Row],[Equipo]],Catalogos!$I$4:$J$46,2,FALSE) | G145: 28.3 | H145: =IFERROR(F145*G145,0)
E146: =VLOOKUP(TablaObra[[#This Row],[Equipo]],Catalogos!$I$4:$J$46,2,FALSE) | H146: =IFERROR(F146*G146,0)
E147: =VLOOKUP(TablaObra[[#This Row],[Equipo]],Catalogos!$I$4:$J$46,2,FALSE) | H147: =IFERROR(F147*G147,0)
E148: =VLOOKUP(TablaObra[[#This Row],[Equipo]],Catalogos!$I$4:$J$46,2,FALSE) | H148: =IFERROR(F148*G148,0)
E149: =VLOOKUP(TablaObra[[#This Row],[Equipo]],Catalogos!$I$4:$J$46,2,FALSE) | H149: =IFERROR(F149*G149,0)
E150: =VLOOKUP(TablaObra[[#This Row],[Equipo]],Catalogos!$I$4:$J$46,2,FALSE) | H150: =IFERROR(F150*G150,0)
E151: =VLOOKUP(TablaObra[[#This Row],[Equipo]],Catalogos!$I$4:$J$46,2,FALSE) | H151: =IFERROR(F151*G151,0)
E152: =VLOOKUP(TablaObra[[#This Row],[Equipo]],Catalogos!$I$4:$J$46,2,FALSE) | H152: =IFERROR(F152*G152,0)
E153: =VLOOKUP(TablaObra[[#This Row],[Equipo]],Catalogos!$I$4:$J$46,2,FALSE) | H153: =IFERROR(F153*G153,0)
E154: =VLOOKUP(TablaObra[[#This Row],[Equipo]],Catalogos!$I$4:$J$46,2,FALSE) | H154: =IFERROR(F154*G154,0)
E155: =VLOOKUP(TablaObra[[#This Row],[Equipo]],Catalogos!$I$4:$J$46,2,FALSE) | H155: =IFERROR(F155*G155,0)
E156: =VLOOKUP(TablaObra[[#This Row],[Equipo]],Catalogos!$I$4:$J$46,2,FALSE) | H156: =IFERROR(F156*G156,0)
E157: =VLOOKUP(TablaObra[[#This Row],[Equipo]],Catalogos!$I$4:$J$46,2,FALSE) | H157: =IFERROR(F157*G157,0)
... E304: =VLOOKUP(TablaObra[[#This Row],[Equipo]],Catalogos!$I$4:$J$46,2,FALSE) | H304: =IFERROR(F304*G304,0)

Sheet Solicitudes
A1: GC-COMB-003 | BITÁCORA DE SOLICITUDES DE COMBUSTIBLE DE OBRA
A2: Ingeniero: | C2: Semana: | E2: Fecha entrega: | G2: Obra: | I2: Costo/L base:
A4: Fecha de Solicitud | B4: Obra | C4: Fecha de Trabajo | D4: Equipo | E4: Económico | F4: Litros Solicitados | G4: Costo/L | H4: Importe | I4: Solicitante | J4: Incidencia | K4: Observaciones
A5: 46180 | B5: México-Toluca | C5: 46181 | D5: Vogel | E5: =VLOOKUP(TablaObra5[[#This Row],[Equipo]],Catalogos!$I$4:$J$39,2,FALSE) | F5: 200 | G5: 28.3 | H5: =IFERROR(F5*G5,0) | I5: =VLOOKUP(TablaObra5[[#This Row],[Obra]],Catalogos!$B$3:$C$8,2,FALSE)
A6: 46180 | B6: México-Toluca | C6: 46181 | D6: Perfiladora | E6: =VLOOKUP(TablaObra5[[#This Row],[Equipo]],Catalogos!$I$4:$J$39,2,FALSE) | F6: 300 | G6: 28.3 | H6: =IFERROR(F6*G6,0) | I6: =VLOOKUP(TablaObra5[[#This Row],[Obra]],Catalogos!$B$3:$C$8,2,FALSE)
A7: 46180 | B7: México-Toluca | C7: 46181 | D7: Retroexcavadora | E7: =VLOOKUP(TablaObra5[[#This Row],[Equipo]],Catalogos!$I$4:$J$39,2,FALSE) | F7: 30 | G7: 28.3 | H7: =IFERROR(F7*G7,0) | I7: =VLOOKUP(TablaObra5[[#This Row],[Obra]],Catalogos!$B$3:$C$8,2,FALSE)
A8: 46180 | B8: México-Toluca | C8: 46181 | D8: Barredora | E8: =VLOOKUP(TablaObra5[[#This Row],[Equipo]],Catalogos!$I$4:$J$39,2,FALSE) | F8: 20 | G8: 28.3 | H8: =IFERROR(F8*G8,0) | I8: =VLOOKUP(TablaObra5[[#This Row],[Obra]],Catalogos!$B$3:$C$8,2,FALSE)
A9: 46180 | B9: México-Toluca | C9: 46181 | D9: Neuomatico | E9: =VLOOKUP(TablaObra5[[#This Row],[Equipo]],Catalogos!$I$4:$J$39,2,FALSE) | F9: 30 | G9: 28.3 | H9: =IFERROR(F9*G9,0) | I9: =VLOOKUP(TablaObra5[[#This Row],[Obra]],Catalogos!$B$3:$C$8,2,FALSE)
A10: 46180 | B10: México-Toluca | C10: 46181 | D10: Compactador | E10: =VLOOKUP(TablaObra5[[#This Row],[Equipo]],Catalogos!$I$4:$J$39,2,FALSE) | F10: 30 | G10: 28.3 | H10: =IFERROR(F10*G10,0) | I10: =VLOOKUP(TablaObra5[[#This Row],[Obra]],Catalogos!$B$3:$C$8,2,FALSE)
A11: 46180 | B11: México-Toluca | C11: 46181 | D11: Limpieza | E11: =VLOOKUP(TablaObra5[[#This Row],[Equipo]],Catalogos!$I$4:$J$39,2,FALSE) | F11: 30 | G11: 28.3 | H11: =IFERROR(F11*G11,0) | I11: =VLOOKUP(TablaObra5[[#This Row],[Obra]],Catalogos!$B$3:$C$8,2,FALSE)
A12: 46180 | B12: Lerma - Tres Marías | C12: 46181 | D12: Retroexcavadora | E12: =VLOOKUP(TablaObra5[[#This Row],[Equipo]],Catalogos!$I$4:$J$39,2,FALSE) | F12: 50 | G12: 28.3 | H12: =IFERROR(F12*G12,0) | I12: =VLOOKUP(TablaObra5[[#This Row],[Obra]],Catalogos!$B$3:$C$8,2,FALSE)
A13: 46180 | B13: Lerma - Tres Marías | C13: 46181 | D13: Neuomatico | E13: =VLOOKUP(TablaObra5[[#This Row],[Equipo]],Catalogos!$I$4:$J$39,2,FALSE) | F13: 50 | G13: 28.3 | H13: =IFERROR(F13*G13,0) | I13: =VLOOKUP(TablaObra5[[#This Row],[Obra]],Catalogos!$B$3:$C$8,2,FALSE)
A14: 46180 | B14: Lerma - Tres Marías | C14: 46181 | D14: Petrolizadora | E14: =VLOOKUP(TablaObra5[[#This Row],[Equipo]],Catalogos!$I$4:$J$39,2,FALSE) | F14: 60 | G14: 28.3 | H14: =IFERROR(F14*G14,0) | I14: =VLOOKUP(TablaObra5[[#This Row],[Obra]],Catalogos!$B$3:$C$8,2,FALSE)
A15: 46181 | B15: Bacheo Toluca | D15: Retroexcavadora | E15: =VLOOKUP(TablaObra5[[#This Row],[Equipo]],Catalogos!$I$4:$J$39,2,FALSE) | F15: 100 | G15: 28.3 | H15: =IFERROR(F15*G15,0) | I15: =VLOOKUP(TablaObra5[[#This Row],[Obra]],Catalogos!$B$3:$C$8,2,FALSE)
A16: 46181 | B16: Chamapa-Lechería | C16: 46181 | D16: Perfiladora Wirgent | E16: =VLOOKUP(TablaObra5[[#This Row],[Equipo]],Catalogos!$I$4:$J$39,2,FALSE) | F16: 250 | G16: 28.3 | H16: =IFERROR(F16*G16,0) | I16: =VLOOKUP(TablaObra5[[#This Row],[Obra]],Catalogos!$B$3:$C$8,2,FALSE)
A17: 46181 | B17: Chamapa-Lechería | C17: 46181 | D17: Perfiladora Cat-PM | E17: =VLOOKUP(TablaObra5[[#This Row],[Equipo]],Catalogos!$I$4:$J$39,2,FALSE) | F17: 150 | G17: 28.3 | H17: =IFERROR(F17*G17,0) | I17: =VLOOKUP(TablaObra5[[#This Row],[Obra]],Catalogos!$B$3:$C$8,2,FALSE)
A18: 46181 | B18: Chamapa-Lechería | C18: 46181 | D18: Barredora Broce | E18: =VLOOKUP(TablaObra5[[#This Row],[Equipo]],Catalogos!$I$4:$J$39,2,FALSE) | F18: 40 | G18: 28.3 | H18: =IFERROR(F18*G18,0) | I18: =VLOOKUP(TablaObra5[[#This Row],[Obra]],Catalogos!$B$3:$C$8,2,FALSE)
A19: 46181 | B19: Chamapa-Lechería | C19: 46181 | D19: Retroexcavadora Jonh Deere | E19: =VLOOKUP(TablaObra5[[#This Row],[Equipo]],Catalogos!$I$4:$J$39,2,FALSE) | F19: 60 | G19: 28.3 | H19: =IFERROR(F19*G19,0) | I19: =VLOOKUP(TablaObra5[[#This Row],[Obra]],Catalogos!$B$3:$C$8,2,FALSE)
A20: 46181 | B20: Chamapa-Lechería | C20: 46181 | D20: Buggy Trasnfer | E20: =VLOOKUP(TablaObra5[[#This Row],[Equipo]],Catalogos!$I$4:$J$39,2,FALSE) | F20: 100 | G20: 28.3 | H20: =IFERROR(F20*G20,0) | I20: =VLOOKUP(TablaObra5[[#This Row],[Obra]],Catalogos!$B$3:$C$8,2,FALSE)
A21: 46181 | B21: Chamapa-Lechería | C21: 46181 | D21: Vogele Guion | E21: =VLOOKUP(TablaObra5[[#This Row],[Equipo]],Catalogos!$I$4:$J$39,2,FALSE) | F21: 100 | G21: 28.3 | H21: =IFERROR(F21*G21,0) | I21: =VLOOKUP(TablaObra5[[#This Row],[Obra]],Catalogos!$B$3:$C$8,2,FALSE)
A22: 46181 | B22: Chamapa-Lechería | C22: 46181 | D22: Limpieza | E22: =VLOOKUP(TablaObra5[[#This Row],[Equipo]],Catalogos!$I$4:$J$39,2,FALSE) | F22: 20 | G22: 28.3 | H22: =IFERROR(F22*G22,0) | I22: =VLOOKUP(TablaObra5[[#This Row],[Obra]],Catalogos!$B$3:$C$8,2,FALSE)
A23: 46181 | B23: Chamapa-Lechería | C23: 46181 | D23: Tandem Hamm | E23: =VLOOKUP(TablaObra5[[#This Row],[Equipo]],Catalogos!$I$4:$J$39,2,FALSE) | F23: 50 | G23: 28.3 | H23: =IFERROR(F23*G23,0) | I23: =VLOOKUP(TablaObra5[[#This Row],[Obra]],Catalogos!$B$3:$C$8,2,FALSE)
A24: 46181 | B24: Chamapa-Lechería | C24: 46181 | D24: Neuomatico Dynapac | E24: =VLOOKUP(TablaObra5[[#This Row],[Equipo]],Catalogos!$I$4:$J$39,2,FALSE) | F24: 50 | G24: 28.3 | H24: =IFERROR(F24*G24,0) | I24: =VLOOKUP(TablaObra5[[#This Row],[Obra]],Catalogos!$B$3:$C$8,2,FALSE)
A25: 46181 | B25: Chamapa-Lechería | C25: 46181 | D25: Petrolizadora Elton | E25: =VLOOKUP(TablaObra5[[#This Row],[Equipo]],Catalogos!$I$4:$J$39,2,FALSE) | F25: 50 | G25: 28.3 | H25: =IFERROR(F25*G25,0) | I25: =VLOOKUP(TablaObra5[[#This Row],[Obra]],Catalogos!$B$3:$C$8,2,FALSE)
A26: 46181 | B26: Chamapa-Lechería | C26: 46181 | D26: Camion de Impacto | E26: =VLOOKUP(TablaObra5[[#This Row],[Equipo]],Catalogos!$I$4:$J$39,2,FALSE) | F26: 20 | G26: 28.3 | H26: =IFERROR(F26*G26,0) | I26: =VLOOKUP(TablaObra5[[#This Row],[Obra]],Catalogos!$B$3:$C$8,2,FALSE)
A27: 46181 | B27: Chamapa-Lechería | C27: 46181 | D27: Maxilihgs | E27: =VLOOKUP(TablaObra5[[#This Row],[Equipo]],Catalogos!$I$4:$J$39,2,FALSE) | F27: 50 | G27: 28.3 | H27: =IFERROR(F27*G27,0) | I27: =VLOOKUP(TablaObra5[[#This Row],[Obra]],Catalogos!$B$3:$C$8,2,FALSE)
... A40: 46182 | B40: Chamapa-Lechería | C40: 46182 | D40: Compresor | E40: =VLOOKUP(TablaObra5[[#This Row],[Equipo]],Catalogos!$I$4:$J$39,2,FALSE) | F40: 30 | G40: 28.3 | H40: =IFERROR(F40*G40,0) | I40: =VLOOKUP(TablaObra5[[#This Row],[Obra]],Catalogos!$B$3:$C$8,2,FALSE)
A41: 46182 | B41: Lerma - Tres Marías | C41: 46182 | D41: Retroexcavadora | E41: =VLOOKUP(TablaObra5[[#This Row],[Equipo]],Catalogos!$I$4:$J$39,2,FALSE) | F41: 50 | G41: 28.3 | H41: =IFERROR(F41*G41,0) | I41: =VLOOKUP(TablaObra5[[#This Row],[Obra]],Catalogos!$B$3:$C$8,2,FALSE) | K41: Segunda solicitud, el dia 7/06/2026, no se relizo la carga
A42: 46182 | B42: Lerma - Tres Marías | C42: 46182 | D42: Neuomatico | E42: =VLOOKUP(TablaObra5[[#This Row],[Equipo]],Catalogos!$I$4:$J$39,2,FALSE) | F42: 50 | G42: 28.3 | H42: =IFERROR(F42*G42,0) | I42: =VLOOKUP(TablaObra5[[#This Row],[Obra]],Catalogos!$B$3:$C$8,2,FALSE)
A43: 46182 | B43: Lerma - Tres Marías | C43: 46182 | D43: Petrolizadora | E43: =VLOOKUP(TablaObra5[[#This Row],[Equipo]],Catalogos!$I$4:$J$39,2,FALSE) | F43: 60 | G43: 28.3 | H43: =IFERROR(F43*G43,0) | I43: =VLOOKUP(TablaObra5[[#This Row],[Obra]],Catalogos!$B$3:$C$8,2,FALSE)
A44: 46182 | B44: Lerma - Tres Marías | C44: 46182 | D44: Doble Rodillo | E44: =VLOOKUP(TablaObra5[[#This Row],[Equipo]],Catalogos!$I$4:$J$39,2,FALSE) | F44: 50 | G44: 28.3 | H44: =IFERROR(F44*G44,0) | I44: =VLOOKUP(TablaObra5[[#This Row],[Obra]],Catalogos!$B$3:$C$8,2,FALSE)
A45: 46182 | B45: Bacheo Toluca | D45: Retroexcavadora | E45: =VLOOKUP(TablaObra5[[#This Row],[Equipo]],Catalogos!$I$4:$J$39,2,FALSE) | F45: 100 | G45: 28.3 | H45: =IFERROR(F45*G45,0) | I45: =VLOOKUP(TablaObra5[[#This Row],[Obra]],Catalogos!$B$3:$C$8,2,FALSE)
A46: 46183 | B46: México-Toluca | C46: 46183 | D46: Perfiladora | E46: =VLOOKUP(TablaObra5[[#This Row],[Equipo]],Catalogos!$I$4:$J$39,2,FALSE) | F46: 250 | G46: 28.3 | H46: =IFERROR(F46*G46,0) | I46: =VLOOKUP(TablaObra5[[#This Row],[Obra]],Catalogos!$B$3:$C$8,2,FALSE)
A47: 46183 | B47: México-Toluca | C47: 46183 | D47: Retroexcavadora | E47: =VLOOKUP(TablaObra5[[#This Row],[Equipo]],Catalogos!$I$4:$J$39,2,FALSE) | F47: 30 | G47: 28.3 | H47: =IFERROR(F47*G47,0) | I47: =VLOOKUP(TablaObra5[[#This Row],[Obra]],Catalogos!$B$3:$C$8,2,FALSE)
A48: 46183 | B48: México-Toluca | C48: 46183 | D48: Barredora | E48: =VLOOKUP(TablaObra5[[#This Row],[Equipo]],Catalogos!$I$4:$J$39,2,FALSE) | F48: 20 | G48: 28.3 | H48: =IFERROR(F48*G48,0) | I48: =VLOOKUP(TablaObra5[[#This Row],[Obra]],Catalogos!$B$3:$C$8,2,FALSE)
A49: 46183 | B49: México-Toluca | C49: 46183 | D49: Maxilihgs | E49: =VLOOKUP(TablaObra5[[#This Row],[Equipo]],Catalogos!$I$4:$J$39,2,FALSE) | F49: 20 | G49: 28.3 | H49: =IFERROR(F49*G49,0) | I49: =VLOOKUP(TablaObra5[[#This Row],[Obra]],Catalogos!$B$3:$C$8,2,FALSE)
A50: 46184 | B50: Lerma - Tres Marías | C50: 46184 | D50: Petrolizadora | E50: =VLOOKUP(TablaObra5[[#This Row],[Equipo]],Catalogos!$I$4:$J$39,2,FALSE) | F50: 80 | G50: 28.3 | H50: =IFERROR(F50*G50,0) | I50: =VLOOKUP(TablaObra5[[#This Row],[Obra]],Catalogos!$B$3:$C$8,2,FALSE)
A51: 46184 | B51: Lerma - Tres Marías | C51: 46184 | D51: Camion de Impacto | E51: =VLOOKUP(TablaObra5[[#This Row],[Equipo]],Catalogos!$I$4:$J$39,2,FALSE) | F51: 80 | G51: 28.3 | H51: =IFERROR(F51*G51,0) | I51: =VLOOKUP(TablaObra5[[#This Row],[Obra]],Catalogos!$B$3:$C$8,2,FALSE)
A52: 46184 | B52: Lerma - Tres Marías | C52: 46184 | D52: Retroexcavadora | E52: =VLOOKUP(TablaObra5[[#This Row],[Equipo]],Catalogos!$I$4:$J$39,2,FALSE) | F52: 70 | G52: 28.3 | H52: =IFERROR(F52*G52,0) | I52: =VLOOKUP(TablaObra5[[#This Row],[Obra]],Catalogos!$B$3:$C$8,2,FALSE)
A53: 46184 | B53: Lerma - Tres Marías | C53: 46184 | D53: Doble Rodillo | E53: =VLOOKUP(TablaObra5[[#This Row],[Equipo]],Catalogos!$I$4:$J$39,2,FALSE) | F53: 40 | G53: 28.3 | H53: =IFERROR(F53*G53,0) | I53: =VLOOKUP(TablaObra5[[#This Row],[Obra]],Catalogos!$B$3:$C$8,2,FALSE)
A54: 46184 | B54: Lerma - Tres Marías | C54: 46184 | D54: Vogel | E54: =VLOOKUP(TablaObra5[[#This Row],[Equipo]],Catalogos!$I$4:$J$39,2,FALSE) | F54: 150 | G54: 28.3 | H54: =IFERROR(F54*G54,0) | I54: =VLOOKUP(TablaObra5[[#This Row],[Obra]],Catalogos!$B$3:$C$8,2,FALSE)
A55: 46184 | B55: Lerma - Tres Marías | C55: 46184 | D55: Limpieza | E55: =VLOOKUP(TablaObra5[[#This Row],[Equipo]],Catalogos!$I$4:$J$39,2,FALSE) | F55: 30 | G55: 28.3 | H55: =IFERROR(F55*G55,0) | I55: =VLOOKUP(TablaObra5[[#This Row],[Obra]],Catalogos!$B$3:$C$8,2,FALSE)
A56: 46184 | B56: Lerma - Tres Marías | C56: 46184 | D56: Rastrillador | E56: =VLOOKUP(TablaObra5[[#This Row],[Equipo]],Catalogos!$I$4:$J$39,2,FALSE) | F56: 10 | G56: 28.3 | H56: =IFERROR(F56*G56,0) | I56: =VLOOKUP(TablaObra5[[#This Row],[Obra]],Catalogos!$B$3:$C$8,2,FALSE)
A57: 46184 | B57: Bacheo Toluca | D57: Retroexcavadora | E57: =VLOOKUP(TablaObra5[[#This Row],[Equipo]],Catalogos!$I$4:$J$39,2,FALSE) | F57: 50 | G57: 28.3 | H57: =IFERROR(F57*G57,0) | I57: =VLOOKUP(TablaObra5[[#This Row],[Obra]],Catalogos!$B$3:$C$8,2,FALSE) | K57: Diego Carreola Monroy
A58: 46184 | B58: Bacheo Toluca | D58: Otro | E58: =VLOOKUP(TablaObra5[[#This Row],[Equipo]],Catalogos!$I$4:$J$39,2,FALSE) | F58: 10 | G58: 28.3 | H58: =IFERROR(F58*G58,0) | I58: =VLOOKUP(TablaObra5[[#This Row],[Obra]],Catalogos!$B$3:$C$8,2,FALSE) | K58: Diego Carreola Monroy
A59: 46184 | B59: Bacheo Toluca | D59: Limpieza | E59: =VLOOKUP(TablaObra5[[#This Row],[Equipo]],Catalogos!$I$4:$J$39,2,FALSE) | F59: 10 | G59: 28.3 | H59: =IFERROR(F59*G59,0) | I59: =VLOOKUP(TablaObra5[[#This Row],[Obra]],Catalogos!$B$3:$C$8,2,FALSE) | K59: Diego Carreola Monroy
A60: 46185 | B60: México-Toluca | C60: 46185 | D60: Perfiladora | E60: =VLOOKUP(TablaObra5[[#This Row],[Equipo]],Catalogos!$I$4:$J$39,2,FALSE) | F60: 250 | G60: 28.3 | H60: =IFERROR(F60*G60,0) | I60: =VLOOKUP(TablaObra5[[#This Row],[Obra]],Catalogos!$B$3:$C$8,2,FALSE)
A61: 46185 | B61: México-Toluca | C61: 46185 | D61: Vogel | E61: =VLOOKUP(TablaObra5[[#This Row],[Equipo]],Catalogos!$I$4:$J$39,2,FALSE) | F61: 150 | G61: 28.3 | H61: =IFERROR(F61*G61,0) | I61: =VLOOKUP(TablaObra5[[#This Row],[Obra]],Catalogos!$B$3:$C$8,2,FALSE)
A62: 46185 | B62: México-Toluca | C62: 46185 | D62: Compactador | E62: =VLOOKUP(TablaObra5[[#This Row],[Equipo]],Catalogos!$I$4:$J$39,2,FALSE) | F62: 40 | G62: 28.3 | H62: =IFERROR(F62*G62,0) | I62: =VLOOKUP(TablaObra5[[#This Row],[Obra]],Catalogos!$B$3:$C$8,2,FALSE)
A63: 46185 | B63: México-Toluca | C63: 46185 | D63: Neuomatico | E63: =VLOOKUP(TablaObra5[[#This Row],[Equipo]],Catalogos!$I$4:$J$39,2,FALSE) | F63: 30 | G63: 28.3 | H63: =IFERROR(F63*G63,0) | I63: =VLOOKUP(TablaObra5[[#This Row],[Obra]],Catalogos!$B$3:$C$8,2,FALSE)
A64: 46185 | B64: México-Toluca | C64: 46185 | D64: Retroexcavadora | E64: =VLOOKUP(TablaObra5[[#This Row],[Equipo]],Catalogos!$I$4:$J$39,2,FALSE) | F64: 30 | G64: 28.3 | H64: =IFERROR(F64*G64,0) | I64: =VLOOKUP(TablaObra5[[#This Row],[Obra]],Catalogos!$B$3:$C$8,2,FALSE)
A65: 46185 | B65: México-Toluca | C65: 46185 | D65: Barredora | E65: =VLOOKUP(TablaObra5[[#This Row],[Equipo]],Catalogos!$I$4:$J$39,2,FALSE) | F65: 20 | G65: 28.3 | H65: =IFERROR(F65*G65,0) | I65: =VLOOKUP(TablaObra5[[#This Row],[Obra]],Catalogos!$B$3:$C$8,2,FALSE)
A66: 46185 | B66: México-Toluca | C66: 46185 | D66: Maxilihgs | E66: =VLOOKUP(TablaObra5[[#This Row],[Equipo]],Catalogos!$I$4:$J$39,2,FALSE) | F66: 20 | G66: 28.3 | H66: =IFERROR(F66*G66,0) | I66: =VLOOKUP(TablaObra5[[#This Row],[Obra]],Catalogos!$B$3:$C$8,2,FALSE)
A67: 46185 | B67: Chamapa-Lechería | C67: 46185 | D67: Perfiladora Wirgent | E67: =VLOOKUP(TablaObra5[[#This Row],[Equipo]],Catalogos!$I$4:$J$39,2,FALSE) | F67: 250 | G67: 28.3 | H67: =IFERROR(F67*G67,0) | I67: =VLOOKUP(TablaObra5[[#This Row],[Obra]],Catalogos!$B$3:$C$8,2,FALSE)
A68: 46185 | B68: Chamapa-Lechería | C68: 46185 | D68: Barredora Broce | E68: =VLOOKUP(TablaObra5[[#This Row],[Equipo]],Catalogos!$I$4:$J$39,2,FALSE) | F68: 40 | G68: 28.3 | H68: =IFERROR(F68*G68,0) | I68: =VLOOKUP(TablaObra5[[#This Row],[Obra]],Catalogos!$B$3:$C$8,2,FALSE)
A69: 46185 | B69: Chamapa-Lechería | C69: 46185 | D69: Retroexcavadora Jonh Deere | E69: =VLOOKUP(TablaObra5[[#This Row],[Equipo]],Catalogos!$I$4:$J$39,2,FALSE) | F69: 60 | G69: 28.3 | H69: =IFERROR(F69*G69,0) | I69: =VLOOKUP(TablaObra5[[#This Row],[Obra]],Catalogos!$B$3:$C$8,2,FALSE)
A70: 46185 | B70: Chamapa-Lechería | C70: 46185 | D70: Vogele Guion | E70: =VLOOKUP(TablaObra5[[#This Row],[Equipo]],Catalogos!$I$4:$J$39,2,FALSE) | F70: 100 | G70: 28.3 | H70: =IFERROR(F70*G70,0) | I70: =VLOOKUP(TablaObra5[[#This Row],[Obra]],Catalogos!$B$3:$C$8,2,FALSE)
A71: 46185 | B71: Chamapa-Lechería | C71: 46185 | D71: Limpieza | E71: =VLOOKUP(TablaObra5[[#This Row],[Equipo]],Catalogos!$I$4:$J$39,2,FALSE) | F71: 20 | G71: 28.3 | H71: =IFERROR(F71*G71,0) | I71: =VLOOKUP(TablaObra5[[#This Row],[Obra]],Catalogos!$B$3:$C$8,2,FALSE)
... A85: 46187 | B85: Lerma - Tres Marías | C85: 46188 | D85: Barredora | E85: =VLOOKUP(TablaObra5[[#This Row],[Equipo]],Catalogos!$I$4:$J$39,2,FALSE) | F85: 40 | G85: 28.3 | H85: =IFERROR(F85*G85,0) | I85: =VLOOKUP(TablaObra5[[#This Row],[Obra]],Catalogos!$B$3:$C$8,2,FALSE)
A86: 46188 | B86: Bacheo Toluca | D86: Retroexcavadora | E86: =VLOOKUP(TablaObra5[[#This Row],[Equipo]],Catalogos!$I$4:$J$39,2,FALSE) | F86: 70 | G86: 28.3 | H86: =IFERROR(F86*G86,0) | I86: =VLOOKUP(TablaObra5[[#This Row],[Obra]],Catalogos!$B$3:$C$8,2,FALSE)
A87: 46188 | B87: Bacheo Toluca | D87: Perfiladora | E87: =VLOOKUP(TablaObra5[[#This Row],[Equipo]],Catalogos!$I$4:$J$39,2,FALSE) | F87: 200 | G87: 28.3 | H87: =IFERROR(F87*G87,0) | I87: =VLOOKUP(TablaObra5[[#This Row],[Obra]],Catalogos!$B$3:$C$8,2,FALSE)
A88: 46188 | B88: Bacheo Toluca | D88: Doble Rodillo | E88: =VLOOKUP(TablaObra5[[#This Row],[Equipo]],Catalogos!$I$4:$J$39,2,FALSE) | F88: 40 | G88: 28.3 | H88: =IFERROR(F88*G88,0) | I88: =VLOOKUP(TablaObra5[[#This Row],[Obra]],Catalogos!$B$3:$C$8,2,FALSE)
A89: 46188 | B89: Lerma - Tres Marías | C89: 46189 | D89: Limpieza | E89: =VLOOKUP(TablaObra5[[#This Row],[Equipo]],Catalogos!$I$4:$J$39,2,FALSE) | F89: 25 | G89: 28.3 | H89: =IFERROR(F89*G89,0) | I89: =VLOOKUP(TablaObra5[[#This Row],[Obra]],Catalogos!$B$3:$C$8,2,FALSE)
A90: 46188 | B90: Lerma - Tres Marías | C90: 46189 | D90: Petrolizadora | E90: =VLOOKUP(TablaObra5[[#This Row],[Equipo]],Catalogos!$I$4:$J$39,2,FALSE) | F90: 60 | G90: 28.3 | H90: =IFERROR(F90*G90,0) | I90: =VLOOKUP(TablaObra5[[#This Row],[Obra]],Catalogos!$B$3:$C$8,2,FALSE)
A91: 46188 | B91: Lerma - Tres Marías | C91: 46189 | D91: Tandem Hamm | E91: =VLOOKUP(TablaObra5[[#This Row],[Equipo]],Catalogos!$I$4:$J$39,2,FALSE) | F91: 50 | G91: 28.3 | H91: =IFERROR(F91*G91,0) | I91: =VLOOKUP(TablaObra5[[#This Row],[Obra]],Catalogos!$B$3:$C$8,2,FALSE)
A92: 46188 | B92: Lerma - Tres Marías | C92: 46189 | D92: Perfiladora | E92: =VLOOKUP(TablaObra5[[#This Row],[Equipo]],Catalogos!$I$4:$J$39,2,FALSE) | F92: 250 | G92: 28.3 | H92: =IFERROR(F92*G92,0) | I92: =VLOOKUP(TablaObra5[[#This Row],[Obra]],Catalogos!$B$3:$C$8,2,FALSE)
A93: 46188 | B93: Lerma - Tres Marías | C93: 46189 | D93: Barredora | E93: =VLOOKUP(TablaObra5[[#This Row],[Equipo]],Catalogos!$I$4:$J$39,2,FALSE) | F93: 70 | G93: 28.3 | H93: =IFERROR(F93*G93,0) | I93: =VLOOKUP(TablaObra5[[#This Row],[Obra]],Catalogos!$B$3:$C$8,2,FALSE)
A94: 46188 | B94: Lerma - Tres Marías | C94: 46189 | D94: Retroexcavadora | E94: =VLOOKUP(TablaObra5[[#This Row],[Equipo]],Catalogos!$I$4:$J$39,2,FALSE) | F94: 50 | G94: 28.3 | H94: =IFERROR(F94*G94,0) | I94: =VLOOKUP(TablaObra5[[#This Row],[Obra]],Catalogos!$B$3:$C$8,2,FALSE)
A95: 46188 | B95: México-Toluca | C95: 46189 | D95: Perfiladora Wirgent | E95: =VLOOKUP(TablaObra5[[#This Row],[Equipo]],Catalogos!$I$4:$J$39,2,FALSE) | F95: 250 | G95: 28.3 | H95: =IFERROR(F95*G95,0) | I95: =VLOOKUP(TablaObra5[[#This Row],[Obra]],Catalogos!$B$3:$C$8,2,FALSE)
A96: 46188 | B96: México-Toluca | C96: 46189 | D96: Vogele Guion | E96: =VLOOKUP(TablaObra5[[#This Row],[Equipo]],Catalogos!$I$4:$J$39,2,FALSE) | F96: 200 | G96: 28.3 | H96: =IFERROR(F96*G96,0) | I96: =VLOOKUP(TablaObra5[[#This Row],[Obra]],Catalogos!$B$3:$C$8,2,FALSE)
A97: 46188 | B97: México-Toluca | C97: 46189 | D97: Limpieza | E97: =VLOOKUP(TablaObra5[[#This Row],[Equipo]],Catalogos!$I$4:$J$39,2,FALSE) | F97: 20 | G97: 28.3 | H97: =IFERROR(F97*G97,0) | I97: =VLOOKUP(TablaObra5[[#This Row],[Obra]],Catalogos!$B$3:$C$8,2,FALSE)
A98: 46188 | B98: México-Toluca | C98: 46189 | D98: Tandem Hamm | E98: =VLOOKUP(TablaObra5[[#This Row],[Equipo]],Catalogos!$I$4:$J$39,2,FALSE) | F98: 50 | G98: 28.3 | H98: =IFERROR(F98*G98,0) | I98: =VLOOKUP(TablaObra5[[#This Row],[Obra]],Catalogos!$B$3:$C$8,2,FALSE)
A99: 46188 | B99: México-Toluca | C99: 46189 | D99: Neuomatico | E99: =VLOOKUP(TablaObra5[[#This Row],[Equipo]],Catalogos!$I$4:$J$39,2,FALSE) | F99: 50 | G99: 28.3 | H99: =IFERROR(F99*G99,0) | I99: =VLOOKUP(TablaObra5[[#This Row],[Obra]],Catalogos!$B$3:$C$8,2,FALSE)
A100: 46188 | B100: México-Toluca | C100: 46189 | D100: Barredora Broce | E100: =VLOOKUP(TablaObra5[[#This Row],[Equipo]],Catalogos!$I$4:$J$39,2,FALSE) | F100: 40 | G100: 28.3 | H100: =IFERROR(F100*G100,0) | I100: =VLOOKUP(TablaObra5[[#This Row],[Obra]],Catalogos!$B$3:$C$8,2,FALSE)
... A153: 46192 | B153: México-Toluca | C153: 46192 | D153: Petrolizadora | E153: =VLOOKUP(TablaObra5[[#This Row],[Equipo]],Catalogos!$I$4:$J$39,2,FALSE) | F153: 50 | G153: 28.3 | H153: =IFERROR(F153*G153,0) | I153: =VLOOKUP(TablaObra5[[#This Row],[Obra]],Catalogos!$B$3:$C$8,2,FALSE)
E154: =VLOOKUP(TablaObra5[[#This Row],[Equipo]],Catalogos!$I$4:$J$39,2,FALSE) | G154: 28.3 | H154: =IFERROR(F154*G154,0) | I154: =VLOOKUP(TablaObra5[[#This Row],[Obra]],Catalogos!$B$3:$C$8,2,FALSE)
E155: =VLOOKUP(TablaObra5[[#This Row],[Equipo]],Catalogos!$I$4:$J$39,2,FALSE) | G155: 28.3 | H155: =IFERROR(F155*G155,0) | I155: =VLOOKUP(TablaObra5[[#This Row],[Obra]],Catalogos!$B$3:$C$8,2,FALSE)
E156: =VLOOKUP(TablaObra5[[#This Row],[Equipo]],Catalogos!$I$4:$J$39,2,FALSE) | G156: 28.3 | H156: =IFERROR(F156*G156,0) | I156: =VLOOKUP(TablaObra5[[#This Row],[Obra]],Catalogos!$B$3:$C$8,2,FALSE)
E157: =VLOOKUP(TablaObra5[[#This Row],[Equipo]],Catalogos!$I$4:$J$39,2,FALSE) | G157: 28.3 | H157: =IFERROR(F157*G157,0) | I157: =VLOOKUP(TablaObra5[[#This Row],[Obra]],Catalogos!$B$3:$C$8,2,FALSE)
E158: =VLOOKUP(TablaObra5[[#This Row],[Equipo]],Catalogos!$I$4:$J$39,2,FALSE) | G158: 28.3 | H158: =IFERROR(F158*G158,0) | I158: =VLOOKUP(TablaObra5[[#This Row],[Obra]],Catalogos!$B$3:$C$8,2,FALSE)
E159: =VLOOKUP(TablaObra5[[#This Row],[Equipo]],Catalogos!$I$4:$J$39,2,FALSE) | G159: 28.3 | H159: =IFERROR(F159*G159,0) | I159: =VLOOKUP(TablaObra5[[#This Row],[Obra]],Catalogos!$B$3:$C$8,2,FALSE)
E160: =VLOOKUP(TablaObra5[[#This Row],[Equipo]],Catalogos!$I$4:$J$39,2,FALSE) | G160: 28.3 | H160: =IFERROR(F160*G160,0) | I160: =VLOOKUP(TablaObra5[[#This Row],[Obra]],Catalogos!$B$3:$C$8,2,FALSE)
E161: =VLOOKUP(TablaObra5[[#This Row],[Equipo]],Catalogos!$I$4:$J$39,2,FALSE) | G161: 28.3 | H161: =IFERROR(F161*G161,0) | I161: =VLOOKUP(TablaObra5[[#This Row],[Obra]],Catalogos!$B$3:$C$8,2,FALSE)
E162: =VLOOKUP(TablaObra5[[#This Row],[Equipo]],Catalogos!$I$4:$J$39,2,FALSE) | G162: 28.3 | H162: =IFERROR(F162*G162,0) | I162: =VLOOKUP(TablaObra5[[#This Row],[Obra]],Catalogos!$B$3:$C$8,2,FALSE)
E163: =VLOOKUP(TablaObra5[[#This Row],[Equipo]],Catalogos!$I$4:$J$39,2,FALSE) | G163: 28.3 | H163: =IFERROR(F163*G163,0) | I163: =VLOOKUP(TablaObra5[[#This Row],[Obra]],Catalogos!$B$3:$C$8,2,FALSE)
E164: =VLOOKUP(TablaObra5[[#This Row],[Equipo]],Catalogos!$I$4:$J$39,2,FALSE) | G164: 28.3 | H164: =IFERROR(F164*G164,0) | I164: =VLOOKUP(TablaObra5[[#This Row],[Obra]],Catalogos!$B$3:$C$8,2,FALSE)
E165: =VLOOKUP(TablaObra5[[#This Row],[Equipo]],Catalogos!$I$4:$J$39,2,FALSE) | G165: 28.3 | H165: =IFERROR(F165*G165,0) | I165: =VLOOKUP(TablaObra5[[#This Row],[Obra]],Catalogos!$B$3:$C$8,2,FALSE)
... E306: =VLOOKUP(TablaObra5[[#This Row],[Equipo]],Catalogos!$I$4:$J$39,2,FALSE) | G306: 28.3 | H306: =IFERROR(F306*G306,0) | I306: =VLOOKUP(TablaObra5[[#This Row],[Obra]],Catalogos!$B$3:$C$8,2,FALSE)

Sheet Conciliacion
A1: CONCILIACIÓN SEMANAL / MENSUAL
A3: Concepto | B3: Litros
A4: Entradas a Pegaso | B4: =SUM(Captura_Pegaso!G5:G206)
A5: Salidas Pegaso a Marimba | B5: =SUMIF(Captura_Pegaso!B5:B206,"Salida a Marimba",Captura_Pegaso!H5:H206)
A6: Salidas Pegaso directo a Máquinas | B6: =SUMIF(Captura_Pegaso!B5:B206,"Salida Directa Máquina",Captura_Pegaso!H5:H206)
A7: Entradas registradas en Marimba | B7: =SUMIF(Captura_Marimba_M01!B5:B206,"Entrada desde Pegaso",Captura_Marimba_M01!F5:F206)
A8: Salidas Marimba a Obra | B8: =SUMIF(Captura_Marimba_M01!B5:B206,"Salida a Obra",Captura_Marimba_M01!G5:G206)
A9: Litros reconocidos por Obras | B9: =SUM(Captura_Obra!F5:F304)
A10: Diferencia Pegaso vs Marimba | B10: =B5-B7
A11: Diferencia Marimba vs Obra | B11: =B8-(B9-B6)
A12: Diferencia Total a Revisar | B12: =B10+B11
A14: Obra | B14: Litros Recibidos | C14: Costo | D14: % Consumo
A15: México-Toluca | B15: =SUMIF(Captura_Obra!B:B,A15,Captura_Obra!F:F) | C15: =SUMIF(Captura_Obra!B:B,A15,Captura_Obra!H:H) | D15: =IFERROR(B15/$B$21,0)
A16: Lerma - Tres Marías | B16: =SUMIF(Captura_Obra!B:B,A16,Captura_Obra!F:F) | C16: =SUMIF(Captura_Obra!B:B,A16,Captura_Obra!H:H) | D16: =IFERROR(B16/$B$21,0)
A17: Chamapa-Lechería | B17: =SUMIF(Captura_Obra!B:B,A17,Captura_Obra!F:F) | C17: =SUMIF(Captura_Obra!B:B,A17,Captura_Obra!H:H) | D17: =IFERROR(B17/$B$21,0)
A18: Bacheo Toluca | B18: =SUMIF(Captura_Obra!B:B,A18,Captura_Obra!F:F) | C18: =SUMIF(Captura_Obra!B:B,A18,Captura_Obra!H:H) | D18: =IFERROR(B18/$B$21,0)
A19: Planta Asfalto Pegaso | B19: =SUMIF(Captura_Obra!B:B,A19,Captura_Obra!F:F) | C19: =SUMIF(Captura_Obra!B:B,A19,Captura_Obra!H:H) | D19: =IFERROR(B19/$B$21,0)
A20: Planta Asflato Huixquilucan | B20: =SUMIF(Captura_Obra!B:B,A20,Captura_Obra!F:F) | C20: =SUMIF(Captura_Obra!B:B,A20,Captura_Obra!H:H) | D20: =IFERROR(B20/$B$21,0)
A21: TOTAL | B21: =SUM(B15:B20) | C21: =SUM(C15:C20) | D21: =SUM(D15:D20)
A23: Validación Corporativa
A24: Revisó Gobierno Corporativo | C24: Fecha | E24: Estatus | G24: Observaciones
E25: □ Correcto □ Observado □ Pendiente
A26: Firma

Sheet Catalogos
A1: CATÁLOGOS OFICIALES - CONTROL DE COMBUSTIBLE
K2: Obras Dropdown | L2: Semanas Dropdown
A3: Código Obra | B3: Obra | C3: Ingeniero | E3: Código | F3: Fuente / Origen | I3: Tipo de Equipo | J3: Económico
A4: MT | B4: México-Toluca | C4: Francisco Javier | E4: GAS | F4: Gasolinera Huixquilucan | I4: Fresadora | J4: FR-01 | K4: México-Toluca | L4: 46167
A5: L3M | B5: Lerma - Tres Marías | C5: Apolinar | E5: PEG | F5: Tanque Pegaso | I5: Compactador | J5: CP-01 | K5: Lerma - Tres Marías | L5: 46174
A6: NP | B6: No aplica | E6: PAP | F6: Planta Asfalto Pegaso | I6: Excavadora | J6: EX-01 | K6: Chamapa-Lechería | L6: 46181
A7: CL | B7: Chamapa-Lechería | C7: Francisco Javier | E7: M01 | F7: Marimba M-01 | I7: Retroexcavadora | J7: RT-01 | K7: Bacheo Toluca | L7: 46188
A8: BT | B8: Bacheo Toluca | C8: Diego Carreola | E8: DIR | F8: Carga directa | I8: Motoconformadora | J8: MG-01 | K8: Planta Asfalto Pegaso | L8: 46195
A9: PAP | B9: Planta Asfalto Pegaso | E9: PAH | F9: Planta Asfaltos | I9: Petrolizadora | J9: PT-01 | K9: Planta Asflato Huixquilucan | L9: 46202
A10: PAH | B10: Planta Asflato Huixquilucan | E10: ENT | F10: Entrada | I10: Pipa | J10: PP-01 | K10: Dragones | L10: 46209
B11: Dragones | E11: SD | F11: Salida | I11: Camión | J11: CM-01 | K11: Jalisco | L11: 46216
B12: Jalisco | I12: Perfiladora Wirgent | J12: PR-02 | K12: Todas | L12: 46223
I13: Perfiladora Cat-PM | J13: PR-03 | L13: 46230
I14: Barredora Broce | J14: BR-02 | L14: 46237
I15: Retroexcavadora Jonh Deere | J15: RT-02 | L15: 46244
I16: Buggy Trasnfer | J16: BG-01 | L16: 46251
I17: Cargador | J17: CR-01 | L17: 46258
I18: Vogel | J18: VG-01 | L18: 46265
I19: Perfiladora | J19: PR-01 | L19: 46272
I20: Barredora | J20: BR-01 | L20: 46279
I21: Neuomatico | J21: NM-01 | L21: 46286
I22: Vogele Guion | J22: VG-02 | L22: 46293
I23: Tandem Hamm | J23: TD-01 | L23: 46300
I24: Neuomatico Dynapac | J24: NM-02 | L24: 46307
... I33: PayLoder | J33: PL-01 | L33: 46370
I34: Otro | J34: OT-01
I35: Marimba | J35: MB-01
I36: Generador | J36: GR-01
I37: Criba Roja | J37: CR-01
I38: Tandem CAT | J38: TC-01
I39: Motoconformadora Rentada | J39: MGR-01
I40: Vibro Compactador | J40: VC-01

Sheet Formatos_Fisicos
A1: FORMATOS FÍSICOS PARA IMPRESIÓN Y FIRMA
A3: GC-COMB-001 BITÁCORA PEGASO
A4: Semana: | B4: Responsable: | C4: Existencia Inicial: | D4: Existencia Final Física: | E4: Fecha Entrega: | F4: Firma:
A6: Fecha | B6: Movimiento | C6: Origen/Destino | D6: Obra | E6: Equipo/Económico | F6: Entrada (L) | G6: Salida (L) | H6: Operador (firma) | I6: Ingeniero Responsable
A16: GC-COMB-002 BITÁCORA MARIMBA M-01
A17: Semana: | B17: Operador: | C17: Inventario Inicial: | D17: Inventario Final: | E17: Fecha Entrega: | F17: Firma:
A19: Fecha | B19: Movimiento | C19: Obra | D19: Equipo | E19: Económico | F19: Entrada (L) | G19: Salida (L) | H19: Observaciones
A29: GC-COMB-003 BITÁCORA DE OBRA
A30: Semana: | B30: Obra: | C30: Ingeniero: | D30: Fecha Entrega: | E30: Firma:
A32: Fecha | B32: Fuente | C32: Equipo | D32: Económico | E32: Litros Recibidos | F32: Actividad | G32: Incidencia | H32: Observaciones

Sheet Instrucciones
A1: PROCEDIMIENTO OPERATIVO GC-COMB-01
A3: 1 | B3: Gasolinera → Pegaso | C3: Vigilante registra entrada en GC-COMB-001 con factura/remisión y litros recibidos.
A4: 2 | B4: Pegaso → Marimba M-01 | C4: Vigilante registra salida en GC-COMB-001. Operador de Marimba registra entrada en GC-COMB-002.
A5: 3 | B5: Pegaso → Máquina | C5: Vigilante registra salida directa en GC-COMB-001. Ingeniero registra recepción en GC-COMB-003.
A6: 4 | B6: Marimba → Obras/Máquinas | C6: Operador registra cada suministro en GC-COMB-002. Ingeniero reconoce litros por obra en GC-COMB-003.
A7: 5 | B7: Obras actuales | C7: México-Toluca, Lerma - Tres Marías y Chamapa-Lechería.
A8: 6 | B8: Horómetro | C8: No es obligatorio porque no funciona en la mayoría de equipos. El control principal será por litros, obra, equipo, actividad e incidencia.
A9: 7 | B9: Costo | C9: Capturar costo/litro en cada registro para obtener costo por obra y costo total semanal.
A10: 8 | B10: Cierre semanal | C10: Todos entregan bitácoras físicas firmadas. Gobierno Corporativo captura y revisa conciliación.
A11: 9 | B11: Alertas | C11: Si la diferencia total es distinta de cero, revisar Pegaso vs Marimba y Marimba/Pegaso vs Obra.
A12: 10 | B12: Reunión lunes | C12: Usar Dashboard para mostrar consumo, costo y diferencias al Ing. Pepe.
A14: Responsables | C14: Vigilante Pegaso = inventario / Operador Marimba = distribución / Ingeniero = validación de obra / Gobierno Corporativo = conciliación y pago.
A16: Documentación soporte | C16: Factura, remisión, bitácoras físicas firmadas, evidencias de incidencias cuando existan.
A18: Nota | C18: Este archivo no usa macros. Funciona con fórmulas, catálogos y validaciones para evitar dependencia de VBA.
