Workbook

Sheet Dashboard
A1: DASHBOARD EJECUTIVO DE CONTROL DE COMBUSTIBLE | GRUPO TRUJANO
A3: FILTROS DEL DASHBOARD (Celdas en amarillo editables en Excel) | E3: ESTADO DE LA CONCILIACIÓN SEMANAL
B4: Obra Seleccionada: | C4: Lerma - Tres Marías | E4: =IF(I28=0, "🟢 TODO COINCIDE (0 L)", "🔴 DISCREPANCIA: " & I28 & " L")
B5: Fecha Inicio (Lunes): | C5: 46188
B6: Fecha Fin (Rango): | C6: 46188
B7: Precio Diésel ($/L): | C7: 28.3
B8: Período Resumen: | C8: Semana Seleccionada
A10: COMPARATIVA: SOLICITADO (PETICIONES) VS ENTREGADO EN OBRA
A11: Día | B11: Fecha | C11: Lts Solicitados | D11: Lts Recibidos Obra | E11: Dif. Litros (Obra-Sol) | F11: Costo Solicitado | G11: Costo Real Obra | H11: Dif. Costo (Real-Sol)
A12: Lunes | B12: =C$5 | C12: =IF(C$4="Todas", SUMIFS(Solicitudes!F:F, Solicitudes!C:C, B12), SUMIFS(Solicitudes!F:F, Solicitudes!B:B, C$4, Solicitudes!C:C, B12)) | D12: =IF(C$4="Jalisco", SUMIFS(Captura_Jalisco!G:G, Captura_Jalisco!A:A, B12, Captura_Jalisco!B:B, "Salida"), IF(C$4="Todas", SUMIFS(Captura_Obra!F:F, Captura_Obra!A:A, B12) + SUMIFS(Captura_Jalisco!G:G, Captura_Jalisco!A:A, B12, Captura_Jalisco!B:B, "Salida"), SUMIFS(Captura_Obra!F:F, Captura_Obra!B:B, C$4, Captura_Obra!A:A, B12))) | E12: =D12-C12 | F12: =C12*C$7 | G12: =D12*C$7 | H12: =G12-F12
A13: Martes | B13: =B12+1 | C13: =IF(C$4="Todas", SUMIFS(Solicitudes!F:F, Solicitudes!C:C, B13), SUMIFS(Solicitudes!F:F, Solicitudes!B:B, C$4, Solicitudes!C:C, B13)) | D13: =IF(C$4="Jalisco", SUMIFS(Captura_Jalisco!G:G, Captura_Jalisco!A:A, B13, Captura_Jalisco!B:B, "Salida"), IF(C$4="Todas", SUMIFS(Captura_Obra!F:F, Captura_Obra!A:A, B13) + SUMIFS(Captura_Jalisco!G:G, Captura_Jalisco!A:A, B13, Captura_Jalisco!B:B, "Salida"), SUMIFS(Captura_Obra!F:F, Captura_Obra!B:B, C$4, Captura_Obra!A:A, B13))) | E13: =D13-C13 | F13: =C13*C$7 | G13: =D13*C$7 | H13: =G13-F13
A14: Miércoles | B14: =B13+1 | C14: =IF(C$4="Todas", SUMIFS(Solicitudes!F:F, Solicitudes!C:C, B14), SUMIFS(Solicitudes!F:F, Solicitudes!B:B, C$4, Solicitudes!C:C, B14)) | D14: =IF(C$4="Jalisco", SUMIFS(Captura_Jalisco!G:G, Captura_Jalisco!A:A, B14, Captura_Jalisco!B:B, "Salida"), IF(C$4="Todas", SUMIFS(Captura_Obra!F:F, Captura_Obra!A:A, B14) + SUMIFS(Captura_Jalisco!G:G, Captura_Jalisco!A:A, B14, Captura_Jalisco!B:B, "Salida"), SUMIFS(Captura_Obra!F:F, Captura_Obra!B:B, C$4, Captura_Obra!A:A, B14))) | E14: =D14-C14 | F14: =C14*C$7 | G14: =D14*C$7 | H14: =G14-F14
A15: Jueves | B15: =B14+1 | C15: =IF(C$4="Todas", SUMIFS(Solicitudes!F:F, Solicitudes!C:C, B15), SUMIFS(Solicitudes!F:F, Solicitudes!B:B, C$4, Solicitudes!C:C, B15)) | D15: =IF(C$4="Jalisco", SUMIFS(Captura_Jalisco!G:G, Captura_Jalisco!A:A, B15, Captura_Jalisco!B:B, "Salida"), IF(C$4="Todas", SUMIFS(Captura_Obra!F:F, Captura_Obra!A:A, B15) + SUMIFS(Captura_Jalisco!G:G, Captura_Jalisco!A:A, B15, Captura_Jalisco!B:B, "Salida"), SUMIFS(Captura_Obra!F:F, Captura_Obra!B:B, C$4, Captura_Obra!A:A, B15))) | E15: =D15-C15 | F15: =C15*C$7 | G15: =D15*C$7 | H15: =G15-F15
A16: Viernes | B16: =B15+1 | C16: =IF(C$4="Todas", SUMIFS(Solicitudes!F:F, Solicitudes!C:C, B16), SUMIFS(Solicitudes!F:F, Solicitudes!B:B, C$4, Solicitudes!C:C, B16)) | D16: =IF(C$4="Jalisco", SUMIFS(Captura_Jalisco!G:G, Captura_Jalisco!A:A, B16, Captura_Jalisco!B:B, "Salida"), IF(C$4="Todas", SUMIFS(Captura_Obra!F:F, Captura_Obra!A:A, B16) + SUMIFS(Captura_Jalisco!G:G, Captura_Jalisco!A:A, B16, Captura_Jalisco!B:B, "Salida"), SUMIFS(Captura_Obra!F:F, Captura_Obra!B:B, C$4, Captura_Obra!A:A, B16))) | E16: =D16-C16 | F16: =C16*C$7 | G16: =D16*C$7 | H16: =G16-F16
A17: Sábado | B17: =B16+1 | C17: =IF(C$4="Todas", SUMIFS(Solicitudes!F:F, Solicitudes!C:C, B17), SUMIFS(Solicitudes!F:F, Solicitudes!B:B, C$4, Solicitudes!C:C, B17)) | D17: =IF(C$4="Jalisco", SUMIFS(Captura_Jalisco!G:G, Captura_Jalisco!A:A, B17, Captura_Jalisco!B:B, "Salida"), IF(C$4="Todas", SUMIFS(Captura_Obra!F:F, Captura_Obra!A:A, B17) + SUMIFS(Captura_Jalisco!G:G, Captura_Jalisco!A:A, B17, Captura_Jalisco!B:B, "Salida"), SUMIFS(Captura_Obra!F:F, Captura_Obra!B:B, C$4, Captura_Obra!A:A, B17))) | E17: =D17-C17 | F17: =C17*C$7 | G17: =D17*C$7 | H17: =G17-F17
A18: TOTAL SEMANAL | C18: =SUM(C12:C17) | D18: =SUM(D12:D17) | E18: =SUM(E12:E17) | F18: =SUM(F12:F17) | G18: =SUM(G12:G17) | H18: =SUM(H12:H17)
A20: CONCILIACIÓN FÍSICA Y DISCREPANCIAS (OBRA VS MARIMBA Y PEGASO)
A21: Día | B21: Fecha | C21: Obra Recibió (M) | D21: Marimba Despachó | E21: Dif. Marimba | F21: Obra Recibió (P) | G21: Pegaso Despachó | H21: Dif. Pegaso | I21: Dif. Total (L) | J21: Observaciones / Justificación
A22: Lunes | B22: =B12 | C22: =IF(C$4="Todas", SUMIFS(Captura_Obra!F:F, Captura_Obra!A:A, B22, Captura_Obra!C:C, "Marimba M-01"), SUMIFS(Captura_Obra!F:F, Captura_Obra!B:B, C$4, Captura_Obra!A:A, B22, Captura_Obra!C:C, "Marimba M-01")) | D22: =IF(C$4="Todas", SUMIFS(Captura_Marimba_M01!G:G, Captura_Marimba_M01!A:A, B22, Captura_Marimba_M01!B:B, "Salida"), SUMIFS(Captura_Marimba_M01!G:G, Captura_Marimba_M01!C:C, C$4, Captura_Marimba_M01!A:A, B22, Captura_Marimba_M01!B:B, "Salida")) | E22: =C22-D22 | F22: =IF(C$4="Todas", SUMIFS(Captura_Obra!F:F, Captura_Obra!A:A, B22, Captura_Obra!C:C, "Pegaso Directo"), SUMIFS(Captura_Obra!F:F, Captura_Obra!B:B, C$4, Captura_Obra!A:A, B22, Captura_Obra!C:C, "Pegaso Directo")) | G22: =IF(C$4="Todas", SUMIFS(Captura_Pegaso!H:H, Captura_Pegaso!A:A, B22, Captura_Pegaso!B:B, "Salida"), SUMIFS(Captura_Pegaso!H:H, Captura_Pegaso!D:D, C$4, Captura_Pegaso!A:A, B22, Captura_Pegaso!B:B, "Salida")) | H22: =F22-G22 | I22: =E22+H22
A23: Martes | B23: =B13 | C23: =IF(C$4="Todas", SUMIFS(Captura_Obra!F:F, Captura_Obra!A:A, B23, Captura_Obra!C:C, "Marimba M-01"), SUMIFS(Captura_Obra!F:F, Captura_Obra!B:B, C$4, Captura_Obra!A:A, B23, Captura_Obra!C:C, "Marimba M-01")) | D23: =IF(C$4="Todas", SUMIFS(Captura_Marimba_M01!G:G, Captura_Marimba_M01!A:A, B23, Captura_Marimba_M01!B:B, "Salida"), SUMIFS(Captura_Marimba_M01!G:G, Captura_Marimba_M01!C:C, C$4, Captura_Marimba_M01!A:A, B23, Captura_Marimba_M01!B:B, "Salida")) | E23: =C23-D23 | F23: =IF(C$4="Todas", SUMIFS(Captura_Obra!F:F, Captura_Obra!A:A, B23, Captura_Obra!C:C, "Pegaso Directo"), SUMIFS(Captura_Obra!F:F, Captura_Obra!B:B, C$4, Captura_Obra!A:A, B23, Captura_Obra!C:C, "Pegaso Directo")) | G23: =IF(C$4="Todas", SUMIFS(Captura_Pegaso!H:H, Captura_Pegaso!A:A, B23, Captura_Pegaso!B:B, "Salida"), SUMIFS(Captura_Pegaso!H:H, Captura_Pegaso!D:D, C$4, Captura_Pegaso!A:A, B23, Captura_Pegaso!B:B, "Salida")) | H23: =F23-G23 | I23: =E23+H23
A24: Miércoles | B24: =B14 | C24: =IF(C$4="Todas", SUMIFS(Captura_Obra!F:F, Captura_Obra!A:A, B24, Captura_Obra!C:C, "Marimba M-01"), SUMIFS(Captura_Obra!F:F, Captura_Obra!B:B, C$4, Captura_Obra!A:A, B24, Captura_Obra!C:C, "Marimba M-01")) | D24: =IF(C$4="Todas", SUMIFS(Captura_Marimba_M01!G:G, Captura_Marimba_M01!A:A, B24, Captura_Marimba_M01!B:B, "Salida"), SUMIFS(Captura_Marimba_M01!G:G, Captura_Marimba_M01!C:C, C$4, Captura_Marimba_M01!A:A, B24, Captura_Marimba_M01!B:B, "Salida")) | E24: =C24-D24 | F24: =IF(C$4="Todas", SUMIFS(Captura_Obra!F:F, Captura_Obra!A:A, B24, Captura_Obra!C:C, "Pegaso Directo"), SUMIFS(Captura_Obra!F:F, Captura_Obra!B:B, C$4, Captura_Obra!A:A, B24, Captura_Obra!C:C, "Pegaso Directo")) | G24: =IF(C$4="Todas", SUMIFS(Captura_Pegaso!H:H, Captura_Pegaso!A:A, B24, Captura_Pegaso!B:B, "Salida"), SUMIFS(Captura_Pegaso!H:H, Captura_Pegaso!D:D, C$4, Captura_Pegaso!A:A, B24, Captura_Pegaso!B:B, "Salida")) | H24: =F24-G24 | I24: =E24+H24
A25: Jueves | B25: =B15 | C25: =IF(C$4="Todas", SUMIFS(Captura_Obra!F:F, Captura_Obra!A:A, B25, Captura_Obra!C:C, "Marimba M-01"), SUMIFS(Captura_Obra!F:F, Captura_Obra!B:B, C$4, Captura_Obra!A:A, B25, Captura_Obra!C:C, "Marimba M-01")) | D25: =IF(C$4="Todas", SUMIFS(Captura_Marimba_M01!G:G, Captura_Marimba_M01!A:A, B25, Captura_Marimba_M01!B:B, "Salida"), SUMIFS(Captura_Marimba_M01!G:G, Captura_Marimba_M01!C:C, C$4, Captura_Marimba_M01!A:A, B25, Captura_Marimba_M01!B:B, "Salida")) | E25: =C25-D25 | F25: =IF(C$4="Todas", SUMIFS(Captura_Obra!F:F, Captura_Obra!A:A, B25, Captura_Obra!C:C, "Pegaso Directo"), SUMIFS(Captura_Obra!F:F, Captura_Obra!B:B, C$4, Captura_Obra!A:A, B25, Captura_Obra!C:C, "Pegaso Directo")) | G25: =IF(C$4="Todas", SUMIFS(Captura_Pegaso!H:H, Captura_Pegaso!A:A, B25, Captura_Pegaso!B:B, "Salida"), SUMIFS(Captura_Pegaso!H:H, Captura_Pegaso!D:D, C$4, Captura_Pegaso!A:A, B25, Captura_Pegaso!B:B, "Salida")) | H25: =F25-G25 | I25: =E25+H25
A26: Viernes | B26: =B16 | C26: =IF(C$4="Todas", SUMIFS(Captura_Obra!F:F, Captura_Obra!A:A, B26, Captura_Obra!C:C, "Marimba M-01"), SUMIFS(Captura_Obra!F:F, Captura_Obra!B:B, C$4, Captura_Obra!A:A, B26, Captura_Obra!C:C, "Marimba M-01")) | D26: =IF(C$4="Todas", SUMIFS(Captura_Marimba_M01!G:G, Captura_Marimba_M01!A:A, B26, Captura_Marimba_M01!B:B, "Salida"), SUMIFS(Captura_Marimba_M01!G:G, Captura_Marimba_M01!C:C, C$4, Captura_Marimba_M01!A:A, B26, Captura_Marimba_M01!B:B, "Salida")) | E26: =C26-D26 | F26: =IF(C$4="Todas", SUMIFS(Captura_Obra!F:F, Captura_Obra!A:A, B26, Captura_Obra!C:C, "Pegaso Directo"), SUMIFS(Captura_Obra!F:F, Captura_Obra!B:B, C$4, Captura_Obra!A:A, B26, Captura_Obra!C:C, "Pegaso Directo")) | G26: =IF(C$4="Todas", SUMIFS(Captura_Pegaso!H:H, Captura_Pegaso!A:A, B26, Captura_Pegaso!B:B, "Salida"), SUMIFS(Captura_Pegaso!H:H, Captura_Pegaso!D:D, C$4, Captura_Pegaso!A:A, B26, Captura_Pegaso!B:B, "Salida")) | H26: =F26-G26 | I26: =E26+H26
A27: Sábado | B27: =B17 | C27: =IF(C$4="Todas", SUMIFS(Captura_Obra!F:F, Captura_Obra!A:A, B27, Captura_Obra!C:C, "Marimba M-01"), SUMIFS(Captura_Obra!F:F, Captura_Obra!B:B, C$4, Captura_Obra!A:A, B27, Captura_Obra!C:C, "Marimba M-01")) | D27: =IF(C$4="Todas", SUMIFS(Captura_Marimba_M01!G:G, Captura_Marimba_M01!A:A, B27, Captura_Marimba_M01!B:B, "Salida"), SUMIFS(Captura_Marimba_M01!G:G, Captura_Marimba_M01!C:C, C$4, Captura_Marimba_M01!A:A, B27, Captura_Marimba_M01!B:B, "Salida")) | E27: =C27-D27 | F27: =IF(C$4="Todas", SUMIFS(Captura_Obra!F:F, Captura_Obra!A:A, B27, Captura_Obra!C:C, "Pegaso Directo"), SUMIFS(Captura_Obra!F:F, Captura_Obra!B:B, C$4, Captura_Obra!A:A, B27, Captura_Obra!C:C, "Pegaso Directo")) | G27: =IF(C$4="Todas", SUMIFS(Captura_Pegaso!H:H, Captura_Pegaso!A:A, B27, Captura_Pegaso!B:B, "Salida"), SUMIFS(Captura_Pegaso!H:H, Captura_Pegaso!D:D, C$4, Captura_Pegaso!A:A, B27, Captura_Pegaso!B:B, "Salida")) | H27: =F27-G27 | I27: =E27+H27
A28: TOTAL CONCILIADO | C28: =SUM(C22:C27) | D28: =SUM(D22:D27) | E28: =SUM(E22:E27) | F28: =SUM(F22:F27) | G28: =SUM(G22:G27) | H28: =SUM(H22:H27) | I28: =SUM(I22:I27)
Q30: ="SOLICITUDES DE DISEL DIARIAS Y SEMANALES POR OBRA (SEMANA " & YEAR(C5) & "-" & TEXT(MONTH(C5),"00") & "-" & TEXT(DAY(C5),"00") & ")"
A31: RESUMEN ACUMULADO POR OBRA / PERÍODO SELECCIONADO | Q31: Obra | R31: Solicitante | S31: Lunes | U31: Martes | W31: Miércoles | Y31: Jueves | AA31: Viernes | AC31: Sábado | AE31: Total Semanal Solicitado | AF31: Total Seamanal Autorizado
A32: Obra | B32: Total Litros Suministrados | C32: Costo Total Acumulado | S32: Solicitado | T32: Autorizado | U32: Solicitado | V32: Autorizado | W32: Solicitado | X32: Autorizado | Y32: Solicitado | Z32: Autorizado | AA32: Solicitado | AB32: Autorizado | AC32: Solicitado | AD32: Autorizado
A33: México-Toluca | B33: =IF(C$8="Acumulado Histórico", SUMIFS(Captura_Obra!F:F, Captura_Obra!B:B, A33), IF(C$8="Rango de Fechas", SUMIFS(Captura_Obra!F:F, Captura_Obra!B:B, A33, Captura_Obra!A:A, ">="&C$5, Captura_Obra!A:A, "<="&(C$6+5)), SUMIFS(Captura_Obra!F:F, Captura_Obra!B:B, A33, Captura_Obra!A:A, ">="&C$5, Captura_Obra!A:A, "<="&(C$5+5)))) | C33: =B33*C$7 | P33: m | Q33: =A33 | R33: =VLOOKUP(Q33,Catalogos!$B$4:$C$18,2,FALSE) | S33: =SUMIFS(Solicitudes!$F:$F, Solicitudes!$B:$B, $Q33, Solicitudes!$C:$C, $B$12) | T33: 550 | U33: =SUMIFS(Solicitudes!$F:$F, Solicitudes!$B:$B, $Q33, Solicitudes!$C:$C, $B$13) | V33: 550 | W33: =SUMIFS(Solicitudes!$F:$F, Solicitudes!$B:$B, $Q33, Solicitudes!$C:$C, $B$14) | X33: 550 | Y33: =SUMIFS(Solicitudes!$F:$F, Solicitudes!$B:$B, $Q33, Solicitudes!$C:$C, $B$15) | Z33: 550 | AA33: =SUMIFS(Solicitudes!$F:$F, Solicitudes!$B:$B, $Q33, Solicitudes!$C:$C, $B$16) | AB33: 550 | AC33: =SUMIFS(Solicitudes!$F:$F, Solicitudes!$B:$B, $Q33, Solicitudes!$C:$C, $B$17) | AD33: 0 | AE33: =SUM(S33,U33,W33,Y33,AA33,AC33,) | AF33: =SUM(T33,V33,X33,Z33,AB33,AD33)
A34: Lerma - Tres Marías | B34: =IF(C$8="Acumulado Histórico", SUMIFS(Captura_Obra!F:F, Captura_Obra!B:B, A34), IF(C$8="Rango de Fechas", SUMIFS(Captura_Obra!F:F, Captura_Obra!B:B, A34, Captura_Obra!A:A, ">="&C$5, Captura_Obra!A:A, "<="&(C$6+5)), SUMIFS(Captura_Obra!F:F, Captura_Obra!B:B, A34, Captura_Obra!A:A, ">="&C$5, Captura_Obra!A:A, "<="&(C$5+5)))) | C34: =B34*C$7 | P34: p | Q34: =A34 | R34: =VLOOKUP(Q34,Catalogos!$B$4:$C$18,2,FALSE) | S34: =SUMIFS(Solicitudes!$F:$F, Solicitudes!$B:$B, $Q34, Solicitudes!$C:$C, $B$12) | T34: 400 | U34: =SUMIFS(Solicitudes!$F:$F, Solicitudes!$B:$B, $Q34, Solicitudes!$C:$C, $B$13) | V34: 400 | W34: =SUMIFS(Solicitudes!$F:$F, Solicitudes!$B:$B, $Q34, Solicitudes!$C:$C, $B$14) | X34: 400 | Y34: =SUMIFS(Solicitudes!$F:$F, Solicitudes!$B:$B, $Q34, Solicitudes!$C:$C, $B$15) | Z34: 400 | AA34: =SUMIFS(Solicitudes!$F:$F, Solicitudes!$B:$B, $Q34, Solicitudes!$C:$C, $B$16) | AB34: 400 | AC34: =SUMIFS(Solicitudes!$F:$F, Solicitudes!$B:$B, $Q34, Solicitudes!$C:$C, $B$17) | AD34: =SUMIFS(Solicitudes!$F:$F, Solicitudes!$B:$B, $Q34, Solicitudes!$C:$C, ($B$17+1)) | AE34: =SUM(S34,U34,W34,Y34,AA34,AC34,) | AF34: =SUM(T34,V34,X34,Z34,AB34,AD34)
A35: Chamapa-Lechería | B35: =IF(C$8="Acumulado Histórico", SUMIFS(Captura_Obra!F:F, Captura_Obra!B:B, A35), IF(C$8="Rango de Fechas", SUMIFS(Captura_Obra!F:F, Captura_Obra!B:B, A35, Captura_Obra!A:A, ">="&C$5, Captura_Obra!A:A, "<="&(C$6+5)), SUMIFS(Captura_Obra!F:F, Captura_Obra!B:B, A35, Captura_Obra!A:A, ">="&C$5, Captura_Obra!A:A, "<="&(C$5+5)))) | C35: =B35*C$7 | P35: p | Q35: =A36 | R35: =VLOOKUP(Q35,Catalogos!$B$4:$C$18,2,FALSE) | S35: =SUMIFS(Solicitudes!$F:$F, Solicitudes!$B:$B, $Q35, Solicitudes!$C:$C, $B$12) | T35: 100 | U35: =SUMIFS(Solicitudes!$F:$F, Solicitudes!$B:$B, $Q35, Solicitudes!$C:$C, $B$13) | V35: 100 | W35: =SUMIFS(Solicitudes!$F:$F, Solicitudes!$B:$B, $Q35, Solicitudes!$C:$C, $B$14) | X35: 100 | Y35: =SUMIFS(Solicitudes!$F:$F, Solicitudes!$B:$B, $Q35, Solicitudes!$C:$C, $B$15) | Z35: 100 | AA35: =SUMIFS(Solicitudes!$F:$F, Solicitudes!$B:$B, $Q35, Solicitudes!$C:$C, $B$16) | AB35: 100 | AC35: =SUMIFS(Solicitudes!$F:$F, Solicitudes!$B:$B, $Q35, Solicitudes!$C:$C, $B$17) | AD35: =SUMIFS(Solicitudes!$F:$F, Solicitudes!$B:$B, $Q35, Solicitudes!$C:$C, ($B$17+1)) | AE35: =SUM(S35,U35,W35,Y35,AA35,AC35,) | AF35: =SUM(T35,V35,X35,Z35,AB35,AD35)
A36: Bacheo Toluca | B36: =IF(C$8="Acumulado Histórico", SUMIFS(Captura_Obra!F:F, Captura_Obra!B:B, A36), IF(C$8="Rango de Fechas", SUMIFS(Captura_Obra!F:F, Captura_Obra!B:B, A36, Captura_Obra!A:A, ">="&C$5, Captura_Obra!A:A, "<="&(C$6+5)), SUMIFS(Captura_Obra!F:F, Captura_Obra!B:B, A36, Captura_Obra!A:A, ">="&C$5, Captura_Obra!A:A, "<="&(C$5+5)))) | C36: =B36*C$7 | P36: p | Q36: =A37 | R36: =VLOOKUP(Q36,Catalogos!$B$4:$C$18,2,FALSE) | S36: =SUMIFS(Solicitudes!$F:$F, Solicitudes!$B:$B, $Q36, Solicitudes!$C:$C, $B$12) | T36: 0 | U36: =SUMIFS(Solicitudes!$F:$F, Solicitudes!$B:$B, $Q36, Solicitudes!$C:$C, $B$13) | V36: 300 | W36: =SUMIFS(Solicitudes!$F:$F, Solicitudes!$B:$B, $Q36, Solicitudes!$C:$C, $B$14) | X36: 1000 | Y36: =SUMIFS(Solicitudes!$F:$F, Solicitudes!$B:$B, $Q36, Solicitudes!$C:$C, $B$15) | Z36: 300 | AA36: =SUMIFS(Solicitudes!$F:$F, Solicitudes!$B:$B, $Q36, Solicitudes!$C:$C, $B$16) | AB36: 0 | AC36: =SUMIFS(Solicitudes!$F:$F, Solicitudes!$B:$B, $Q36, Solicitudes!$C:$C, $B$17) | AD36: =SUMIFS(Solicitudes!$F:$F, Solicitudes!$B:$B, $Q36, Solicitudes!$C:$C, ($B$17+1)) | AE36: =SUM(S36,U36,W36,Y36,AA36,AC36,) | AF36: =SUM(T36,V36,X36,Z36,AB36,AD36)
A37: Planta Asfalto Pegaso | B37: =IF(C$8="Acumulado Histórico", SUMIFS(Captura_Obra!F:F, Captura_Obra!B:B, A37), IF(C$8="Rango de Fechas", SUMIFS(Captura_Obra!F:F, Captura_Obra!B:B, A37, Captura_Obra!A:A, ">="&C$5, Captura_Obra!A:A, "<="&(C$6+5)), SUMIFS(Captura_Obra!F:F, Captura_Obra!B:B, A37, Captura_Obra!A:A, ">="&C$5, Captura_Obra!A:A, "<="&(C$5+5)))) | C37: =B37*C$7 | P37: h | Q37: =A38 | R37: =VLOOKUP(Q37,Catalogos!$B$4:$C$18,2,FALSE) | S37: =SUMIFS(Solicitudes!$F:$F, Solicitudes!$B:$B, $Q37, Solicitudes!$C:$C, $B$12) | T37: 500 | U37: =SUMIFS(Solicitudes!$F:$F, Solicitudes!$B:$B, $Q37, Solicitudes!$C:$C, $B$13) | V37: 500 | W37: =SUMIFS(Solicitudes!$F:$F, Solicitudes!$B:$B, $Q37, Solicitudes!$C:$C, $B$14) | X37: 500 | Y37: =SUMIFS(Solicitudes!$F:$F, Solicitudes!$B:$B, $Q37, Solicitudes!$C:$C, $B$15) | Z37: 500 | AA37: =SUMIFS(Solicitudes!$F:$F, Solicitudes!$B:$B, $Q37, Solicitudes!$C:$C, $B$16) | AB37: 500 | AC37: =SUMIFS(Solicitudes!$F:$F, Solicitudes!$B:$B, $Q37, Solicitudes!$C:$C, $B$17) | AD37: =SUMIFS(Solicitudes!$F:$F, Solicitudes!$B:$B, $Q37, Solicitudes!$C:$C, ($B$17+1)) | AE37: =SUM(S37,U37,W37,Y37,AA37,AC37,) | AF37: =SUM(T37,V37,X37,Z37,AB37,AD37)
A38: Planta Asflato Huixquilucan | B38: =IF(C$8="Acumulado Histórico", SUMIFS(Captura_Obra!F:F, Captura_Obra!B:B, A38), IF(C$8="Rango de Fechas", SUMIFS(Captura_Obra!F:F, Captura_Obra!B:B, A38, Captura_Obra!A:A, ">="&C$5, Captura_Obra!A:A, "<="&(C$6+5)), SUMIFS(Captura_Obra!F:F, Captura_Obra!B:B, A38, Captura_Obra!A:A, ">="&C$5, Captura_Obra!A:A, "<="&(C$5+5)))) | C38: =B38*C$7 | Q38: =A41 | S38: =SUM(S33:S37) | T38: =SUM(T33:T37) | U38: =SUM(U33:U37) | V38: =SUM(V33:V37) | W38: =SUM(W33:W37) | X38: =SUM(X33:X37) | Y38: =SUM(Y33:Y37) | Z38: =SUM(Z33:Z37) | ... AE38: =SUM(AE33:AE37) | AF38: =SUM(T38,V38,X38,Z38,AB38,AD38)
A39: Dragones | B39: =IF(C$8="Acumulado Histórico", SUMIFS(Captura_Obra!F:F, Captura_Obra!B:B, A39), IF(C$8="Rango de Fechas", SUMIFS(Captura_Obra!F:F, Captura_Obra!B:B, A39, Captura_Obra!A:A, ">="&C$5, Captura_Obra!A:A, "<="&(C$6+5)), SUMIFS(Captura_Obra!F:F, Captura_Obra!B:B, A39, Captura_Obra!A:A, ">="&C$5, Captura_Obra!A:A, "<="&(C$5+5)))) | C39: =B39*C$7
A40: Jalisco | B40: =IF(C$8="Acumulado Histórico", SUMIFS(Captura_Jalisco!G:G, Captura_Jalisco!B:B, "Salida"), IF(C$8="Rango de Fechas", SUMIFS(Captura_Jalisco!G:G, Captura_Jalisco!B:B, "Salida", Captura_Jalisco!A:A, ">="&C$5, Captura_Jalisco!A:A, "<="&(C$6+5)), SUMIFS(Captura_Jalisco!G:G, Captura_Jalisco!B:B, "Salida", Captura_Jalisco!A:A, ">="&C$5, Captura_Jalisco!A:A, "<="&(C$5+5)))) | C40: =B40*C$7
A41: TOTAL GENERAL | B41: =SUM(B33:B40) | C41: =SUM(C33:C40)
A43: RESUMEN DE CONSUMO SEMANAL POR OBRA (DETALLE HISTÓRICO POR SEMANA)
B44: Obra (Tabla Semanal): | C44: Todas
B45: Precio Diésel ($/L): | C45: 27
A47: Semana (Lunes) | B47: Saldo Inicial (Vales) | C47: Litros Despachados | D47: Costo/L ($) | E47: Costo Combustible ($) | F47: Gasolina | G47: Saldo Final (Vales) | H47: Ajuste semanal | I47: Litros de Disel Acumulado
A48: 46167 | B48: =IF(OR(C$44="Jalisco", C$44="Todas"), Captura_Jalisco!K5, "") | C48: =IF(C$44="Jalisco", SUMIFS(Captura_Jalisco!G:G, Captura_Jalisco!B:B, "Salida", Captura_Jalisco!A:A, ">="&A48, Captura_Jalisco!A:A, "<="&(A48+5)), IF(C$44="Todas", SUMIFS(Captura_Obra!F:F, Captura_Obra!A:A, ">="&A48, Captura_Obra!A:A, "<="&(A48+5)) + SUMIFS(Captura_Jalisco!G:G, Captura_Jalisco!B:B, "Salida", Captura_Jalisco!A:A, ">="&A48, Captura_Jalisco!A:A, "<="&(A48+5)), SUMIFS(Captura_Obra!F:F, Captura_Obra!B:B, C$44, Captura_Obra!A:A, ">="&A48, Captura_Obra!A:A, "<="&(A48+5)))) | D48: =C$45 | E48: =C48*D48 | F48: =IF(OR(C$44="Jalisco", C$44="Todas"), SUMIFS(Captura_Jalisco!$N$5:$N$250, Captura_Jalisco!$A$5:$A$250, ">="&A48, Captura_Jalisco!$A$5:$A$250, "<="&(A48+5)), 0) | G48: =IF(OR(C$44="Jalisco", C$44="Todas"), B48-E48-F48, "") | H48: =IF(OR(C$44="Jalisco", C$44="Todas"), SUMIFS(Captura_Jalisco!$M$5:$M$250, Captura_Jalisco!$A$5:$A$250, ">="&A48, Captura_Jalisco!$A$5:$A$250, "<="&(A48+5)), 0) | I48: =C48
A49: 46174 | B49: =IF(OR(C$44="Jalisco", C$44="Todas"), G48+H48, "") | C49: =IF(C$44="Jalisco", SUMIFS(Captura_Jalisco!G:G, Captura_Jalisco!B:B, "Salida", Captura_Jalisco!A:A, ">="&A49, Captura_Jalisco!A:A, "<="&(A49+5)), IF(C$44="Todas", SUMIFS(Captura_Obra!F:F, Captura_Obra!A:A, ">="&A49, Captura_Obra!A:A, "<="&(A49+5)) + SUMIFS(Captura_Jalisco!G:G, Captura_Jalisco!B:B, "Salida", Captura_Jalisco!A:A, ">="&A49, Captura_Jalisco!A:A, "<="&(A49+5)), SUMIFS(Captura_Obra!F:F, Captura_Obra!B:B, C$44, Captura_Obra!A:A, ">="&A49, Captura_Obra!A:A, "<="&(A49+5)))) | D49: =C$45 | E49: =C49*D49 | F49: =IF(OR(C$44="Jalisco", C$44="Todas"), SUMIFS(Captura_Jalisco!$N$5:$N$250, Captura_Jalisco!$A$5:$A$250, ">="&A49, Captura_Jalisco!$A$5:$A$250, "<="&(A49+5)), 0) | G49: =IF(OR(C$44="Jalisco", C$44="Todas"), B49-E49-F49, "") | H49: =IF(OR(C$44="Jalisco", C$44="Todas"), SUMIFS(Captura_Jalisco!$M$5:$M$250, Captura_Jalisco!$A$5:$A$250, ">="&A49, Captura_Jalisco!$A$5:$A$250, "<="&(A49+5)), 0) | I49: =I48+C49
A50: 46181 | B50: =IF(OR(C$44="Jalisco", C$44="Todas"), G49+H49, "") | C50: =IF(C$44="Jalisco", SUMIFS(Captura_Jalisco!G:G, Captura_Jalisco!B:B, "Salida", Captura_Jalisco!A:A, ">="&A50, Captura_Jalisco!A:A, "<="&(A50+5)), IF(C$44="Todas", SUMIFS(Captura_Obra!F:F, Captura_Obra!A:A, ">="&A50, Captura_Obra!A:A, "<="&(A50+5)) + SUMIFS(Captura_Jalisco!G:G, Captura_Jalisco!B:B, "Salida", Captura_Jalisco!A:A, ">="&A50, Captura_Jalisco!A:A, "<="&(A50+5)), SUMIFS(Captura_Obra!F:F, Captura_Obra!B:B, C$44, Captura_Obra!A:A, ">="&A50, Captura_Obra!A:A, "<="&(A50+5)))) | D50: =C$45 | E50: =C50*D50 | F50: =IF(OR(C$44="Jalisco", C$44="Todas"), SUMIFS(Captura_Jalisco!$N$5:$N$250, Captura_Jalisco!$A$5:$A$250, ">="&A50, Captura_Jalisco!$A$5:$A$250, "<="&(A50+5)), 0) | G50: =IF(OR(C$44="Jalisco", C$44="Todas"), B50-E50-F50, "") | H50: =IF(OR(C$44="Jalisco", C$44="Todas"), SUMIFS(Captura_Jalisco!$M$5:$M$250, Captura_Jalisco!$A$5:$A$250, ">="&A50, Captura_Jalisco!$A$5:$A$250, "<="&(A50+5)), 0) | I50: =I49+C50
A51: 46188 | B51: =IF(OR(C$44="Jalisco", C$44="Todas"), G50+H50, "") | C51: =IF(C$44="Jalisco", SUMIFS(Captura_Jalisco!G:G, Captura_Jalisco!B:B, "Salida", Captura_Jalisco!A:A, ">="&DATE(2026,6,15), Captura_Jalisco!A:A, "<="&DATE(2026,6,18)), IF(C$44="Todas", SUMIFS(Captura_Obra!F:F, Captura_Obra!A:A, ">="&DATE(2026,6,15), Captura_Obra!A:A, "<="&DATE(2026,6,18)) + SUMIFS(Captura_Jalisco!G:G, Captura_Jalisco!B:B, "Salida", Captura_Jalisco!A:A, ">="&DATE(2026,6,15), Captura_Jalisco!A:A, "<="&DATE(2026,6,18)), SUMIFS(Captura_Obra!F:F, Captura_Obra!B:B, C$44, Captura_Obra!A:A, ">="&DATE(2026,6,15), Captura_Obra!A:A, "<="&DATE(2026,6,18)))) | D51: =C$45 | E51: =C51*D51 | F51: =IF(OR(C$44="Jalisco", C$44="Todas"), SUMIFS(Captura_Jalisco!$N$5:$N$250, Captura_Jalisco!$A$5:$A$250, ">="&DATE(2026,6,15), Captura_Jalisco!$A$5:$A$250, "<="&DATE(2026,6,18)), 0) | G51: =IF(OR(C$44="Jalisco", C$44="Todas"), B51-E51-F51, "") | H51: =IF(OR(C$44="Jalisco", C$44="Todas"), SUMIFS(Captura_Jalisco!$M$5:$M$250, Captura_Jalisco!$A$5:$A$250, ">="&DATE(2026,6,15), Captura_Jalisco!$A$5:$A$250, "<="&DATE(2026,6,18)), 0) | I51: =I50+C51
A52: TOTAL ACUMULADO | B52: =IF(OR(C$44="Jalisco", C$44="Todas"), B48, "") | C52: =SUM(C48:C51) | E52: =SUM(E48:E51) | F52: =SUM(F48:F51) | G52: =IF(OR(C$44="Jalisco", C$44="Todas"), G51, "") | H52: =SUM(H48:H51) | I52: =I51
B54: RENDIMIENTO POR OBRA (TODAS LAS OBRAS)
B55: SEMANA: | C55: 46195 | D55: Costo Diésel/L: | E55: 28
B56: Obra | C56: Lts Solicitados | D56: Lts Suministrados | E56: Rendimiento por Obra (Dif.) | F56: Costo Solicitado | G56: Costo Suministrado | H56: Diferencia Costo
B57: =IF(ROWS($57:57)<=MAX(Catalogos!$N$4:$N$11), IFERROR(INDEX(Catalogos!$B$4:$B$11, MATCH(ROWS($57:57), Catalogos!$N$4:$N$11, 0)), ""), IF(ROWS($57:57)=MAX(Catalogos!$N$4:$N$11)+1, "TOTAL GENERAL", "")) | C57: =IF(ROWS($57:57)<=MAX(Catalogos!$N$4:$N$11), SUMIFS(Solicitudes!$F:$F, Solicitudes!$B:$B, $B57, Solicitudes!$C:$C, ">=" & $C$55, Solicitudes!$C:$C, "<=" & ($C$55+6)), IF(ROWS($57:57)=MAX(Catalogos!$N$4:$N$11)+1, SUMIFS(Solicitudes!$F:$F, Solicitudes!$C:$C, ">=" & $C$55, Solicitudes!$C:$C, "<=" & ($C$55+6)), "")) | D57: =IF(ROWS($57:57)<=MAX(Catalogos!$N$4:$N$11), IF($B57="Jalisco", SUMIFS(Captura_Jalisco!$G:$G, Captura_Jalisco!$A:$A, ">=" & $C$55, Captura_Jalisco!$A:$A, "<=" & ($C$55+6), Captura_Jalisco!$B:$B, "Salida"), SUMIFS(Captura_Obra!$F:$F, Captura_Obra!$B:$B, $B57, Captura_Obra!$A:$A, ">=" & $C$55, Captura_Obra!$A:$A, "<=" & ($C$55+6))), IF(ROWS($57:57)=MAX(Catalogos!$N$4:$N$11)+1, SUMIFS(Captura_Obra!$F:$F, Captura_Obra!$A:$A, ">=" & $C$55, Captura_Obra!$A:$A, "<=" & ($C$55+6)) + SUMIFS(Captura_Jalisco!$G:$G, Captura_Jalisco!$A:$A, ">=" & $C$55, Captura_Jalisco!$A:$A, "<=" & ($C$55+6), Captura_Jalisco!$B:$B, "Salida"), "")) | E57: =IF(ROWS($57:57)<=MAX(Catalogos!$N$4:$N$11)+1, C57 - D57, "") | F57: =IF(ROWS($57:57)<=MAX(Catalogos!$N$4:$N$11)+1, C57 * $E$55, "") | G57: =IF(ROWS($57:57)<=MAX(Catalogos!$N$4:$N$11)+1, D57 * $E$55, "") | H57: =IF(ROWS($57:57)<=MAX(Catalogos!$N$4:$N$11)+1, F57 - G57, "")
B58: =IF(ROWS($57:58)<=MAX(Catalogos!$N$4:$N$11), IFERROR(INDEX(Catalogos!$B$4:$B$11, MATCH(ROWS($57:58), Catalogos!$N$4:$N$11, 0)), ""), IF(ROWS($57:58)=MAX(Catalogos!$N$4:$N$11)+1, "TOTAL GENERAL", "")) | C58: =IF(ROWS($57:58)<=MAX(Catalogos!$N$4:$N$11), SUMIFS(Solicitudes!$F:$F, Solicitudes!$B:$B, $B58, Solicitudes!$C:$C, ">=" & $C$55, Solicitudes!$C:$C, "<=" & ($C$55+6)), IF(ROWS($57:58)=MAX(Catalogos!$N$4:$N$11)+1, SUMIFS(Solicitudes!$F:$F, Solicitudes!$C:$C, ">=" & $C$55, Solicitudes!$C:$C, "<=" & ($C$55+6)), "")) | D58: =IF(ROWS($57:58)<=MAX(Catalogos!$N$4:$N$11), IF($B58="Jalisco", SUMIFS(Captura_Jalisco!$G:$G, Captura_Jalisco!$A:$A, ">=" & $C$55, Captura_Jalisco!$A:$A, "<=" & ($C$55+6), Captura_Jalisco!$B:$B, "Salida"), SUMIFS(Captura_Obra!$F:$F, Captura_Obra!$B:$B, $B58, Captura_Obra!$A:$A, ">=" & $C$55, Captura_Obra!$A:$A, "<=" & ($C$55+6))), IF(ROWS($57:58)=MAX(Catalogos!$N$4:$N$11)+1, SUMIFS(Captura_Obra!$F:$F, Captura_Obra!$A:$A, ">=" & $C$55, Captura_Obra!$A:$A, "<=" & ($C$55+6)) + SUMIFS(Captura_Jalisco!$G:$G, Captura_Jalisco!$A:$A, ">=" & $C$55, Captura_Jalisco!$A:$A, "<=" & ($C$55+6), Captura_Jalisco!$B:$B, "Salida"), "")) | E58: =IF(ROWS($57:58)<=MAX(Catalogos!$N$4:$N$11)+1, C58 - D58, "") | F58: =IF(ROWS($57:58)<=MAX(Catalogos!$N$4:$N$11)+1, C58 * $E$55, "") | G58: =IF(ROWS($57:58)<=MAX(Catalogos!$N$4:$N$11)+1, D58 * $E$55, "") | H58: =IF(ROWS($57:58)<=MAX(Catalogos!$N$4:$N$11)+1, F58 - G58, "")
B59: =IF(ROWS($57:59)<=MAX(Catalogos!$N$4:$N$11), IFERROR(INDEX(Catalogos!$B$4:$B$11, MATCH(ROWS($57:59), Catalogos!$N$4:$N$11, 0)), ""), IF(ROWS($57:59)=MAX(Catalogos!$N$4:$N$11)+1, "TOTAL GENERAL", "")) | C59: =IF(ROWS($57:59)<=MAX(Catalogos!$N$4:$N$11), SUMIFS(Solicitudes!$F:$F, Solicitudes!$B:$B, $B59, Solicitudes!$C:$C, ">=" & $C$55, Solicitudes!$C:$C, "<=" & ($C$55+6)), IF(ROWS($57:59)=MAX(Catalogos!$N$4:$N$11)+1, SUMIFS(Solicitudes!$F:$F, Solicitudes!$C:$C, ">=" & $C$55, Solicitudes!$C:$C, "<=" & ($C$55+6)), "")) | D59: =IF(ROWS($57:59)<=MAX(Catalogos!$N$4:$N$11), IF($B59="Jalisco", SUMIFS(Captura_Jalisco!$G:$G, Captura_Jalisco!$A:$A, ">=" & $C$55, Captura_Jalisco!$A:$A, "<=" & ($C$55+6), Captura_Jalisco!$B:$B, "Salida"), SUMIFS(Captura_Obra!$F:$F, Captura_Obra!$B:$B, $B59, Captura_Obra!$A:$A, ">=" & $C$55, Captura_Obra!$A:$A, "<=" & ($C$55+6))), IF(ROWS($57:59)=MAX(Catalogos!$N$4:$N$11)+1, SUMIFS(Captura_Obra!$F:$F, Captura_Obra!$A:$A, ">=" & $C$55, Captura_Obra!$A:$A, "<=" & ($C$55+6)) + SUMIFS(Captura_Jalisco!$G:$G, Captura_Jalisco!$A:$A, ">=" & $C$55, Captura_Jalisco!$A:$A, "<=" & ($C$55+6), Captura_Jalisco!$B:$B, "Salida"), "")) | E59: =IF(ROWS($57:59)<=MAX(Catalogos!$N$4:$N$11)+1, C59 - D59, "") | F59: =IF(ROWS($57:59)<=MAX(Catalogos!$N$4:$N$11)+1, C59 * $E$55, "") | G59: =IF(ROWS($57:59)<=MAX(Catalogos!$N$4:$N$11)+1, D59 * $E$55, "") | H59: =IF(ROWS($57:59)<=MAX(Catalogos!$N$4:$N$11)+1, F59 - G59, "")
B60: =IF(ROWS($57:60)<=MAX(Catalogos!$N$4:$N$11), IFERROR(INDEX(Catalogos!$B$4:$B$11, MATCH(ROWS($57:60), Catalogos!$N$4:$N$11, 0)), ""), IF(ROWS($57:60)=MAX(Catalogos!$N$4:$N$11)+1, "TOTAL GENERAL", "")) | C60: =IF(ROWS($57:60)<=MAX(Catalogos!$N$4:$N$11), SUMIFS(Solicitudes!$F:$F, Solicitudes!$B:$B, $B60, Solicitudes!$C:$C, ">=" & $C$55, Solicitudes!$C:$C, "<=" & ($C$55+6)), IF(ROWS($57:60)=MAX(Catalogos!$N$4:$N$11)+1, SUMIFS(Solicitudes!$F:$F, Solicitudes!$C:$C, ">=" & $C$55, Solicitudes!$C:$C, "<=" & ($C$55+6)), "")) | D60: =IF(ROWS($57:60)<=MAX(Catalogos!$N$4:$N$11), IF($B60="Jalisco", SUMIFS(Captura_Jalisco!$G:$G, Captura_Jalisco!$A:$A, ">=" & $C$55, Captura_Jalisco!$A:$A, "<=" & ($C$55+6), Captura_Jalisco!$B:$B, "Salida"), SUMIFS(Captura_Obra!$F:$F, Captura_Obra!$B:$B, $B60, Captura_Obra!$A:$A, ">=" & $C$55, Captura_Obra!$A:$A, "<=" & ($C$55+6))), IF(ROWS($57:60)=MAX(Catalogos!$N$4:$N$11)+1, SUMIFS(Captura_Obra!$F:$F, Captura_Obra!$A:$A, ">=" & $C$55, Captura_Obra!$A:$A, "<=" & ($C$55+6)) + SUMIFS(Captura_Jalisco!$G:$G, Captura_Jalisco!$A:$A, ">=" & $C$55, Captura_Jalisco!$A:$A, "<=" & ($C$55+6), Captura_Jalisco!$B:$B, "Salida"), "")) | E60: =IF(ROWS($57:60)<=MAX(Catalogos!$N$4:$N$11)+1, C60 - D60, "") | F60: =IF(ROWS($57:60)<=MAX(Catalogos!$N$4:$N$11)+1, C60 * $E$55, "") | G60: =IF(ROWS($57:60)<=MAX(Catalogos!$N$4:$N$11)+1, D60 * $E$55, "") | H60: =IF(ROWS($57:60)<=MAX(Catalogos!$N$4:$N$11)+1, F60 - G60, "")
B61: =IF(ROWS($57:61)<=MAX(Catalogos!$N$4:$N$11), IFERROR(INDEX(Catalogos!$B$4:$B$11, MATCH(ROWS($57:61), Catalogos!$N$4:$N$11, 0)), ""), IF(ROWS($57:61)=MAX(Catalogos!$N$4:$N$11)+1, "TOTAL GENERAL", "")) | C61: =IF(ROWS($57:61)<=MAX(Catalogos!$N$4:$N$11), SUMIFS(Solicitudes!$F:$F, Solicitudes!$B:$B, $B61, Solicitudes!$C:$C, ">=" & $C$55, Solicitudes!$C:$C, "<=" & ($C$55+6)), IF(ROWS($57:61)=MAX(Catalogos!$N$4:$N$11)+1, SUMIFS(Solicitudes!$F:$F, Solicitudes!$C:$C, ">=" & $C$55, Solicitudes!$C:$C, "<=" & ($C$55+6)), "")) | D61: =IF(ROWS($57:61)<=MAX(Catalogos!$N$4:$N$11), IF($B61="Jalisco", SUMIFS(Captura_Jalisco!$G:$G, Captura_Jalisco!$A:$A, ">=" & $C$55, Captura_Jalisco!$A:$A, "<=" & ($C$55+6), Captura_Jalisco!$B:$B, "Salida"), SUMIFS(Captura_Obra!$F:$F, Captura_Obra!$B:$B, $B61, Captura_Obra!$A:$A, ">=" & $C$55, Captura_Obra!$A:$A, "<=" & ($C$55+6))), IF(ROWS($57:61)=MAX(Catalogos!$N$4:$N$11)+1, SUMIFS(Captura_Obra!$F:$F, Captura_Obra!$A:$A, ">=" & $C$55, Captura_Obra!$A:$A, "<=" & ($C$55+6)) + SUMIFS(Captura_Jalisco!$G:$G, Captura_Jalisco!$A:$A, ">=" & $C$55, Captura_Jalisco!$A:$A, "<=" & ($C$55+6), Captura_Jalisco!$B:$B, "Salida"), "")) | E61: =IF(ROWS($57:61)<=MAX(Catalogos!$N$4:$N$11)+1, C61 - D61, "") | F61: =IF(ROWS($57:61)<=MAX(Catalogos!$N$4:$N$11)+1, C61 * $E$55, "") | G61: =IF(ROWS($57:61)<=MAX(Catalogos!$N$4:$N$11)+1, D61 * $E$55, "") | H61: =IF(ROWS($57:61)<=MAX(Catalogos!$N$4:$N$11)+1, F61 - G61, "")
B62: =IF(ROWS($57:62)<=MAX(Catalogos!$N$4:$N$11), IFERROR(INDEX(Catalogos!$B$4:$B$11, MATCH(ROWS($57:62), Catalogos!$N$4:$N$11, 0)), ""), IF(ROWS($57:62)=MAX(Catalogos!$N$4:$N$11)+1, "TOTAL GENERAL", "")) | C62: =IF(ROWS($57:62)<=MAX(Catalogos!$N$4:$N$11), SUMIFS(Solicitudes!$F:$F, Solicitudes!$B:$B, $B62, Solicitudes!$C:$C, ">=" & $C$55, Solicitudes!$C:$C, "<=" & ($C$55+6)), IF(ROWS($57:62)=MAX(Catalogos!$N$4:$N$11)+1, SUMIFS(Solicitudes!$F:$F, Solicitudes!$C:$C, ">=" & $C$55, Solicitudes!$C:$C, "<=" & ($C$55+6)), "")) | D62: =IF(ROWS($57:62)<=MAX(Catalogos!$N$4:$N$11), IF($B62="Jalisco", SUMIFS(Captura_Jalisco!$G:$G, Captura_Jalisco!$A:$A, ">=" & $C$55, Captura_Jalisco!$A:$A, "<=" & ($C$55+6), Captura_Jalisco!$B:$B, "Salida"), SUMIFS(Captura_Obra!$F:$F, Captura_Obra!$B:$B, $B62, Captura_Obra!$A:$A, ">=" & $C$55, Captura_Obra!$A:$A, "<=" & ($C$55+6))), IF(ROWS($57:62)=MAX(Catalogos!$N$4:$N$11)+1, SUMIFS(Captura_Obra!$F:$F, Captura_Obra!$A:$A, ">=" & $C$55, Captura_Obra!$A:$A, "<=" & ($C$55+6)) + SUMIFS(Captura_Jalisco!$G:$G, Captura_Jalisco!$A:$A, ">=" & $C$55, Captura_Jalisco!$A:$A, "<=" & ($C$55+6), Captura_Jalisco!$B:$B, "Salida"), "")) | E62: =IF(ROWS($57:62)<=MAX(Catalogos!$N$4:$N$11)+1, C62 - D62, "") | F62: =IF(ROWS($57:62)<=MAX(Catalogos!$N$4:$N$11)+1, C62 * $E$55, "") | G62: =IF(ROWS($57:62)<=MAX(Catalogos!$N$4:$N$11)+1, D62 * $E$55, "") | H62: =IF(ROWS($57:62)<=MAX(Catalogos!$N$4:$N$11)+1, F62 - G62, "")
B63: =IF(ROWS($57:63)<=MAX(Catalogos!$N$4:$N$11), IFERROR(INDEX(Catalogos!$B$4:$B$11, MATCH(ROWS($57:63), Catalogos!$N$4:$N$11, 0)), ""), IF(ROWS($57:63)=MAX(Catalogos!$N$4:$N$11)+1, "TOTAL GENERAL", "")) | C63: =IF(ROWS($57:63)<=MAX(Catalogos!$N$4:$N$11), SUMIFS(Solicitudes!$F:$F, Solicitudes!$B:$B, $B63, Solicitudes!$C:$C, ">=" & $C$55, Solicitudes!$C:$C, "<=" & ($C$55+6)), IF(ROWS($57:63)=MAX(Catalogos!$N$4:$N$11)+1, SUMIFS(Solicitudes!$F:$F, Solicitudes!$C:$C, ">=" & $C$55, Solicitudes!$C:$C, "<=" & ($C$55+6)), "")) | D63: =IF(ROWS($57:63)<=MAX(Catalogos!$N$4:$N$11), IF($B63="Jalisco", SUMIFS(Captura_Jalisco!$G:$G, Captura_Jalisco!$A:$A, ">=" & $C$55, Captura_Jalisco!$A:$A, "<=" & ($C$55+6), Captura_Jalisco!$B:$B, "Salida"), SUMIFS(Captura_Obra!$F:$F, Captura_Obra!$B:$B, $B63, Captura_Obra!$A:$A, ">=" & $C$55, Captura_Obra!$A:$A, "<=" & ($C$55+6))), IF(ROWS($57:63)=MAX(Catalogos!$N$4:$N$11)+1, SUMIFS(Captura_Obra!$F:$F, Captura_Obra!$A:$A, ">=" & $C$55, Captura_Obra!$A:$A, "<=" & ($C$55+6)) + SUMIFS(Captura_Jalisco!$G:$G, Captura_Jalisco!$A:$A, ">=" & $C$55, Captura_Jalisco!$A:$A, "<=" & ($C$55+6), Captura_Jalisco!$B:$B, "Salida"), "")) | E63: =IF(ROWS($57:63)<=MAX(Catalogos!$N$4:$N$11)+1, C63 - D63, "") | F63: =IF(ROWS($57:63)<=MAX(Catalogos!$N$4:$N$11)+1, C63 * $E$55, "") | G63: =IF(ROWS($57:63)<=MAX(Catalogos!$N$4:$N$11)+1, D63 * $E$55, "") | H63: =IF(ROWS($57:63)<=MAX(Catalogos!$N$4:$N$11)+1, F63 - G63, "")
B64: =IF(ROWS($57:64)<=MAX(Catalogos!$N$4:$N$11), IFERROR(INDEX(Catalogos!$B$4:$B$11, MATCH(ROWS($57:64), Catalogos!$N$4:$N$11, 0)), ""), IF(ROWS($57:64)=MAX(Catalogos!$N$4:$N$11)+1, "TOTAL GENERAL", "")) | C64: =IF(ROWS($57:64)<=MAX(Catalogos!$N$4:$N$11), SUMIFS(Solicitudes!$F:$F, Solicitudes!$B:$B, $B64, Solicitudes!$C:$C, ">=" & $C$55, Solicitudes!$C:$C, "<=" & ($C$55+6)), IF(ROWS($57:64)=MAX(Catalogos!$N$4:$N$11)+1, SUMIFS(Solicitudes!$F:$F, Solicitudes!$C:$C, ">=" & $C$55, Solicitudes!$C:$C, "<=" & ($C$55+6)), "")) | D64: =IF(ROWS($57:64)<=MAX(Catalogos!$N$4:$N$11), IF($B64="Jalisco", SUMIFS(Captura_Jalisco!$G:$G, Captura_Jalisco!$A:$A, ">=" & $C$55, Captura_Jalisco!$A:$A, "<=" & ($C$55+6), Captura_Jalisco!$B:$B, "Salida"), SUMIFS(Captura_Obra!$F:$F, Captura_Obra!$B:$B, $B64, Captura_Obra!$A:$A, ">=" & $C$55, Captura_Obra!$A:$A, "<=" & ($C$55+6))), IF(ROWS($57:64)=MAX(Catalogos!$N$4:$N$11)+1, SUMIFS(Captura_Obra!$F:$F, Captura_Obra!$A:$A, ">=" & $C$55, Captura_Obra!$A:$A, "<=" & ($C$55+6)) + SUMIFS(Captura_Jalisco!$G:$G, Captura_Jalisco!$A:$A, ">=" & $C$55, Captura_Jalisco!$A:$A, "<=" & ($C$55+6), Captura_Jalisco!$B:$B, "Salida"), "")) | E64: =IF(ROWS($57:64)<=MAX(Catalogos!$N$4:$N$11)+1, C64 - D64, "") | F64: =IF(ROWS($57:64)<=MAX(Catalogos!$N$4:$N$11)+1, C64 * $E$55, "") | G64: =IF(ROWS($57:64)<=MAX(Catalogos!$N$4:$N$11)+1, D64 * $E$55, "") | H64: =IF(ROWS($57:64)<=MAX(Catalogos!$N$4:$N$11)+1, F64 - G64, "")
B65: =IF(ROWS($57:65)<=MAX(Catalogos!$N$4:$N$11), IFERROR(INDEX(Catalogos!$B$4:$B$11, MATCH(ROWS($57:65), Catalogos!$N$4:$N$11, 0)), ""), IF(ROWS($57:65)=MAX(Catalogos!$N$4:$N$11)+1, "TOTAL GENERAL", "")) | C65: =IF(ROWS($57:65)<=MAX(Catalogos!$N$4:$N$11), SUMIFS(Solicitudes!$F:$F, Solicitudes!$B:$B, $B65, Solicitudes!$C:$C, ">=" & $C$55, Solicitudes!$C:$C, "<=" & ($C$55+6)), IF(ROWS($57:65)=MAX(Catalogos!$N$4:$N$11)+1, SUMIFS(Solicitudes!$F:$F, Solicitudes!$C:$C, ">=" & $C$55, Solicitudes!$C:$C, "<=" & ($C$55+6)), "")) | D65: =IF(ROWS($57:65)<=MAX(Catalogos!$N$4:$N$11), IF($B65="Jalisco", SUMIFS(Captura_Jalisco!$G:$G, Captura_Jalisco!$A:$A, ">=" & $C$55, Captura_Jalisco!$A:$A, "<=" & ($C$55+6), Captura_Jalisco!$B:$B, "Salida"), SUMIFS(Captura_Obra!$F:$F, Captura_Obra!$B:$B, $B65, Captura_Obra!$A:$A, ">=" & $C$55, Captura_Obra!$A:$A, "<=" & ($C$55+6))), IF(ROWS($57:65)=MAX(Catalogos!$N$4:$N$11)+1, SUMIFS(Captura_Obra!$F:$F, Captura_Obra!$A:$A, ">=" & $C$55, Captura_Obra!$A:$A, "<=" & ($C$55+6)) + SUMIFS(Captura_Jalisco!$G:$G, Captura_Jalisco!$A:$A, ">=" & $C$55, Captura_Jalisco!$A:$A, "<=" & ($C$55+6), Captura_Jalisco!$B:$B, "Salida"), "")) | E65: =IF(ROWS($57:65)<=MAX(Catalogos!$N$4:$N$11)+1, C65 - D65, "") | F65: =IF(ROWS($57:65)<=MAX(Catalogos!$N$4:$N$11)+1, C65 * $E$55, "") | G65: =IF(ROWS($57:65)<=MAX(Catalogos!$N$4:$N$11)+1, D65 * $E$55, "") | H65: =IF(ROWS($57:65)<=MAX(Catalogos!$N$4:$N$11)+1, F65 - G65, "")

Sheet Dashboard_Ejecutivo
B2: Peticiones por Día y Obra | G2: Salidas Marimba por Día y Obra | L2: Salidas Pegaso a Obra | Q2: Consumo Total en Obra | V2: Resumen Semanal por Obra
B4: Fecha | C4: Obra | D4: Litros Solicitados | E4: Costo Estimado ($) | G4: Fecha | H4: Obra | I4: Salida (L) | J4: Costo Surtido ($) | L4: Fecha | M4: Obra | N4: Salida (L) | O4: Costo Surtido ($) | Q4: Fecha | R4: Obra | S4: Litros Recibidos | T4: Costo Surtido ($) | V4: Obra | W4: Litros Recibidos | X4: Costo Surtido ($)
B5: 2026-06-07 | C5: Lerma - Tres Marías | D5: 160 | E5: 4528 | G5: 2026-06-08 | H5: Chamapa-Lechería | I5: 455 | J5: 12876.5 | L5: 2026-06-08 | M5: Bacheo Toluca | N5: 180 | O5: 5094 | Q5: 2026-06-08 | R5: Bacheo Toluca | S5: 100 | T5: 2830 | V5: Bacheo Toluca | W5: 200 | X5: 5660
B6: 2026-06-07 | C6: México-Toluca | D6: 640 | E6: 18112 | G6: 2026-06-08 | H6: Lerma - Tres Marías | I6: 97 | J6: 2745.1 | L6: 2026-06-08 | M6: Planta Asfalto Pegaso | N6: 409 | O6: 11574.7 | Q6: 2026-06-08 | R6: Chamapa-Lechería | S6: 455 | T6: 12876.5 | V6: Chamapa-Lechería | W6: 1693 | X6: 47911.9
B7: 2026-06-08 | C7: Bacheo Toluca | D7: 100 | E7: 2830 | G7: 2026-06-08 | H7: México-Toluca | I7: 369 | J7: 10442.7 | L7: 2026-06-09 | M7: Lerma - Tres Marías | N7: 180 | O7: 5094 | Q7: 2026-06-08 | R7: Lerma - Tres Marías | S7: 97 | T7: 2745.1 | V7: Lerma - Tres Marías | W7: 872 | X7: 24677.6
B8: 2026-06-08 | C8: Chamapa-Lechería | D8: 990 | E8: 28017 | G8: 2026-06-09 | H8: Chamapa-Lechería | I8: 736 | J8: 20828.8 | L8: 2026-06-10 | M8: Bacheo Toluca | N8: 100 | O8: 2830 | Q8: 2026-06-08 | R8: México-Toluca | S8: 369 | T8: 10442.7 | V8: México-Toluca | W8: 1285 | X8: 36365.5
B9: 2026-06-09 | C9: Bacheo Toluca | D9: 100 | E9: 2830 | G9: 2026-06-10 | H9: México-Toluca | I9: 300 | J9: 8490 | L9: 2026-06-11 | M9: Lerma - Tres Marías | N9: 595 | O9: 16838.5 | Q9: 2026-06-08 | R9: Planta Asfalto Pegaso | S9: 409 | T9: 11574.7 | V9: Planta Asfalto Pegaso | W9: 647 | X9: 18310.1
B10: 2026-06-09 | C10: Chamapa-Lechería | D10: 790 | E10: 22357 | G10: 2026-06-11 | H10: México-Toluca | I10: 256 | J10: 7244.8 | L10: 2026-06-11 | M10: Planta Asfalto Pegaso | N10: 238 | O10: 6735.4 | Q10: 2026-06-09 | R10: Chamapa-Lechería | S10: 736 | T10: 20828.8 | X10: =SUM(X5:X9)
B11: 2026-06-09 | C11: Lerma - Tres Marías | D11: 210 | E11: 5943 | G11: 2026-06-12 | H11: Chamapa-Lechería | I11: 502 | J11: 14206.6 | L11: 2026-06-12 | M11: Bacheo Toluca | N11: 70 | O11: 1981 | Q11: 2026-06-09 | R11: Lerma - Tres Marías | S11: 180 | T11: 5094
B12: 2026-06-10 | C12: México-Toluca | D12: 320 | E12: 9056 | G12: 2026-06-12 | H12: México-Toluca | I12: 360 | J12: 10188 | Q12: 2026-06-10 | R12: Bacheo Toluca | S12: 100 | T12: 2830
B13: 2026-06-11 | C13: Bacheo Toluca | D13: 70 | E13: 1981 | Q13: 2026-06-10 | R13: México-Toluca | S13: 300 | T13: 8490
B14: 2026-06-11 | C14: Lerma - Tres Marías | D14: 460 | E14: 13018 | Q14: 2026-06-11 | R14: Lerma - Tres Marías | S14: 595 | T14: 16838.5
B15: 2026-06-12 | C15: Chamapa-Lechería | D15: 620 | E15: 17546 | Q15: 2026-06-11 | R15: México-Toluca | S15: 256 | T15: 7244.8
B16: 2026-06-12 | C16: México-Toluca | D16: 540 | E16: 15282 | Q16: 2026-06-11 | R16: Planta Asfalto Pegaso | S16: 238 | T16: 6735.4
Q17: 2026-06-12 | R17: Chamapa-Lechería | S17: 502 | T17: 14206.6
Q18: 2026-06-12 | R18: México-Toluca | S18: 360 | T18: 10188
B35: Costos por Día (Petición vs Surtido) | G35: Costos por Obra (Petición vs Surtido) | L35: Totales Generales por Día | Q35: Totales Generales por Obra | V35: Reporte de Discrepancias (Faltantes/Sobrantes)
B37: Fecha | C37: Costo Solicitado ($) | D37: Costo Surtido ($) | G37: Obra | H37: Costo Solicitado ($) | I37: Costo Surtido ($) | L37: Fecha | M37: Litros Totales | N37: Costo Total ($) | Q37: Obra | R37: Litros Totales | S37: Costo Total ($) | V37: Fecha | W37: Obra | X37: Litros Surtidos | Y37: Litros Recibidos | Z37: Discrepancia (L)
B38: 2026-06-07 | C38: 22640 | D38: 0 | G38: Bacheo Toluca | H38: 7641 | I38: 9905 | L38: 2026-06-08 | M38: 1510 | N38: 42733 | Q38: Bacheo Toluca | R38: 350 | S38: 9905 | V38: 2026-06-08 | W38: Bacheo Toluca | X38: 180 | Y38: 100 | Z38: 80
B39: 2026-06-08 | C39: 30847 | D39: 42733 | G39: Chamapa-Lechería | H39: 67920 | I39: 47911.9 | L39: 2026-06-09 | M39: 916 | N39: 25922.8 | Q39: Chamapa-Lechería | R39: 1693 | S39: 47911.9 | V39: 2026-06-12 | W39: Bacheo Toluca | X39: 70 | Y39: 0 | Z39: 70
B40: 2026-06-09 | C40: 31130 | D40: 25922.8 | G40: Lerma - Tres Marías | H40: 23489 | I40: 24677.6 | L40: 2026-06-10 | M40: 400 | N40: 11320 | Q40: Lerma - Tres Marías | R40: 872 | S40: 24677.6
B41: 2026-06-10 | C41: 9056 | D41: 11320 | G41: México-Toluca | H41: 42450 | I41: 36365.5 | L41: 2026-06-11 | M41: 1089 | N41: 30818.7 | Q41: México-Toluca | R41: 1285 | S41: 36365.5
B42: 2026-06-11 | C42: 14999 | D42: 30818.7 | G42: Planta Asfalto Pegaso | H42: 0 | I42: 18310.1 | L42: 2026-06-12 | M42: 932 | N42: 26375.6 | Q42: Planta Asfalto Pegaso | R42: 647 | S42: 18310.1
B43: 2026-06-12 | C43: 32828 | D43: 26375.6

Sheet Captura_Pegaso
A1: GC-COMB-001 | BITÁCORA DE INVENTARIO PEGASO
A2: Responsable: | C2: Semana: | F2: Fecha entrega: | H2: Tanque: | I2: Pegaso | J2: Costo por litro base:
A3: Folio Ticket | B3: Fecha | C3: Hora | D3: Origen | E3: Destino | F3: Obra Asignada | G3: Litros | H3: Costo/L
F200: =VLOOKUP(TablaPegaso[[#This Row],[Equipo]],Catalogos!$I$4:$J$34,2,FALSE)
F201: =VLOOKUP(TablaPegaso[[#This Row],[Equipo]],Catalogos!$I$4:$J$34,2,FALSE)
F202: =VLOOKUP(TablaPegaso[[#This Row],[Equipo]],Catalogos!$I$4:$J$34,2,FALSE)
F203: =VLOOKUP(TablaPegaso[[#This Row],[Equipo]],Catalogos!$I$4:$J$34,2,FALSE)
F204: =VLOOKUP(TablaPegaso[[#This Row],[Equipo]],Catalogos!$I$4:$J$34,2,FALSE)
F205: =VLOOKUP(TablaPegaso[[#This Row],[Equipo]],Catalogos!$I$4:$J$34,2,FALSE)
F206: =VLOOKUP(TablaPegaso[[#This Row],[Equipo]],Catalogos!$I$4:$J$34,2,FALSE)

Sheet Captura_Marimba_M01
A1: GC-COMB-002 | BITÁCORA DE SUMINISTRO DE MARIMBA M-01
A2: Operador: | C2: Semana: | E2: Fecha entrega: | G2: Marimba: | H2: M-01 | I2: Costo/L base:
A3: Folio Ticket | B3: Fecha | C3: Hora | D3: Origen | E3: Destino | F3: Obra Asignada | G3: Litros | H3: Costo/L
N43: =SUM(G5:G48)
E200: =VLOOKUP(TablaMarimba[[#This Row],[Equipo]],Catalogos!$I$4:$J$35,2,FALSE) | I200: 28.3
E201: =VLOOKUP(TablaMarimba[[#This Row],[Equipo]],Catalogos!$I$4:$J$35,2,FALSE) | I201: 28.3
E202: =VLOOKUP(TablaMarimba[[#This Row],[Equipo]],Catalogos!$I$4:$J$35,2,FALSE) | I202: 28.3
E203: =VLOOKUP(TablaMarimba[[#This Row],[Equipo]],Catalogos!$I$4:$J$35,2,FALSE) | I203: 28.3
E204: =VLOOKUP(TablaMarimba[[#This Row],[Equipo]],Catalogos!$I$4:$J$35,2,FALSE) | I204: 28.3
E205: =VLOOKUP(TablaMarimba[[#This Row],[Equipo]],Catalogos!$I$4:$J$35,2,FALSE) | I205: 28.3
E206: =VLOOKUP(TablaMarimba[[#This Row],[Equipo]],Catalogos!$I$4:$J$35,2,FALSE) | I206: 28.3

Sheet Captura_Jalisco
A1: GC-COMB-002 | BITÁCORA DE SUMINISTRO DE JALISCO
A2: Operador: | C2: Semana: | E2: Fecha entrega: | G2: Marimba: | H2: M-01 | I2: Costo/L base:
A3: Folio Ticket | B3: Fecha | C3: Hora | D3: Origen | E3: Destino | F3: Obra Asignada | G3: Litros | H3: Costo/L
M4: Ajuste | N4: Gasolina | O4: Firma/Validación | P4: Observaciones
M5: 0
M10: 25056
M22: 31320 | N22: 3000
N25: 1556
N33: 3700
R43: =SUM(G5:G48)
E200: =VLOOKUP(TablaMarimba6[[#This Row],[Equipo]],Catalogos!$I$4:$J$35,2,FALSE) | I200: 28.3 | L200: =(TablaMarimba6[[#This Row],[Saldo inicial(vales)]]-TablaMarimba6[[#This Row],[Importe]])
E201: =VLOOKUP(TablaMarimba6[[#This Row],[Equipo]],Catalogos!$I$4:$J$35,2,FALSE) | I201: 28.3 | L201: =(TablaMarimba6[[#This Row],[Saldo inicial(vales)]]-TablaMarimba6[[#This Row],[Importe]])
E202: =VLOOKUP(TablaMarimba6[[#This Row],[Equipo]],Catalogos!$I$4:$J$35,2,FALSE) | I202: 28.3 | L202: =(TablaMarimba6[[#This Row],[Saldo inicial(vales)]]-TablaMarimba6[[#This Row],[Importe]])
E203: =VLOOKUP(TablaMarimba6[[#This Row],[Equipo]],Catalogos!$I$4:$J$35,2,FALSE) | I203: 28.3 | L203: =(TablaMarimba6[[#This Row],[Saldo inicial(vales)]]-TablaMarimba6[[#This Row],[Importe]])
E204: =VLOOKUP(TablaMarimba6[[#This Row],[Equipo]],Catalogos!$I$4:$J$35,2,FALSE) | I204: 28.3 | J204: =IFERROR((F204+G204)*I204,0) | L204: =(TablaMarimba6[[#This Row],[Saldo inicial(vales)]]-TablaMarimba6[[#This Row],[Importe]])
E205: =VLOOKUP(TablaMarimba6[[#This Row],[Equipo]],Catalogos!$I$4:$J$35,2,FALSE) | I205: 28.3 | J205: =IFERROR((F205+G205)*I205,0) | L205: =(TablaMarimba6[[#This Row],[Saldo inicial(vales)]]-TablaMarimba6[[#This Row],[Importe]])
E206: =VLOOKUP(TablaMarimba6[[#This Row],[Equipo]],Catalogos!$I$4:$J$35,2,FALSE) | I206: 28.3 | J206: =IFERROR((F206+G206)*I206,0) | L206: =(TablaMarimba6[[#This Row],[Saldo inicial(vales)]]-TablaMarimba6[[#This Row],[Importe]])

Sheet Captura_Obra
A1: GC-COMB-003 | BITÁCORA DE CONTROL DE COMBUSTIBLE DE OBRA
A2: Ingeniero: | C2: Semana: | E2: Fecha entrega: | G2: Obra: | I2: Costo/L base:
A3: Folio Ticket | B3: Fecha | C3: Hora | D3: Origen | E3: Destino | F3: Obra Asignada | G3: Litros | H3: Costo/L
M14: =SUM(F5:F64)
E200: =VLOOKUP(TablaObra[[#This Row],[Equipo]],Catalogos!$I$4:$J$46,2,FALSE)
E201: =VLOOKUP(TablaObra[[#This Row],[Equipo]],Catalogos!$I$4:$J$46,2,FALSE)
E202: =VLOOKUP(TablaObra[[#This Row],[Equipo]],Catalogos!$I$4:$J$46,2,FALSE)
E203: =VLOOKUP(TablaObra[[#This Row],[Equipo]],Catalogos!$I$4:$J$46,2,FALSE)
E204: =VLOOKUP(TablaObra[[#This Row],[Equipo]],Catalogos!$I$4:$J$46,2,FALSE)
E205: =VLOOKUP(TablaObra[[#This Row],[Equipo]],Catalogos!$I$4:$J$46,2,FALSE)
E206: =VLOOKUP(TablaObra[[#This Row],[Equipo]],Catalogos!$I$4:$J$46,2,FALSE)
E207: =VLOOKUP(TablaObra[[#This Row],[Equipo]],Catalogos!$I$4:$J$46,2,FALSE)
E208: =VLOOKUP(TablaObra[[#This Row],[Equipo]],Catalogos!$I$4:$J$46,2,FALSE)
E209: =VLOOKUP(TablaObra[[#This Row],[Equipo]],Catalogos!$I$4:$J$46,2,FALSE)
E210: =VLOOKUP(TablaObra[[#This Row],[Equipo]],Catalogos!$I$4:$J$46,2,FALSE)
E211: =VLOOKUP(TablaObra[[#This Row],[Equipo]],Catalogos!$I$4:$J$46,2,FALSE)
... E260: =VLOOKUP(TablaObra[[#This Row],[Equipo]],Catalogos!$I$4:$J$46,2,FALSE)
E261: =VLOOKUP(TablaObra[[#This Row],[Equipo]],Catalogos!$I$4:$J$46,2,FALSE) | H261: =IFERROR(F261*G261,0)
E262: =VLOOKUP(TablaObra[[#This Row],[Equipo]],Catalogos!$I$4:$J$46,2,FALSE) | H262: =IFERROR(F262*G262,0)
E263: =VLOOKUP(TablaObra[[#This Row],[Equipo]],Catalogos!$I$4:$J$46,2,FALSE) | H263: =IFERROR(F263*G263,0)
E264: =VLOOKUP(TablaObra[[#This Row],[Equipo]],Catalogos!$I$4:$J$46,2,FALSE) | H264: =IFERROR(F264*G264,0)
E265: =VLOOKUP(TablaObra[[#This Row],[Equipo]],Catalogos!$I$4:$J$46,2,FALSE) | H265: =IFERROR(F265*G265,0)
E266: =VLOOKUP(TablaObra[[#This Row],[Equipo]],Catalogos!$I$4:$J$46,2,FALSE) | H266: =IFERROR(F266*G266,0)
E267: =VLOOKUP(TablaObra[[#This Row],[Equipo]],Catalogos!$I$4:$J$46,2,FALSE) | H267: =IFERROR(F267*G267,0)
E268: =VLOOKUP(TablaObra[[#This Row],[Equipo]],Catalogos!$I$4:$J$46,2,FALSE) | H268: =IFERROR(F268*G268,0)
E269: =VLOOKUP(TablaObra[[#This Row],[Equipo]],Catalogos!$I$4:$J$46,2,FALSE) | H269: =IFERROR(F269*G269,0)
E270: =VLOOKUP(TablaObra[[#This Row],[Equipo]],Catalogos!$I$4:$J$46,2,FALSE) | H270: =IFERROR(F270*G270,0)
E271: =VLOOKUP(TablaObra[[#This Row],[Equipo]],Catalogos!$I$4:$J$46,2,FALSE) | H271: =IFERROR(F271*G271,0)
E272: =VLOOKUP(TablaObra[[#This Row],[Equipo]],Catalogos!$I$4:$J$46,2,FALSE) | H272: =IFERROR(F272*G272,0)
... E304: =VLOOKUP(TablaObra[[#This Row],[Equipo]],Catalogos!$I$4:$J$46,2,FALSE) | H304: =IFERROR(F304*G304,0)

Sheet Solicitudes
A1: GC-COMB-003 | BITÁCORA DE SOLICITUDES DE COMBUSTIBLE DE OBRA
A2: Ingeniero: | C2: Semana: | E2: Fecha entrega: | G2: Obra: | I2: Costo/L base:
A4: Fecha de Solicitud | B4: Obra | C4: Fecha de Trabajo | D4: Equipo | E4: Económico | F4: Litros Solicitados | G4: Costo/L | H4: Importe | I4: Solicitante | J4: Incidencia | K4: Observaciones
A5: 46180 | B5: México-Toluca | C5: 46181 | D5: Vogel | E5: =VLOOKUP(TablaObra5[[#This Row],[Equipo]],Catalogos!$I$4:$J$64,2,FALSE) | F5: 200 | G5: 28.3 | H5: =IFERROR(F5*G5,0) | I5: =VLOOKUP(TablaObra5[[#This Row],[Obra]],Catalogos!$B$3:$C$10,2,FALSE)
A6: 46180 | B6: México-Toluca | C6: 46181 | D6: Perfiladora | E6: =VLOOKUP(TablaObra5[[#This Row],[Equipo]],Catalogos!$I$4:$J$64,2,FALSE) | F6: 300 | G6: 28.3 | H6: =IFERROR(F6*G6,0) | I6: =VLOOKUP(TablaObra5[[#This Row],[Obra]],Catalogos!$B$3:$C$10,2,FALSE)
A7: 46180 | B7: México-Toluca | C7: 46181 | D7: Retroexcavadora | E7: =VLOOKUP(TablaObra5[[#This Row],[Equipo]],Catalogos!$I$4:$J$64,2,FALSE) | F7: 30 | G7: 28.3 | H7: =IFERROR(F7*G7,0) | I7: =VLOOKUP(TablaObra5[[#This Row],[Obra]],Catalogos!$B$3:$C$10,2,FALSE)
A8: 46180 | B8: México-Toluca | C8: 46181 | D8: Barredora | E8: =VLOOKUP(TablaObra5[[#This Row],[Equipo]],Catalogos!$I$4:$J$64,2,FALSE) | F8: 20 | G8: 28.3 | H8: =IFERROR(F8*G8,0) | I8: =VLOOKUP(TablaObra5[[#This Row],[Obra]],Catalogos!$B$3:$C$10,2,FALSE)
A9: 46180 | B9: México-Toluca | C9: 46181 | D9: Neuomatico | E9: =VLOOKUP(TablaObra5[[#This Row],[Equipo]],Catalogos!$I$4:$J$64,2,FALSE) | F9: 30 | G9: 28.3 | H9: =IFERROR(F9*G9,0) | I9: =VLOOKUP(TablaObra5[[#This Row],[Obra]],Catalogos!$B$3:$C$10,2,FALSE)
A10: 46180 | B10: México-Toluca | C10: 46181 | D10: Compactador | E10: =VLOOKUP(TablaObra5[[#This Row],[Equipo]],Catalogos!$I$4:$J$64,2,FALSE) | F10: 30 | G10: 28.3 | H10: =IFERROR(F10*G10,0) | I10: =VLOOKUP(TablaObra5[[#This Row],[Obra]],Catalogos!$B$3:$C$10,2,FALSE)
A11: 46180 | B11: México-Toluca | C11: 46181 | D11: Limpieza | E11: =VLOOKUP(TablaObra5[[#This Row],[Equipo]],Catalogos!$I$4:$J$64,2,FALSE) | F11: 30 | G11: 28.3 | H11: =IFERROR(F11*G11,0) | I11: =VLOOKUP(TablaObra5[[#This Row],[Obra]],Catalogos!$B$3:$C$10,2,FALSE)
A12: 46180 | B12: Lerma - Tres Marías | C12: 46181 | D12: Retroexcavadora | E12: =VLOOKUP(TablaObra5[[#This Row],[Equipo]],Catalogos!$I$4:$J$64,2,FALSE) | F12: 50 | G12: 28.3 | H12: =IFERROR(F12*G12,0) | I12: =VLOOKUP(TablaObra5[[#This Row],[Obra]],Catalogos!$B$3:$C$10,2,FALSE)
A13: 46180 | B13: Lerma - Tres Marías | C13: 46181 | D13: Neuomatico | E13: =VLOOKUP(TablaObra5[[#This Row],[Equipo]],Catalogos!$I$4:$J$64,2,FALSE) | F13: 50 | G13: 28.3 | H13: =IFERROR(F13*G13,0) | I13: =VLOOKUP(TablaObra5[[#This Row],[Obra]],Catalogos!$B$3:$C$10,2,FALSE)
A14: 46180 | B14: Lerma - Tres Marías | C14: 46181 | D14: Petrolizadora | E14: =VLOOKUP(TablaObra5[[#This Row],[Equipo]],Catalogos!$I$4:$J$64,2,FALSE) | F14: 60 | G14: 28.3 | H14: =IFERROR(F14*G14,0) | I14: =VLOOKUP(TablaObra5[[#This Row],[Obra]],Catalogos!$B$3:$C$10,2,FALSE)
A15: 46181 | B15: Bacheo Toluca | D15: Retroexcavadora | E15: =VLOOKUP(TablaObra5[[#This Row],[Equipo]],Catalogos!$I$4:$J$64,2,FALSE) | F15: 100 | G15: 28.3 | H15: =IFERROR(F15*G15,0) | I15: =VLOOKUP(TablaObra5[[#This Row],[Obra]],Catalogos!$B$3:$C$10,2,FALSE)
A16: 46181 | B16: Chamapa-Lechería | C16: 46181 | D16: Perfiladora Wirgent | E16: =VLOOKUP(TablaObra5[[#This Row],[Equipo]],Catalogos!$I$4:$J$64,2,FALSE) | F16: 250 | G16: 28.3 | H16: =IFERROR(F16*G16,0) | I16: =VLOOKUP(TablaObra5[[#This Row],[Obra]],Catalogos!$B$3:$C$10,2,FALSE)
A17: 46181 | B17: Chamapa-Lechería | C17: 46181 | D17: Perfiladora Cat-PM | E17: =VLOOKUP(TablaObra5[[#This Row],[Equipo]],Catalogos!$I$4:$J$64,2,FALSE) | F17: 150 | G17: 28.3 | H17: =IFERROR(F17*G17,0) | I17: =VLOOKUP(TablaObra5[[#This Row],[Obra]],Catalogos!$B$3:$C$10,2,FALSE)
A18: 46181 | B18: Chamapa-Lechería | C18: 46181 | D18: Barredora Broce | E18: =VLOOKUP(TablaObra5[[#This Row],[Equipo]],Catalogos!$I$4:$J$64,2,FALSE) | F18: 40 | G18: 28.3 | H18: =IFERROR(F18*G18,0) | I18: =VLOOKUP(TablaObra5[[#This Row],[Obra]],Catalogos!$B$3:$C$10,2,FALSE)
A19: 46181 | B19: Chamapa-Lechería | C19: 46181 | D19: Retroexcavadora Jonh Deere | E19: =VLOOKUP(TablaObra5[[#This Row],[Equipo]],Catalogos!$I$4:$J$64,2,FALSE) | F19: 60 | G19: 28.3 | H19: =IFERROR(F19*G19,0) | I19: =VLOOKUP(TablaObra5[[#This Row],[Obra]],Catalogos!$B$3:$C$10,2,FALSE)
A20: 46181 | B20: Chamapa-Lechería | C20: 46181 | D20: Buggy Trasnfer | E20: =VLOOKUP(TablaObra5[[#This Row],[Equipo]],Catalogos!$I$4:$J$64,2,FALSE) | F20: 100 | G20: 28.3 | H20: =IFERROR(F20*G20,0) | I20: =VLOOKUP(TablaObra5[[#This Row],[Obra]],Catalogos!$B$3:$C$10,2,FALSE)
A21: 46181 | B21: Chamapa-Lechería | C21: 46181 | D21: Vogele Guion | E21: =VLOOKUP(TablaObra5[[#This Row],[Equipo]],Catalogos!$I$4:$J$64,2,FALSE) | F21: 100 | G21: 28.3 | H21: =IFERROR(F21*G21,0) | I21: =VLOOKUP(TablaObra5[[#This Row],[Obra]],Catalogos!$B$3:$C$10,2,FALSE)
A22: 46181 | B22: Chamapa-Lechería | C22: 46181 | D22: Limpieza | E22: =VLOOKUP(TablaObra5[[#This Row],[Equipo]],Catalogos!$I$4:$J$64,2,FALSE) | F22: 20 | G22: 28.3 | H22: =IFERROR(F22*G22,0) | I22: =VLOOKUP(TablaObra5[[#This Row],[Obra]],Catalogos!$B$3:$C$10,2,FALSE)
A23: 46181 | B23: Chamapa-Lechería | C23: 46181 | D23: Tandem Hamm | E23: =VLOOKUP(TablaObra5[[#This Row],[Equipo]],Catalogos!$I$4:$J$64,2,FALSE) | F23: 50 | G23: 28.3 | H23: =IFERROR(F23*G23,0) | I23: =VLOOKUP(TablaObra5[[#This Row],[Obra]],Catalogos!$B$3:$C$10,2,FALSE)
A24: 46181 | B24: Chamapa-Lechería | C24: 46181 | D24: Neuomatico Dynapac | E24: =VLOOKUP(TablaObra5[[#This Row],[Equipo]],Catalogos!$I$4:$J$64,2,FALSE) | F24: 50 | G24: 28.3 | H24: =IFERROR(F24*G24,0) | I24: =VLOOKUP(TablaObra5[[#This Row],[Obra]],Catalogos!$B$3:$C$10,2,FALSE)
A25: 46181 | B25: Chamapa-Lechería | C25: 46181 | D25: Petrolizadora Elton | E25: =VLOOKUP(TablaObra5[[#This Row],[Equipo]],Catalogos!$I$4:$J$64,2,FALSE) | F25: 50 | G25: 28.3 | H25: =IFERROR(F25*G25,0) | I25: =VLOOKUP(TablaObra5[[#This Row],[Obra]],Catalogos!$B$3:$C$10,2,FALSE)
A26: 46181 | B26: Chamapa-Lechería | C26: 46181 | D26: Camion de Impacto | E26: =VLOOKUP(TablaObra5[[#This Row],[Equipo]],Catalogos!$I$4:$J$64,2,FALSE) | F26: 20 | G26: 28.3 | H26: =IFERROR(F26*G26,0) | I26: =VLOOKUP(TablaObra5[[#This Row],[Obra]],Catalogos!$B$3:$C$10,2,FALSE)
A27: 46181 | B27: Chamapa-Lechería | C27: 46181 | D27: Maxilihgs | E27: =VLOOKUP(TablaObra5[[#This Row],[Equipo]],Catalogos!$I$4:$J$64,2,FALSE) | F27: 50 | G27: 28.3 | H27: =IFERROR(F27*G27,0) | I27: =VLOOKUP(TablaObra5[[#This Row],[Obra]],Catalogos!$B$3:$C$10,2,FALSE)
... A40: 46182 | B40: Chamapa-Lechería | C40: 46182 | D40: Compresor | E40: =VLOOKUP(TablaObra5[[#This Row],[Equipo]],Catalogos!$I$4:$J$64,2,FALSE) | F40: 30 | G40: 28.3 | H40: =IFERROR(F40*G40,0) | I40: =VLOOKUP(TablaObra5[[#This Row],[Obra]],Catalogos!$B$3:$C$10,2,FALSE)
A41: 46182 | B41: Lerma - Tres Marías | C41: 46182 | D41: Retroexcavadora | E41: =VLOOKUP(TablaObra5[[#This Row],[Equipo]],Catalogos!$I$4:$J$64,2,FALSE) | F41: 50 | G41: 28.3 | H41: =IFERROR(F41*G41,0) | I41: =VLOOKUP(TablaObra5[[#This Row],[Obra]],Catalogos!$B$3:$C$10,2,FALSE) | K41: Segunda solicitud, el dia 7/06/2026, no se relizo la carga
A42: 46182 | B42: Lerma - Tres Marías | C42: 46182 | D42: Neuomatico | E42: =VLOOKUP(TablaObra5[[#This Row],[Equipo]],Catalogos!$I$4:$J$64,2,FALSE) | F42: 50 | G42: 28.3 | H42: =IFERROR(F42*G42,0) | I42: =VLOOKUP(TablaObra5[[#This Row],[Obra]],Catalogos!$B$3:$C$10,2,FALSE)
A43: 46182 | B43: Lerma - Tres Marías | C43: 46182 | D43: Petrolizadora | E43: =VLOOKUP(TablaObra5[[#This Row],[Equipo]],Catalogos!$I$4:$J$64,2,FALSE) | F43: 60 | G43: 28.3 | H43: =IFERROR(F43*G43,0) | I43: =VLOOKUP(TablaObra5[[#This Row],[Obra]],Catalogos!$B$3:$C$10,2,FALSE)
A44: 46182 | B44: Lerma - Tres Marías | C44: 46182 | D44: Doble Rodillo | E44: =VLOOKUP(TablaObra5[[#This Row],[Equipo]],Catalogos!$I$4:$J$64,2,FALSE) | F44: 50 | G44: 28.3 | H44: =IFERROR(F44*G44,0) | I44: =VLOOKUP(TablaObra5[[#This Row],[Obra]],Catalogos!$B$3:$C$10,2,FALSE)
A45: 46182 | B45: Bacheo Toluca | D45: Retroexcavadora | E45: =VLOOKUP(TablaObra5[[#This Row],[Equipo]],Catalogos!$I$4:$J$64,2,FALSE) | F45: 100 | G45: 28.3 | H45: =IFERROR(F45*G45,0) | I45: =VLOOKUP(TablaObra5[[#This Row],[Obra]],Catalogos!$B$3:$C$10,2,FALSE)
A46: 46183 | B46: México-Toluca | C46: 46183 | D46: Perfiladora | E46: =VLOOKUP(TablaObra5[[#This Row],[Equipo]],Catalogos!$I$4:$J$64,2,FALSE) | F46: 250 | G46: 28.3 | H46: =IFERROR(F46*G46,0) | I46: =VLOOKUP(TablaObra5[[#This Row],[Obra]],Catalogos!$B$3:$C$10,2,FALSE)
A47: 46183 | B47: México-Toluca | C47: 46183 | D47: Retroexcavadora | E47: =VLOOKUP(TablaObra5[[#This Row],[Equipo]],Catalogos!$I$4:$J$64,2,FALSE) | F47: 30 | G47: 28.3 | H47: =IFERROR(F47*G47,0) | I47: =VLOOKUP(TablaObra5[[#This Row],[Obra]],Catalogos!$B$3:$C$10,2,FALSE)
A48: 46183 | B48: México-Toluca | C48: 46183 | D48: Barredora | E48: =VLOOKUP(TablaObra5[[#This Row],[Equipo]],Catalogos!$I$4:$J$64,2,FALSE) | F48: 20 | G48: 28.3 | H48: =IFERROR(F48*G48,0) | I48: =VLOOKUP(TablaObra5[[#This Row],[Obra]],Catalogos!$B$3:$C$10,2,FALSE)
A49: 46183 | B49: México-Toluca | C49: 46183 | D49: Maxilihgs | E49: =VLOOKUP(TablaObra5[[#This Row],[Equipo]],Catalogos!$I$4:$J$64,2,FALSE) | F49: 20 | G49: 28.3 | H49: =IFERROR(F49*G49,0) | I49: =VLOOKUP(TablaObra5[[#This Row],[Obra]],Catalogos!$B$3:$C$10,2,FALSE)
A50: 46184 | B50: Lerma - Tres Marías | C50: 46184 | D50: Petrolizadora | E50: =VLOOKUP(TablaObra5[[#This Row],[Equipo]],Catalogos!$I$4:$J$64,2,FALSE) | F50: 80 | G50: 28.3 | H50: =IFERROR(F50*G50,0) | I50: =VLOOKUP(TablaObra5[[#This Row],[Obra]],Catalogos!$B$3:$C$10,2,FALSE)
A51: 46184 | B51: Lerma - Tres Marías | C51: 46184 | D51: Camion de Impacto | E51: =VLOOKUP(TablaObra5[[#This Row],[Equipo]],Catalogos!$I$4:$J$64,2,FALSE) | F51: 80 | G51: 28.3 | H51: =IFERROR(F51*G51,0) | I51: =VLOOKUP(TablaObra5[[#This Row],[Obra]],Catalogos!$B$3:$C$10,2,FALSE)
A52: 46184 | B52: Lerma - Tres Marías | C52: 46184 | D52: Retroexcavadora | E52: =VLOOKUP(TablaObra5[[#This Row],[Equipo]],Catalogos!$I$4:$J$64,2,FALSE) | F52: 70 | G52: 28.3 | H52: =IFERROR(F52*G52,0) | I52: =VLOOKUP(TablaObra5[[#This Row],[Obra]],Catalogos!$B$3:$C$10,2,FALSE)
A53: 46184 | B53: Lerma - Tres Marías | C53: 46184 | D53: Doble Rodillo | E53: =VLOOKUP(TablaObra5[[#This Row],[Equipo]],Catalogos!$I$4:$J$64,2,FALSE) | F53: 40 | G53: 28.3 | H53: =IFERROR(F53*G53,0) | I53: =VLOOKUP(TablaObra5[[#This Row],[Obra]],Catalogos!$B$3:$C$10,2,FALSE)
A54: 46184 | B54: Lerma - Tres Marías | C54: 46184 | D54: Vogel | E54: =VLOOKUP(TablaObra5[[#This Row],[Equipo]],Catalogos!$I$4:$J$64,2,FALSE) | F54: 150 | G54: 28.3 | H54: =IFERROR(F54*G54,0) | I54: =VLOOKUP(TablaObra5[[#This Row],[Obra]],Catalogos!$B$3:$C$10,2,FALSE)
A55: 46184 | B55: Lerma - Tres Marías | C55: 46184 | D55: Limpieza | E55: =VLOOKUP(TablaObra5[[#This Row],[Equipo]],Catalogos!$I$4:$J$64,2,FALSE) | F55: 30 | G55: 28.3 | H55: =IFERROR(F55*G55,0) | I55: =VLOOKUP(TablaObra5[[#This Row],[Obra]],Catalogos!$B$3:$C$10,2,FALSE)
A56: 46184 | B56: Lerma - Tres Marías | C56: 46184 | D56: Rastrillador | E56: =VLOOKUP(TablaObra5[[#This Row],[Equipo]],Catalogos!$I$4:$J$64,2,FALSE) | F56: 10 | G56: 28.3 | H56: =IFERROR(F56*G56,0) | I56: =VLOOKUP(TablaObra5[[#This Row],[Obra]],Catalogos!$B$3:$C$10,2,FALSE)
A57: 46184 | B57: Bacheo Toluca | D57: Retroexcavadora | E57: =VLOOKUP(TablaObra5[[#This Row],[Equipo]],Catalogos!$I$4:$J$64,2,FALSE) | F57: 50 | G57: 28.3 | H57: =IFERROR(F57*G57,0) | I57: =VLOOKUP(TablaObra5[[#This Row],[Obra]],Catalogos!$B$3:$C$10,2,FALSE) | K57: Diego Carreola Monroy
A58: 46184 | B58: Bacheo Toluca | D58: Otro | E58: =VLOOKUP(TablaObra5[[#This Row],[Equipo]],Catalogos!$I$4:$J$64,2,FALSE) | F58: 10 | G58: 28.3 | H58: =IFERROR(F58*G58,0) | I58: =VLOOKUP(TablaObra5[[#This Row],[Obra]],Catalogos!$B$3:$C$10,2,FALSE) | K58: Diego Carreola Monroy
A59: 46184 | B59: Bacheo Toluca | D59: Limpieza | E59: =VLOOKUP(TablaObra5[[#This Row],[Equipo]],Catalogos!$I$4:$J$64,2,FALSE) | F59: 10 | G59: 28.3 | H59: =IFERROR(F59*G59,0) | I59: =VLOOKUP(TablaObra5[[#This Row],[Obra]],Catalogos!$B$3:$C$10,2,FALSE) | K59: Diego Carreola Monroy
A60: 46185 | B60: México-Toluca | C60: 46185 | D60: Perfiladora | E60: =VLOOKUP(TablaObra5[[#This Row],[Equipo]],Catalogos!$I$4:$J$64,2,FALSE) | F60: 250 | G60: 28.3 | H60: =IFERROR(F60*G60,0) | I60: =VLOOKUP(TablaObra5[[#This Row],[Obra]],Catalogos!$B$3:$C$10,2,FALSE)
A61: 46185 | B61: México-Toluca | C61: 46185 | D61: Vogel | E61: =VLOOKUP(TablaObra5[[#This Row],[Equipo]],Catalogos!$I$4:$J$64,2,FALSE) | F61: 150 | G61: 28.3 | H61: =IFERROR(F61*G61,0) | I61: =VLOOKUP(TablaObra5[[#This Row],[Obra]],Catalogos!$B$3:$C$10,2,FALSE)
A62: 46185 | B62: México-Toluca | C62: 46185 | D62: Compactador | E62: =VLOOKUP(TablaObra5[[#This Row],[Equipo]],Catalogos!$I$4:$J$64,2,FALSE) | F62: 40 | G62: 28.3 | H62: =IFERROR(F62*G62,0) | I62: =VLOOKUP(TablaObra5[[#This Row],[Obra]],Catalogos!$B$3:$C$10,2,FALSE)
A63: 46185 | B63: México-Toluca | C63: 46185 | D63: Neuomatico | E63: =VLOOKUP(TablaObra5[[#This Row],[Equipo]],Catalogos!$I$4:$J$64,2,FALSE) | F63: 30 | G63: 28.3 | H63: =IFERROR(F63*G63,0) | I63: =VLOOKUP(TablaObra5[[#This Row],[Obra]],Catalogos!$B$3:$C$10,2,FALSE)
A64: 46185 | B64: México-Toluca | C64: 46185 | D64: Retroexcavadora | E64: =VLOOKUP(TablaObra5[[#This Row],[Equipo]],Catalogos!$I$4:$J$64,2,FALSE) | F64: 30 | G64: 28.3 | H64: =IFERROR(F64*G64,0) | I64: =VLOOKUP(TablaObra5[[#This Row],[Obra]],Catalogos!$B$3:$C$10,2,FALSE)
A65: 46185 | B65: México-Toluca | C65: 46185 | D65: Barredora | E65: =VLOOKUP(TablaObra5[[#This Row],[Equipo]],Catalogos!$I$4:$J$64,2,FALSE) | F65: 20 | G65: 28.3 | H65: =IFERROR(F65*G65,0) | I65: =VLOOKUP(TablaObra5[[#This Row],[Obra]],Catalogos!$B$3:$C$10,2,FALSE)
A66: 46185 | B66: México-Toluca | C66: 46185 | D66: Maxilihgs | E66: =VLOOKUP(TablaObra5[[#This Row],[Equipo]],Catalogos!$I$4:$J$64,2,FALSE) | F66: 20 | G66: 28.3 | H66: =IFERROR(F66*G66,0) | I66: =VLOOKUP(TablaObra5[[#This Row],[Obra]],Catalogos!$B$3:$C$10,2,FALSE)
A67: 46185 | B67: Chamapa-Lechería | C67: 46185 | D67: Perfiladora Wirgent | E67: =VLOOKUP(TablaObra5[[#This Row],[Equipo]],Catalogos!$I$4:$J$64,2,FALSE) | F67: 250 | G67: 28.3 | H67: =IFERROR(F67*G67,0) | I67: =VLOOKUP(TablaObra5[[#This Row],[Obra]],Catalogos!$B$3:$C$10,2,FALSE)
A68: 46185 | B68: Chamapa-Lechería | C68: 46185 | D68: Barredora Broce | E68: =VLOOKUP(TablaObra5[[#This Row],[Equipo]],Catalogos!$I$4:$J$64,2,FALSE) | F68: 40 | G68: 28.3 | H68: =IFERROR(F68*G68,0) | I68: =VLOOKUP(TablaObra5[[#This Row],[Obra]],Catalogos!$B$3:$C$10,2,FALSE)
A69: 46185 | B69: Chamapa-Lechería | C69: 46185 | D69: Retroexcavadora Jonh Deere | E69: =VLOOKUP(TablaObra5[[#This Row],[Equipo]],Catalogos!$I$4:$J$64,2,FALSE) | F69: 60 | G69: 28.3 | H69: =IFERROR(F69*G69,0) | I69: =VLOOKUP(TablaObra5[[#This Row],[Obra]],Catalogos!$B$3:$C$10,2,FALSE)
A70: 46185 | B70: Chamapa-Lechería | C70: 46185 | D70: Vogele Guion | E70: =VLOOKUP(TablaObra5[[#This Row],[Equipo]],Catalogos!$I$4:$J$64,2,FALSE) | F70: 100 | G70: 28.3 | H70: =IFERROR(F70*G70,0) | I70: =VLOOKUP(TablaObra5[[#This Row],[Obra]],Catalogos!$B$3:$C$10,2,FALSE)
A71: 46185 | B71: Chamapa-Lechería | C71: 46185 | D71: Limpieza | E71: =VLOOKUP(TablaObra5[[#This Row],[Equipo]],Catalogos!$I$4:$J$64,2,FALSE) | F71: 20 | G71: 28.3 | H71: =IFERROR(F71*G71,0) | I71: =VLOOKUP(TablaObra5[[#This Row],[Obra]],Catalogos!$B$3:$C$10,2,FALSE)
... A85: 46187 | B85: Lerma - Tres Marías | C85: 46188 | D85: Barredora | E85: =VLOOKUP(TablaObra5[[#This Row],[Equipo]],Catalogos!$I$4:$J$64,2,FALSE) | F85: 40 | G85: 28.3 | H85: =IFERROR(F85*G85,0) | I85: =VLOOKUP(TablaObra5[[#This Row],[Obra]],Catalogos!$B$3:$C$10,2,FALSE)
A86: 46188 | B86: Bacheo Toluca | D86: Retroexcavadora | E86: =VLOOKUP(TablaObra5[[#This Row],[Equipo]],Catalogos!$I$4:$J$64,2,FALSE) | F86: 70 | G86: 28.3 | H86: =IFERROR(F86*G86,0) | I86: =VLOOKUP(TablaObra5[[#This Row],[Obra]],Catalogos!$B$3:$C$10,2,FALSE)
A87: 46188 | B87: Bacheo Toluca | D87: Perfiladora | E87: =VLOOKUP(TablaObra5[[#This Row],[Equipo]],Catalogos!$I$4:$J$64,2,FALSE) | F87: 200 | G87: 28.3 | H87: =IFERROR(F87*G87,0) | I87: =VLOOKUP(TablaObra5[[#This Row],[Obra]],Catalogos!$B$3:$C$10,2,FALSE)
A88: 46188 | B88: Bacheo Toluca | D88: Doble Rodillo | E88: =VLOOKUP(TablaObra5[[#This Row],[Equipo]],Catalogos!$I$4:$J$64,2,FALSE) | F88: 40 | G88: 28.3 | H88: =IFERROR(F88*G88,0) | I88: =VLOOKUP(TablaObra5[[#This Row],[Obra]],Catalogos!$B$3:$C$10,2,FALSE)
A89: 46188 | B89: Lerma - Tres Marías | C89: 46189 | D89: Limpieza | E89: =VLOOKUP(TablaObra5[[#This Row],[Equipo]],Catalogos!$I$4:$J$64,2,FALSE) | F89: 25 | G89: 28.3 | H89: =IFERROR(F89*G89,0) | I89: =VLOOKUP(TablaObra5[[#This Row],[Obra]],Catalogos!$B$3:$C$10,2,FALSE)
A90: 46188 | B90: Lerma - Tres Marías | C90: 46189 | D90: Petrolizadora | E90: =VLOOKUP(TablaObra5[[#This Row],[Equipo]],Catalogos!$I$4:$J$64,2,FALSE) | F90: 60 | G90: 28.3 | H90: =IFERROR(F90*G90,0) | I90: =VLOOKUP(TablaObra5[[#This Row],[Obra]],Catalogos!$B$3:$C$10,2,FALSE)
A91: 46188 | B91: Lerma - Tres Marías | C91: 46189 | D91: Tandem Hamm | E91: =VLOOKUP(TablaObra5[[#This Row],[Equipo]],Catalogos!$I$4:$J$64,2,FALSE) | F91: 50 | G91: 28.3 | H91: =IFERROR(F91*G91,0) | I91: =VLOOKUP(TablaObra5[[#This Row],[Obra]],Catalogos!$B$3:$C$10,2,FALSE)
A92: 46188 | B92: Lerma - Tres Marías | C92: 46189 | D92: Perfiladora | E92: =VLOOKUP(TablaObra5[[#This Row],[Equipo]],Catalogos!$I$4:$J$64,2,FALSE) | F92: 250 | G92: 28.3 | H92: =IFERROR(F92*G92,0) | I92: =VLOOKUP(TablaObra5[[#This Row],[Obra]],Catalogos!$B$3:$C$10,2,FALSE)
A93: 46188 | B93: Lerma - Tres Marías | C93: 46189 | D93: Barredora | E93: =VLOOKUP(TablaObra5[[#This Row],[Equipo]],Catalogos!$I$4:$J$64,2,FALSE) | F93: 70 | G93: 28.3 | H93: =IFERROR(F93*G93,0) | I93: =VLOOKUP(TablaObra5[[#This Row],[Obra]],Catalogos!$B$3:$C$10,2,FALSE)
A94: 46188 | B94: Lerma - Tres Marías | C94: 46189 | D94: Retroexcavadora | E94: =VLOOKUP(TablaObra5[[#This Row],[Equipo]],Catalogos!$I$4:$J$64,2,FALSE) | F94: 50 | G94: 28.3 | H94: =IFERROR(F94*G94,0) | I94: =VLOOKUP(TablaObra5[[#This Row],[Obra]],Catalogos!$B$3:$C$10,2,FALSE)
A95: 46188 | B95: México-Toluca | C95: 46189 | D95: Perfiladora Wirgent | E95: =VLOOKUP(TablaObra5[[#This Row],[Equipo]],Catalogos!$I$4:$J$64,2,FALSE) | F95: 250 | G95: 28.3 | H95: =IFERROR(F95*G95,0) | I95: =VLOOKUP(TablaObra5[[#This Row],[Obra]],Catalogos!$B$3:$C$10,2,FALSE)
A96: 46188 | B96: México-Toluca | C96: 46189 | D96: Vogele Guion | E96: =VLOOKUP(TablaObra5[[#This Row],[Equipo]],Catalogos!$I$4:$J$64,2,FALSE) | F96: 200 | G96: 28.3 | H96: =IFERROR(F96*G96,0) | I96: =VLOOKUP(TablaObra5[[#This Row],[Obra]],Catalogos!$B$3:$C$10,2,FALSE)
A97: 46188 | B97: México-Toluca | C97: 46189 | D97: Limpieza | E97: =VLOOKUP(TablaObra5[[#This Row],[Equipo]],Catalogos!$I$4:$J$64,2,FALSE) | F97: 20 | G97: 28.3 | H97: =IFERROR(F97*G97,0) | I97: =VLOOKUP(TablaObra5[[#This Row],[Obra]],Catalogos!$B$3:$C$10,2,FALSE)
A98: 46188 | B98: México-Toluca | C98: 46189 | D98: Tandem Hamm | E98: =VLOOKUP(TablaObra5[[#This Row],[Equipo]],Catalogos!$I$4:$J$64,2,FALSE) | F98: 50 | G98: 28.3 | H98: =IFERROR(F98*G98,0) | I98: =VLOOKUP(TablaObra5[[#This Row],[Obra]],Catalogos!$B$3:$C$10,2,FALSE)
A99: 46188 | B99: México-Toluca | C99: 46189 | D99: Neuomatico | E99: =VLOOKUP(TablaObra5[[#This Row],[Equipo]],Catalogos!$I$4:$J$64,2,FALSE) | F99: 50 | G99: 28.3 | H99: =IFERROR(F99*G99,0) | I99: =VLOOKUP(TablaObra5[[#This Row],[Obra]],Catalogos!$B$3:$C$10,2,FALSE)
A100: 46188 | B100: México-Toluca | C100: 46189 | D100: Barredora Broce | E100: =VLOOKUP(TablaObra5[[#This Row],[Equipo]],Catalogos!$I$4:$J$64,2,FALSE) | F100: 40 | G100: 28.3 | H100: =IFERROR(F100*G100,0) | I100: =VLOOKUP(TablaObra5[[#This Row],[Obra]],Catalogos!$B$3:$C$10,2,FALSE)
... A153: 46192 | B153: México-Toluca | C153: 46192 | D153: Petrolizadora | E153: =VLOOKUP(TablaObra5[[#This Row],[Equipo]],Catalogos!$I$4:$J$64,2,FALSE) | F153: 50 | G153: 28.3 | H153: =IFERROR(F153*G153,0) | I153: =VLOOKUP(TablaObra5[[#This Row],[Obra]],Catalogos!$B$3:$C$10,2,FALSE)
A154: 46192 | B154: Bacheo Toluca | D154: Retroexcavadora | E154: =VLOOKUP(TablaObra5[[#This Row],[Equipo]],Catalogos!$I$4:$J$64,2,FALSE) | F154: 60 | G154: 28.3 | H154: =IFERROR(F154*G154,0) | I154: =VLOOKUP(TablaObra5[[#This Row],[Obra]],Catalogos!$B$3:$C$10,2,FALSE)
A155: 46192 | B155: Bacheo Toluca | D155: Retroexcavadora | E155: =VLOOKUP(TablaObra5[[#This Row],[Equipo]],Catalogos!$I$4:$J$64,2,FALSE) | F155: 50 | G155: 28.3 | H155: =IFERROR(F155*G155,0) | I155: =VLOOKUP(TablaObra5[[#This Row],[Obra]],Catalogos!$B$3:$C$10,2,FALSE)
A156: 46194 | B156: Lerma - Tres Marías | C156: 46195 | D156: PERFILADORA RODATEC RX600E | E156: =VLOOKUP(TablaObra5[[#This Row],[Equipo]],Catalogos!$I$4:$J$64,2,FALSE) | F156: 240 | G156: 28.3 | H156: =IFERROR(F156*G156,0) | I156: =VLOOKUP(TablaObra5[[#This Row],[Obra]],Catalogos!$B$3:$C$10,2,FALSE)
A157: 46194 | B157: Lerma - Tres Marías | C157: 46195 | D157: BARREDORA LAYMOR SM400 | E157: =VLOOKUP(TablaObra5[[#This Row],[Equipo]],Catalogos!$I$4:$J$64,2,FALSE) | F157: 20 | G157: 28.3 | H157: =IFERROR(F157*G157,0) | I157: =VLOOKUP(TablaObra5[[#This Row],[Obra]],Catalogos!$B$3:$C$10,2,FALSE)
A158: 46194 | B158: Lerma - Tres Marías | C158: 46195 | D158: RETROEXCAVADORA JHONDEREE 310 K | E158: =VLOOKUP(TablaObra5[[#This Row],[Equipo]],Catalogos!$I$4:$J$64,2,FALSE) | F158: 30 | G158: 28.3 | H158: =IFERROR(F158*G158,0) | I158: =VLOOKUP(TablaObra5[[#This Row],[Obra]],Catalogos!$B$3:$C$10,2,FALSE)
A159: 46194 | B159: Lerma - Tres Marías | C159: 46195 | D159: PAVIMENTADORA VOGELE 1800-3 I | E159: =VLOOKUP(TablaObra5[[#This Row],[Equipo]],Catalogos!$I$4:$J$64,2,FALSE) | F159: 80 | G159: 28.3 | H159: =IFERROR(F159*G159,0) | I159: =VLOOKUP(TablaObra5[[#This Row],[Obra]],Catalogos!$B$3:$C$10,2,FALSE)
A160: 46194 | B160: Lerma - Tres Marías | C160: 46195 | D160: DOBLE RODILLO RAD ROLLER FILY-325 PRO | E160: =VLOOKUP(TablaObra5[[#This Row],[Equipo]],Catalogos!$I$4:$J$64,2,FALSE) | F160: 40 | G160: 28.3 | H160: =IFERROR(F160*G160,0) | I160: =VLOOKUP(TablaObra5[[#This Row],[Obra]],Catalogos!$B$3:$C$10,2,FALSE)
A161: 46194 | B161: Lerma - Tres Marías | C161: 46195 | D161: NEUMATICO / COMPACTADOR DE NEUMATICOS DINAPAC CP271 | E161: =VLOOKUP(TablaObra5[[#This Row],[Equipo]],Catalogos!$I$4:$J$64,2,FALSE) | F161: 24 | G161: 28.3 | H161: =IFERROR(F161*G161,0) | I161: =VLOOKUP(TablaObra5[[#This Row],[Obra]],Catalogos!$B$3:$C$10,2,FALSE)
A162: 46194 | B162: Lerma - Tres Marías | C162: 46195 | D162: IMPACTO FORD 4300 | E162: =VLOOKUP(TablaObra5[[#This Row],[Equipo]],Catalogos!$I$4:$J$64,2,FALSE) | F162: 60 | G162: 28.3 | H162: =IFERROR(F162*G162,0) | I162: =VLOOKUP(TablaObra5[[#This Row],[Obra]],Catalogos!$B$3:$C$10,2,FALSE)
A163: 46194 | B163: Lerma - Tres Marías | C163: 46195 | D163: COMPRESOR SULLIVAN PALATEK D2010 | E163: =VLOOKUP(TablaObra5[[#This Row],[Equipo]],Catalogos!$I$4:$J$64,2,FALSE) | F163: 24 | G163: 28.3 | H163: =IFERROR(F163*G163,0) | I163: =VLOOKUP(TablaObra5[[#This Row],[Obra]],Catalogos!$B$3:$C$10,2,FALSE)
A164: 46194 | B164: Lerma - Tres Marías | C164: 46195 | D164: PETROLIZADORA INTERNATIONAL | E164: =VLOOKUP(TablaObra5[[#This Row],[Equipo]],Catalogos!$I$4:$J$64,2,FALSE) | F164: 60 | G164: 28.3 | H164: =IFERROR(F164*G164,0) | I164: =VLOOKUP(TablaObra5[[#This Row],[Obra]],Catalogos!$B$3:$C$10,2,FALSE)
A165: 46194 | B165: Lerma - Tres Marías | C165: 46196 | D165: PERFILADORA RODATEC RX600E | E165: =VLOOKUP(TablaObra5[[#This Row],[Equipo]],Catalogos!$I$4:$J$64,2,FALSE) | F165: 240 | G165: 28.3 | H165: =IFERROR(F165*G165,0) | I165: =VLOOKUP(TablaObra5[[#This Row],[Obra]],Catalogos!$B$3:$C$10,2,FALSE)
A166: 46194 | B166: Lerma - Tres Marías | C166: 46196 | D166: BARREDORA LAYMOR SM400 | E166: =VLOOKUP(TablaObra5[[#This Row],[Equipo]],Catalogos!$I$4:$J$64,2,FALSE) | F166: 20 | G166: 28.3 | H166: =IFERROR(F166*G166,0) | I166: =VLOOKUP(TablaObra5[[#This Row],[Obra]],Catalogos!$B$3:$C$10,2,FALSE)
A167: 46194 | B167: Lerma - Tres Marías | C167: 46196 | D167: RETROEXCAVADORA JHONDEREE 310 K | E167: =VLOOKUP(TablaObra5[[#This Row],[Equipo]],Catalogos!$I$4:$J$64,2,FALSE) | F167: 30 | G167: 28.3 | H167: =IFERROR(F167*G167,0) | I167: =VLOOKUP(TablaObra5[[#This Row],[Obra]],Catalogos!$B$3:$C$10,2,FALSE)
... A283: 46194 | B283: Lerma - Tres Marías | C283: 46199 | D283: PIPA DE AGUA (IMPACTO 01) FORD | E283: =VLOOKUP(TablaObra5[[#This Row],[Equipo]],Catalogos!$I$4:$J$64,2,FALSE) | F283: 30 | G283: 28.3 | H283: =IFERROR(F283*G283,0) | I283: =VLOOKUP(TablaObra5[[#This Row],[Obra]],Catalogos!$B$3:$C$10,2,FALSE)
E284: =VLOOKUP(TablaObra5[[#This Row],[Equipo]],Catalogos!$I$4:$J$64,2,FALSE) | G284: 28.3 | H284: =IFERROR(F284*G284,0) | I284: =VLOOKUP(TablaObra5[[#This Row],[Obra]],Catalogos!$B$3:$C$10,2,FALSE)
E285: =VLOOKUP(TablaObra5[[#This Row],[Equipo]],Catalogos!$I$4:$J$64,2,FALSE) | G285: 28.3 | H285: =IFERROR(F285*G285,0) | I285: =VLOOKUP(TablaObra5[[#This Row],[Obra]],Catalogos!$B$3:$C$10,2,FALSE)
E286: =VLOOKUP(TablaObra5[[#This Row],[Equipo]],Catalogos!$I$4:$J$64,2,FALSE) | G286: 28.3 | H286: =IFERROR(F286*G286,0) | I286: =VLOOKUP(TablaObra5[[#This Row],[Obra]],Catalogos!$B$3:$C$10,2,FALSE)
E287: =VLOOKUP(TablaObra5[[#This Row],[Equipo]],Catalogos!$I$4:$J$64,2,FALSE) | G287: 28.3 | H287: =IFERROR(F287*G287,0) | I287: =VLOOKUP(TablaObra5[[#This Row],[Obra]],Catalogos!$B$3:$C$10,2,FALSE)
E288: =VLOOKUP(TablaObra5[[#This Row],[Equipo]],Catalogos!$I$4:$J$64,2,FALSE) | G288: 28.3 | H288: =IFERROR(F288*G288,0) | I288: =VLOOKUP(TablaObra5[[#This Row],[Obra]],Catalogos!$B$3:$C$10,2,FALSE)
E289: =VLOOKUP(TablaObra5[[#This Row],[Equipo]],Catalogos!$I$4:$J$64,2,FALSE) | G289: 28.3 | H289: =IFERROR(F289*G289,0) | I289: =VLOOKUP(TablaObra5[[#This Row],[Obra]],Catalogos!$B$3:$C$10,2,FALSE)
E290: =VLOOKUP(TablaObra5[[#This Row],[Equipo]],Catalogos!$I$4:$J$64,2,FALSE) | G290: 28.3 | H290: =IFERROR(F290*G290,0) | I290: =VLOOKUP(TablaObra5[[#This Row],[Obra]],Catalogos!$B$3:$C$10,2,FALSE)
E291: =VLOOKUP(TablaObra5[[#This Row],[Equipo]],Catalogos!$I$4:$J$64,2,FALSE) | G291: 28.3 | H291: =IFERROR(F291*G291,0) | I291: =VLOOKUP(TablaObra5[[#This Row],[Obra]],Catalogos!$B$3:$C$10,2,FALSE)
E292: =VLOOKUP(TablaObra5[[#This Row],[Equipo]],Catalogos!$I$4:$J$64,2,FALSE) | G292: 28.3 | H292: =IFERROR(F292*G292,0) | I292: =VLOOKUP(TablaObra5[[#This Row],[Obra]],Catalogos!$B$3:$C$10,2,FALSE)
E293: =VLOOKUP(TablaObra5[[#This Row],[Equipo]],Catalogos!$I$4:$J$64,2,FALSE) | G293: 28.3 | H293: =IFERROR(F293*G293,0) | I293: =VLOOKUP(TablaObra5[[#This Row],[Obra]],Catalogos!$B$3:$C$10,2,FALSE)
...

Sheet Conciliacion
B2: CONCILIACIÓN SEMANAL: DESPACHADO VS RECIBIDO
B3: SEMANA: | C3: =Dashboard!C5
B5: Obra | C5: Despachado por Marimba (Lts) | D5: Despachado por Pegaso (Lts) | E5: Total Despachado (Lts) | F5: Recibido en Obra (Lts) | G5: Diferencia / Desvío (Lts)
B6: =IF(ROWS($6:6)<=MAX(Catalogos!$R$4:$R$11), IFERROR(INDEX(Catalogos!$B$4:$B$11, MATCH(ROWS($6:6), Catalogos!$R$4:$R$11, 0)), ""), IF(ROWS($6:6)=MAX(Catalogos!$R$4:$R$11)+1, "TOTAL GENERAL", "")) | C6: =IF(ROWS($6:6)<=MAX(Catalogos!$R$4:$R$11), SUMIFS(Captura_Marimba_M01!$G:$G, Captura_Marimba_M01!$C:$C, $B6, Captura_Marimba_M01!$A:$A, ">=" & $C$3, Captura_Marimba_M01!$A:$A, "<=" & ($C$3+6)), IF(ROWS($6:6)=MAX(Catalogos!$R$4:$R$11)+1, SUMIFS(Captura_Marimba_M01!$G:$G, Captura_Marimba_M01!$A:$A, ">=" & $C$3, Captura_Marimba_M01!$A:$A, "<=" & ($C$3+6)), "")) | D6: =IF(ROWS($6:6)<=MAX(Catalogos!$R$4:$R$11), SUMIFS(Captura_Pegaso!$H:$H, Captura_Pegaso!$D:$D, $B6, Captura_Pegaso!$A:$A, ">=" & $C$3, Captura_Pegaso!$A:$A, "<=" & ($C$3+6)), IF(ROWS($6:6)=MAX(Catalogos!$R$4:$R$11)+1, SUMIFS(Captura_Pegaso!$H:$H, Captura_Pegaso!$A:$A, ">=" & $C$3, Captura_Pegaso!$A:$A, "<=" & ($C$3+6)), "")) | E6: =IF(ROWS($6:6)<=MAX(Catalogos!$R$4:$R$11)+1, C6+D6, "") | F6: =IF(ROWS($6:6)<=MAX(Catalogos!$R$4:$R$11), SUMIFS(Captura_Obra!$F:$F, Captura_Obra!$B:$B, $B6, Captura_Obra!$A:$A, ">=" & $C$3, Captura_Obra!$A:$A, "<=" & ($C$3+6)), IF(ROWS($6:6)=MAX(Catalogos!$R$4:$R$11)+1, SUMIFS(Captura_Obra!$F:$F, Captura_Obra!$A:$A, ">=" & $C$3, Captura_Obra!$A:$A, "<=" & ($C$3+6)), "")) | G6: =IF(ROWS($6:6)<=MAX(Catalogos!$R$4:$R$11)+1, E6-F6, "")
B7: =IF(ROWS($6:7)<=MAX(Catalogos!$R$4:$R$11), IFERROR(INDEX(Catalogos!$B$4:$B$11, MATCH(ROWS($6:7), Catalogos!$R$4:$R$11, 0)), ""), IF(ROWS($6:7)=MAX(Catalogos!$R$4:$R$11)+1, "TOTAL GENERAL", "")) | C7: =IF(ROWS($6:7)<=MAX(Catalogos!$R$4:$R$11), SUMIFS(Captura_Marimba_M01!$G:$G, Captura_Marimba_M01!$C:$C, $B7, Captura_Marimba_M01!$A:$A, ">=" & $C$3, Captura_Marimba_M01!$A:$A, "<=" & ($C$3+6)), IF(ROWS($6:7)=MAX(Catalogos!$R$4:$R$11)+1, SUMIFS(Captura_Marimba_M01!$G:$G, Captura_Marimba_M01!$A:$A, ">=" & $C$3, Captura_Marimba_M01!$A:$A, "<=" & ($C$3+6)), "")) | D7: =IF(ROWS($6:7)<=MAX(Catalogos!$R$4:$R$11), SUMIFS(Captura_Pegaso!$H:$H, Captura_Pegaso!$D:$D, $B7, Captura_Pegaso!$A:$A, ">=" & $C$3, Captura_Pegaso!$A:$A, "<=" & ($C$3+6)), IF(ROWS($6:7)=MAX(Catalogos!$R$4:$R$11)+1, SUMIFS(Captura_Pegaso!$H:$H, Captura_Pegaso!$A:$A, ">=" & $C$3, Captura_Pegaso!$A:$A, "<=" & ($C$3+6)), "")) | E7: =IF(ROWS($6:7)<=MAX(Catalogos!$R$4:$R$11)+1, C7+D7, "") | F7: =IF(ROWS($6:7)<=MAX(Catalogos!$R$4:$R$11), SUMIFS(Captura_Obra!$F:$F, Captura_Obra!$B:$B, $B7, Captura_Obra!$A:$A, ">=" & $C$3, Captura_Obra!$A:$A, "<=" & ($C$3+6)), IF(ROWS($6:7)=MAX(Catalogos!$R$4:$R$11)+1, SUMIFS(Captura_Obra!$F:$F, Captura_Obra!$A:$A, ">=" & $C$3, Captura_Obra!$A:$A, "<=" & ($C$3+6)), "")) | G7: =IF(ROWS($6:7)<=MAX(Catalogos!$R$4:$R$11)+1, E7-F7, "")
B8: =IF(ROWS($6:8)<=MAX(Catalogos!$R$4:$R$11), IFERROR(INDEX(Catalogos!$B$4:$B$11, MATCH(ROWS($6:8), Catalogos!$R$4:$R$11, 0)), ""), IF(ROWS($6:8)=MAX(Catalogos!$R$4:$R$11)+1, "TOTAL GENERAL", "")) | C8: =IF(ROWS($6:8)<=MAX(Catalogos!$R$4:$R$11), SUMIFS(Captura_Marimba_M01!$G:$G, Captura_Marimba_M01!$C:$C, $B8, Captura_Marimba_M01!$A:$A, ">=" & $C$3, Captura_Marimba_M01!$A:$A, "<=" & ($C$3+6)), IF(ROWS($6:8)=MAX(Catalogos!$R$4:$R$11)+1, SUMIFS(Captura_Marimba_M01!$G:$G, Captura_Marimba_M01!$A:$A, ">=" & $C$3, Captura_Marimba_M01!$A:$A, "<=" & ($C$3+6)), "")) | D8: =IF(ROWS($6:8)<=MAX(Catalogos!$R$4:$R$11), SUMIFS(Captura_Pegaso!$H:$H, Captura_Pegaso!$D:$D, $B8, Captura_Pegaso!$A:$A, ">=" & $C$3, Captura_Pegaso!$A:$A, "<=" & ($C$3+6)), IF(ROWS($6:8)=MAX(Catalogos!$R$4:$R$11)+1, SUMIFS(Captura_Pegaso!$H:$H, Captura_Pegaso!$A:$A, ">=" & $C$3, Captura_Pegaso!$A:$A, "<=" & ($C$3+6)), "")) | E8: =IF(ROWS($6:8)<=MAX(Catalogos!$R$4:$R$11)+1, C8+D8, "") | F8: =IF(ROWS($6:8)<=MAX(Catalogos!$R$4:$R$11), SUMIFS(Captura_Obra!$F:$F, Captura_Obra!$B:$B, $B8, Captura_Obra!$A:$A, ">=" & $C$3, Captura_Obra!$A:$A, "<=" & ($C$3+6)), IF(ROWS($6:8)=MAX(Catalogos!$R$4:$R$11)+1, SUMIFS(Captura_Obra!$F:$F, Captura_Obra!$A:$A, ">=" & $C$3, Captura_Obra!$A:$A, "<=" & ($C$3+6)), "")) | G8: =IF(ROWS($6:8)<=MAX(Catalogos!$R$4:$R$11)+1, E8-F8, "")
B9: =IF(ROWS($6:9)<=MAX(Catalogos!$R$4:$R$11), IFERROR(INDEX(Catalogos!$B$4:$B$11, MATCH(ROWS($6:9), Catalogos!$R$4:$R$11, 0)), ""), IF(ROWS($6:9)=MAX(Catalogos!$R$4:$R$11)+1, "TOTAL GENERAL", "")) | C9: =IF(ROWS($6:9)<=MAX(Catalogos!$R$4:$R$11), SUMIFS(Captura_Marimba_M01!$G:$G, Captura_Marimba_M01!$C:$C, $B9, Captura_Marimba_M01!$A:$A, ">=" & $C$3, Captura_Marimba_M01!$A:$A, "<=" & ($C$3+6)), IF(ROWS($6:9)=MAX(Catalogos!$R$4:$R$11)+1, SUMIFS(Captura_Marimba_M01!$G:$G, Captura_Marimba_M01!$A:$A, ">=" & $C$3, Captura_Marimba_M01!$A:$A, "<=" & ($C$3+6)), "")) | D9: =IF(ROWS($6:9)<=MAX(Catalogos!$R$4:$R$11), SUMIFS(Captura_Pegaso!$H:$H, Captura_Pegaso!$D:$D, $B9, Captura_Pegaso!$A:$A, ">=" & $C$3, Captura_Pegaso!$A:$A, "<=" & ($C$3+6)), IF(ROWS($6:9)=MAX(Catalogos!$R$4:$R$11)+1, SUMIFS(Captura_Pegaso!$H:$H, Captura_Pegaso!$A:$A, ">=" & $C$3, Captura_Pegaso!$A:$A, "<=" & ($C$3+6)), "")) | E9: =IF(ROWS($6:9)<=MAX(Catalogos!$R$4:$R$11)+1, C9+D9, "") | F9: =IF(ROWS($6:9)<=MAX(Catalogos!$R$4:$R$11), SUMIFS(Captura_Obra!$F:$F, Captura_Obra!$B:$B, $B9, Captura_Obra!$A:$A, ">=" & $C$3, Captura_Obra!$A:$A, "<=" & ($C$3+6)), IF(ROWS($6:9)=MAX(Catalogos!$R$4:$R$11)+1, SUMIFS(Captura_Obra!$F:$F, Captura_Obra!$A:$A, ">=" & $C$3, Captura_Obra!$A:$A, "<=" & ($C$3+6)), "")) | G9: =IF(ROWS($6:9)<=MAX(Catalogos!$R$4:$R$11)+1, E9-F9, "")
B10: =IF(ROWS($6:10)<=MAX(Catalogos!$R$4:$R$11), IFERROR(INDEX(Catalogos!$B$4:$B$11, MATCH(ROWS($6:10), Catalogos!$R$4:$R$11, 0)), ""), IF(ROWS($6:10)=MAX(Catalogos!$R$4:$R$11)+1, "TOTAL GENERAL", "")) | C10: =IF(ROWS($6:10)<=MAX(Catalogos!$R$4:$R$11), SUMIFS(Captura_Marimba_M01!$G:$G, Captura_Marimba_M01!$C:$C, $B10, Captura_Marimba_M01!$A:$A, ">=" & $C$3, Captura_Marimba_M01!$A:$A, "<=" & ($C$3+6)), IF(ROWS($6:10)=MAX(Catalogos!$R$4:$R$11)+1, SUMIFS(Captura_Marimba_M01!$G:$G, Captura_Marimba_M01!$A:$A, ">=" & $C$3, Captura_Marimba_M01!$A:$A, "<=" & ($C$3+6)), "")) | D10: =IF(ROWS($6:10)<=MAX(Catalogos!$R$4:$R$11), SUMIFS(Captura_Pegaso!$H:$H, Captura_Pegaso!$D:$D, $B10, Captura_Pegaso!$A:$A, ">=" & $C$3, Captura_Pegaso!$A:$A, "<=" & ($C$3+6)), IF(ROWS($6:10)=MAX(Catalogos!$R$4:$R$11)+1, SUMIFS(Captura_Pegaso!$H:$H, Captura_Pegaso!$A:$A, ">=" & $C$3, Captura_Pegaso!$A:$A, "<=" & ($C$3+6)), "")) | E10: =IF(ROWS($6:10)<=MAX(Catalogos!$R$4:$R$11)+1, C10+D10, "") | F10: =IF(ROWS($6:10)<=MAX(Catalogos!$R$4:$R$11), SUMIFS(Captura_Obra!$F:$F, Captura_Obra!$B:$B, $B10, Captura_Obra!$A:$A, ">=" & $C$3, Captura_Obra!$A:$A, "<=" & ($C$3+6)), IF(ROWS($6:10)=MAX(Catalogos!$R$4:$R$11)+1, SUMIFS(Captura_Obra!$F:$F, Captura_Obra!$A:$A, ">=" & $C$3, Captura_Obra!$A:$A, "<=" & ($C$3+6)), "")) | G10: =IF(ROWS($6:10)<=MAX(Catalogos!$R$4:$R$11)+1, E10-F10, "")
B11: =IF(ROWS($6:11)<=MAX(Catalogos!$R$4:$R$11), IFERROR(INDEX(Catalogos!$B$4:$B$11, MATCH(ROWS($6:11), Catalogos!$R$4:$R$11, 0)), ""), IF(ROWS($6:11)=MAX(Catalogos!$R$4:$R$11)+1, "TOTAL GENERAL", "")) | C11: =IF(ROWS($6:11)<=MAX(Catalogos!$R$4:$R$11), SUMIFS(Captura_Marimba_M01!$G:$G, Captura_Marimba_M01!$C:$C, $B11, Captura_Marimba_M01!$A:$A, ">=" & $C$3, Captura_Marimba_M01!$A:$A, "<=" & ($C$3+6)), IF(ROWS($6:11)=MAX(Catalogos!$R$4:$R$11)+1, SUMIFS(Captura_Marimba_M01!$G:$G, Captura_Marimba_M01!$A:$A, ">=" & $C$3, Captura_Marimba_M01!$A:$A, "<=" & ($C$3+6)), "")) | D11: =IF(ROWS($6:11)<=MAX(Catalogos!$R$4:$R$11), SUMIFS(Captura_Pegaso!$H:$H, Captura_Pegaso!$D:$D, $B11, Captura_Pegaso!$A:$A, ">=" & $C$3, Captura_Pegaso!$A:$A, "<=" & ($C$3+6)), IF(ROWS($6:11)=MAX(Catalogos!$R$4:$R$11)+1, SUMIFS(Captura_Pegaso!$H:$H, Captura_Pegaso!$A:$A, ">=" & $C$3, Captura_Pegaso!$A:$A, "<=" & ($C$3+6)), "")) | E11: =IF(ROWS($6:11)<=MAX(Catalogos!$R$4:$R$11)+1, C11+D11, "") | F11: =IF(ROWS($6:11)<=MAX(Catalogos!$R$4:$R$11), SUMIFS(Captura_Obra!$F:$F, Captura_Obra!$B:$B, $B11, Captura_Obra!$A:$A, ">=" & $C$3, Captura_Obra!$A:$A, "<=" & ($C$3+6)), IF(ROWS($6:11)=MAX(Catalogos!$R$4:$R$11)+1, SUMIFS(Captura_Obra!$F:$F, Captura_Obra!$A:$A, ">=" & $C$3, Captura_Obra!$A:$A, "<=" & ($C$3+6)), "")) | G11: =IF(ROWS($6:11)<=MAX(Catalogos!$R$4:$R$11)+1, E11-F11, "")
B12: =IF(ROWS($6:12)<=MAX(Catalogos!$R$4:$R$11), IFERROR(INDEX(Catalogos!$B$4:$B$11, MATCH(ROWS($6:12), Catalogos!$R$4:$R$11, 0)), ""), IF(ROWS($6:12)=MAX(Catalogos!$R$4:$R$11)+1, "TOTAL GENERAL", "")) | C12: =IF(ROWS($6:12)<=MAX(Catalogos!$R$4:$R$11), SUMIFS(Captura_Marimba_M01!$G:$G, Captura_Marimba_M01!$C:$C, $B12, Captura_Marimba_M01!$A:$A, ">=" & $C$3, Captura_Marimba_M01!$A:$A, "<=" & ($C$3+6)), IF(ROWS($6:12)=MAX(Catalogos!$R$4:$R$11)+1, SUMIFS(Captura_Marimba_M01!$G:$G, Captura_Marimba_M01!$A:$A, ">=" & $C$3, Captura_Marimba_M01!$A:$A, "<=" & ($C$3+6)), "")) | D12: =IF(ROWS($6:12)<=MAX(Catalogos!$R$4:$R$11), SUMIFS(Captura_Pegaso!$H:$H, Captura_Pegaso!$D:$D, $B12, Captura_Pegaso!$A:$A, ">=" & $C$3, Captura_Pegaso!$A:$A, "<=" & ($C$3+6)), IF(ROWS($6:12)=MAX(Catalogos!$R$4:$R$11)+1, SUMIFS(Captura_Pegaso!$H:$H, Captura_Pegaso!$A:$A, ">=" & $C$3, Captura_Pegaso!$A:$A, "<=" & ($C$3+6)), "")) | E12: =IF(ROWS($6:12)<=MAX(Catalogos!$R$4:$R$11)+1, C12+D12, "") | F12: =IF(ROWS($6:12)<=MAX(Catalogos!$R$4:$R$11), SUMIFS(Captura_Obra!$F:$F, Captura_Obra!$B:$B, $B12, Captura_Obra!$A:$A, ">=" & $C$3, Captura_Obra!$A:$A, "<=" & ($C$3+6)), IF(ROWS($6:12)=MAX(Catalogos!$R$4:$R$11)+1, SUMIFS(Captura_Obra!$F:$F, Captura_Obra!$A:$A, ">=" & $C$3, Captura_Obra!$A:$A, "<=" & ($C$3+6)), "")) | G12: =IF(ROWS($6:12)<=MAX(Catalogos!$R$4:$R$11)+1, E12-F12, "")
B13: =IF(ROWS($6:13)<=MAX(Catalogos!$R$4:$R$11), IFERROR(INDEX(Catalogos!$B$4:$B$11, MATCH(ROWS($6:13), Catalogos!$R$4:$R$11, 0)), ""), IF(ROWS($6:13)=MAX(Catalogos!$R$4:$R$11)+1, "TOTAL GENERAL", "")) | C13: =IF(ROWS($6:13)<=MAX(Catalogos!$R$4:$R$11), SUMIFS(Captura_Marimba_M01!$G:$G, Captura_Marimba_M01!$C:$C, $B13, Captura_Marimba_M01!$A:$A, ">=" & $C$3, Captura_Marimba_M01!$A:$A, "<=" & ($C$3+6)), IF(ROWS($6:13)=MAX(Catalogos!$R$4:$R$11)+1, SUMIFS(Captura_Marimba_M01!$G:$G, Captura_Marimba_M01!$A:$A, ">=" & $C$3, Captura_Marimba_M01!$A:$A, "<=" & ($C$3+6)), "")) | D13: =IF(ROWS($6:13)<=MAX(Catalogos!$R$4:$R$11), SUMIFS(Captura_Pegaso!$H:$H, Captura_Pegaso!$D:$D, $B13, Captura_Pegaso!$A:$A, ">=" & $C$3, Captura_Pegaso!$A:$A, "<=" & ($C$3+6)), IF(ROWS($6:13)=MAX(Catalogos!$R$4:$R$11)+1, SUMIFS(Captura_Pegaso!$H:$H, Captura_Pegaso!$A:$A, ">=" & $C$3, Captura_Pegaso!$A:$A, "<=" & ($C$3+6)), "")) | E13: =IF(ROWS($6:13)<=MAX(Catalogos!$R$4:$R$11)+1, C13+D13, "") | F13: =IF(ROWS($6:13)<=MAX(Catalogos!$R$4:$R$11), SUMIFS(Captura_Obra!$F:$F, Captura_Obra!$B:$B, $B13, Captura_Obra!$A:$A, ">=" & $C$3, Captura_Obra!$A:$A, "<=" & ($C$3+6)), IF(ROWS($6:13)=MAX(Catalogos!$R$4:$R$11)+1, SUMIFS(Captura_Obra!$F:$F, Captura_Obra!$A:$A, ">=" & $C$3, Captura_Obra!$A:$A, "<=" & ($C$3+6)), "")) | G13: =IF(ROWS($6:13)<=MAX(Catalogos!$R$4:$R$11)+1, E13-F13, "")
B14: =IF(ROWS($6:14)<=MAX(Catalogos!$R$4:$R$11), IFERROR(INDEX(Catalogos!$B$4:$B$11, MATCH(ROWS($6:14), Catalogos!$R$4:$R$11, 0)), ""), IF(ROWS($6:14)=MAX(Catalogos!$R$4:$R$11)+1, "TOTAL GENERAL", "")) | C14: =IF(ROWS($6:14)<=MAX(Catalogos!$R$4:$R$11), SUMIFS(Captura_Marimba_M01!$G:$G, Captura_Marimba_M01!$C:$C, $B14, Captura_Marimba_M01!$A:$A, ">=" & $C$3, Captura_Marimba_M01!$A:$A, "<=" & ($C$3+6)), IF(ROWS($6:14)=MAX(Catalogos!$R$4:$R$11)+1, SUMIFS(Captura_Marimba_M01!$G:$G, Captura_Marimba_M01!$A:$A, ">=" & $C$3, Captura_Marimba_M01!$A:$A, "<=" & ($C$3+6)), "")) | D14: =IF(ROWS($6:14)<=MAX(Catalogos!$R$4:$R$11), SUMIFS(Captura_Pegaso!$H:$H, Captura_Pegaso!$D:$D, $B14, Captura_Pegaso!$A:$A, ">=" & $C$3, Captura_Pegaso!$A:$A, "<=" & ($C$3+6)), IF(ROWS($6:14)=MAX(Catalogos!$R$4:$R$11)+1, SUMIFS(Captura_Pegaso!$H:$H, Captura_Pegaso!$A:$A, ">=" & $C$3, Captura_Pegaso!$A:$A, "<=" & ($C$3+6)), "")) | E14: =IF(ROWS($6:14)<=MAX(Catalogos!$R$4:$R$11)+1, C14+D14, "") | F14: =IF(ROWS($6:14)<=MAX(Catalogos!$R$4:$R$11), SUMIFS(Captura_Obra!$F:$F, Captura_Obra!$B:$B, $B14, Captura_Obra!$A:$A, ">=" & $C$3, Captura_Obra!$A:$A, "<=" & ($C$3+6)), IF(ROWS($6:14)=MAX(Catalogos!$R$4:$R$11)+1, SUMIFS(Captura_Obra!$F:$F, Captura_Obra!$A:$A, ">=" & $C$3, Captura_Obra!$A:$A, "<=" & ($C$3+6)), "")) | G14: =IF(ROWS($6:14)<=MAX(Catalogos!$R$4:$R$11)+1, E14-F14, "")
B18: CONCILIACIÓN DIARIA POR OBRA: DESPACHADO VS RECIBIDO
B19: SEMANA: | C19: =$C$3
B20: OBRA: | C20: Lerma - Tres Marías
B22: Día de la Semana | C22: Despachado por Marimba (Lts) | D22: Despachado por Pegaso (Lts) | E22: Total Despachado (Lts) | F22: Recibido en Obra (Lts) | G22: Diferencia / Desvío (Lts)
B23: =$C$19 | C23: =IF(OR($C$19="", $C$20=""), "", SUMIFS(Captura_Marimba_M01!$G:$G, Captura_Marimba_M01!$C:$C, $C$20, Captura_Marimba_M01!$A:$A, $B23)) | D23: =IF(OR($C$19="", $C$20=""), "", SUMIFS(Captura_Pegaso!$H:$H, Captura_Pegaso!$D:$D, $C$20, Captura_Pegaso!$A:$A, $B23)) | E23: =IF(OR($C$19="", $C$20=""), "", C23+D23) | F23: =IF(OR($C$19="", $C$20=""), "", SUMIFS(Captura_Obra!$F:$F, Captura_Obra!$B:$B, $C$20, Captura_Obra!$A:$A, $B23)) | G23: =IF(OR($C$19="", $C$20=""), "", E23-F23)
B24: =B23+1 | C24: =IF(OR($C$19="", $C$20=""), "", SUMIFS(Captura_Marimba_M01!$G:$G, Captura_Marimba_M01!$C:$C, $C$20, Captura_Marimba_M01!$A:$A, $B24)) | D24: =IF(OR($C$19="", $C$20=""), "", SUMIFS(Captura_Pegaso!$H:$H, Captura_Pegaso!$D:$D, $C$20, Captura_Pegaso!$A:$A, $B24)) | E24: =IF(OR($C$19="", $C$20=""), "", C24+D24) | F24: =IF(OR($C$19="", $C$20=""), "", SUMIFS(Captura_Obra!$F:$F, Captura_Obra!$B:$B, $C$20, Captura_Obra!$A:$A, $B24)) | G24: =IF(OR($C$19="", $C$20=""), "", E24-F24)
B25: =B24+1 | C25: =IF(OR($C$19="", $C$20=""), "", SUMIFS(Captura_Marimba_M01!$G:$G, Captura_Marimba_M01!$C:$C, $C$20, Captura_Marimba_M01!$A:$A, $B25)) | D25: =IF(OR($C$19="", $C$20=""), "", SUMIFS(Captura_Pegaso!$H:$H, Captura_Pegaso!$D:$D, $C$20, Captura_Pegaso!$A:$A, $B25)) | E25: =IF(OR($C$19="", $C$20=""), "", C25+D25) | F25: =IF(OR($C$19="", $C$20=""), "", SUMIFS(Captura_Obra!$F:$F, Captura_Obra!$B:$B, $C$20, Captura_Obra!$A:$A, $B25)) | G25: =IF(OR($C$19="", $C$20=""), "", E25-F25)
B26: =B25+1 | C26: =IF(OR($C$19="", $C$20=""), "", SUMIFS(Captura_Marimba_M01!$G:$G, Captura_Marimba_M01!$C:$C, $C$20, Captura_Marimba_M01!$A:$A, $B26)) | D26: =IF(OR($C$19="", $C$20=""), "", SUMIFS(Captura_Pegaso!$H:$H, Captura_Pegaso!$D:$D, $C$20, Captura_Pegaso!$A:$A, $B26)) | E26: =IF(OR($C$19="", $C$20=""), "", C26+D26) | F26: =IF(OR($C$19="", $C$20=""), "", SUMIFS(Captura_Obra!$F:$F, Captura_Obra!$B:$B, $C$20, Captura_Obra!$A:$A, $B26)) | G26: =IF(OR($C$19="", $C$20=""), "", E26-F26)
B27: =B26+1 | C27: =IF(OR($C$19="", $C$20=""), "", SUMIFS(Captura_Marimba_M01!$G:$G, Captura_Marimba_M01!$C:$C, $C$20, Captura_Marimba_M01!$A:$A, $B27)) | D27: =IF(OR($C$19="", $C$20=""), "", SUMIFS(Captura_Pegaso!$H:$H, Captura_Pegaso!$D:$D, $C$20, Captura_Pegaso!$A:$A, $B27)) | E27: =IF(OR($C$19="", $C$20=""), "", C27+D27) | F27: =IF(OR($C$19="", $C$20=""), "", SUMIFS(Captura_Obra!$F:$F, Captura_Obra!$B:$B, $C$20, Captura_Obra!$A:$A, $B27)) | G27: =IF(OR($C$19="", $C$20=""), "", E27-F27)
B28: =B27+1 | C28: =IF(OR($C$19="", $C$20=""), "", SUMIFS(Captura_Marimba_M01!$G:$G, Captura_Marimba_M01!$C:$C, $C$20, Captura_Marimba_M01!$A:$A, $B28)) | D28: =IF(OR($C$19="", $C$20=""), "", SUMIFS(Captura_Pegaso!$H:$H, Captura_Pegaso!$D:$D, $C$20, Captura_Pegaso!$A:$A, $B28)) | E28: =IF(OR($C$19="", $C$20=""), "", C28+D28) | F28: =IF(OR($C$19="", $C$20=""), "", SUMIFS(Captura_Obra!$F:$F, Captura_Obra!$B:$B, $C$20, Captura_Obra!$A:$A, $B28)) | G28: =IF(OR($C$19="", $C$20=""), "", E28-F28)
B29: =B28+1 | C29: =IF(OR($C$19="", $C$20=""), "", SUMIFS(Captura_Marimba_M01!$G:$G, Captura_Marimba_M01!$C:$C, $C$20, Captura_Marimba_M01!$A:$A, $B29)) | D29: =IF(OR($C$19="", $C$20=""), "", SUMIFS(Captura_Pegaso!$H:$H, Captura_Pegaso!$D:$D, $C$20, Captura_Pegaso!$A:$A, $B29)) | E29: =IF(OR($C$19="", $C$20=""), "", C29+D29) | F29: =IF(OR($C$19="", $C$20=""), "", SUMIFS(Captura_Obra!$F:$F, Captura_Obra!$B:$B, $C$20, Captura_Obra!$A:$A, $B29)) | G29: =IF(OR($C$19="", $C$20=""), "", E29-F29)
B30: TOTAL GENERAL | C30: =IF(OR($C$19="", $C$20=""), "", SUM(C23:C29)) | D30: =IF(OR($C$19="", $C$20=""), "", SUM(D23:D29)) | E30: =IF(OR($C$19="", $C$20=""), "", SUM(E23:E29)) | F30: =IF(OR($C$19="", $C$20=""), "", SUM(F23:F29)) | G30: =IF(OR($C$19="", $C$20=""), "", SUM(G23:G29))

Sheet Catalogos
A1: CATÁLOGOS OFICIALES - CONTROL DE COMBUSTIBLE
K2: Obras Dropdown | L2: Semanas Dropdown | U2: ASIGNACIÓN DE MAQUINARIA A OBRAS Y OPERADORES
A3: Código Obra | B3: Obra | C3: Ingeniero | E3: Código | F3: Fuente / Origen | I3: Tipo de Equipo | J3: Económico | M3: Total Lts (Semana Dashboard) | N3: 0 | Q3: Total Lts (Conciliacion) | R3: 0 | U3: No. Económico | V3: Tipo de Equipo | W3: Obra Asignada | X3: Operador Asignado
A4: MT | B4: México-Toluca | C4: Francisco Javier | E4: GAS | F4: Gasolinera Huixquilucan | I4: RETROEXCAVADORA CASE 580 N | J4: RT-01 | K4: México-Toluca | L4: 46167 | M4: =SUMIFS(Solicitudes!$F:$F, Solicitudes!$B:$B, $B4, Solicitudes!$C:$C, ">=" & Dashboard!$C$55, Solicitudes!$C:$C, "<=" & (Dashboard!$C$55+6)) + IF($B4="Jalisco", SUMIFS(Captura_Jalisco!$G:$G, Captura_Jalisco!$A:$A, ">=" & Dashboard!$C$55, Captura_Jalisco!$A:$A, "<=" & (Dashboard!$C$55+6), Captura_Jalisco!$B:$B, "Salida"), SUMIFS(Captura_Obra!$F:$F, Captura_Obra!$B:$B, $B4, Captura_Obra!$A:$A, ">=" & Dashboard!$C$55, Captura_Obra!$A:$A, "<=" & (Dashboard!$C$55+6))) | N4: =IF(M4>0, MAX($N$3:N3)+1, "") | Q4: =SUMIFS(Captura_Pegaso!$H:$H, Captura_Pegaso!$D:$D, $B4, Captura_Pegaso!$A:$A, ">=" & Conciliacion!$C$3, Captura_Pegaso!$A:$A, "<=" & (Conciliacion!$C$3+6)) + SUMIFS(Captura_Marimba_M01!$G:$G, Captura_Marimba_M01!$C:$C, $B4, Captura_Marimba_M01!$A:$A, ">=" & Conciliacion!$C$3, Captura_Marimba_M01!$A:$A, "<=" & (Conciliacion!$C$3+6)) + SUMIFS(Captura_Obra!$F:$F, Captura_Obra!$B:$B, $B4, Captura_Obra!$A:$A, ">=" & Conciliacion!$C$3, Captura_Obra!$A:$A, "<=" & (Conciliacion!$C$3+6)) | R4: =IF(Q4>0, MAX($R$3:R3)+1, "") | U4: RT-03 | V4: RETROEXCAVADORA CASE 580 N
A5: L3M | B5: Lerma - Tres Marías | C5: Apolinar | E5: PEG | F5: Tanque Pegaso | I5: RETROEXCAVADORA JHONDEREE 310 K | J5: RT-02 | K5: Lerma - Tres Marías | L5: 46174 | M5: =SUMIFS(Solicitudes!$F:$F, Solicitudes!$B:$B, $B5, Solicitudes!$C:$C, ">=" & Dashboard!$C$55, Solicitudes!$C:$C, "<=" & (Dashboard!$C$55+6)) + IF($B5="Jalisco", SUMIFS(Captura_Jalisco!$G:$G, Captura_Jalisco!$A:$A, ">=" & Dashboard!$C$55, Captura_Jalisco!$A:$A, "<=" & (Dashboard!$C$55+6), Captura_Jalisco!$B:$B, "Salida"), SUMIFS(Captura_Obra!$F:$F, Captura_Obra!$B:$B, $B5, Captura_Obra!$A:$A, ">=" & Dashboard!$C$55, Captura_Obra!$A:$A, "<=" & (Dashboard!$C$55+6))) | N5: =IF(M5>0, MAX($N$3:N4)+1, "") | Q5: =SUMIFS(Captura_Pegaso!$H:$H, Captura_Pegaso!$D:$D, $B5, Captura_Pegaso!$A:$A, ">=" & Conciliacion!$C$3, Captura_Pegaso!$A:$A, "<=" & (Conciliacion!$C$3+6)) + SUMIFS(Captura_Marimba_M01!$G:$G, Captura_Marimba_M01!$C:$C, $B5, Captura_Marimba_M01!$A:$A, ">=" & Conciliacion!$C$3, Captura_Marimba_M01!$A:$A, "<=" & (Conciliacion!$C$3+6)) + SUMIFS(Captura_Obra!$F:$F, Captura_Obra!$B:$B, $B5, Captura_Obra!$A:$A, ">=" & Conciliacion!$C$3, Captura_Obra!$A:$A, "<=" & (Conciliacion!$C$3+6)) | R5: =IF(Q5>0, MAX($R$3:R4)+1, "") | U5: VG-01 | V5: PAVIMENTADORA VOGELE 1800-3 i | W5: México-Toluca | X5: Gerardo Ezequiel Piña Fernández
A6: NP | B6: No aplica | E6: PAP | F6: Planta Asfalto Pegaso | I6: RETROEXCAVADORA CASE 580 N | J6: RT-03 | K6: Chamapa-Lechería | L6: 46181 | M6: =SUMIFS(Solicitudes!$F:$F, Solicitudes!$B:$B, $B6, Solicitudes!$C:$C, ">=" & Dashboard!$C$55, Solicitudes!$C:$C, "<=" & (Dashboard!$C$55+6)) + IF($B6="Jalisco", SUMIFS(Captura_Jalisco!$G:$G, Captura_Jalisco!$A:$A, ">=" & Dashboard!$C$55, Captura_Jalisco!$A:$A, "<=" & (Dashboard!$C$55+6), Captura_Jalisco!$B:$B, "Salida"), SUMIFS(Captura_Obra!$F:$F, Captura_Obra!$B:$B, $B6, Captura_Obra!$A:$A, ">=" & Dashboard!$C$55, Captura_Obra!$A:$A, "<=" & (Dashboard!$C$55+6))) | N6: =IF(M6>0, MAX($N$3:N5)+1, "") | Q6: =SUMIFS(Captura_Pegaso!$H:$H, Captura_Pegaso!$D:$D, $B6, Captura_Pegaso!$A:$A, ">=" & Conciliacion!$C$3, Captura_Pegaso!$A:$A, "<=" & (Conciliacion!$C$3+6)) + SUMIFS(Captura_Marimba_M01!$G:$G, Captura_Marimba_M01!$C:$C, $B6, Captura_Marimba_M01!$A:$A, ">=" & Conciliacion!$C$3, Captura_Marimba_M01!$A:$A, "<=" & (Conciliacion!$C$3+6)) + SUMIFS(Captura_Obra!$F:$F, Captura_Obra!$B:$B, $B6, Captura_Obra!$A:$A, ">=" & Conciliacion!$C$3, Captura_Obra!$A:$A, "<=" & (Conciliacion!$C$3+6)) | R6: =IF(Q6>0, MAX($R$3:R5)+1, "") | U6: VG-02 | V6: PAVIMENTADORA VOGELE 1800-2 SJ
A7: CL | B7: Chamapa-Lechería | C7: Francisco Javier | E7: M01 | F7: Marimba M-01 | I7: PAVIMENTADORA VOGELE 1800-3 I | J7: VG-01 | K7: Bacheo Toluca | L7: 46188 | M7: =SUMIFS(Solicitudes!$F:$F, Solicitudes!$B:$B, $B7, Solicitudes!$C:$C, ">=" & Dashboard!$C$55, Solicitudes!$C:$C, "<=" & (Dashboard!$C$55+6)) + IF($B7="Jalisco", SUMIFS(Captura_Jalisco!$G:$G, Captura_Jalisco!$A:$A, ">=" & Dashboard!$C$55, Captura_Jalisco!$A:$A, "<=" & (Dashboard!$C$55+6), Captura_Jalisco!$B:$B, "Salida"), SUMIFS(Captura_Obra!$F:$F, Captura_Obra!$B:$B, $B7, Captura_Obra!$A:$A, ">=" & Dashboard!$C$55, Captura_Obra!$A:$A, "<=" & (Dashboard!$C$55+6))) | N7: =IF(M7>0, MAX($N$3:N6)+1, "") | Q7: =SUMIFS(Captura_Pegaso!$H:$H, Captura_Pegaso!$D:$D, $B7, Captura_Pegaso!$A:$A, ">=" & Conciliacion!$C$3, Captura_Pegaso!$A:$A, "<=" & (Conciliacion!$C$3+6)) + SUMIFS(Captura_Marimba_M01!$G:$G, Captura_Marimba_M01!$C:$C, $B7, Captura_Marimba_M01!$A:$A, ">=" & Conciliacion!$C$3, Captura_Marimba_M01!$A:$A, "<=" & (Conciliacion!$C$3+6)) + SUMIFS(Captura_Obra!$F:$F, Captura_Obra!$B:$B, $B7, Captura_Obra!$A:$A, ">=" & Conciliacion!$C$3, Captura_Obra!$A:$A, "<=" & (Conciliacion!$C$3+6)) | R7: =IF(Q7>0, MAX($R$3:R6)+1, "") | U7: VG-03 | V7: PAVIMENTADORA VOGELE SJ 1800-3 | W7: Lerma - Tres Marías | X7: Jose de Jesus Eusebio Martinez
A8: BT | B8: Bacheo Toluca | C8: Diego Carreola | E8: DIR | F8: Carga directa | I8: PAVIMENTADORA VOGELE 1800-2 SJ | J8: VG-02 | K8: Planta Asfalto Pegaso | L8: 46195 | M8: =SUMIFS(Solicitudes!$F:$F, Solicitudes!$B:$B, $B8, Solicitudes!$C:$C, ">=" & Dashboard!$C$55, Solicitudes!$C:$C, "<=" & (Dashboard!$C$55+6)) + IF($B8="Jalisco", SUMIFS(Captura_Jalisco!$G:$G, Captura_Jalisco!$A:$A, ">=" & Dashboard!$C$55, Captura_Jalisco!$A:$A, "<=" & (Dashboard!$C$55+6), Captura_Jalisco!$B:$B, "Salida"), SUMIFS(Captura_Obra!$F:$F, Captura_Obra!$B:$B, $B8, Captura_Obra!$A:$A, ">=" & Dashboard!$C$55, Captura_Obra!$A:$A, "<=" & (Dashboard!$C$55+6))) | N8: =IF(M8>0, MAX($N$3:N7)+1, "") | Q8: =SUMIFS(Captura_Pegaso!$H:$H, Captura_Pegaso!$D:$D, $B8, Captura_Pegaso!$A:$A, ">=" & Conciliacion!$C$3, Captura_Pegaso!$A:$A, "<=" & (Conciliacion!$C$3+6)) + SUMIFS(Captura_Marimba_M01!$G:$G, Captura_Marimba_M01!$C:$C, $B8, Captura_Marimba_M01!$A:$A, ">=" & Conciliacion!$C$3, Captura_Marimba_M01!$A:$A, "<=" & (Conciliacion!$C$3+6)) + SUMIFS(Captura_Obra!$F:$F, Captura_Obra!$B:$B, $B8, Captura_Obra!$A:$A, ">=" & Conciliacion!$C$3, Captura_Obra!$A:$A, "<=" & (Conciliacion!$C$3+6)) | R8: =IF(Q8>0, MAX($R$3:R7)+1, "") | U8: PR-01 | V8: PERFILADORA RODATEC RX600-4-4008
A9: PAP | B9: Planta Asfalto Pegaso | C9: Janeth | E9: PAH | F9: Planta Asfaltos | I9: PAVIMENTADORA VOGELE SJ 1800-3 | J9: VG-03 | K9: Planta Asflato Huixquilucan | L9: 46202 | M9: =SUMIFS(Solicitudes!$F:$F, Solicitudes!$B:$B, $B9, Solicitudes!$C:$C, ">=" & Dashboard!$C$55, Solicitudes!$C:$C, "<=" & (Dashboard!$C$55+6)) + IF($B9="Jalisco", SUMIFS(Captura_Jalisco!$G:$G, Captura_Jalisco!$A:$A, ">=" & Dashboard!$C$55, Captura_Jalisco!$A:$A, "<=" & (Dashboard!$C$55+6), Captura_Jalisco!$B:$B, "Salida"), SUMIFS(Captura_Obra!$F:$F, Captura_Obra!$B:$B, $B9, Captura_Obra!$A:$A, ">=" & Dashboard!$C$55, Captura_Obra!$A:$A, "<=" & (Dashboard!$C$55+6))) | N9: =IF(M9>0, MAX($N$3:N8)+1, "") | Q9: =SUMIFS(Captura_Pegaso!$H:$H, Captura_Pegaso!$D:$D, $B9, Captura_Pegaso!$A:$A, ">=" & Conciliacion!$C$3, Captura_Pegaso!$A:$A, "<=" & (Conciliacion!$C$3+6)) + SUMIFS(Captura_Marimba_M01!$G:$G, Captura_Marimba_M01!$C:$C, $B9, Captura_Marimba_M01!$A:$A, ">=" & Conciliacion!$C$3, Captura_Marimba_M01!$A:$A, "<=" & (Conciliacion!$C$3+6)) + SUMIFS(Captura_Obra!$F:$F, Captura_Obra!$B:$B, $B9, Captura_Obra!$A:$A, ">=" & Conciliacion!$C$3, Captura_Obra!$A:$A, "<=" & (Conciliacion!$C$3+6)) | R9: =IF(Q9>0, MAX($R$3:R8)+1, "") | U9: PR-02 | V9: PERFILADORA RODATEC RX600E | W9: Lerma - Tres Marías | X9: Alan Alexis Gutierrez Flores
A10: PAH | B10: Planta Asflato Huixquilucan | C10: Luis | E10: ENT | F10: Entrada | I10: PERFILADORA RODATEC RX600-4-4008 | J10: PR-01 | K10: Dragones | L10: 46209 | M10: =SUMIFS(Solicitudes!$F:$F, Solicitudes!$B:$B, $B10, Solicitudes!$C:$C, ">=" & Dashboard!$C$55, Solicitudes!$C:$C, "<=" & (Dashboard!$C$55+6)) + IF($B10="Jalisco", SUMIFS(Captura_Jalisco!$G:$G, Captura_Jalisco!$A:$A, ">=" & Dashboard!$C$55, Captura_Jalisco!$A:$A, "<=" & (Dashboard!$C$55+6), Captura_Jalisco!$B:$B, "Salida"), SUMIFS(Captura_Obra!$F:$F, Captura_Obra!$B:$B, $B10, Captura_Obra!$A:$A, ">=" & Dashboard!$C$55, Captura_Obra!$A:$A, "<=" & (Dashboard!$C$55+6))) | N10: =IF(M10>0, MAX($N$3:N9)+1, "") | Q10: =SUMIFS(Captura_Pegaso!$H:$H, Captura_Pegaso!$D:$D, $B10, Captura_Pegaso!$A:$A, ">=" & Conciliacion!$C$3, Captura_Pegaso!$A:$A, "<=" & (Conciliacion!$C$3+6)) + SUMIFS(Captura_Marimba_M01!$G:$G, Captura_Marimba_M01!$C:$C, $B10, Captura_Marimba_M01!$A:$A, ">=" & Conciliacion!$C$3, Captura_Marimba_M01!$A:$A, "<=" & (Conciliacion!$C$3+6)) + SUMIFS(Captura_Obra!$F:$F, Captura_Obra!$B:$B, $B10, Captura_Obra!$A:$A, ">=" & Conciliacion!$C$3, Captura_Obra!$A:$A, "<=" & (Conciliacion!$C$3+6)) | R10: =IF(Q10>0, MAX($R$3:R9)+1, "") | U10: BR-01 | V10: BARREDORA BROCE RJ350 | W10: México-Toluca | X10: Edgar Rosales Martinez
B11: Dragones | E11: SD | F11: Salida | I11: PERFILADORA RODATEC RX600E | J11: PR-02 | K11: Jalisco | L11: 46216 | M11: =SUMIFS(Solicitudes!$F:$F, Solicitudes!$B:$B, $B11, Solicitudes!$C:$C, ">=" & Dashboard!$C$55, Solicitudes!$C:$C, "<=" & (Dashboard!$C$55+6)) + IF($B11="Jalisco", SUMIFS(Captura_Jalisco!$G:$G, Captura_Jalisco!$A:$A, ">=" & Dashboard!$C$55, Captura_Jalisco!$A:$A, "<=" & (Dashboard!$C$55+6), Captura_Jalisco!$B:$B, "Salida"), SUMIFS(Captura_Obra!$F:$F, Captura_Obra!$B:$B, $B11, Captura_Obra!$A:$A, ">=" & Dashboard!$C$55, Captura_Obra!$A:$A, "<=" & (Dashboard!$C$55+6))) | N11: =IF(M11>0, MAX($N$3:N10)+1, "") | Q11: =SUMIFS(Captura_Pegaso!$H:$H, Captura_Pegaso!$D:$D, $B11, Captura_Pegaso!$A:$A, ">=" & Conciliacion!$C$3, Captura_Pegaso!$A:$A, "<=" & (Conciliacion!$C$3+6)) + SUMIFS(Captura_Marimba_M01!$G:$G, Captura_Marimba_M01!$C:$C, $B11, Captura_Marimba_M01!$A:$A, ">=" & Conciliacion!$C$3, Captura_Marimba_M01!$A:$A, "<=" & (Conciliacion!$C$3+6)) + SUMIFS(Captura_Obra!$F:$F, Captura_Obra!$B:$B, $B11, Captura_Obra!$A:$A, ">=" & Conciliacion!$C$3, Captura_Obra!$A:$A, "<=" & (Conciliacion!$C$3+6)) | R11: =IF(Q11>0, MAX($R$3:R10)+1, "") | U11: BR-02 | V11: BARREDORA LAYMOR SM400
B12: Jalisco | I12: BARREDORA BROCE RJ350 | J12: BR-01 | K12: Todas | L12: 46223 | U12: BR-03 | V12: BARREDORA SUPERIOR BROOM DT80J
I13: BARREDORA LAYMOR SM400 | J13: BR-02 | L13: 46230 | U13: BR-04 | V13: BARREDORA LAYMOR SM400 | W13: Lerma - Tres Marías | X13: Fernando Angeles Reyes
I14: BARREDORA SUPERIOR BROOM DT80J | J14: BR-03 | L14: 46237 | U14: DR-01 | V14: DOBLE RODILLO/VIBROCOMPACTADOR DE RODILLOS HAMM 120HD VV | W14: México-Toluca | X14: POR ASIGNAR
I15: BARREDORA LAYMOR SM400 | J15: BR-04 | L15: 46244 | U15: DR-02 | V15: DOBLE RODILLO/VIBROCOMPACTADOR DE RODILLOS HAMM 140HD | W15: México-Toluca | X15: Julián Piña Hernández
I16: DOBLE RODILLO/VIBROCOMPACTADOR DE RODILLOS HAMM 120HD VV | J16: DR-01 | L16: 46251 | U16: TD-01 | V16: TANDEM DOBLE RODILLO / VIBROCOMPACTOR RODILLO CAT CB54
I17: DOBLE RODILLO/VIBROCOMPACTADOR DE RODILLOS HAMM 140HD | J17: DR-02 | L17: 46258 | U17: VC-01 | V17: VIBROCOMPACTADOR CATERPILLAR CB66B | W17: Lerma - Tres Marías | X17: Jose Manuel Reyes Flores
I18: TANDEM DOBLE RODILLO / VIBROCOMPACTOR RODILLO CAT CB54 | J18: TD-01 | L18: 46265 | U18: NM-01 | V18: NEUMATICO / COMPACTADOR DE NEUMATICOS DINAPAC CP271 | W18: Lerma - Tres Marías | X18: Marco Antonio Estrada Arellano
I19: VIBROCOMPACTADOR CATERPILLAR CB66B | J19: VC-01 | L19: 46272 | U19: NM-02 | V19: NEUMATICO VOLVO PT-240R | W19: México-Toluca | X19: Luis Fernando Mendiola Vivero
I20: NEUMATICO / COMPACTADOR DE NEUMATICOS DINAPAC CP271 | J20: NM-01 | L20: 46279 | U20: CPR-01 | V20: COMPRESOR SULLIVAN PALATEK D2010 | W20: Lerma - Tres Marías | X20: Eduardo Guadarrama Garcia
I21: NEUMATICO VOLVO PT-240R | J21: NM-02 | L21: 46286 | U21: CPR-02 | V21: COMPRESOR SULLIVAN PALATEK D2010
I22: COMPRESOR SULLIVAN PALATEK D2010 | J22: CPR-01 | L22: 46293 | U22: RT-04 | V22: RETROEXCAVADORA CASE 420DN
I23: COMPRESOR SULLIVAN PALATEK D2010 | J23: CPR-02 | L23: 46300 | U23: BR-05 | V23: BARREDORA BROCE BROOM KR350
I24: RETROEXCAVADORA CASE 420DN | J24: RT-04 | L24: 46307 | U24: RT-05 | V24: RETROEXCAVADORA JHONDEREE 310SK | W24: México-Toluca | X24: Adolfo Nava Lopez
I25: BARREDORA BROCE BROOM KR350 | J25: BR-05 | L25: 46314 | U25: BR-06 | V25: BARREDORA BROCE BROOM KR350
I26: RETROEXCAVADORA JHONDEREE 310SK | J26: RT-05 | L26: 46321 | U26: DR-03 | V26: DOBLE RODILLO INGERSOLL RAND DD-108HF
I27: BARREDORA BROCE BROOM KR350 | J27: BR-06 | L27: 46328 | U27: BG-01 | V27: TRASFER BUGGI RODATEC
I28: DOBLE RODILLO INGERSOLL RAND DD-108HF | J28: DR-03 | L28: 46335 | U28: CI-01 | V28: IMPACTO FORD 4300
I29: TRASFER BUGGI RODATEC | J29: BG-01 | L29: 46342 | U29: CI-02 | V29: IMPACTO FORD F800 | W29: Lerma - Tres Marías | X29: Marco Antonio Millan Centeno
I30: IMPACTO FORD 4300 | J30: CI-01 | L30: 46349 | U30: PT-01 | V30: PETROLIZADORA (IMPACTO 04) FORD F800
I31: IMPACTO FORD F800 | J31: CI-02 | L31: 46356 | U31: PT-02 | V31: PETROLIZADORA INTERNATIONAL | W31: Lerma - Tres Marías | X31: Francisco Gomora Angeles / Elthon Eduardo
I32: PETROLIZADORA (IMPACTO 04) FORD F800 | J32: PT-01 | L32: 46363 | U32: PP-01 | V32: PIPA DE AGUA (IMPACTO 01) FORD
I33: PETROLIZADORA INTERNATIONAL | J33: PT-02 | L33: 46370 | U33: DR-04 | V33: DOBLE RODILLO RAD ROLLER FILY-325 PRO
I34: PIPA DE AGUA (IMPACTO 01) FORD | J34: PP-01 | U34: S/N (WIRGENT) | V34: PERFILADORA WIRGENT-W200i | W34: México-Toluca | X34: Alejandro de Jesus Fuentes Tapia
I35: DOBLE RODILLO RAD ROLLER FILY-325 PRO | J35: DR-04 | U35: S/N (IR185) | V35: COMPRESOR INGERSOLL RAND IR185 | W35: México-Toluca | X35: Jose Carlos Romero Tellez
I36: BIDONES | J36: BD-01
I37: OTRO | J37: OT-01
I38: MARIMBA | J38: MB-01
I39: GENERADOR | J39: GR-01
I40: CRIBA ROJA | J40: CR-01
I41: TANDEM CAT | J41: TC-01
I42: MOTOCONFORMADORA RENTADA | J42: MGR-01
I43: VIBRO COMPACTADOR | J43: VC-01
I44: PAYLODER | J44: PL-01
I45: LIMPIEZA | J45: LP-01
I46: RASTRILLADOR | J46: RS-01
I47: MAXILIGHT | J47: MX-01
... I51: CALDERA TRIASO | J51: CTR-01

Sheet Instrucciones
A1: PROCEDIMIENTO OPERATIVO GC-COMB-01
A3: 1 | B3: Gasolinera → Pegaso | C3: Vigilante registra entrada en GC-COMB-001 con factura/remisión y litros recibidos.
A4: 2 | B4: Pegaso → Marimba M-01 | C4: Vigilante registra salida en GC-COMB-001. Operador de Marimba registra entrada en GC-COMB-002.
A5: 3 | B5: Pegaso → Máquina | C5: Vigilante registra salida directa en GC-COMB-001. Ingeniero registra recepción en GC-COMB-003.
A6: 4 | B6: Marimba → Obras/Máquinas | C6: Operador registra cada suministro en GC-COMB-002. Ingeniero reconoce litros por obra en GC-COMB-003.
A7: 5 | B7: Obras actuales | C7: México-Toluca, Lerma - Tres Marías y Chamapa-Lechería.
A8: 6 | B8: Horómetro | C8: No es obligatorio porque no funciona en la mayoría de equipos. El control principal será por litros, obra, equipo, actividad e incidencia.
A9: 7 | B9: Costo | C9: Capturar costo/litro en cada registro para obtener costo por obra y costo total semanal.
A10: 8 | B10: Cierre semanal | C10: Todos entregan bitácoras físicas firmadas. Gobierno Corporativo captura y revisa conciliación.
A11: 9 | B11: Alertas | C11: Si la diferencia total es distinta de cero, revisar Pegaso vs Marimba y Marimba/Pegaso vs Obra.
A12: 10 | B12: Reunión lunes | C12: Usar Dashboard para mostrar consumo, costo y diferencias al Ing. Pepe.
A14: Responsables | C14: Vigilante Pegaso = inventario / Operador Marimba = distribución / Ingeniero = validación de obra / Gobierno Corporativo = conciliación y pago.
A16: Documentación soporte | C16: Factura, remisión, bitácoras físicas firmadas, evidencias de incidencias cuando existan.
A18: Nota | C18: Este archivo no usa macros. Funciona con fórmulas, catálogos y validaciones para evitar dependencia de VBA.

Sheet Maquinaria_Inventario
A1: Número | B1: Unidad | C1: Dueño | D1: Marca | E1: Modelo | F1: Año | G1: No. Serie | H1: Rendimiento Nuevo | I1: Unidad de Medida | J1: Edad (Años) | K1: Rendimiento Ajustado (2026) | L1: Económico
A2: 1 | B2: RETROEXCAVADORA | C2: TRITURADORA ROCA DURA SAN MIGUEL S.A. DE C.V. | D2: CASE | E2: 580 N | F2: 2011 | G2: JJGN580NABC540211 | H2: 6.5 | I2: L/h | J2: =IF(OR(ISBLANK(F2), F2=""), Maquinaria_Calculo_Rendimiento!$B$5, Maquinaria_Calculo_Rendimiento!$B$3 - F2) | K2: =IF(I2="km/L", H2 / (1 + (J2 * Maquinaria_Calculo_Rendimiento!$B$4)), H2 * (1 + (J2 * Maquinaria_Calculo_Rendimiento!$B$4))) | L2: RT-01
A3: 2 | B3: RETROEXCAVADORA | D3: JHONDEREE | E3: 310 K | F3: 2010 | G3: 1T0231KXTEE258108 | H3: 6.5 | I3: L/h | J3: =IF(OR(ISBLANK(F3), F3=""), Maquinaria_Calculo_Rendimiento!$B$5, Maquinaria_Calculo_Rendimiento!$B$3 - F3) | K3: =IF(I3="km/L", H3 / (1 + (J3 * Maquinaria_Calculo_Rendimiento!$B$4)), H3 * (1 + (J3 * Maquinaria_Calculo_Rendimiento!$B$4))) | L3: RT-02
A4: 3 | B4: RETROEXCAVADORA | C4: TRITURADORA ROCA DURA SAN MIGUEL S.A. DE C.V. | D4: CASE | E4: 580 N | F4: 2010 | G4: JJGN58NHAC535026 | H4: 6.5 | I4: L/h | J4: =IF(OR(ISBLANK(F4), F4=""), Maquinaria_Calculo_Rendimiento!$B$5, Maquinaria_Calculo_Rendimiento!$B$3 - F4) | K4: =IF(I4="km/L", H4 / (1 + (J4 * Maquinaria_Calculo_Rendimiento!$B$4)), H4 * (1 + (J4 * Maquinaria_Calculo_Rendimiento!$B$4))) | L4: RT-03
A5: 4 | B5: PAVIMENTADORA | C5: JDJ EQUIPO Y CONSTRUCCIONES S.A. DE C.V. | D5: VOGELE | E5: 1800-3 i | F5: 2016 | G5: 14821687 | H5: 14.5 | I5: L/h | J5: =IF(OR(ISBLANK(F5), F5=""), Maquinaria_Calculo_Rendimiento!$B$5, Maquinaria_Calculo_Rendimiento!$B$3 - F5) | K5: =IF(I5="km/L", H5 / (1 + (J5 * Maquinaria_Calculo_Rendimiento!$B$4)), H5 * (1 + (J5 * Maquinaria_Calculo_Rendimiento!$B$4))) | L5: VG-01
A6: 5 | B6: PAVIMENTADORA | C6: TRITURADORA ROCA DURA SAN MIGUEL S.A. DE C.V. | D6: VOGELE | E6: 1800-2 SJ | F6: 2009 | G6: 11821564 | H6: 14.5 | I6: L/h | J6: =IF(OR(ISBLANK(F6), F6=""), Maquinaria_Calculo_Rendimiento!$B$5, Maquinaria_Calculo_Rendimiento!$B$3 - F6) | K6: =IF(I6="km/L", H6 / (1 + (J6 * Maquinaria_Calculo_Rendimiento!$B$4)), H6 * (1 + (J6 * Maquinaria_Calculo_Rendimiento!$B$4))) | L6: VG-02
A7: 6 | B7: PAVIMENTADORA | C7: JDJ EQUIPO Y CONSTRUCCIONES S.A. DE C.V. | D7: VOGELE | E7: SJ 1800-3 | F7: 2021 | G7: 14823977 | H7: 14.5 | I7: L/h | J7: =IF(OR(ISBLANK(F7), F7=""), Maquinaria_Calculo_Rendimiento!$B$5, Maquinaria_Calculo_Rendimiento!$B$3 - F7) | K7: =IF(I7="km/L", H7 / (1 + (J7 * Maquinaria_Calculo_Rendimiento!$B$4)), H7 * (1 + (J7 * Maquinaria_Calculo_Rendimiento!$B$4))) | L7: VG-03
A8: 7 | B8: PERFILADORA | C8: JDJ EQUIPO Y CONSTRUCCIONES S.A. DE C.V. | D8: RODATEC | E8: RX600-4-4008 | F8: 2015 | G8: 79816538 | H8: 65 | I8: L/h | J8: =IF(OR(ISBLANK(F8), F8=""), Maquinaria_Calculo_Rendimiento!$B$5, Maquinaria_Calculo_Rendimiento!$B$3 - F8) | K8: =IF(I8="km/L", H8 / (1 + (J8 * Maquinaria_Calculo_Rendimiento!$B$4)), H8 * (1 + (J8 * Maquinaria_Calculo_Rendimiento!$B$4))) | L8: PR-01
A9: 8 | B9: PERFILADORA | D9: RODATEC | E9: RX600E | F9: 2013 | G9: 79549560 | H9: 65 | I9: L/h | J9: =IF(OR(ISBLANK(F9), F9=""), Maquinaria_Calculo_Rendimiento!$B$5, Maquinaria_Calculo_Rendimiento!$B$3 - F9) | K9: =IF(I9="km/L", H9 / (1 + (J9 * Maquinaria_Calculo_Rendimiento!$B$4)), H9 * (1 + (J9 * Maquinaria_Calculo_Rendimiento!$B$4))) | L9: PR-02
A10: 9 | B10: BARREDORA | C10: JDJ EQUIPO Y CONSTRUCCIONES S.A. DE C.V. | D10: BROCE | E10: RJ350 | F10: 2010 | G10: 89602 | H10: 7.5 | I10: L/h | J10: =IF(OR(ISBLANK(F10), F10=""), Maquinaria_Calculo_Rendimiento!$B$5, Maquinaria_Calculo_Rendimiento!$B$3 - F10) | K10: =IF(I10="km/L", H10 / (1 + (J10 * Maquinaria_Calculo_Rendimiento!$B$4)), H10 * (1 + (J10 * Maquinaria_Calculo_Rendimiento!$B$4))) | L10: BR-01
A11: 10 | B11: BARREDORA | C11: TRITURADORA ROCA DURA SAN MIGUEL S.A. DE C.V. | D11: LAYMOR | E11: SM400 | F11: 2016 | G11: 36864 | H11: 7.5 | I11: L/h | J11: =IF(OR(ISBLANK(F11), F11=""), Maquinaria_Calculo_Rendimiento!$B$5, Maquinaria_Calculo_Rendimiento!$B$3 - F11) | K11: =IF(I11="km/L", H11 / (1 + (J11 * Maquinaria_Calculo_Rendimiento!$B$4)), H11 * (1 + (J11 * Maquinaria_Calculo_Rendimiento!$B$4))) | L11: BR-02
A12: 11 | B12: BARREDORA | D12: SUPERIOR BROOM | E12: DT80J | F12: 2015 | G12: 804108 | H12: 7.5 | I12: L/h | J12: =IF(OR(ISBLANK(F12), F12=""), Maquinaria_Calculo_Rendimiento!$B$5, Maquinaria_Calculo_Rendimiento!$B$3 - F12) | K12: =IF(I12="km/L", H12 / (1 + (J12 * Maquinaria_Calculo_Rendimiento!$B$4)), H12 * (1 + (J12 * Maquinaria_Calculo_Rendimiento!$B$4))) | L12: BR-03
A13: 12 | B13: BARREDORA | C13: JDJ EQUIPO Y CONSTRUCCIONES S.A. DE C.V. | D13: LAYMOR | E13: SM400 | F13: 2017 | G13: 34091 | H13: 7.5 | I13: L/h | J13: =IF(OR(ISBLANK(F13), F13=""), Maquinaria_Calculo_Rendimiento!$B$5, Maquinaria_Calculo_Rendimiento!$B$3 - F13) | K13: =IF(I13="km/L", H13 / (1 + (J13 * Maquinaria_Calculo_Rendimiento!$B$4)), H13 * (1 + (J13 * Maquinaria_Calculo_Rendimiento!$B$4))) | L13: BR-04
A14: 13 | B14: DOBLE RODILLO/VIBROCOMPACTADOR DE RODILLOS | C14: TRITURADORA ROCA DURA SAN MIGUEL S.A. DE C.V. | D14: HAMM | E14: 120HD VV | F14: 2010 | G14: H1840093 | H14: 12 | I14: L/h | J14: =IF(OR(ISBLANK(F14), F14=""), Maquinaria_Calculo_Rendimiento!$B$5, Maquinaria_Calculo_Rendimiento!$B$3 - F14) | K14: =IF(I14="km/L", H14 / (1 + (J14 * Maquinaria_Calculo_Rendimiento!$B$4)), H14 * (1 + (J14 * Maquinaria_Calculo_Rendimiento!$B$4))) | L14: DR-01
A15: 14 | B15: DOBLE RODILLO/VIBROCOMPACTADOR DE RODILLOS | C15: JDJ EQUIPO Y CONSTRUCCIONES S.A. DE C.V. | D15: HAMM | E15: 140HD | F15: 2010 | G15: H1840234 | H15: 12 | I15: L/h | J15: =IF(OR(ISBLANK(F15), F15=""), Maquinaria_Calculo_Rendimiento!$B$5, Maquinaria_Calculo_Rendimiento!$B$3 - F15) | K15: =IF(I15="km/L", H15 / (1 + (J15 * Maquinaria_Calculo_Rendimiento!$B$4)), H15 * (1 + (J15 * Maquinaria_Calculo_Rendimiento!$B$4))) | L15: DR-02
A16: 15 | B16: TANDEM DOBLE RODILLO / VIBROCOMPACTOR RODILLO | C16: TRITURADORA ROCA DURA SAN MIGUEL S.A. DE C.V. | D16: CAT | E16: CB54 | F16: 2014 | G16: CAT0CB54PJLM00895 | H16: 12 | I16: L/h | J16: =IF(OR(ISBLANK(F16), F16=""), Maquinaria_Calculo_Rendimiento!$B$5, Maquinaria_Calculo_Rendimiento!$B$3 - F16) | K16: =IF(I16="km/L", H16 / (1 + (J16 * Maquinaria_Calculo_Rendimiento!$B$4)), H16 * (1 + (J16 * Maquinaria_Calculo_Rendimiento!$B$4))) | L16: TD-01
A17: 16 | B17: VIBROCOMPACTADOR | C17: JDJ EQUIPO Y CONSTRUCCIONES S.A. DE C.V. | D17: CATERPILLAR | E17: CB66B | F17: 2017 | G17: CATCB66BVB6600136 | H17: 12 | I17: L/h | J17: =IF(OR(ISBLANK(F17), F17=""), Maquinaria_Calculo_Rendimiento!$B$5, Maquinaria_Calculo_Rendimiento!$B$3 - F17) | K17: =IF(I17="km/L", H17 / (1 + (J17 * Maquinaria_Calculo_Rendimiento!$B$4)), H17 * (1 + (J17 * Maquinaria_Calculo_Rendimiento!$B$4))) | L17: VC-01
A18: 17 | B18: NEUMATICO / COMPACTADOR DE NEUMATICOS | C18: TRITURADORA ROCA DURA SAN MIGUEL S.A. DE C.V. | D18: DINAPAC | E18: CP271 | F18: 2010 | G18: 23620561 | H18: 9.5 | I18: L/h | J18: =IF(OR(ISBLANK(F18), F18=""), Maquinaria_Calculo_Rendimiento!$B$5, Maquinaria_Calculo_Rendimiento!$B$3 - F18) | K18: =IF(I18="km/L", H18 / (1 + (J18 * Maquinaria_Calculo_Rendimiento!$B$4)), H18 * (1 + (J18 * Maquinaria_Calculo_Rendimiento!$B$4))) | L18: NM-01
A19: 18 | B19: NEUMATICO | C19: JDJ EQUIPO Y CONSTRUCCIONES S.A. DE C.V. | D19: VOLVO | E19: PT-240R | F19: 2014 | G19: VCE0T240A0S325028 | H19: 9.5 | I19: L/h | J19: =IF(OR(ISBLANK(F19), F19=""), Maquinaria_Calculo_Rendimiento!$B$5, Maquinaria_Calculo_Rendimiento!$B$3 - F19) | K19: =IF(I19="km/L", H19 / (1 + (J19 * Maquinaria_Calculo_Rendimiento!$B$4)), H19 * (1 + (J19 * Maquinaria_Calculo_Rendimiento!$B$4))) | L19: NM-02
A20: 19 | B20: COMPRESOR | D20: SULLIVAN PALATEK | E20: D2010 | F20: 2017 | G20: PHD25B330551 | H20: 9 | I20: L/h | J20: =IF(OR(ISBLANK(F20), F20=""), Maquinaria_Calculo_Rendimiento!$B$5, Maquinaria_Calculo_Rendimiento!$B$3 - F20) | K20: =IF(I20="km/L", H20 / (1 + (J20 * Maquinaria_Calculo_Rendimiento!$B$4)), H20 * (1 + (J20 * Maquinaria_Calculo_Rendimiento!$B$4))) | L20: CPR-01
A21: 20 | B21: COMPRESOR | D21: SULLIVAN PALATEK | E21: D2010 | F21: 2017 | G21: PHD25B330552 | H21: 9 | I21: L/h | J21: =IF(OR(ISBLANK(F21), F21=""), Maquinaria_Calculo_Rendimiento!$B$5, Maquinaria_Calculo_Rendimiento!$B$3 - F21) | K21: =IF(I21="km/L", H21 / (1 + (J21 * Maquinaria_Calculo_Rendimiento!$B$4)), H21 * (1 + (J21 * Maquinaria_Calculo_Rendimiento!$B$4))) | L21: CPR-02
A22: 21 | B22: RETROEXCAVADORA | D22: CASE | E22: 420DN | G22: CAT0420DTFDP27091 | H22: 6.5 | I22: L/h | J22: =IF(OR(ISBLANK(F22), F22=""), Maquinaria_Calculo_Rendimiento!$B$5, Maquinaria_Calculo_Rendimiento!$B$3 - F22) | K22: =IF(I22="km/L", H22 / (1 + (J22 * Maquinaria_Calculo_Rendimiento!$B$4)), H22 * (1 + (J22 * Maquinaria_Calculo_Rendimiento!$B$4))) | L22: RT-04
A23: 22 | B23: BARREDORA | D23: BROCE BROOM | E23: KR350 | G23: 407123 | H23: 7.5 | I23: L/h | J23: =IF(OR(ISBLANK(F23), F23=""), Maquinaria_Calculo_Rendimiento!$B$5, Maquinaria_Calculo_Rendimiento!$B$3 - F23) | K23: =IF(I23="km/L", H23 / (1 + (J23 * Maquinaria_Calculo_Rendimiento!$B$4)), H23 * (1 + (J23 * Maquinaria_Calculo_Rendimiento!$B$4))) | L23: BR-05
A24: 23 | B24: RETROEXCAVADORA | D24: JHONDEREE | E24: 310SK | G24: 1T0310SKAEE262172 | H24: 6.5 | I24: L/h | J24: =IF(OR(ISBLANK(F24), F24=""), Maquinaria_Calculo_Rendimiento!$B$5, Maquinaria_Calculo_Rendimiento!$B$3 - F24) | K24: =IF(I24="km/L", H24 / (1 + (J24 * Maquinaria_Calculo_Rendimiento!$B$4)), H24 * (1 + (J24 * Maquinaria_Calculo_Rendimiento!$B$4))) | L24: RT-05
A25: 24 | B25: BARREDORA | D25: BROCE BROOM | E25: KR350 | G25: 408531 | H25: 7.5 | I25: L/h | J25: =IF(OR(ISBLANK(F25), F25=""), Maquinaria_Calculo_Rendimiento!$B$5, Maquinaria_Calculo_Rendimiento!$B$3 - F25) | K25: =IF(I25="km/L", H25 / (1 + (J25 * Maquinaria_Calculo_Rendimiento!$B$4)), H25 * (1 + (J25 * Maquinaria_Calculo_Rendimiento!$B$4))) | L25: BR-06
A26: 25 | B26: DOBLE RODILLO | D26: INGERSOLL RAND | E26: DD-108HF | G26: 189989 | H26: 12 | I26: L/h | J26: =IF(OR(ISBLANK(F26), F26=""), Maquinaria_Calculo_Rendimiento!$B$5, Maquinaria_Calculo_Rendimiento!$B$3 - F26) | K26: =IF(I26="km/L", H26 / (1 + (J26 * Maquinaria_Calculo_Rendimiento!$B$4)), H26 * (1 + (J26 * Maquinaria_Calculo_Rendimiento!$B$4))) | L26: DR-03
A27: 26 | B27: TRASFER BUGGI | D27: RODATEC | G27: CB-2500B 538 | H27: 30 | I27: L/h | J27: =IF(OR(ISBLANK(F27), F27=""), Maquinaria_Calculo_Rendimiento!$B$5, Maquinaria_Calculo_Rendimiento!$B$3 - F27) | K27: =IF(I27="km/L", H27 / (1 + (J27 * Maquinaria_Calculo_Rendimiento!$B$4)), H27 * (1 + (J27 * Maquinaria_Calculo_Rendimiento!$B$4))) | L27: BG-01
A28: 27 | B28: IMPACTO | C28: JDJ EQUIPO Y CONSTRUCCIONES S.A. DE C.V. | D28: FORD | E28: 4300 | F28: 2013 | G28: 1HTMMAAL2DH158631 | H28: 3.5 | I28: km/L | J28: =IF(OR(ISBLANK(F28), F28=""), Maquinaria_Calculo_Rendimiento!$B$5, Maquinaria_Calculo_Rendimiento!$B$3 - F28) | K28: =IF(I28="km/L", H28 / (1 + (J28 * Maquinaria_Calculo_Rendimiento!$B$4)), H28 * (1 + (J28 * Maquinaria_Calculo_Rendimiento!$B$4))) | L28: CI-01
A29: 28 | B29: IMPACTO | C29: JDJ EQUIPO Y CONSTRUCCIONES S.A. DE C.V. | D29: FORD | E29: F800 | F29: 1998 | G29: 1FDNF80C7WVA19892 | H29: 3.5 | I29: km/L | J29: =IF(OR(ISBLANK(F29), F29=""), Maquinaria_Calculo_Rendimiento!$B$5, Maquinaria_Calculo_Rendimiento!$B$3 - F29) | K29: =IF(I29="km/L", H29 / (1 + (J29 * Maquinaria_Calculo_Rendimiento!$B$4)), H29 * (1 + (J29 * Maquinaria_Calculo_Rendimiento!$B$4))) | L29: CI-02
A30: 29 | B30: PETROLIZADORA (IMPACTO 04) | C30: JDJ EQUIPO Y CONSTRUCCIONES S.A. DE C.V. | D30: FORD | E30: F800 | F30: 1998 | G30: 1FDNF80C2WVA22179 | H30: 10 | I30: L/h | J30: =IF(OR(ISBLANK(F30), F30=""), Maquinaria_Calculo_Rendimiento!$B$5, Maquinaria_Calculo_Rendimiento!$B$3 - F30) | K30: =IF(I30="km/L", H30 / (1 + (J30 * Maquinaria_Calculo_Rendimiento!$B$4)), H30 * (1 + (J30 * Maquinaria_Calculo_Rendimiento!$B$4))) | L30: PT-01
A31: 30 | B31: PETROLIZADORA | D31: INTERNATIONAL | F31: 2003 | G31: 3HTMMAAR830567 | H31: 10 | I31: L/h | J31: =IF(OR(ISBLANK(F31), F31=""), Maquinaria_Calculo_Rendimiento!$B$5, Maquinaria_Calculo_Rendimiento!$B$3 - F31) | K31: =IF(I31="km/L", H31 / (1 + (J31 * Maquinaria_Calculo_Rendimiento!$B$4)), H31 * (1 + (J31 * Maquinaria_Calculo_Rendimiento!$B$4))) | L31: PT-02
A32: 31 | B32: PIPA DE AGUA (IMPACTO 01) | C32: JDJ EQUIPO Y CONSTRUCCIONES S.A. DE C.V. | D32: FORD | G32: 1FDYR80U0GVA15942 | H32: 3.5 | I32: km/L | J32: =IF(OR(ISBLANK(F32), F32=""), Maquinaria_Calculo_Rendimiento!$B$5, Maquinaria_Calculo_Rendimiento!$B$3 - F32) | K32: =IF(I32="km/L", H32 / (1 + (J32 * Maquinaria_Calculo_Rendimiento!$B$4)), H32 * (1 + (J32 * Maquinaria_Calculo_Rendimiento!$B$4))) | L32: PP-01
A33: 32 | B33: DOBLE RODILLO | D33: RAD ROLLER | E33: FILY-325 PRO | G33: LD600JN2026012501 | H33: 12 | I33: L/h | J33: =IF(OR(ISBLANK(F33), F33=""), Maquinaria_Calculo_Rendimiento!$B$5, Maquinaria_Calculo_Rendimiento!$B$3 - F33) | K33: =IF(I33="km/L", H33 / (1 + (J33 * Maquinaria_Calculo_Rendimiento!$B$4)), H33 * (1 + (J33 * Maquinaria_Calculo_Rendimiento!$B$4))) | L33: DR-04

Sheet Maquinaria_Calculo_Rendimiento
A1: CÁLCULO DE RENDIMIENTOS AJUSTADOS POR DESGASTE Y TIEMPO
A3: Año Actual de Auditoría: | B3: 2026
A4: Tasa de Desgaste Anual (T): | B4: 0.01
A5: Edad Promedio Default: | B5: 10
A7: EXPLICACIÓN DE FÓRMULAS
A9: 1. Edad del Equipo (Años):
A10: Calculada como: [Año Auditoría] - [Año de Fabricación].
A11: Si el año es desconocido (nulo), se asume la Edad Promedio Default (10 años).
A13: 2. Maquinaria Medida en Horas (L/h):
A14: A mayor edad, se incrementa el consumo de combustible por desgaste mecánico:
A15: Fórmula: [Rendimiento Nuevo] * (1 + (Edad * Tasa de Desgaste))
A17: 3. Transporte y Soporte Medido en Kilómetros (km/L):
A18: A mayor edad, se reduce el rendimiento en distancia recorrida por litro:
A19: Fórmula: [Rendimiento Nuevo] / (1 + (Edad * Tasa de Desgaste))
A21: NOTA DE AUDITORÍA:
A22: El desgaste anual del 1.0% anual es el estándar industrial recomendado para maquinaria pesada.
... A24: identificar desvíos de combustible reales sin castigar a los equipos de mayor antigüedad.
